{
  "type": "Feature",
  "properties": {
    "gn:admin1_code":"29.0",
    "gn:asciiname":"Farig as Sora `Awadab",
    "gn:country_code":"SD",
    "gn:dem":452,
    "gn:feature_class":"P",
    "gn:feature_code":"PPL",
    "gn:name":"Farig as Sora \u2018Awadab",
    "gn:population":0,
    "gn:timezone":"Africa/Khartoum",
    "iso:country":"SD",
    "name:und_x_variant":[
        "Farig as Sora \u2018Awadab"
    ],
    "wof:name":"Farig as Sora `Awadab",
    "wof:placetype":"locality"
},
  "geometry": {"coordinates":[33.3104,15.5104],"type":"Point"}
}