{
  "type": "Feature",
  "properties": {
    "gn:admin1_code":"29.0",
    "gn:asciiname":"Sawba Sharq",
    "gn:cc2":"SD",
    "gn:country_code":"SD",
    "gn:dem":378,
    "gn:feature_class":"P",
    "gn:feature_code":"PPL",
    "gn:name":"Sawb\u0101 Sharq",
    "gn:population":0,
    "gn:timezone":"Africa/Khartoum",
    "iso:country":"SD",
    "name:und_x_variant":[
        "Soba Sharq",
        "Soba East",
        "Sawb\u0101 Sharq"
    ],
    "wof:name":"Sawba Sharq",
    "wof:placetype":"locality"
},
  "geometry": {"coordinates":[32.68333,15.48333],"type":"Point"}
}