{
  "type": "Feature",
  "properties": {
    "gn:admin1_code":"41.0",
    "gn:asciiname":"Ad Danqu",
    "gn:country_code":"SD",
    "gn:dem":418,
    "gn:feature_class":"P",
    "gn:feature_code":"PPL",
    "gn:name":"Ad Danqu",
    "gn:population":0,
    "gn:timezone":"Africa/Khartoum",
    "iso:country":"SD",
    "wof:name":"Ad Danqu",
    "wof:placetype":"locality"
},
  "geometry": {"coordinates":[31.8549,12.6554],"type":"Point"}
}