{
  "type": "Feature",
  "properties": {
    "gn:admin1_code":"47.0",
    "gn:asciiname":"Didima",
    "gn:country_code":"SD",
    "gn:dem":898,
    "gn:feature_class":"P",
    "gn:feature_code":"PPL",
    "gn:name":"Didima",
    "gn:population":0,
    "gn:timezone":"Africa/Khartoum",
    "iso:country":"SD",
    "wof:name":"Didima",
    "wof:placetype":"locality"
},
  "geometry": {"coordinates":[22.84125,14.27293],"type":"Point"}
}