{
  "type": "Feature",
  "properties": {
    "gn:admin1_code":"41.0",
    "gn:asciiname":"Wad An Nora Al Qadima",
    "gn:country_code":"SD",
    "gn:dem":391,
    "gn:feature_class":"P",
    "gn:feature_code":"PPL",
    "gn:name":"Wad An N\u014dra Al Qad\u012bma",
    "gn:population":0,
    "gn:timezone":"Africa/Khartoum",
    "iso:country":"SD",
    "name:und_x_variant":[
        "Wad An N\u014dra Al Qad\u012bma"
    ],
    "wof:name":"Wad An Nora Al Qadima",
    "wof:placetype":"locality"
},
  "geometry": {"coordinates":[32.5039,14.5549],"type":"Point"}
}