{
  "type": "Feature",
  "properties": {
    "gn:admin1_code":"50.0",
    "gn:asciiname":"Tabaldiyya",
    "gn:country_code":"SD",
    "gn:dem":649,
    "gn:feature_class":"P",
    "gn:feature_code":"PPL",
    "gn:name":"Tabaldiyya",
    "gn:population":0,
    "gn:timezone":"Africa/Khartoum",
    "iso:country":"SD",
    "wof:name":"Tabaldiyya",
    "wof:placetype":"locality"
},
  "geometry": {"coordinates":[30.3567,11.8715],"type":"Point"}
}