{
  "type": "Feature",
  "properties": {
    "gn:admin1_code":"56.0",
    "gn:asciiname":"Al Haraniyya",
    "gn:country_code":"SD",
    "gn:dem":433,
    "gn:feature_class":"P",
    "gn:feature_code":"PPL",
    "gn:name":"Al Haraniyya",
    "gn:population":0,
    "gn:timezone":"Africa/Khartoum",
    "iso:country":"SD",
    "wof:name":"Al Haraniyya",
    "wof:placetype":"locality"
},
  "geometry": {"coordinates":[31.6129,12.9566],"type":"Point"}
}