{
  "type": "Feature",
  "properties": {
    "gn:admin1_code":"49.0",
    "gn:asciiname":"Kubbum",
    "gn:country_code":"SD",
    "gn:dem":702,
    "gn:feature_class":"P",
    "gn:feature_code":"PPL",
    "gn:name":"Kubbum",
    "gn:population":0,
    "gn:timezone":"Africa/Khartoum",
    "iso:country":"SD",
    "name:und_x_variant":[
        "Kubum",
        "Kubbum"
    ],
    "wof:name":"Kubbum",
    "wof:placetype":"locality"
},
  "geometry": {"coordinates":[23.78333,11.78333],"type":"Point"}
}