{
  "type": "Feature",
  "properties": {
    "gn:admin1_code":"38.0",
    "gn:asciiname":"`Amarat an Nefeidiya",
    "gn:country_code":"SD",
    "gn:dem":417,
    "gn:feature_class":"P",
    "gn:feature_code":"PPL",
    "gn:name":"\u2018Am\u0101rat an Nefeidiya",
    "gn:population":0,
    "gn:timezone":"Africa/Khartoum",
    "iso:country":"SD",
    "name:und_x_variant":[
        "\u2018Amarat en Nefeidiya",
        "\u2018Am\u0101rat an Nefeidiya"
    ],
    "wof:name":"`Amarat an Nefeidiya",
    "wof:placetype":"locality"
},
  "geometry": {"coordinates":[33.76667,14.15],"type":"Point"}
}