{
  "type": "Feature",
  "properties": {
    "gn:admin1_code":"38.0",
    "gn:asciiname":"Wad aj Jamal",
    "gn:country_code":"SD",
    "gn:dem":410,
    "gn:feature_class":"P",
    "gn:feature_code":"PPL",
    "gn:name":"Wad aj Jamal",
    "gn:population":0,
    "gn:timezone":"Africa/Khartoum",
    "iso:country":"SD",
    "wof:name":"Wad aj Jamal",
    "wof:placetype":"locality"
},
  "geometry": {"coordinates":[33.2301,14.3805],"type":"Point"}
}