{
  "type": "Feature",
  "properties": {
    "gn:admin1_code":"58.0",
    "gn:asciiname":"Dar al Bakhitah",
    "gn:country_code":"SD",
    "gn:dem":436,
    "gn:feature_class":"P",
    "gn:feature_code":"PPL",
    "gn:name":"D\u0101r al Bakh\u012btah",
    "gn:population":0,
    "gn:timezone":"Africa/Khartoum",
    "iso:country":"SD",
    "name:und_x_variant":[
        "Hillet el Bir",
        "D\u0101r el Bakhita",
        "D\u0101r al Bakh\u012btah"
    ],
    "wof:name":"Dar al Bakhitah",
    "wof:placetype":"locality"
},
  "geometry": {"coordinates":[33.56667,13.45],"type":"Point"}
}