{
  "type": "Feature",
  "properties": {
    "gn:admin1_code":"56.0",
    "gn:asciiname":"Umm Dukaykah",
    "gn:country_code":"SD",
    "gn:dem":482,
    "gn:feature_class":"P",
    "gn:feature_code":"PPL",
    "gn:name":"Umm Dukaykah",
    "gn:population":0,
    "gn:timezone":"Africa/Khartoum",
    "iso:country":"SD",
    "name:und_x_variant":[
        "Umm Dukeika",
        "Umm Dukaykah"
    ],
    "wof:name":"Umm Dukaykah",
    "wof:placetype":"locality"
},
  "geometry": {"coordinates":[30.81667,13.23333],"type":"Point"}
}