{
  "type": "Feature",
  "properties": {
    "gn:admin1_code":"55.0",
    "gn:asciiname":"Lil Korat",
    "gn:country_code":"SD",
    "gn:dem":1003,
    "gn:feature_class":"P",
    "gn:feature_code":"PPL",
    "gn:name":"Lil Korat",
    "gn:population":0,
    "gn:timezone":"Africa/Khartoum",
    "iso:country":"SD",
    "wof:name":"Lil Korat",
    "wof:placetype":"locality"
},
  "geometry": {"coordinates":[24.06667,15.05],"type":"Point"}
}