{
  "type": "Feature",
  "properties": {
    "gn:admin1_code":"55.0",
    "gn:asciiname":"Wad Hassib",
    "gn:country_code":"SD",
    "gn:dem":472,
    "gn:feature_class":"P",
    "gn:feature_code":"PPL",
    "gn:name":"Wad Hassib",
    "gn:population":0,
    "gn:timezone":"Africa/Khartoum",
    "iso:country":"SD",
    "wof:name":"Wad Hassib",
    "wof:placetype":"locality"
},
  "geometry": {"coordinates":[26.85,11.75],"type":"Point"}
}