{
  "type": "Feature",
  "properties": {
    "gn:admin1_code":"50.0",
    "gn:asciiname":"Mashturey",
    "gn:country_code":"SD",
    "gn:dem":877,
    "gn:feature_class":"P",
    "gn:feature_code":"PPL",
    "gn:name":"Mash\u0163\u016brey",
    "gn:population":0,
    "gn:timezone":"Africa/Khartoum",
    "iso:country":"SD",
    "name:und_x_variant":[
        "Mash\u0163\u016brey"
    ],
    "wof:name":"Mashturey",
    "wof:placetype":"locality"
},
  "geometry": {"coordinates":[31.061,12.0503],"type":"Point"}
}