{
  "type": "Feature",
  "properties": {
    "gn:admin1_code":"38.0",
    "gn:asciiname":"Hillat Abu Habara",
    "gn:country_code":"SD",
    "gn:dem":393,
    "gn:feature_class":"P",
    "gn:feature_code":"PPL",
    "gn:name":"Hillat Abu Habara",
    "gn:population":0,
    "gn:timezone":"Africa/Khartoum",
    "iso:country":"SD",
    "wof:name":"Hillat Abu Habara",
    "wof:placetype":"locality"
},
  "geometry": {"coordinates":[32.827,15.1096],"type":"Point"}
}