{
  "type": "Feature",
  "properties": {
    "gn:admin1_code":"61.0",
    "gn:asciiname":"Korei",
    "gn:country_code":"SD",
    "gn:dem":857,
    "gn:feature_class":"P",
    "gn:feature_code":"PPL",
    "gn:name":"Korei",
    "gn:population":0,
    "gn:timezone":"Africa/Khartoum",
    "iso:country":"SD",
    "wof:name":"Korei",
    "wof:placetype":"locality"
},
  "geometry": {"coordinates":[23.35821,12.91813],"type":"Point"}
}