{
  "type": "Feature",
  "properties": {
    "gn:admin1_code":"50.0",
    "gn:asciiname":"Hillat Awlad Tibeg",
    "gn:country_code":"SD",
    "gn:dem":587,
    "gn:feature_class":"P",
    "gn:feature_code":"PPL",
    "gn:name":"Hillat Awl\u0101d Tib\u0113g",
    "gn:population":0,
    "gn:timezone":"Africa/Khartoum",
    "iso:country":"SD",
    "name:und_x_variant":[
        "Hillat Awl\u0101d Tib\u0113g"
    ],
    "wof:name":"Hillat Awlad Tibeg",
    "wof:placetype":"locality"
},
  "geometry": {"coordinates":[29.5624,11.2743],"type":"Point"}
}