{
  "type": "Feature",
  "properties": {
    "gn:admin1_code":"50.0",
    "gn:asciiname":"Sesaban",
    "gn:country_code":"SD",
    "gn:dem":670,
    "gn:feature_class":"P",
    "gn:feature_code":"PPL",
    "gn:name":"S\u0113sab\u0101n",
    "gn:population":0,
    "gn:timezone":"Africa/Khartoum",
    "iso:country":"SD",
    "name:und_x_variant":[
        "Seisaban",
        "Saysab\u0101n",
        "S\u0113sab\u0101n"
    ],
    "wof:name":"Sesaban",
    "wof:placetype":"locality"
},
  "geometry": {"coordinates":[31.0322,11.5237],"type":"Point"}
}