{
  "type": "Feature",
  "properties": {
    "gn:admin1_code":"47.0",
    "gn:asciiname":"Leijaina",
    "gn:country_code":"SD",
    "gn:dem":964,
    "gn:feature_class":"P",
    "gn:feature_code":"PPL",
    "gn:name":"Leijaina",
    "gn:population":0,
    "gn:timezone":"Africa/Khartoum",
    "iso:country":"SD",
    "name:eng_x_preferred":[
        "Leijaina"
    ],
    "name:und_x_variant":[
        "Obwani"
    ],
    "wof:name":"Leijaina",
    "wof:placetype":"locality"
},
  "geometry": {"coordinates":[22.2602,13.79938],"type":"Point"}
}