{
  "type": "Feature",
  "properties": {
    "gn:admin1_code":"41.0",
    "gn:asciiname":"Kitra",
    "gn:country_code":"SD",
    "gn:dem":414,
    "gn:feature_class":"P",
    "gn:feature_code":"PPL",
    "gn:name":"Kitra",
    "gn:population":0,
    "gn:timezone":"Africa/Khartoum",
    "iso:country":"SD",
    "wof:name":"Kitra",
    "wof:placetype":"locality"
},
  "geometry": {"coordinates":[31.9645,12.7191],"type":"Point"}
}