{
  "type": "Feature",
  "properties": {
    "gn:admin1_code":"41.0",
    "gn:asciiname":"Um Takkal",
    "gn:country_code":"SD",
    "gn:dem":385,
    "gn:feature_class":"P",
    "gn:feature_code":"PPL",
    "gn:name":"Um Takk\u0101l",
    "gn:population":0,
    "gn:timezone":"Africa/Khartoum",
    "iso:country":"SD",
    "name:und_x_variant":[
        "Um Takk\u0101l"
    ],
    "wof:name":"Um Takkal",
    "wof:placetype":"locality"
},
  "geometry": {"coordinates":[32.2904,13.9034],"type":"Point"}
}