{
  "type": "Feature",
  "properties": {
    "gn:admin1_code":"41.0",
    "gn:asciiname":"Al Quwezat",
    "gn:country_code":"SD",
    "gn:dem":393,
    "gn:feature_class":"P",
    "gn:feature_code":"PPL",
    "gn:name":"Al Quwez\u0101t",
    "gn:population":0,
    "gn:timezone":"Africa/Khartoum",
    "iso:country":"SD",
    "name:ara_x_preferred":[
        "Al Quwez\u0101t"
    ],
    "wof:name":"Al Quwezat",
    "wof:placetype":"locality"
},
  "geometry": {"coordinates":[32.7279,12.3707],"type":"Point"}
}