{
  "type": "Feature",
  "properties": {
    "gn:admin1_code":"60.0",
    "gn:asciiname":"Silkhalaq",
    "gn:country_code":"SD",
    "gn:dem":466,
    "gn:feature_class":"P",
    "gn:feature_code":"PPL",
    "gn:name":"Silkhalaq",
    "gn:population":0,
    "gn:timezone":"Africa/Khartoum",
    "iso:country":"SD",
    "wof:name":"Silkhalaq",
    "wof:placetype":"locality"
},
  "geometry": {"coordinates":[25.65,11.21667],"type":"Point"}
}