{
  "type": "Feature",
  "properties": {
    "gn:admin1_code":"42.0",
    "gn:asciiname":"Harun Al Bahar",
    "gn:country_code":"SD",
    "gn:dem":462,
    "gn:feature_class":"P",
    "gn:feature_code":"PPL",
    "gn:name":"H\u0101r\u016bn Al Bahar",
    "gn:population":0,
    "gn:timezone":"Africa/Khartoum",
    "iso:country":"SD",
    "name:und_x_variant":[
        "H\u0101r\u016bn Al Bahar"
    ],
    "wof:lang_x_official":[
        "ara",
        "eng"
    ],
    "wof:lang_x_spoken":[
        "ara",
        "eng"
    ],
    "wof:name":"Harun Al Bahar",
    "wof:placetype":"locality"
},
  "geometry": {"coordinates":[34.3376,12.2497],"type":"Point"}
}