{
  "type": "Feature",
  "properties": {
    "gn:admin1_code":"49.0",
    "gn:asciiname":"Tu",
    "gn:country_code":"SD",
    "gn:dem":1944,
    "gn:feature_class":"P",
    "gn:feature_code":"PPL",
    "gn:name":"Tu",
    "gn:population":0,
    "gn:timezone":"Africa/Khartoum",
    "iso:country":"SD",
    "wof:name":"Tu",
    "wof:placetype":"locality"
},
  "geometry": {"coordinates":[24.36218,12.87255],"type":"Point"}
}