{
  "type": "Feature",
  "properties": {
    "gn:admin1_code":"61.0",
    "gn:asciiname":"Botai",
    "gn:country_code":"SD",
    "gn:dem":639,
    "gn:feature_class":"P",
    "gn:feature_code":"PPL",
    "gn:name":"Botai",
    "gn:population":0,
    "gn:timezone":"Africa/Khartoum",
    "iso:country":"SD",
    "name:eng_x_preferred":[
        "Botai"
    ],
    "wof:name":"Botai",
    "wof:placetype":"locality"
},
  "geometry": {"coordinates":[22.89561,12.11696],"type":"Point"}
}