{
  "type": "Feature",
  "properties": {
    "gn:admin1_code":"38.0",
    "gn:asciiname":"Qashsharat al Madina `Arab",
    "gn:country_code":"SD",
    "gn:dem":410,
    "gn:feature_class":"P",
    "gn:feature_code":"PPL",
    "gn:name":"Qashsharat al Mad\u012bna \u2018Arab",
    "gn:population":0,
    "gn:timezone":"Africa/Khartoum",
    "iso:country":"SD",
    "name:und_x_variant":[
        "Qashsharat al Mad\u012bna \u2018Arab"
    ],
    "wof:name":"Qashsharat al Madina `Arab",
    "wof:placetype":"locality"
},
  "geometry": {"coordinates":[33.3234,14.3682],"type":"Point"}
}