{
  "type": "Feature",
  "properties": {
    "gn:admin1_code":"29.0",
    "gn:asciiname":"Al `Usharah",
    "gn:country_code":"SD",
    "gn:dem":387,
    "gn:feature_class":"P",
    "gn:feature_code":"PPL",
    "gn:name":"Al \u2018Usharah",
    "gn:population":0,
    "gn:timezone":"Africa/Khartoum",
    "iso:country":"SD",
    "name:und_x_variant":[
        "El \u2018Ushara",
        "Al \u2018Usharah"
    ],
    "wof:name":"Al `Usharah",
    "wof:placetype":"locality"
},
  "geometry": {"coordinates":[32.58333,15.31667],"type":"Point"}
}