{
  "type": "Feature",
  "properties": {
    "gn:admin1_code":"41.0",
    "gn:asciiname":"Hamrat ash Shekh as Sufi",
    "gn:country_code":"SD",
    "gn:dem":397,
    "gn:feature_class":"P",
    "gn:feature_code":"PPL",
    "gn:name":"\u1e28amrat ash Sh\u0113kh a\u1e63 \u1e62\u016bfi",
    "gn:population":0,
    "gn:timezone":"Africa/Khartoum",
    "iso:country":"SD",
    "name:und_x_variant":[
        "\u1e28amrat ash Sh\u0113kh a\u1e63 \u1e62\u016bfi"
    ],
    "wof:lang_x_official":[
        "ara",
        "eng"
    ],
    "wof:lang_x_spoken":[
        "ara",
        "eng"
    ],
    "wof:name":"Hamrat ash Shekh as Sufi",
    "wof:placetype":"locality"
},
  "geometry": {"coordinates":[32.0399,13.966],"type":"Point"}
}