{
  "type": "Feature",
  "properties": {
    "gn:admin1_code":"61.0",
    "gn:asciiname":"Mingyeir",
    "gn:country_code":"SD",
    "gn:dem":699,
    "gn:feature_class":"P",
    "gn:feature_code":"PPL",
    "gn:name":"Mingyeir",
    "gn:population":0,
    "gn:timezone":"Africa/Khartoum",
    "iso:country":"SD",
    "wof:name":"Mingyeir",
    "wof:placetype":"locality"
},
  "geometry": {"coordinates":[22.81667,12.85],"type":"Point"}
}