{
  "type": "Feature",
  "properties": {
    "gn:admin1_code":"47.0",
    "gn:asciiname":"Bardai",
    "gn:country_code":"SD",
    "gn:dem":637,
    "gn:feature_class":"P",
    "gn:feature_code":"PPL",
    "gn:name":"Bardai",
    "gn:population":0,
    "gn:timezone":"Africa/Khartoum",
    "iso:country":"SD",
    "wof:name":"Bardai",
    "wof:placetype":"locality"
},
  "geometry": {"coordinates":[21.88333,12.71667],"type":"Point"}
}