{
  "type": "Feature",
  "properties": {
    "gn:admin1_code":"55.0",
    "gn:asciiname":"Shaqq `Umar",
    "gn:country_code":"SD",
    "gn:dem":474,
    "gn:feature_class":"P",
    "gn:feature_code":"PPL",
    "gn:name":"Shaqq \u2018Umar",
    "gn:population":0,
    "gn:timezone":"Africa/Khartoum",
    "iso:country":"SD",
    "wof:name":"Shaqq `Umar",
    "wof:placetype":"locality"
},
  "geometry": {"coordinates":[26.96667,11.88333],"type":"Point"}
}