{
  "type": "Feature",
  "properties": {
    "gn:admin1_code":"53.0",
    "gn:asciiname":"Mwes",
    "gn:country_code":"SD",
    "gn:dem":366,
    "gn:feature_class":"P",
    "gn:feature_code":"PPL",
    "gn:name":"Mwes",
    "gn:population":0,
    "gn:timezone":"Africa/Khartoum",
    "iso:country":"SD",
    "wof:name":"Mwes",
    "wof:placetype":"locality"
},
  "geometry": {"coordinates":[33.3681,16.6694],"type":"Point"}
}