{
  "type": "Feature",
  "properties": {
    "gn:admin1_code":"53.0",
    "gn:asciiname":"Hillat el Kandarya",
    "gn:country_code":"SD",
    "gn:dem":372,
    "gn:feature_class":"P",
    "gn:feature_code":"PPL",
    "gn:name":"Hillat el Kandarya",
    "gn:population":0,
    "gn:timezone":"Africa/Khartoum",
    "iso:country":"SD",
    "wof:name":"Hillat el Kandarya",
    "wof:placetype":"locality"
},
  "geometry": {"coordinates":[32.8208,16.4491],"type":"Point"}
}