{
  "type": "Feature",
  "properties": {
    "gn:admin1_code":"50.0",
    "gn:asciiname":"Fakarin",
    "gn:country_code":"SD",
    "gn:dem":492,
    "gn:feature_class":"P",
    "gn:feature_code":"PPL",
    "gn:name":"Fak\u0101r\u012bn",
    "gn:population":0,
    "gn:timezone":"Africa/Khartoum",
    "iso:country":"SD",
    "name:und_x_variant":[
        "El Fakharin",
        "Al Fakharin",
        "Fak\u0101r\u012bn"
    ],
    "wof:lang_x_official":[
        "ara",
        "eng"
    ],
    "wof:lang_x_spoken":[
        "ara",
        "eng"
    ],
    "wof:name":"Fakarin",
    "wof:placetype":"locality"
},
  "geometry": {"coordinates":[31.2791,12.5884],"type":"Point"}
}