{
  "type": "Feature",
  "properties": {
    "gn:admin1_code":"42.0",
    "gn:asciiname":"Baqis",
    "gn:country_code":"SD",
    "gn:dem":557,
    "gn:feature_class":"P",
    "gn:feature_code":"PPL",
    "gn:name":"Baq\u012bs",
    "gn:population":0,
    "gn:timezone":"Africa/Khartoum",
    "iso:country":"SD",
    "name:und_x_variant":[
        "Baq\u012bs"
    ],
    "wof:name":"Baqis",
    "wof:placetype":"locality"
},
  "geometry": {"coordinates":[34.1847,11.5747],"type":"Point"}
}