{
  "type": "Feature",
  "properties": {
    "gn:admin1_code":"38.0",
    "gn:asciiname":"Tabbalat",
    "gn:country_code":"SD",
    "gn:dem":408,
    "gn:feature_class":"P",
    "gn:feature_code":"PPL",
    "gn:name":"Tabbalat",
    "gn:population":0,
    "gn:timezone":"Africa/Khartoum",
    "iso:country":"SD",
    "wof:name":"Tabbalat",
    "wof:placetype":"locality"
},
  "geometry": {"coordinates":[33.3033,14.3933],"type":"Point"}
}