{
  "type": "Feature",
  "properties": {
    "gn:admin1_code":"38.0",
    "gn:asciiname":"Qineda",
    "gn:country_code":"SD",
    "gn:dem":396,
    "gn:feature_class":"P",
    "gn:feature_code":"PPL",
    "gn:name":"Qineda",
    "gn:population":0,
    "gn:timezone":"Africa/Khartoum",
    "iso:country":"SD",
    "wof:name":"Qineda",
    "wof:placetype":"locality"
},
  "geometry": {"coordinates":[32.6421,14.147],"type":"Point"}
}