{
  "type": "Feature",
  "properties": {
    "gn:admin1_code":"38.0",
    "gn:asciiname":"Tabi",
    "gn:country_code":"SD",
    "gn:dem":390,
    "gn:feature_class":"P",
    "gn:feature_code":"PPL",
    "gn:name":"Tabi",
    "gn:population":0,
    "gn:timezone":"Africa/Khartoum",
    "iso:country":"SD",
    "wof:name":"Tabi",
    "wof:placetype":"locality"
},
  "geometry": {"coordinates":[33.2425,15.06556],"type":"Point"}
}