{
  "type": "Feature",
  "properties": {
    "gn:admin1_code":"43.0",
    "gn:asciiname":"Kosha",
    "gn:country_code":"SD",
    "gn:dem":193,
    "gn:feature_class":"P",
    "gn:feature_code":"PPL",
    "gn:name":"Kosha",
    "gn:population":0,
    "gn:timezone":"Africa/Khartoum",
    "iso:country":"SD",
    "wof:name":"Kosha",
    "wof:placetype":"locality"
},
  "geometry": {"coordinates":[30.54194,20.83056],"type":"Point"}
}