{
  "type": "Feature",
  "properties": {
    "gn:admin1_code":"43.0",
    "gn:asciiname":"Kosha",
    "gn:country_code":"SD",
    "gn:dem":193,
    "gn:feature_class":"P",
    "gn:feature_code":"PPL",
    "gn:name":"Kosha",
    "gn:population":0,
    "gn:timezone":"Africa/Khartoum",
    "iso:country":"SD",
    "name:bul_x_preferred":[
        "\u041a\u043e\u0448\u0430"
    ],
    "name:fra_x_preferred":[
        "Kosha"
    ],
    "name:hin_x_preferred":[
        "\u0915\u094b\u0937"
    ],
    "name:hun_x_preferred":[
        "K\u00f3sa"
    ],
    "name:ita_x_preferred":[
        "Kosha"
    ],
    "name:nld_x_preferred":[
        "Kosha"
    ],
    "name:nor_x_preferred":[
        "Koshaer"
    ],
    "name:pol_x_preferred":[
        "Pa\u0144\u0107ako\u015ba"
    ],
    "name:rus_x_preferred":[
        "\u041a\u043e\u0448\u0430"
    ],
    "name:zho_x_preferred":[
        "\u8ec0\u7789"
    ],
    "wof:name":"Kosha",
    "wof:placetype":"locality"
},
  "geometry": {"coordinates":[30.54194,20.83056],"type":"Point"}
}