{
  "type": "Feature",
  "properties": {
    "gn:admin1_code":"43.0",
    "gn:asciiname":"At Tur`ah",
    "gn:country_code":"SD",
    "gn:dem":225,
    "gn:feature_class":"P",
    "gn:feature_code":"PPL",
    "gn:name":"At Tur\u2018ah",
    "gn:population":0,
    "gn:timezone":"Africa/Khartoum",
    "iso:country":"SD",
    "name:und_x_variant":[
        "Et Tur\u2018a",
        "At Tur\u2018ah"
    ],
    "wof:lang_x_official":[
        "ara",
        "eng"
    ],
    "wof:lang_x_spoken":[
        "ara",
        "eng"
    ],
    "wof:name":"At Tur`ah",
    "wof:placetype":"locality"
},
  "geometry": {"coordinates":[30.46667,19.31667],"type":"Point"}
}