{
  "type": "Feature",
  "properties": {
    "gn:admin1_code":"61.0",
    "gn:asciiname":"Juguma",
    "gn:country_code":"SD",
    "gn:dem":641,
    "gn:feature_class":"P",
    "gn:feature_code":"PPL",
    "gn:name":"Juguma",
    "gn:population":0,
    "gn:timezone":"Africa/Khartoum",
    "iso:country":"SD",
    "wof:name":"Juguma",
    "wof:placetype":"locality"
},
  "geometry": {"coordinates":[22.76942,11.74016],"type":"Point"}
}