{
  "type": "Feature",
  "properties": {
    "gn:admin1_code":"61.0",
    "gn:asciiname":"Birganga",
    "gn:country_code":"SD",
    "gn:dem":806,
    "gn:feature_class":"P",
    "gn:feature_code":"PPL",
    "gn:name":"Birganga",
    "gn:population":0,
    "gn:timezone":"Africa/Khartoum",
    "iso:country":"SD",
    "wof:name":"Birganga",
    "wof:placetype":"locality"
},
  "geometry": {"coordinates":[23.14114,12.81655],"type":"Point"}
}