{
  "type": "Feature",
  "properties": {
    "gn:admin1_code":"47.0",
    "gn:asciiname":"Gundo",
    "gn:country_code":"SD",
    "gn:dem":843,
    "gn:feature_class":"P",
    "gn:feature_code":"PPL",
    "gn:name":"Gundo",
    "gn:population":0,
    "gn:timezone":"Africa/Khartoum",
    "iso:country":"SD",
    "name:eng_x_preferred":[
        "Gundo"
    ],
    "wof:name":"Gundo",
    "wof:placetype":"locality"
},
  "geometry": {"coordinates":[22.46923,13.24682],"type":"Point"}
}