{
  "type": "Feature",
  "properties": {
    "gn:admin1_code":"29.0",
    "gn:asciiname":"Umm Badda",
    "gn:country_code":"SD",
    "gn:dem":394,
    "gn:feature_class":"P",
    "gn:feature_code":"PPL",
    "gn:name":"Umm Badda",
    "gn:population":0,
    "gn:timezone":"Africa/Khartoum",
    "iso:country":"SD",
    "wof:name":"Umm Badda",
    "wof:placetype":"locality"
},
  "geometry": {"coordinates":[32.441,15.6599],"type":"Point"}
}