{
  "type": "Feature",
  "properties": {
    "gn:admin1_code":"53.0",
    "gn:asciiname":"Hillat Tartor",
    "gn:country_code":"SD",
    "gn:dem":363,
    "gn:feature_class":"P",
    "gn:feature_code":"PPL",
    "gn:name":"Hillat Tartor",
    "gn:population":0,
    "gn:timezone":"Africa/Khartoum",
    "iso:country":"SD",
    "wof:name":"Hillat Tartor",
    "wof:placetype":"locality"
},
  "geometry": {"coordinates":[33.5551,16.7103],"type":"Point"}
}