{
  "type": "Feature",
  "properties": {
    "gn:admin1_code":"49.0",
    "gn:asciiname":"Rabatet",
    "gn:country_code":"SD",
    "gn:dem":491,
    "gn:feature_class":"P",
    "gn:feature_code":"PPL",
    "gn:name":"Rabatet",
    "gn:population":0,
    "gn:timezone":"Africa/Khartoum",
    "iso:country":"SD",
    "wof:name":"Rabatet",
    "wof:placetype":"locality"
},
  "geometry": {"coordinates":[24.8381,10.70796],"type":"Point"}
}