{
  "type": "Feature",
  "properties": {
    "gn:admin1_code":"41.0",
    "gn:asciiname":"Al Maslaha",
    "gn:country_code":"SD",
    "gn:dem":382,
    "gn:feature_class":"P",
    "gn:feature_code":"PPL",
    "gn:name":"Al Ma\u015fla\u1e29a",
    "gn:population":0,
    "gn:timezone":"Africa/Khartoum",
    "iso:country":"SD",
    "name:und_x_variant":[
        "Al Ma\u015fla\u1e29a"
    ],
    "wof:name":"Al Maslaha",
    "wof:placetype":"locality"
},
  "geometry": {"coordinates":[32.4314,13.5768],"type":"Point"}
}