{
  "type": "Feature",
  "properties": {
    "gn:admin1_code":"61.0",
    "gn:asciiname":"Kabira",
    "gn:country_code":"SD",
    "gn:dem":633,
    "gn:feature_class":"P",
    "gn:feature_code":"PPL",
    "gn:name":"Kabira",
    "gn:population":0,
    "gn:timezone":"Africa/Khartoum",
    "iso:country":"SD",
    "name:ceb_x_preferred":[
        "Kabira"
    ],
    "name:swe_x_preferred":[
        "Kabira"
    ],
    "name:und_x_variant":[
        "Kab\u012brah"
    ],
    "wof:name":"Kabira",
    "wof:placetype":"locality"
},
  "geometry": {"coordinates":[22.69406,12.50962],"type":"Point"}
}