{
  "type": "Feature",
  "properties": {
    "gn:admin1_code":"52.0",
    "gn:asciiname":"Qaryah Ithnan",
    "gn:country_code":"SD",
    "gn:dem":462,
    "gn:feature_class":"P",
    "gn:feature_code":"PPL",
    "gn:name":"Qaryah Ithn\u0101n",
    "gn:population":0,
    "gn:timezone":"Africa/Khartoum",
    "iso:country":"SD",
    "name:und_x_variant":[
        "Qaryah Ithn\u0101n"
    ],
    "wof:name":"Qaryah Ithnan",
    "wof:placetype":"locality"
},
  "geometry": {"coordinates":[35.6938,15.1501],"type":"Point"}
}