{
  "type": "Feature",
  "properties": {
    "gn:admin1_code":"50.0",
    "gn:asciiname":"Dar aj Jam",
    "gn:country_code":"SD",
    "gn:dem":558,
    "gn:feature_class":"P",
    "gn:feature_code":"PPL",
    "gn:name":"D\u0101r aj Jam",
    "gn:population":0,
    "gn:timezone":"Africa/Khartoum",
    "iso:country":"SD",
    "name:und_x_variant":[
        "D\u0101r aj Jam"
    ],
    "wof:name":"Dar aj Jam",
    "wof:placetype":"locality"
},
  "geometry": {"coordinates":[31.5865,11.6768],"type":"Point"}
}