{
  "type": "Feature",
  "properties": {
    "gn:admin1_code":"41.0",
    "gn:asciiname":"Wad Jami`",
    "gn:country_code":"SD",
    "gn:dem":394,
    "gn:feature_class":"P",
    "gn:feature_code":"PPL",
    "gn:name":"Wad J\u0101mi\u2018",
    "gn:population":0,
    "gn:timezone":"Africa/Khartoum",
    "iso:country":"SD",
    "name:und_x_variant":[
        "Wad J\u0101mi\u2018"
    ],
    "wof:name":"Wad Jami`",
    "wof:placetype":"locality"
},
  "geometry": {"coordinates":[32.0865,13.6231],"type":"Point"}
}