{
  "type": "Feature",
  "properties": {
    "gn:admin1_code":"47.0",
    "gn:asciiname":"Cherro",
    "gn:country_code":"SD",
    "gn:dem":701,
    "gn:feature_class":"P",
    "gn:feature_code":"PPL",
    "gn:name":"Cherro",
    "gn:population":0,
    "gn:timezone":"Africa/Khartoum",
    "iso:country":"SD",
    "name:eng_x_preferred":[
        "Cherro"
    ],
    "wof:name":"Cherro",
    "wof:placetype":"locality"
},
  "geometry": {"coordinates":[22.11468,12.73242],"type":"Point"}
}