{
  "type": "Feature",
  "properties": {
    "gn:admin1_code":"50.0",
    "gn:asciiname":"Tarambal",
    "gn:country_code":"SD",
    "gn:dem":657,
    "gn:feature_class":"P",
    "gn:feature_code":"PPL",
    "gn:name":"Tarambal",
    "gn:population":0,
    "gn:timezone":"Africa/Khartoum",
    "iso:country":"SD",
    "wof:name":"Tarambal",
    "wof:placetype":"locality"
},
  "geometry": {"coordinates":[31.0583,11.6303],"type":"Point"}
}