{
  "type": "Feature",
  "properties": {
    "gn:admin1_code":"55.0",
    "gn:asciiname":"Sitteib",
    "gn:country_code":"SD",
    "gn:dem":871,
    "gn:feature_class":"P",
    "gn:feature_code":"PPL",
    "gn:name":"Sitteib",
    "gn:population":0,
    "gn:timezone":"Africa/Khartoum",
    "iso:country":"SD",
    "wof:name":"Sitteib",
    "wof:placetype":"locality"
},
  "geometry": {"coordinates":[22.91251,14.52104],"type":"Point"}
}