{
  "type": "Feature",
  "properties": {
    "gn:admin1_code":"50.0",
    "gn:asciiname":"Al Hafira Shariq",
    "gn:country_code":"SD",
    "gn:dem":494,
    "gn:feature_class":"P",
    "gn:feature_code":"PPL",
    "gn:name":"Al Haf\u012bra Shariq",
    "gn:population":0,
    "gn:timezone":"Africa/Khartoum",
    "iso:country":"SD",
    "name:und_x_variant":[
        "Al Haf\u012bra Shariq"
    ],
    "wof:name":"Al Hafira Shariq",
    "wof:placetype":"locality"
},
  "geometry": {"coordinates":[31.5111,12.4544],"type":"Point"}
}