{
  "type": "Feature",
  "properties": {
    "gn:admin1_code":"41.0",
    "gn:asciiname":"Um Kiweka",
    "gn:country_code":"SD",
    "gn:dem":424,
    "gn:feature_class":"P",
    "gn:feature_code":"PPL",
    "gn:name":"Um Kiweka",
    "gn:population":0,
    "gn:timezone":"Africa/Khartoum",
    "iso:country":"SD",
    "name:und_x_variant":[
        "Umm Koweika",
        "Umm Kuwaykah",
        "Um Kiweka"
    ],
    "wof:lang_x_official":[
        "ara",
        "eng"
    ],
    "wof:lang_x_spoken":[
        "ara",
        "eng"
    ],
    "wof:name":"Um Kiweka",
    "wof:placetype":"locality"
},
  "geometry": {"coordinates":[31.8707,12.8057],"type":"Point"}
}