{
  "type": "Feature",
  "properties": {
    "gn:admin1_code":"55.0",
    "gn:asciiname":"Kabga",
    "gn:country_code":"SD",
    "gn:dem":739,
    "gn:feature_class":"P",
    "gn:feature_code":"PPL",
    "gn:name":"Kabga",
    "gn:population":0,
    "gn:timezone":"Africa/Khartoum",
    "iso:country":"SD",
    "wof:name":"Kabga",
    "wof:placetype":"locality"
},
  "geometry": {"coordinates":[25.26667,13.25],"type":"Point"}
}