{
  "type": "Feature",
  "properties": {
    "gn:admin1_code":"53.0",
    "gn:asciiname":"Wadi Bushara",
    "gn:country_code":"SD",
    "gn:dem":371,
    "gn:feature_class":"P",
    "gn:feature_code":"PPL",
    "gn:name":"Wadi Bushara",
    "gn:population":0,
    "gn:timezone":"Africa/Khartoum",
    "iso:country":"SD",
    "wof:name":"Wadi Bushara",
    "wof:placetype":"locality"
},
  "geometry": {"coordinates":[32.71056,16.39528],"type":"Point"}
}