{
  "type": "Feature",
  "properties": {
    "gn:admin1_code":"49.0",
    "gn:asciiname":"Umm Kurdus",
    "gn:country_code":"SD",
    "gn:dem":576,
    "gn:feature_class":"P",
    "gn:feature_code":"PPL",
    "gn:name":"Umm Kurd\u016bs",
    "gn:population":0,
    "gn:timezone":"Africa/Khartoum",
    "iso:country":"SD",
    "name:und_x_variant":[
        "Umm Kardus",
        "Umm Kurd\u016bs"
    ],
    "wof:name":"Umm Kurdus",
    "wof:placetype":"locality"
},
  "geometry": {"coordinates":[25.18333,11.98333],"type":"Point"}
}