{
  "type": "Feature",
  "properties": {
    "gn:country":"SD",
    "gn:fcode":"PPL",
    "gn:pop":9038,
    "iso:country":"SD",
    "name:unk_x_variant":[
        "Umm Garr"
    ],
    "qs:name":"Um Jar Al Gharbiyya",
    "qs:photos_9r":0,
    "qs:photos_sr":0,
    "qs:pop_sr":"5",
    "wof:name":"Um Jar Al Gharbiyya",
    "wof:placetype":"locality",
    "wof:population":9038
},
  "geometry": {"coordinates":[32.4078,13.8013],"type":"Point"}
}