{
  "type": "Feature",
  "properties": {
    "gn:admin1_code":"58.0",
    "gn:asciiname":"Ash Shaykh Hajju",
    "gn:country_code":"SD",
    "gn:dem":438,
    "gn:feature_class":"P",
    "gn:feature_code":"PPL",
    "gn:name":"Ash Shaykh \u1e28\u0101jj\u016b",
    "gn:population":0,
    "gn:timezone":"Africa/Khartoum",
    "iso:country":"SD",
    "name:und_x_variant":[
        "Esh Sheikh Hagu",
        "Ash Shaykh \u1e28\u0101jj\u016b"
    ],
    "wof:lang_x_official":[
        "ara",
        "eng"
    ],
    "wof:lang_x_spoken":[
        "ara",
        "eng"
    ],
    "wof:name":"Ash Shaykh Hajju",
    "wof:placetype":"locality"
},
  "geometry": {"coordinates":[33.45,13.71667],"type":"Point"}
}