{
  "type": "Feature",
  "properties": {
    "gn:admin1_code":"41.0",
    "gn:asciiname":"Abu Ghanim",
    "gn:country_code":"SD",
    "gn:dem":393,
    "gn:feature_class":"P",
    "gn:feature_code":"PPL",
    "gn:name":"Abu Ghan\u012bm",
    "gn:population":0,
    "gn:timezone":"Africa/Khartoum",
    "iso:country":"SD",
    "name:und_x_variant":[
        "Abu Ghan\u012bm"
    ],
    "wof:name":"Abu Ghanim",
    "wof:placetype":"locality"
},
  "geometry": {"coordinates":[32.4215,14.7211],"type":"Point"}
}