{
  "type": "Feature",
  "properties": {
    "gn:admin1_code":"41.0",
    "gn:asciiname":"Dabbat at Tar",
    "gn:country_code":"SD",
    "gn:dem":388,
    "gn:feature_class":"P",
    "gn:feature_code":"PPL",
    "gn:name":"Dabbat at T\u0101r",
    "gn:population":0,
    "gn:timezone":"Africa/Khartoum",
    "iso:country":"SD",
    "name:und_x_variant":[
        "Dabbat at T\u0101r"
    ],
    "wof:name":"Dabbat at Tar",
    "wof:placetype":"locality"
},
  "geometry": {"coordinates":[32.7282,12.1295],"type":"Point"}
}