{
  "type": "Feature",
  "properties": {
    "gn:admin1_code":"61.0",
    "gn:asciiname":"Turunga",
    "gn:country_code":"SD",
    "gn:dem":1015,
    "gn:feature_class":"P",
    "gn:feature_code":"PPL",
    "gn:name":"Turunga",
    "gn:population":0,
    "gn:timezone":"Africa/Khartoum",
    "iso:country":"SD",
    "wof:name":"Turunga",
    "wof:placetype":"locality"
},
  "geometry": {"coordinates":[23.75853,13.44022],"type":"Point"}
}