{
  "type": "Feature",
  "properties": {
    "gn:admin1_code":"56.0",
    "gn:asciiname":"Hasab al Karim",
    "gn:country_code":"SD",
    "gn:dem":572,
    "gn:feature_class":"P",
    "gn:feature_code":"PPL",
    "gn:name":"\u1e28asab al Kar\u012bm",
    "gn:population":0,
    "gn:timezone":"Africa/Khartoum",
    "iso:country":"SD",
    "name:und_x_variant":[
        "Hasab el Karim",
        "\u1e28asab al Kar\u012bm"
    ],
    "wof:lang_x_official":[
        "ara",
        "eng"
    ],
    "wof:lang_x_spoken":[
        "ara",
        "eng"
    ],
    "wof:name":"Hasab al Karim",
    "wof:placetype":"locality"
},
  "geometry": {"coordinates":[29.56667,13.65],"type":"Point"}
}