{
  "type": "Feature",
  "properties": {
    "gn:admin1_code":"49.0",
    "gn:asciiname":"Koringo",
    "gn:country_code":"SD",
    "gn:dem":1071,
    "gn:feature_class":"P",
    "gn:feature_code":"PPL",
    "gn:name":"Koringo",
    "gn:population":0,
    "gn:timezone":"Africa/Khartoum",
    "iso:country":"SD",
    "wof:name":"Koringo",
    "wof:placetype":"locality"
},
  "geometry": {"coordinates":[23.85,12.71667],"type":"Point"}
}