{
  "type": "Feature",
  "properties": {
    "gn:admin1_code":"42.0",
    "gn:asciiname":"Faraj Allah Abu Kura`",
    "gn:country_code":"SD",
    "gn:dem":492,
    "gn:feature_class":"P",
    "gn:feature_code":"PPL",
    "gn:name":"Faraj All\u0101h Ab\u016b Kur\u0101\u2018",
    "gn:population":0,
    "gn:timezone":"Africa/Khartoum",
    "iso:country":"SD",
    "name:eng_x_preferred":[
        "Faragullah Abu Kura\u2018"
    ],
    "name:und_x_variant":[
        "Faraj All\u0101h Ab\u016b Kur\u0101\u2018"
    ],
    "wof:name":"Faraj Allah Abu Kura`",
    "wof:placetype":"locality"
},
  "geometry": {"coordinates":[33.91319,10.18959],"type":"Point"}
}