{
  "type": "Feature",
  "properties": {
    "gn:admin1_code":"49.0",
    "gn:asciiname":"Tirba",
    "gn:country_code":"SD",
    "gn:dem":2172,
    "gn:feature_class":"P",
    "gn:feature_code":"PPL",
    "gn:name":"Tirba",
    "gn:population":0,
    "gn:timezone":"Africa/Khartoum",
    "iso:country":"SD",
    "wof:name":"Tirba",
    "wof:placetype":"locality"
},
  "geometry": {"coordinates":[24.28664,12.91528],"type":"Point"}
}