{
  "type": "Feature",
  "properties": {
    "gn:admin1_code":"41.0",
    "gn:asciiname":"Um Arkha",
    "gn:country_code":"SD",
    "gn:dem":421,
    "gn:feature_class":"P",
    "gn:feature_code":"PPL",
    "gn:name":"Um Arkha",
    "gn:population":0,
    "gn:timezone":"Africa/Khartoum",
    "iso:country":"SD",
    "wof:name":"Um Arkha",
    "wof:placetype":"locality"
},
  "geometry": {"coordinates":[31.8374,12.7764],"type":"Point"}
}