{
  "type": "Feature",
  "properties": {
    "gn:admin1_code":"50.0",
    "gn:asciiname":"Tase `Abd Assalam",
    "gn:country_code":"SD",
    "gn:dem":670,
    "gn:feature_class":"P",
    "gn:feature_code":"PPL",
    "gn:name":"T\u0101s\u0113 \u2018Abd Assal\u0101m",
    "gn:population":0,
    "gn:timezone":"Africa/Khartoum",
    "iso:country":"SD",
    "name:und_x_variant":[
        "Tays\u012b \u2018Abd as Sal\u0101m",
        "Teisi \u2018Abd es Salam",
        "T\u0101s\u0113 \u2018Abd Assal\u0101m"
    ],
    "wof:lang_x_official":[
        "ara",
        "eng"
    ],
    "wof:lang_x_spoken":[
        "ara",
        "eng"
    ],
    "wof:name":"Tase `Abd Assalam",
    "wof:placetype":"locality"
},
  "geometry": {"coordinates":[29.76472,11.11778],"type":"Point"}
}