{
  "type": "Feature",
  "properties": {
    "gn:admin1_code":"49.0",
    "gn:asciiname":"Kulli",
    "gn:country_code":"SD",
    "gn:dem":1328,
    "gn:feature_class":"P",
    "gn:feature_code":"PPL",
    "gn:name":"Kulli",
    "gn:population":0,
    "gn:timezone":"Africa/Khartoum",
    "iso:country":"SD",
    "name:ceb_x_preferred":[
        "Kulli"
    ],
    "name:ces_x_preferred":[
        "Kulli"
    ],
    "name:est_x_preferred":[
        "Kulli"
    ],
    "name:fin_x_preferred":[
        "Kulli"
    ],
    "name:nld_x_preferred":[
        "Kulli"
    ],
    "name:pol_x_preferred":[
        "Kulli"
    ],
    "name:spa_x_preferred":[
        "Kulli"
    ],
    "name:ukr_x_preferred":[
        "\u041a\u0443\u043b\u043b\u0456"
    ],
    "name:vol_x_preferred":[
        "Kulli"
    ],
    "wof:name":"Kulli",
    "wof:placetype":"locality"
},
  "geometry": {"coordinates":[24.47136,12.78947],"type":"Point"}
}