{
  "type": "Feature",
  "properties": {
    "gn:admin1_code":"38.0",
    "gn:asciiname":"Salim",
    "gn:country_code":"SD",
    "gn:dem":398,
    "gn:feature_class":"P",
    "gn:feature_code":"PPL",
    "gn:name":"Sal\u012bm",
    "gn:population":0,
    "gn:timezone":"Africa/Khartoum",
    "iso:country":"SD",
    "name:ita_x_preferred":[
        "Salim"
    ],
    "name:und_x_variant":[
        "Sal\u012bm"
    ],
    "wof:name":"Salim",
    "wof:placetype":"locality"
},
  "geometry": {"coordinates":[32.9564,14.8864],"type":"Point"}
}