{
  "type": "Feature",
  "properties": {
    "gn:admin1_code":"56.0",
    "gn:asciiname":"Umm Dawmah",
    "gn:country_code":"SD",
    "gn:dem":589,
    "gn:feature_class":"P",
    "gn:feature_code":"PPL",
    "gn:name":"Umm Dawmah",
    "gn:population":0,
    "gn:timezone":"Africa/Khartoum",
    "iso:country":"SD",
    "name:und_x_variant":[
        "Umm Doma",
        "Umm Dawmah"
    ],
    "wof:name":"Umm Dawmah",
    "wof:placetype":"locality"
},
  "geometry": {"coordinates":[30.05,13.16667],"type":"Point"}
}