{
  "type": "Feature",
  "properties": {
    "gn:admin1_code":"38.0",
    "gn:asciiname":"Al Kiter",
    "gn:country_code":"SD",
    "gn:dem":401,
    "gn:feature_class":"P",
    "gn:feature_code":"PPL",
    "gn:name":"Al Kiter",
    "gn:population":0,
    "gn:timezone":"Africa/Khartoum",
    "iso:country":"SD",
    "wof:name":"Al Kiter",
    "wof:placetype":"locality"
},
  "geometry": {"coordinates":[32.7997,14.4597],"type":"Point"}
}