{
  "type": "Feature",
  "properties": {
    "gn:admin1_code":"38.0",
    "gn:asciiname":"Kitrah",
    "gn:country_code":"SD",
    "gn:dem":400,
    "gn:feature_class":"P",
    "gn:feature_code":"PPL",
    "gn:name":"Kitrah",
    "gn:population":0,
    "gn:timezone":"Africa/Khartoum",
    "iso:country":"SD",
    "name:und_x_variant":[
        "Kitra",
        "Kitrah"
    ],
    "wof:name":"Kitrah",
    "wof:placetype":"locality"
},
  "geometry": {"coordinates":[32.68333,14.38333],"type":"Point"}
}