{
  "type": "Feature",
  "properties": {
    "gn:admin1_code":"58.0",
    "gn:asciiname":"At Tawfiqiyya",
    "gn:country_code":"SD",
    "gn:dem":443,
    "gn:feature_class":"P",
    "gn:feature_code":"PPL",
    "gn:name":"At Tawf\u012bqiyya",
    "gn:population":0,
    "gn:timezone":"Africa/Khartoum",
    "iso:country":"SD",
    "name:und_x_variant":[
        "At Tawf\u012bqiyya"
    ],
    "wof:name":"At Tawfiqiyya",
    "wof:placetype":"locality"
},
  "geometry": {"coordinates":[33.9885,12.9459],"type":"Point"}
}