{
  "type": "Feature",
  "properties": {
    "gn:admin1_code":"38.0",
    "gn:asciiname":"Al Basatna",
    "gn:country_code":"SD",
    "gn:dem":412,
    "gn:feature_class":"P",
    "gn:feature_code":"PPL",
    "gn:name":"Al Bas\u0101tna",
    "gn:population":0,
    "gn:timezone":"Africa/Khartoum",
    "iso:country":"SD",
    "name:und_x_variant":[
        "Rasatna",
        "Al Bas\u0101tna"
    ],
    "wof:name":"Al Basatna",
    "wof:placetype":"locality"
},
  "geometry": {"coordinates":[33.4446,14.3815],"type":"Point"}
}