{
  "type": "Feature",
  "properties": {
    "gn:admin1_code":"42.0",
    "gn:asciiname":"Ad Doha Fallata",
    "gn:country_code":"SD",
    "gn:dem":455,
    "gn:feature_class":"P",
    "gn:feature_code":"PPL",
    "gn:name":"Ad Do\u1e29a Fall\u0101ta",
    "gn:population":0,
    "gn:timezone":"Africa/Khartoum",
    "iso:country":"SD",
    "name:und_x_variant":[
        "Ad Do\u1e29a Fall\u0101ta"
    ],
    "wof:lang_x_official":[
        "ara",
        "eng"
    ],
    "wof:lang_x_spoken":[
        "ara",
        "eng"
    ],
    "wof:name":"Ad Doha Fallata",
    "wof:placetype":"locality"
},
  "geometry": {"coordinates":[34.3273,12.0427],"type":"Point"}
}