{
  "type": "Feature",
  "properties": {
    "gn:admin1_code":"29.0",
    "gn:asciiname":"Faki `Abd ar Rahman",
    "gn:country_code":"SD",
    "gn:dem":387,
    "gn:feature_class":"P",
    "gn:feature_code":"PPL",
    "gn:name":"Fak\u012b \u2018Abd ar Ra\u1e29m\u0101n",
    "gn:population":0,
    "gn:timezone":"Africa/Khartoum",
    "iso:country":"SD",
    "name:und_x_variant":[
        "Faki \u2018Abd er Rahman",
        "Fak\u012b \u2018Abd ar Ra\u1e29m\u0101n"
    ],
    "wof:name":"Faki `Abd ar Rahman",
    "wof:placetype":"locality"
},
  "geometry": {"coordinates":[32.56667,15.36667],"type":"Point"}
}