{
  "type": "Feature",
  "properties": {
    "gn:admin1_code":"39.0",
    "gn:asciiname":"Wad Abu Nahl",
    "gn:country_code":"SD",
    "gn:dem":458,
    "gn:feature_class":"P",
    "gn:feature_code":"PPL",
    "gn:name":"Wad Ab\u016b Na\u1e29l",
    "gn:population":0,
    "gn:timezone":"Africa/Khartoum",
    "iso:country":"SD",
    "wof:name":"Wad Abu Nahl",
    "wof:placetype":"locality"
},
  "geometry": {"coordinates":[34.93333,13.13333],"type":"Point"}
}