{
  "type": "Feature",
  "properties": {
    "gn:admin1_code":"56.0",
    "gn:asciiname":"Tayba",
    "gn:country_code":"SD",
    "gn:dem":461,
    "gn:feature_class":"P",
    "gn:feature_code":"PPL",
    "gn:name":"\u0162ayba",
    "gn:population":0,
    "gn:timezone":"Africa/Khartoum",
    "iso:country":"SD",
    "name:und_x_variant":[
        "Et Taiyiba",
        "Taiyiba",
        "A\u0163 \u0162ayyibah",
        "\u0162ayba"
    ],
    "wof:name":"Tayba",
    "wof:placetype":"locality"
},
  "geometry": {"coordinates":[31.2172,12.8024],"type":"Point"}
}