{
  "type": "Feature",
  "properties": {
    "gn:admin1_code":"38.0",
    "gn:asciiname":"Al Miheriba",
    "gn:country_code":"SD",
    "gn:dem":399,
    "gn:feature_class":"P",
    "gn:feature_code":"PPL",
    "gn:name":"Al Mi\u1e29er\u012bba",
    "gn:population":0,
    "gn:timezone":"Africa/Khartoum",
    "iso:country":"SD",
    "name:und_x_variant":[
        "Meheiriba",
        "Al Mi\u1e29er\u012bba"
    ],
    "wof:name":"Al Miheriba",
    "wof:placetype":"locality"
},
  "geometry": {"coordinates":[33.0233,14.8385],"type":"Point"}
}