{
  "type": "Feature",
  "properties": {
    "gn:admin1_code":"38.0",
    "gn:asciiname":"Al Qiwez",
    "gn:country_code":"SD",
    "gn:dem":407,
    "gn:feature_class":"P",
    "gn:feature_code":"PPL",
    "gn:name":"Al Qiwez",
    "gn:population":0,
    "gn:timezone":"Africa/Khartoum",
    "iso:country":"SD",
    "name:und_x_variant":[
        "Qoz Muheina",
        "Qawz Muheina",
        "Al Qiwez"
    ],
    "wof:name":"Al Qiwez",
    "wof:placetype":"locality"
},
  "geometry": {"coordinates":[33.0512,14.2861],"type":"Point"}
}