{
  "type": "Feature",
  "properties": {
    "gn:admin1_code":"41.0",
    "gn:asciiname":"As Sinetaya",
    "gn:country_code":"SD",
    "gn:dem":423,
    "gn:feature_class":"P",
    "gn:feature_code":"PPL",
    "gn:name":"A\u1e63 \u1e62ine\u0163aya",
    "gn:population":0,
    "gn:timezone":"Africa/Khartoum",
    "iso:country":"SD",
    "name:und_x_variant":[
        "A\u1e63 \u1e62ine\u0163aya"
    ],
    "wof:lang_x_official":[
        "ara",
        "eng"
    ],
    "wof:lang_x_spoken":[
        "ara",
        "eng"
    ],
    "wof:name":"As Sinetaya",
    "wof:placetype":"locality"
},
  "geometry": {"coordinates":[31.8947,12.6913],"type":"Point"}
}