{
  "type": "Feature",
  "properties": {
    "gn:country":"SD",
    "gn:fcode":"PPLA",
    "gn:pop":44626,
    "iso:country":"SD",
    "name:ara_x_preferred":[
        "\u0633\u0646\u062c\u0629"
    ],
    "name:ben_x_preferred":[
        "\u09b8\u09bf\u09a8\u0997\u09be"
    ],
    "name:dan_x_preferred":[
        "Singa"
    ],
    "name:ell_x_preferred":[
        "\u03a3\u03af\u03bd\u03b3\u03ba\u03b1"
    ],
    "name:eng_x_preferred":[
        "Singa"
    ],
    "name:fas_x_preferred":[
        "\u0633\u0646\u062c\u0647"
    ],
    "name:fin_x_preferred":[
        "Singa"
    ],
    "name:fra_x_preferred":[
        "Singa"
    ],
    "name:guj_x_preferred":[
        "\u0ab8\u0abf\u0a82\u0a97\u0abe"
    ],
    "name:hin_x_preferred":[
        "\u0938\u093f\u0902\u0917\u093e"
    ],
    "name:ind_x_preferred":[
        "Singa"
    ],
    "name:ita_x_preferred":[
        "Singa"
    ],
    "name:jpn_x_preferred":[
        "\u30b7\u30f3\u30ac"
    ],
    "name:kan_x_preferred":[
        "\u0cb8\u0cbf\u0c82\u0c97"
    ],
    "name:kor_x_preferred":[
        "\uc2e0\uac00"
    ],
    "name:lav_x_preferred":[
        "Singa"
    ],
    "name:lit_x_preferred":[
        "Singa"
    ],
    "name:mar_x_preferred":[
        "\u0938\u093f\u0902\u0917"
    ],
    "name:msa_x_preferred":[
        "Singa"
    ],
    "name:nld_x_preferred":[
        "Singa"
    ],
    "name:nob_x_preferred":[
        "Singa"
    ],
    "name:pol_x_preferred":[
        "Singa"
    ],
    "name:por_x_preferred":[
        "Singa"
    ],
    "name:rus_x_preferred":[
        "\u0421\u0438\u043d\u0434\u0436\u0430"
    ],
    "name:sin_x_preferred":[
        "\u0dc3\u0dd2\u0db1\u0dca\u0d9c\u0dcf"
    ],
    "name:spa_x_preferred":[
        "Singa"
    ],
    "name:swe_x_preferred":[
        "Singa"
    ],
    "name:tam_x_preferred":[
        "\u0b9a\u0bbf\u0ba9\u0bcd\u0b95\u0bbe"
    ],
    "name:tel_x_preferred":[
        "\u0c38\u0c3f\u0c02\u0c17"
    ],
    "name:tha_x_preferred":[
        "\u0e0b\u0e34\u0e19\u0e01\u0e32"
    ],
    "name:tur_x_preferred":[
        "Singa"
    ],
    "name:ukr_x_preferred":[
        "\u0421\u0456\u043d\u0434\u0436\u0430"
    ],
    "name:unk_x_variant":[
        "Singa"
    ],
    "name:urd_x_preferred":[
        "\u0633\u0646\u06af\u06be\u0627"
    ],
    "name:vie_x_preferred":[
        "Singa"
    ],
    "qs:name":"Sinja",
    "qs:photos_9r":0,
    "qs:photos_sr":0,
    "qs:pop_sr":"7",
    "wd:wordcount":297,
    "wof:name":"Sinja",
    "wof:placetype":"locality",
    "wof:population":44626
},
  "geometry": {"coordinates":[33.93333,13.15],"type":"Point"}
}