{
  "type": "Feature",
  "properties": {
    "gn:admin1_code":"61.0",
    "gn:asciiname":"Sawala Magella",
    "gn:country_code":"SD",
    "gn:dem":1058,
    "gn:feature_class":"P",
    "gn:feature_code":"PPL",
    "gn:name":"Sawala Magella",
    "gn:population":0,
    "gn:timezone":"Africa/Khartoum",
    "iso:country":"SD",
    "wof:name":"Sawala Magella",
    "wof:placetype":"locality"
},
  "geometry": {"coordinates":[23.95574,13.12155],"type":"Point"}
}