{
  "type": "Feature",
  "properties": {
    "gn:admin1_code":"47.0",
    "gn:asciiname":"Dukeit",
    "gn:country_code":"SD",
    "gn:dem":810,
    "gn:feature_class":"P",
    "gn:feature_code":"PPL",
    "gn:name":"Dukeit",
    "gn:population":0,
    "gn:timezone":"Africa/Khartoum",
    "iso:country":"SD",
    "name:eng_x_preferred":[
        "Dukeit"
    ],
    "wof:name":"Dukeit",
    "wof:placetype":"locality"
},
  "geometry": {"coordinates":[22.23303,13.50106],"type":"Point"}
}