{
  "type": "Feature",
  "properties": {
    "gn:admin1_code":"41.0",
    "gn:asciiname":"As Sa`ada",
    "gn:country_code":"SD",
    "gn:dem":387,
    "gn:feature_class":"P",
    "gn:feature_code":"PPL",
    "gn:name":"As Sa\u2018ada",
    "gn:population":0,
    "gn:timezone":"Africa/Khartoum",
    "iso:country":"SD",
    "name:und_x_variant":[
        "As Sa\u2018ada"
    ],
    "wof:name":"As Sa`ada",
    "wof:placetype":"locality"
},
  "geometry": {"coordinates":[32.7828,12.5124],"type":"Point"}
}