{
  "type": "Feature",
  "properties": {
    "gn:admin1_code":"55.0",
    "gn:asciiname":"Minamara",
    "gn:country_code":"SD",
    "gn:dem":1131,
    "gn:feature_class":"P",
    "gn:feature_code":"PPL",
    "gn:name":"Minamara",
    "gn:population":0,
    "gn:timezone":"Africa/Khartoum",
    "iso:country":"SD",
    "wof:name":"Minamara",
    "wof:placetype":"locality"
},
  "geometry": {"coordinates":[25.06667,14.61667],"type":"Point"}
}