{
  "type": "Feature",
  "properties": {
    "gn:admin1_code":"53.0",
    "gn:asciiname":"Al Buqayr",
    "gn:cc2":"SD",
    "gn:country_code":"SD",
    "gn:dem":359,
    "gn:feature_class":"P",
    "gn:feature_code":"PPL",
    "gn:name":"Al Buqayr",
    "gn:population":0,
    "gn:timezone":"Africa/Khartoum",
    "iso:country":"SD",
    "name:und_x_variant":[
        "El Baqeir",
        "Al Buqayr"
    ],
    "wof:name":"Al Buqayr",
    "wof:placetype":"locality"
},
  "geometry": {"coordinates":[33.85,17.35],"type":"Point"}
}