{
  "type": "Feature",
  "properties": {
    "gn:admin1_code":"41.0",
    "gn:asciiname":"Wad Al Bilebli",
    "gn:country_code":"SD",
    "gn:dem":420,
    "gn:feature_class":"P",
    "gn:feature_code":"PPL",
    "gn:name":"Wad Al Bilebli",
    "gn:population":0,
    "gn:timezone":"Africa/Khartoum",
    "iso:country":"SD",
    "wof:name":"Wad Al Bilebli",
    "wof:placetype":"locality"
},
  "geometry": {"coordinates":[31.8304,12.8981],"type":"Point"}
}