{
  "type": "Feature",
  "properties": {
    "gn:admin1_code":"38.0",
    "gn:asciiname":"Wad Maknun",
    "gn:country_code":"SD",
    "gn:dem":407,
    "gn:feature_class":"P",
    "gn:feature_code":"PPL",
    "gn:name":"Wad Makn\u016bn",
    "gn:population":0,
    "gn:timezone":"Africa/Khartoum",
    "iso:country":"SD",
    "name:und_x_variant":[
        "Wad Magnun",
        "Wad Majn\u016bn",
        "Wad Makn\u016bn"
    ],
    "wof:name":"Wad Maknun",
    "wof:placetype":"locality"
},
  "geometry": {"coordinates":[33.1268,14.4589],"type":"Point"}
}