{
  "type": "Feature",
  "properties": {
    "gn:admin1_code":"53.0",
    "gn:asciiname":"Hosh ed Dar",
    "gn:country_code":"SD",
    "gn:dem":348,
    "gn:feature_class":"P",
    "gn:feature_code":"PPL",
    "gn:name":"Hosh ed Dar",
    "gn:population":0,
    "gn:timezone":"Africa/Khartoum",
    "iso:country":"SD",
    "name:und_x_variant":[
        "\u1e28awsh ad D\u0101r"
    ],
    "wof:name":"Hosh ed Dar",
    "wof:placetype":"locality"
},
  "geometry": {"coordinates":[33.98718,18.03685],"type":"Point"}
}