{
  "type": "Feature",
  "properties": {
    "gn:admin1_code":"52.0",
    "gn:asciiname":"Shintishrab",
    "gn:country_code":"SD",
    "gn:dem":487,
    "gn:feature_class":"P",
    "gn:feature_code":"PPL",
    "gn:name":"Shintishrab",
    "gn:population":0,
    "gn:timezone":"Africa/Khartoum",
    "iso:country":"SD",
    "wof:name":"Shintishrab",
    "wof:placetype":"locality"
},
  "geometry": {"coordinates":[36.25,15.53333],"type":"Point"}
}