{
  "type": "Feature",
  "properties": {
    "gn:admin1_code":"47.0",
    "gn:asciiname":"Maragibir",
    "gn:country_code":"SD",
    "gn:dem":768,
    "gn:feature_class":"P",
    "gn:feature_code":"PPL",
    "gn:name":"Maragibir",
    "gn:population":0,
    "gn:timezone":"Africa/Khartoum",
    "iso:country":"SD",
    "name:eng_x_preferred":[
        "Maragibir"
    ],
    "wof:name":"Maragibir",
    "wof:placetype":"locality"
},
  "geometry": {"coordinates":[22.27495,13.42584],"type":"Point"}
}