{
  "type": "Feature",
  "properties": {
    "gn:admin1_code":"47.0",
    "gn:asciiname":"Tendelti",
    "gn:country_code":"SD",
    "gn:dem":836,
    "gn:feature_class":"P",
    "gn:feature_code":"PPL",
    "gn:name":"Tendelti",
    "gn:population":0,
    "gn:timezone":"Africa/Khartoum",
    "iso:country":"SD",
    "name:und_x_variant":[
        "Tandalt\u012b"
    ],
    "wof:name":"Tendelti",
    "wof:placetype":"locality"
},
  "geometry": {"coordinates":[22.13306,13.67179],"type":"Point"}
}