{
  "type": "Feature",
  "properties": {
    "gn:admin1_code":"29.0",
    "gn:asciiname":"Qawz Nusayr",
    "gn:cc2":"SD",
    "gn:country_code":"SD",
    "gn:dem":377,
    "gn:feature_class":"P",
    "gn:feature_code":"PPL",
    "gn:name":"Qawz Nusayr",
    "gn:population":0,
    "gn:timezone":"Africa/Khartoum",
    "iso:country":"SD",
    "name:und_x_variant":[
        "Qoz Niseir",
        "Qawz Nusayr"
    ],
    "wof:lang_x_official":[
        "ara",
        "eng"
    ],
    "wof:lang_x_spoken":[
        "ara",
        "eng"
    ],
    "wof:name":"Qawz Nusayr",
    "wof:placetype":"locality"
},
  "geometry": {"coordinates":[32.46667,15.35],"type":"Point"}
}