{
  "type": "Feature",
  "properties": {
    "gn:admin1_code":"53.0",
    "gn:asciiname":"Umm Hashima",
    "gn:country_code":"SD",
    "gn:dem":405,
    "gn:feature_class":"P",
    "gn:feature_code":"PPL",
    "gn:name":"Umm Hashima",
    "gn:population":0,
    "gn:timezone":"Africa/Khartoum",
    "iso:country":"SD",
    "wof:name":"Umm Hashima",
    "wof:placetype":"locality"
},
  "geometry": {"coordinates":[34.03333,16.41667],"type":"Point"}
}