{
  "type": "Feature",
  "properties": {
    "gn:admin1_code":"50.0",
    "gn:asciiname":"Al Oddaiya",
    "gn:country_code":"SD",
    "gn:dem":547,
    "gn:feature_class":"P",
    "gn:feature_code":"PPL",
    "gn:name":"Al Oddaiya",
    "gn:population":0,
    "gn:timezone":"Africa/Khartoum",
    "iso:country":"SD",
    "name:und_x_variant":[
        "Oddaiya",
        "El Oddaiya",
        "Al Oddaiya"
    ],
    "wof:lang_x_official":[
        "ara",
        "eng"
    ],
    "wof:lang_x_spoken":[
        "ara",
        "eng"
    ],
    "wof:name":"Al Oddaiya",
    "wof:placetype":"locality"
},
  "geometry": {"coordinates":[30.03333,12.45],"type":"Point"}
}