{
  "type": "Feature",
  "properties": {
    "gn:admin1_code":"41.0",
    "gn:asciiname":"Al Usayfir",
    "gn:country_code":"SD",
    "gn:dem":392,
    "gn:feature_class":"P",
    "gn:feature_code":"PPL",
    "gn:name":"Al U\u015fayfir",
    "gn:population":0,
    "gn:timezone":"Africa/Khartoum",
    "iso:country":"SD",
    "name:und_x_variant":[
        "El Useifir",
        "Useifir",
        "Al U\u015fayfir"
    ],
    "wof:name":"Al Usayfir",
    "wof:placetype":"locality"
},
  "geometry": {"coordinates":[32.51667,14.63333],"type":"Point"}
}