{
  "type": "Feature",
  "properties": {
    "gn:admin1_code":"61.0",
    "gn:asciiname":"Mura",
    "gn:country_code":"SD",
    "gn:dem":928,
    "gn:feature_class":"P",
    "gn:feature_code":"PPL",
    "gn:name":"Mura",
    "gn:population":0,
    "gn:timezone":"Africa/Khartoum",
    "iso:country":"SD",
    "wof:name":"Mura",
    "wof:placetype":"locality"
},
  "geometry": {"coordinates":[23.26588,12.6103],"type":"Point"}
}