{
  "type": "Feature",
  "properties": {
    "gn:admin1_code":"56.0",
    "gn:asciiname":"Janqaro",
    "gn:country_code":"SD",
    "gn:dem":541,
    "gn:feature_class":"P",
    "gn:feature_code":"PPL",
    "gn:name":"Janq\u0101ro",
    "gn:population":0,
    "gn:timezone":"Africa/Khartoum",
    "iso:country":"SD",
    "name:und_x_variant":[
        "Janq\u0101ro"
    ],
    "wof:name":"Janqaro",
    "wof:placetype":"locality"
},
  "geometry": {"coordinates":[31.0204,12.4989],"type":"Point"}
}