{
  "type": "Feature",
  "properties": {
    "gn:admin1_code":"56.0",
    "gn:asciiname":"Umm Sa`idah",
    "gn:country_code":"SD",
    "gn:dem":431,
    "gn:feature_class":"P",
    "gn:feature_code":"PPL",
    "gn:name":"Umm Sa\u2018\u012bdah",
    "gn:population":0,
    "gn:timezone":"Africa/Khartoum",
    "iso:country":"SD",
    "name:und_x_variant":[
        "Umm Sa\u2018ida",
        "Umm Sa\u2018\u012bdah"
    ],
    "wof:lang_x_official":[
        "ara",
        "eng"
    ],
    "wof:lang_x_spoken":[
        "ara",
        "eng"
    ],
    "wof:name":"Umm Sa`idah",
    "wof:placetype":"locality"
},
  "geometry": {"coordinates":[31.63333,13.48333],"type":"Point"}
}