{
  "type": "Feature",
  "properties": {
    "gn:admin1_code":"58.0",
    "gn:asciiname":"Ad Dem",
    "gn:country_code":"SD",
    "gn:dem":441,
    "gn:feature_class":"P",
    "gn:feature_code":"PPL",
    "gn:name":"Ad Dem",
    "gn:population":0,
    "gn:timezone":"Africa/Khartoum",
    "iso:country":"SD",
    "wof:name":"Ad Dem",
    "wof:placetype":"locality"
},
  "geometry": {"coordinates":[34.0271,12.9123],"type":"Point"}
}