{
  "type": "Feature",
  "properties": {
    "gn:admin1_code":"41.0",
    "gn:asciiname":"Aj Jide`at",
    "gn:country_code":"SD",
    "gn:dem":387,
    "gn:feature_class":"P",
    "gn:feature_code":"PPL",
    "gn:name":"Aj Jide\u2018at",
    "gn:population":0,
    "gn:timezone":"Africa/Khartoum",
    "iso:country":"SD",
    "name:und_x_variant":[
        "Aj Jide\u2018at"
    ],
    "wof:name":"Aj Jide`at",
    "wof:placetype":"locality"
},
  "geometry": {"coordinates":[32.7402,12.9027],"type":"Point"}
}