{
  "type": "Feature",
  "properties": {
    "gn:admin1_code":"29.0",
    "gn:asciiname":"Hillat Kubour Ab Kiday",
    "gn:country_code":"SD",
    "gn:dem":392,
    "gn:feature_class":"P",
    "gn:feature_code":"PPL",
    "gn:name":"Hillat Kubour Ab Kiday",
    "gn:population":0,
    "gn:timezone":"Africa/Khartoum",
    "iso:country":"SD",
    "wof:lang_x_official":[
        "ara",
        "eng"
    ],
    "wof:lang_x_spoken":[
        "ara",
        "eng"
    ],
    "wof:name":"Hillat Kubour Ab Kiday",
    "wof:placetype":"locality"
},
  "geometry": {"coordinates":[32.3892,15.4457],"type":"Point"}
}