{
  "type": "Feature",
  "properties": {
    "gn:admin1_code":"58.0",
    "gn:asciiname":"Khashm al Batta",
    "gn:country_code":"SD",
    "gn:dem":473,
    "gn:feature_class":"P",
    "gn:feature_code":"PPL",
    "gn:name":"Khashm al Ba\u0163\u0163a",
    "gn:population":0,
    "gn:timezone":"Africa/Khartoum",
    "iso:country":"SD",
    "name:und_x_variant":[
        "Khashm al Ba\u0163\u0163a"
    ],
    "wof:lang_x_official":[
        "ara",
        "eng"
    ],
    "wof:lang_x_spoken":[
        "ara",
        "eng"
    ],
    "wof:name":"Khashm al Batta",
    "wof:placetype":"locality"
},
  "geometry": {"coordinates":[35.1292,12.8985],"type":"Point"}
}