{
  "type": "Feature",
  "properties": {
    "gn:admin1_code":"38.0",
    "gn:asciiname":"Abu `Aqla",
    "gn:country_code":"SD",
    "gn:dem":417,
    "gn:feature_class":"P",
    "gn:feature_code":"PPL",
    "gn:name":"Ab\u016b \u2018Aqla",
    "gn:population":0,
    "gn:timezone":"Africa/Khartoum",
    "iso:country":"SD",
    "wof:name":"Abu `Aqla",
    "wof:placetype":"locality"
},
  "geometry": {"coordinates":[33.56667,14.93333],"type":"Point"}
}