{
  "type": "Feature",
  "properties": {
    "gn:admin1_code":"49.0",
    "gn:asciiname":"Hureiz",
    "gn:country_code":"SD",
    "gn:dem":808,
    "gn:feature_class":"P",
    "gn:feature_code":"PPL",
    "gn:name":"Hureiz",
    "gn:population":0,
    "gn:timezone":"Africa/Khartoum",
    "iso:country":"SD",
    "name:ara_x_preferred":[
        "\u062d\u0631\u064a\u0632"
    ],
    "name:cat_x_preferred":[
        "Hureiz"
    ],
    "name:heb_x_preferred":[
        "\u05d7\u05d5\u05e8\u05d9\u05d6"
    ],
    "name:nno_x_preferred":[
        "Hureiz"
    ],
    "name:und_x_variant":[
        "Hereiz",
        "Hureiz"
    ],
    "wof:name":"Hureiz",
    "wof:placetype":"locality"
},
  "geometry": {"coordinates":[23.88333,12.05],"type":"Point"}
}