{
  "type": "Feature",
  "properties": {
    "gn:admin1_code":"41.0",
    "gn:asciiname":"Um Bol",
    "gn:country_code":"SD",
    "gn:dem":417,
    "gn:feature_class":"P",
    "gn:feature_code":"PPL",
    "gn:name":"Um Bol",
    "gn:population":0,
    "gn:timezone":"Africa/Khartoum",
    "iso:country":"SD",
    "wof:name":"Um Bol",
    "wof:placetype":"locality"
},
  "geometry": {"coordinates":[31.8809,12.9102],"type":"Point"}
}