{
  "type": "Feature",
  "properties": {
    "gn:admin1_code":"53.0",
    "gn:asciiname":"Hilla",
    "gn:country_code":"SD",
    "gn:dem":404,
    "gn:feature_class":"P",
    "gn:feature_code":"PPL",
    "gn:name":"Hilla",
    "gn:population":0,
    "gn:timezone":"Africa/Khartoum",
    "iso:country":"SD",
    "wof:name":"Hilla",
    "wof:placetype":"locality"
},
  "geometry": {"coordinates":[33.4969,16.5181],"type":"Point"}
}