{
  "type": "Feature",
  "properties": {
    "gn:admin1_code":"50.0",
    "gn:asciiname":"Um Hashima",
    "gn:country_code":"SD",
    "gn:dem":525,
    "gn:feature_class":"P",
    "gn:feature_code":"PPL",
    "gn:name":"Um Hash\u012bma",
    "gn:population":0,
    "gn:timezone":"Africa/Khartoum",
    "iso:country":"SD",
    "name:und_x_variant":[
        "Ab\u016b Hashim",
        "Um Hash\u012bma"
    ],
    "wof:name":"Um Hashima",
    "wof:placetype":"locality"
},
  "geometry": {"coordinates":[31.4021,11.3548],"type":"Point"}
}