{
  "type": "Feature",
  "properties": {
    "gn:admin1_code":"53.0",
    "gn:asciiname":"El Gibrab",
    "gn:country_code":"SD",
    "gn:dem":354,
    "gn:feature_class":"P",
    "gn:feature_code":"PPL",
    "gn:name":"El Gibrab",
    "gn:population":0,
    "gn:timezone":"Africa/Khartoum",
    "iso:country":"SD",
    "wof:name":"El Gibrab",
    "wof:placetype":"locality"
},
  "geometry": {"coordinates":[33.8935,17.5026],"type":"Point"}
}