{
  "type": "Feature",
  "properties": {
    "gn:admin1_code":"61.0",
    "gn:asciiname":"Meiram",
    "gn:country_code":"SD",
    "gn:dem":885,
    "gn:feature_class":"P",
    "gn:feature_code":"PPL",
    "gn:name":"Meiram",
    "gn:population":0,
    "gn:timezone":"Africa/Khartoum",
    "iso:country":"SD",
    "wof:name":"Meiram",
    "wof:placetype":"locality"
},
  "geometry": {"coordinates":[23.49754,12.94743],"type":"Point"}
}