{
  "type": "Feature",
  "properties": {
    "gn:admin1_code":"50.0",
    "gn:asciiname":"Ed Dikeri",
    "gn:country_code":"SD",
    "gn:dem":460,
    "gn:feature_class":"P",
    "gn:feature_code":"PPL",
    "gn:name":"Ed Dikeri",
    "gn:population":0,
    "gn:timezone":"Africa/Khartoum",
    "iso:country":"SD",
    "name:und_x_variant":[
        "Ad Dikeri"
    ],
    "wof:name":"Ed Dikeri",
    "wof:placetype":"locality"
},
  "geometry": {"coordinates":[30.28317,10.53775],"type":"Point"}
}