{
  "type": "Feature",
  "properties": {
    "gn:admin1_code":"53.0",
    "gn:asciiname":"Ageida",
    "gn:country_code":"SD",
    "gn:dem":360,
    "gn:feature_class":"P",
    "gn:feature_code":"PPL",
    "gn:name":"Ageida",
    "gn:population":0,
    "gn:timezone":"Africa/Khartoum",
    "iso:country":"SD",
    "wof:name":"Ageida",
    "wof:placetype":"locality"
},
  "geometry": {"coordinates":[33.71667,17.28333],"type":"Point"}
}