{
  "type": "Feature",
  "properties": {
    "gn:admin1_code":"41.0",
    "gn:asciiname":"Ar Radis",
    "gn:country_code":"SD",
    "gn:dem":390,
    "gn:feature_class":"P",
    "gn:feature_code":"PPL",
    "gn:name":"Ar Rad\u012bs",
    "gn:population":0,
    "gn:timezone":"Africa/Khartoum",
    "iso:country":"SD",
    "name:und_x_variant":[
        "Ar Rid\u0113s",
        "Redeis",
        "Rudays",
        "Ar Rad\u012bs"
    ],
    "wof:name":"Ar Radis",
    "wof:placetype":"locality"
},
  "geometry": {"coordinates":[32.7436,12.61],"type":"Point"}
}