{
  "type": "Feature",
  "properties": {
    "gn:admin1_code":"41.0",
    "gn:asciiname":"Dahar Jihena",
    "gn:country_code":"SD",
    "gn:dem":385,
    "gn:feature_class":"P",
    "gn:feature_code":"PPL",
    "gn:name":"\u1e10ahar Jihena",
    "gn:population":0,
    "gn:timezone":"Africa/Khartoum",
    "iso:country":"SD",
    "name:und_x_variant":[
        "\u1e10ahar Jihena"
    ],
    "wof:name":"Dahar Jihena",
    "wof:placetype":"locality"
},
  "geometry": {"coordinates":[32.2392,13.9499],"type":"Point"}
}