{
  "type": "Feature",
  "properties": {
    "gn:admin1_code":"38.0",
    "gn:asciiname":"Al Masallamiyya",
    "gn:country_code":"SD",
    "gn:dem":399,
    "gn:feature_class":"P",
    "gn:feature_code":"PPL",
    "gn:name":"Al Masallamiyya",
    "gn:population":0,
    "gn:timezone":"Africa/Khartoum",
    "iso:country":"SD",
    "wof:name":"Al Masallamiyya",
    "wof:placetype":"locality"
},
  "geometry": {"coordinates":[33.1177,14.8679],"type":"Point"}
}