{
  "type": "Feature",
  "properties": {
    "gn:admin1_code":"50.0",
    "gn:asciiname":"Deldum",
    "gn:country_code":"SD",
    "gn:dem":728,
    "gn:feature_class":"P",
    "gn:feature_code":"PPL",
    "gn:name":"Deldum",
    "gn:population":0,
    "gn:timezone":"Africa/Khartoum",
    "iso:country":"SD",
    "wof:name":"Deldum",
    "wof:placetype":"locality"
},
  "geometry": {"coordinates":[30.72815,10.23594],"type":"Point"}
}