{
  "type": "Feature",
  "properties": {
    "gn:admin1_code":"50.0",
    "gn:asciiname":"Toris",
    "gn:country_code":"SD",
    "gn:dem":977,
    "gn:feature_class":"P",
    "gn:feature_code":"PPL",
    "gn:name":"\u0162\u014dris",
    "gn:population":0,
    "gn:timezone":"Africa/Khartoum",
    "iso:country":"SD",
    "name:ara_x_preferred":[
        "\u0162\u014dris"
    ],
    "name:eng_x_preferred":[
        "Gardud el Badry"
    ],
    "name:und_x_variant":[
        "Gardud al Badry"
    ],
    "wof:name":"Toris",
    "wof:placetype":"locality"
},
  "geometry": {"coordinates":[31.14848,12.05825],"type":"Point"}
}