{
  "type": "Feature",
  "properties": {
    "gn:admin1_code":"41.0",
    "gn:asciiname":"Al Ghuwaytab",
    "gn:country_code":"SD",
    "gn:dem":439,
    "gn:feature_class":"P",
    "gn:feature_code":"PPL",
    "gn:name":"Al Ghuwayt\u0101b",
    "gn:population":0,
    "gn:timezone":"Africa/Khartoum",
    "iso:country":"SD",
    "name:und_x_variant":[
        "Al Ghuwayt\u0101b"
    ],
    "wof:name":"Al Ghuwaytab",
    "wof:placetype":"locality"
},
  "geometry": {"coordinates":[33.0696,12.8235],"type":"Point"}
}