{
  "type": "Feature",
  "properties": {
    "gn:admin1_code":"53.0",
    "gn:asciiname":"Hillat ej Jablab",
    "gn:country_code":"SD",
    "gn:dem":359,
    "gn:feature_class":"P",
    "gn:feature_code":"PPL",
    "gn:name":"Hillat ej Jablab",
    "gn:population":0,
    "gn:timezone":"Africa/Khartoum",
    "iso:country":"SD",
    "name:und_x_variant":[
        "Gabalab",
        "Hillat ej Jablab"
    ],
    "wof:name":"Hillat ej Jablab",
    "wof:placetype":"locality"
},
  "geometry": {"coordinates":[33.6278,16.8718],"type":"Point"}
}