{
  "type": "Feature",
  "properties": {
    "gn:admin1_code":"43.0",
    "gn:asciiname":"`Arab Hajj",
    "gn:country_code":"SD",
    "gn:dem":237,
    "gn:feature_class":"P",
    "gn:feature_code":"PPL",
    "gn:name":"\u2018Arab \u1e28\u0101jj",
    "gn:population":0,
    "gn:timezone":"Africa/Khartoum",
    "iso:country":"SD",
    "name:und_x_variant":[
        "\u2018Arab Hag",
        "\u2018Arab \u1e28\u0101jj"
    ],
    "wof:lang_x_official":[
        "ara",
        "eng"
    ],
    "wof:lang_x_spoken":[
        "ara",
        "eng"
    ],
    "wof:name":"`Arab Hajj",
    "wof:placetype":"locality"
},
  "geometry": {"coordinates":[30.71667,18.38333],"type":"Point"}
}