{
  "type": "Feature",
  "properties": {
    "gn:admin1_code":"50.0",
    "gn:asciiname":"Abu `Udam",
    "gn:country_code":"SD",
    "gn:dem":659,
    "gn:feature_class":"P",
    "gn:feature_code":"PPL",
    "gn:name":"Abu \u2018U\u1e11\u0101m",
    "gn:population":0,
    "gn:timezone":"Africa/Khartoum",
    "iso:country":"SD",
    "name:ara_x_preferred":[
        "Abu \u2018U\u1e11\u0101m"
    ],
    "wof:lang_x_official":[
        "ara",
        "eng"
    ],
    "wof:lang_x_spoken":[
        "ara",
        "eng"
    ],
    "wof:name":"Abu `Udam",
    "wof:placetype":"locality"
},
  "geometry": {"coordinates":[31.0257,11.5159],"type":"Point"}
}