{
  "type": "Feature",
  "properties": {
    "gn:admin1_code":"47.0",
    "gn:asciiname":"Kaghiggum",
    "gn:country_code":"SD",
    "gn:dem":977,
    "gn:feature_class":"P",
    "gn:feature_code":"PPL",
    "gn:name":"Kaghiggum",
    "gn:population":0,
    "gn:timezone":"Africa/Khartoum",
    "iso:country":"SD",
    "wof:name":"Kaghiggum",
    "wof:placetype":"locality"
},
  "geometry": {"coordinates":[22.46387,14.29899],"type":"Point"}
}