{
  "type": "Feature",
  "properties": {
    "gn:admin1_code":"56.0",
    "gn:asciiname":"Umm Matariq",
    "gn:country_code":"SD",
    "gn:dem":506,
    "gn:feature_class":"P",
    "gn:feature_code":"PPL",
    "gn:name":"Umm Ma\u0163\u0101riq",
    "gn:population":0,
    "gn:timezone":"Africa/Khartoum",
    "iso:country":"SD",
    "wof:name":"Umm Matariq",
    "wof:placetype":"locality"
},
  "geometry": {"coordinates":[30.61667000000001,13.06667],"type":"Point"}
}