{
  "type": "Feature",
  "properties": {
    "gn:admin1_code":"56.0",
    "gn:asciiname":"Qaradaya",
    "gn:country_code":"SD",
    "gn:dem":478,
    "gn:feature_class":"P",
    "gn:feature_code":"PPL",
    "gn:name":"Qara\u1e11\u0101ya",
    "gn:population":0,
    "gn:timezone":"Africa/Khartoum",
    "iso:country":"SD",
    "name:und_x_variant":[
        "Qara\u1e11\u0101ya"
    ],
    "wof:name":"Qaradaya",
    "wof:placetype":"locality"
},
  "geometry": {"coordinates":[31.2031,12.6913],"type":"Point"}
}