{
  "type": "Feature",
  "properties": {
    "gn:admin1_code":"56.0",
    "gn:asciiname":"Ar Rijela As Suq",
    "gn:country_code":"SD",
    "gn:dem":483,
    "gn:feature_class":"P",
    "gn:feature_code":"PPL",
    "gn:name":"Ar Rijela As S\u016bq",
    "gn:population":0,
    "gn:timezone":"Africa/Khartoum",
    "iso:country":"SD",
    "name:und_x_variant":[
        "Ar Rijela As S\u016bq"
    ],
    "wof:name":"Ar Rijela As Suq",
    "wof:placetype":"locality"
},
  "geometry": {"coordinates":[31.0691,12.7501],"type":"Point"}
}