{
  "type": "Feature",
  "properties": {
    "gn:admin1_code":"49.0",
    "gn:asciiname":"Barkaz",
    "gn:country_code":"SD",
    "gn:dem":619,
    "gn:feature_class":"P",
    "gn:feature_code":"PPL",
    "gn:name":"Barkaz",
    "gn:population":0,
    "gn:timezone":"Africa/Khartoum",
    "iso:country":"SD",
    "wof:name":"Barkaz",
    "wof:placetype":"locality"
},
  "geometry": {"coordinates":[25.33333,12.35],"type":"Point"}
}