{
  "type": "Feature",
  "properties": {
    "gn:admin1_code":"29.0",
    "gn:asciiname":"Walad el Balla",
    "gn:country_code":"SD",
    "gn:dem":389,
    "gn:feature_class":"P",
    "gn:feature_code":"PPL",
    "gn:name":"Walad el Balla",
    "gn:population":0,
    "gn:timezone":"Africa/Khartoum",
    "iso:country":"SD",
    "wof:name":"Walad el Balla",
    "wof:placetype":"locality"
},
  "geometry": {"coordinates":[32.61667,15.31667],"type":"Point"}
}