{
  "type": "Feature",
  "properties": {
    "gn:admin1_code":"58.0",
    "gn:asciiname":"Lubayn",
    "gn:country_code":"SD",
    "gn:dem":433,
    "gn:feature_class":"P",
    "gn:feature_code":"PPL",
    "gn:name":"Lubayn",
    "gn:population":0,
    "gn:timezone":"Africa/Khartoum",
    "iso:country":"SD",
    "name:und_x_variant":[
        "Libein",
        "Lubayn"
    ],
    "wof:name":"Lubayn",
    "wof:placetype":"locality"
},
  "geometry": {"coordinates":[34.33333,13.43333],"type":"Point"}
}