{
  "type": "Feature",
  "properties": {
    "gn:admin1_code":"58.0",
    "gn:asciiname":"Lubayn",
    "gn:country_code":"SD",
    "gn:dem":433,
    "gn:feature_class":"P",
    "gn:feature_code":"PPL",
    "gn:name":"Lubayn",
    "gn:population":0,
    "gn:timezone":"Africa/Khartoum",
    "iso:country":"SD",
    "name:ara_x_preferred":[
        "\u0644\u0628\u064a\u0646"
    ],
    "name:fas_x_preferred":[
        "\u0644\u0628\u06cc\u0646"
    ],
    "name:pol_x_preferred":[
        "Lubajn"
    ],
    "name:ukr_x_preferred":[
        "\u041b\u044e\u0431\u0430\u0457\u043d"
    ],
    "name:und_x_variant":[
        "Libein"
    ],
    "name:vie_x_preferred":[
        "Lubayn"
    ],
    "wof:name":"Lubayn",
    "wof:placetype":"locality"
},
  "geometry": {"coordinates":[34.33333,13.43333],"type":"Point"}
}