{
  "type": "Feature",
  "properties": {
    "gn:admin1_code":"49.0",
    "gn:asciiname":"Al Akhdar",
    "gn:country_code":"SD",
    "gn:dem":467,
    "gn:feature_class":"P",
    "gn:feature_code":"PPL",
    "gn:name":"Al Akh\u1e11ar",
    "gn:population":0,
    "gn:timezone":"Africa/Khartoum",
    "iso:country":"SD",
    "name:fas_x_preferred":[
        "\u0627\u0644\u0627\u062e\u062f\u0631"
    ],
    "name:nno_x_preferred":[
        "Al Akhdar"
    ],
    "name:und_x_variant":[
        "El Akhdar",
        "Al Akh\u1e11ar"
    ],
    "wof:name":"Al Akhdar",
    "wof:placetype":"locality"
},
  "geometry": {"coordinates":[25.16667,10.55],"type":"Point"}
}