{
  "type": "Feature",
  "properties": {
    "gn:admin1_code":"41.0",
    "gn:asciiname":"Al Mazrub",
    "gn:country_code":"SD",
    "gn:dem":426,
    "gn:feature_class":"P",
    "gn:feature_code":"PPL",
    "gn:name":"Al Mazr\u016bb",
    "gn:population":0,
    "gn:timezone":"Africa/Khartoum",
    "iso:country":"SD",
    "name:und_x_variant":[
        "Al Mazr\u016bb"
    ],
    "wof:name":"Al Mazrub",
    "wof:placetype":"locality"
},
  "geometry": {"coordinates":[31.9445,12.8458],"type":"Point"}
}