{
  "type": "Feature",
  "properties": {
    "gn:admin1_code":"38.0",
    "gn:asciiname":"Jibeliyya",
    "gn:country_code":"SD",
    "gn:dem":411,
    "gn:feature_class":"P",
    "gn:feature_code":"PPL",
    "gn:name":"Jibeliyya",
    "gn:population":0,
    "gn:timezone":"Africa/Khartoum",
    "iso:country":"SD",
    "wof:name":"Jibeliyya",
    "wof:placetype":"locality"
},
  "geometry": {"coordinates":[33.3187,14.4559],"type":"Point"}
}