{
  "type": "Feature",
  "properties": {
    "gn:admin1_code":"39.0",
    "gn:asciiname":"Abu Zarad",
    "gn:country_code":"SD",
    "gn:dem":604,
    "gn:feature_class":"P",
    "gn:feature_code":"PPL",
    "gn:name":"Ab\u016b Zarad",
    "gn:population":0,
    "gn:timezone":"Africa/Khartoum",
    "iso:country":"SD",
    "wof:name":"Abu Zarad",
    "wof:placetype":"locality"
},
  "geometry": {"coordinates":[35.85,12.96667],"type":"Point"}
}