{
  "type": "Feature",
  "properties": {
    "gn:admin1_code":"38.0",
    "gn:asciiname":"Fawayda",
    "gn:country_code":"SD",
    "gn:dem":413,
    "gn:feature_class":"P",
    "gn:feature_code":"PPL",
    "gn:name":"Faw\u0101yda",
    "gn:population":0,
    "gn:timezone":"Africa/Khartoum",
    "iso:country":"SD",
    "name:und_x_variant":[
        "Faw\u0101yda"
    ],
    "wof:name":"Fawayda",
    "wof:placetype":"locality"
},
  "geometry": {"coordinates":[33.4501,14.1444],"type":"Point"}
}