{
  "type": "Feature",
  "properties": {
    "gn:admin1_code":"55.0",
    "gn:asciiname":"Turter",
    "gn:country_code":"SD",
    "gn:dem":866,
    "gn:feature_class":"P",
    "gn:feature_code":"PPL",
    "gn:name":"Turter",
    "gn:population":0,
    "gn:timezone":"Africa/Khartoum",
    "iso:country":"SD",
    "wof:name":"Turter",
    "wof:placetype":"locality"
},
  "geometry": {"coordinates":[24.96654,13.23891],"type":"Point"}
}