{
  "type": "Feature",
  "properties": {
    "gn:admin1_code":"55.0",
    "gn:asciiname":"Kerkera",
    "gn:country_code":"SD",
    "gn:dem":809,
    "gn:feature_class":"P",
    "gn:feature_code":"PPL",
    "gn:name":"Kerkera",
    "gn:population":0,
    "gn:timezone":"Africa/Khartoum",
    "iso:country":"SD",
    "name:ara_x_preferred":[
        "\u0627\u0644\u0643\u0631\u0643\u0631\u0629"
    ],
    "name:ceb_x_preferred":[
        "Kerkera"
    ],
    "name:fra_x_preferred":[
        "Kerkera"
    ],
    "name:ita_x_preferred":[
        "Kerkera"
    ],
    "name:kab_x_preferred":[
        "Kerkera"
    ],
    "name:msa_x_preferred":[
        "Kerkera"
    ],
    "name:por_x_preferred":[
        "Kerkera"
    ],
    "name:ron_x_preferred":[
        "Kerkera"
    ],
    "name:spa_x_preferred":[
        "Kerkera"
    ],
    "name:swe_x_preferred":[
        "Kerkera"
    ],
    "name:vie_x_preferred":[
        "Kerkera"
    ],
    "name:zho_x_preferred":[
        "\u51f1\u723e\u51f1\u62c9"
    ],
    "wof:name":"Kerkera",
    "wof:placetype":"locality"
},
  "geometry": {"coordinates":[25.36667000000001,13.86667],"type":"Point"}
}