{
  "type": "Feature",
  "properties": {
    "gn:admin1_code":"49.0",
    "gn:asciiname":"Umm Sarir",
    "gn:country_code":"SD",
    "gn:dem":574,
    "gn:feature_class":"P",
    "gn:feature_code":"PPL",
    "gn:name":"Umm Sar\u012br",
    "gn:population":0,
    "gn:timezone":"Africa/Khartoum",
    "iso:country":"SD",
    "wof:name":"Umm Sarir",
    "wof:placetype":"locality"
},
  "geometry": {"coordinates":[25.13333,11.85],"type":"Point"}
}