{
  "type": "Feature",
  "properties": {
    "gn:admin1_code":"55.0",
    "gn:asciiname":"Umm Habilah",
    "gn:country_code":"SD",
    "gn:dem":554,
    "gn:feature_class":"P",
    "gn:feature_code":"PPL",
    "gn:name":"Umm Hab\u012blah",
    "gn:population":0,
    "gn:timezone":"Africa/Khartoum",
    "iso:country":"SD",
    "name:und_x_variant":[
        "Umm Habila",
        "Umm Harila",
        "Umm Hab\u012blah"
    ],
    "wof:lang_x_official":[
        "ara",
        "eng"
    ],
    "wof:lang_x_spoken":[
        "ara",
        "eng"
    ],
    "wof:name":"Umm Habilah",
    "wof:placetype":"locality"
},
  "geometry": {"coordinates":[26.93333,13.18333],"type":"Point"}
}