{
  "type": "Feature",
  "properties": {
    "gn:admin1_code":"47.0",
    "gn:asciiname":"Ghubayshat",
    "gn:country_code":"SD",
    "gn:dem":862,
    "gn:feature_class":"P",
    "gn:feature_code":"PPL",
    "gn:name":"Ghubaysh\u0101t",
    "gn:population":0,
    "gn:timezone":"Africa/Khartoum",
    "iso:country":"SD",
    "name:und_x_variant":[
        "Ghubeishat",
        "Ghubaysh\u0101t"
    ],
    "wof:lang_x_official":[
        "ara",
        "eng"
    ],
    "wof:lang_x_spoken":[
        "ara",
        "eng"
    ],
    "wof:name":"Ghubayshat",
    "wof:placetype":"locality"
},
  "geometry": {"coordinates":[23.15,13.78333],"type":"Point"}
}