{
  "type": "Feature",
  "properties": {
    "gn:admin1_code":"38.0",
    "gn:asciiname":"Wad ash Shiqil",
    "gn:country_code":"SD",
    "gn:dem":406,
    "gn:feature_class":"P",
    "gn:feature_code":"PPL",
    "gn:name":"Wad ash Shiqil",
    "gn:population":0,
    "gn:timezone":"Africa/Khartoum",
    "iso:country":"SD",
    "name:und_x_variant":[
        "Wad esh Shigil",
        "Wad ash Shigil",
        "Wad ash Shiqil"
    ],
    "wof:name":"Wad ash Shiqil",
    "wof:placetype":"locality"
},
  "geometry": {"coordinates":[32.9528,14.152],"type":"Point"}
}