{
  "type": "Feature",
  "properties": {
    "gn:admin1_code":"38.0",
    "gn:asciiname":"Kamlin Sharq",
    "gn:country_code":"SD",
    "gn:dem":395,
    "gn:feature_class":"P",
    "gn:feature_code":"PPL",
    "gn:name":"Kamlin Sharq",
    "gn:population":0,
    "gn:timezone":"Africa/Khartoum",
    "iso:country":"SD",
    "wof:name":"Kamlin Sharq",
    "wof:placetype":"locality"
},
  "geometry": {"coordinates":[33.20778,15.04083],"type":"Point"}
}