{
  "type": "Feature",
  "properties": {
    "gn:admin1_code":"38.0",
    "gn:asciiname":"Al Khulab",
    "gn:country_code":"SD",
    "gn:dem":410,
    "gn:feature_class":"P",
    "gn:feature_code":"PPL",
    "gn:name":"Al Kh\u016bl\u0101b",
    "gn:population":0,
    "gn:timezone":"Africa/Khartoum",
    "iso:country":"SD",
    "name:ara_x_preferred":[
        "Al Kh\u016bl\u0101b"
    ],
    "name:und_x_variant":[
        "El Khulab"
    ],
    "wof:name":"Al Khulab",
    "wof:placetype":"locality"
},
  "geometry": {"coordinates":[33.3421,14.4877],"type":"Point"}
}