{
  "type": "Feature",
  "properties": {
    "gn:admin1_code":"38.0",
    "gn:asciiname":"Al Mikherif",
    "gn:country_code":"SD",
    "gn:dem":411,
    "gn:feature_class":"P",
    "gn:feature_code":"PPL",
    "gn:name":"Al Mikherif",
    "gn:population":0,
    "gn:timezone":"Africa/Khartoum",
    "iso:country":"SD",
    "name:und_x_variant":[
        "El Mekheirif",
        "Al Mukhayrif",
        "Al Mikherif"
    ],
    "wof:name":"Al Mikherif",
    "wof:placetype":"locality"
},
  "geometry": {"coordinates":[33.3989,14.2589],"type":"Point"}
}