{
  "type": "Feature",
  "properties": {
    "gn:admin1_code":"53.0",
    "gn:asciiname":"Shankuk",
    "gn:country_code":"SD",
    "gn:dem":318,
    "gn:feature_class":"P",
    "gn:feature_code":"PPL",
    "gn:name":"Shankuk",
    "gn:population":0,
    "gn:timezone":"Africa/Khartoum",
    "iso:country":"SD",
    "wof:name":"Shankuk",
    "wof:placetype":"locality"
},
  "geometry": {"coordinates":[32.48333,19.13333],"type":"Point"}
}