{
  "type": "Feature",
  "properties": {
    "gn:admin1_code":"38.0",
    "gn:asciiname":"Masa`ad",
    "gn:country_code":"SD",
    "gn:dem":410,
    "gn:feature_class":"P",
    "gn:feature_code":"PPL",
    "gn:name":"Mas\u0101\u2018ad",
    "gn:population":0,
    "gn:timezone":"Africa/Khartoum",
    "iso:country":"SD",
    "name:und_x_variant":[
        "Mas\u0101\u2018ad"
    ],
    "wof:name":"Masa`ad",
    "wof:placetype":"locality"
},
  "geometry": {"coordinates":[33.4119,14.4561],"type":"Point"}
}