{
  "type": "Feature",
  "properties": {
    "gn:admin1_code":"61.0",
    "gn:asciiname":"Tululu",
    "gn:country_code":"SD",
    "gn:dem":829,
    "gn:feature_class":"P",
    "gn:feature_code":"PPL",
    "gn:name":"Tululu",
    "gn:population":0,
    "gn:timezone":"Africa/Khartoum",
    "iso:country":"SD",
    "name:und_x_variant":[
        "Tougougou",
        "Tululu"
    ],
    "wof:name":"Tululu",
    "wof:placetype":"locality"
},
  "geometry": {"coordinates":[23.16667,12.78333],"type":"Point"}
}