{
  "type": "Feature",
  "properties": {
    "gn:admin1_code":"49.0",
    "gn:asciiname":"Mesheitir",
    "gn:country_code":"SD",
    "gn:dem":511,
    "gn:feature_class":"P",
    "gn:feature_code":"PPL",
    "gn:name":"Mesheitir",
    "gn:population":0,
    "gn:timezone":"Africa/Khartoum",
    "iso:country":"SD",
    "name:und_x_variant":[
        "Mushay\u0163\u012br"
    ],
    "wof:name":"Mesheitir",
    "wof:placetype":"locality"
},
  "geometry": {"coordinates":[24.68036,9.83186],"type":"Point"}
}