{
  "type": "Feature",
  "properties": {
    "gn:admin1_code":"42.0",
    "gn:asciiname":"Hamra",
    "gn:country_code":"SD",
    "gn:dem":452,
    "gn:feature_class":"P",
    "gn:feature_code":"PPL",
    "gn:name":"Hamra",
    "gn:population":0,
    "gn:timezone":"Africa/Khartoum",
    "iso:country":"SD",
    "name:ceb_x_preferred":[
        "Hamra"
    ],
    "name:deu_x_preferred":[
        "Hamra"
    ],
    "name:fra_x_preferred":[
        "Hamra"
    ],
    "name:heb_x_preferred":[
        "\u05d7\u05de\u05e8\u05d4"
    ],
    "name:nld_x_preferred":[
        "Hamra"
    ],
    "name:swe_x_preferred":[
        "Hamra"
    ],
    "wof:lang_x_official":[
        "ara",
        "eng"
    ],
    "wof:lang_x_spoken":[
        "ara",
        "eng"
    ],
    "wof:name":"Hamra",
    "wof:placetype":"locality"
},
  "geometry": {"coordinates":[34.3617,12.2277],"type":"Point"}
}