{
  "type": "Feature",
  "properties": {
    "gn:admin1_code":"53.0",
    "gn:asciiname":"El A`lyab",
    "gn:country_code":"SD",
    "gn:dem":355,
    "gn:feature_class":"P",
    "gn:feature_code":"PPL",
    "gn:name":"El A\u2018lyab",
    "gn:population":0,
    "gn:timezone":"Africa/Khartoum",
    "iso:country":"SD",
    "name:und_x_variant":[
        "\u2018Aliab",
        "El A\u2018lyab"
    ],
    "wof:name":"El A`lyab",
    "wof:placetype":"locality"
},
  "geometry": {"coordinates":[33.7928,17.317],"type":"Point"}
}