{
  "type": "Feature",
  "properties": {
    "gn:admin1_code":"42.0",
    "gn:asciiname":"Bal`ar",
    "gn:country_code":"SD",
    "gn:dem":466,
    "gn:feature_class":"P",
    "gn:feature_code":"PPL",
    "gn:name":"Bal\u2018ar",
    "gn:population":0,
    "gn:timezone":"Africa/Khartoum",
    "iso:country":"SD",
    "name:und_x_variant":[
        "Bal\u2018ar"
    ],
    "wof:name":"Bal`ar",
    "wof:placetype":"locality"
},
  "geometry": {"coordinates":[34.3701,11.8759],"type":"Point"}
}