{
  "type": "Feature",
  "properties": {
    "gn:admin1_code":"41.0",
    "gn:asciiname":"Ash Sheikh al Imam",
    "gn:country_code":"SD",
    "gn:dem":386,
    "gn:feature_class":"P",
    "gn:feature_code":"PPL",
    "gn:name":"Ash Sheikh al Im\u0101m",
    "gn:population":0,
    "gn:timezone":"Africa/Khartoum",
    "iso:country":"SD",
    "name:und_x_variant":[
        "Esh Sheikh el Imam",
        "Ash Shaykh al Im\u0101m",
        "Ash Sheikh al Im\u0101m"
    ],
    "wof:lang_x_official":[
        "ara",
        "eng"
    ],
    "wof:lang_x_spoken":[
        "ara",
        "eng"
    ],
    "wof:name":"Ash Sheikh al Imam",
    "wof:placetype":"locality"
},
  "geometry": {"coordinates":[32.307,14.1226],"type":"Point"}
}