{
  "type": "Feature",
  "properties": {
    "gn:admin1_code":"53.0",
    "gn:asciiname":"Ei Qobosh",
    "gn:country_code":"SD",
    "gn:dem":350,
    "gn:feature_class":"P",
    "gn:feature_code":"PPL",
    "gn:name":"Ei Qobosh",
    "gn:population":0,
    "gn:timezone":"Africa/Khartoum",
    "iso:country":"SD",
    "name:und_x_variant":[
        "Ghubsh",
        "Ei Qobosh"
    ],
    "wof:name":"Ei Qobosh",
    "wof:placetype":"locality"
},
  "geometry": {"coordinates":[33.9589,17.9583],"type":"Point"}
}