{
  "type": "Feature",
  "properties": {
    "gn:admin1_code":"50.0",
    "gn:asciiname":"Singeir",
    "gn:country_code":"SD",
    "gn:dem":688,
    "gn:feature_class":"P",
    "gn:feature_code":"PPL",
    "gn:name":"Singeir",
    "gn:population":0,
    "gn:timezone":"Africa/Khartoum",
    "iso:country":"SD",
    "wof:name":"Singeir",
    "wof:placetype":"locality"
},
  "geometry": {"coordinates":[31.46667,11.98333],"type":"Point"}
}