{
  "type": "Feature",
  "properties": {
    "gn:admin1_code":"50.0",
    "gn:asciiname":"Qurdud al Khaymah",
    "gn:country_code":"SD",
    "gn:dem":564,
    "gn:feature_class":"P",
    "gn:feature_code":"PPL",
    "gn:name":"Qurd\u016bd al Khaymah",
    "gn:population":0,
    "gn:timezone":"Africa/Khartoum",
    "iso:country":"SD",
    "name:und_x_variant":[
        "El Qardud",
        "Qardad el Kheima",
        "Qardud el Kheima",
        "Qurd\u016bd al Khaymah"
    ],
    "wof:name":"Qurdud al Khaymah",
    "wof:placetype":"locality"
},
  "geometry": {"coordinates":[30.68333,11.98333],"type":"Point"}
}