{
  "type": "Feature",
  "properties": {
    "gn:admin1_code":"53.0",
    "gn:asciiname":"Mideini",
    "gn:country_code":"SD",
    "gn:dem":364,
    "gn:feature_class":"P",
    "gn:feature_code":"PPL",
    "gn:name":"Mideini",
    "gn:population":0,
    "gn:timezone":"Africa/Khartoum",
    "iso:country":"SD",
    "wof:name":"Mideini",
    "wof:placetype":"locality"
},
  "geometry": {"coordinates":[32.71667,16.35],"type":"Point"}
}