{
  "type": "Feature",
  "properties": {
    "gn:admin1_code":"41.0",
    "gn:asciiname":"Al Halawa",
    "gn:country_code":"SD",
    "gn:dem":389,
    "gn:feature_class":"P",
    "gn:feature_code":"PPL",
    "gn:name":"Al \u1e28al\u0101wa",
    "gn:population":0,
    "gn:timezone":"Africa/Khartoum",
    "iso:country":"SD",
    "name:und_x_variant":[
        "Al \u1e28al\u0101wa"
    ],
    "wof:name":"Al Halawa",
    "wof:placetype":"locality"
},
  "geometry": {"coordinates":[32.6242,12.9804],"type":"Point"}
}