{
  "type": "Feature",
  "properties": {
    "gn:admin1_code":"53.0",
    "gn:asciiname":"El Basaber el Sok",
    "gn:country_code":"SD",
    "gn:dem":369,
    "gn:feature_class":"P",
    "gn:feature_code":"PPL",
    "gn:name":"El Basaber el Sok",
    "gn:population":0,
    "gn:timezone":"Africa/Khartoum",
    "iso:country":"SD",
    "wof:name":"El Basaber el Sok",
    "wof:placetype":"locality"
},
  "geometry": {"coordinates":[32.9926,16.5258],"type":"Point"}
}