{
  "type": "Feature",
  "properties": {
    "gn:admin1_code":"52.0",
    "gn:asciiname":"Qaryah al Qurashi",
    "gn:country_code":"SD",
    "gn:dem":463,
    "gn:feature_class":"P",
    "gn:feature_code":"PPL",
    "gn:name":"Qaryah al Qurashi",
    "gn:population":0,
    "gn:timezone":"Africa/Khartoum",
    "iso:country":"SD",
    "name:und_x_variant":[
        "El Qurashi",
        "Qaryah al Qurashi"
    ],
    "wof:name":"Qaryah al Qurashi",
    "wof:placetype":"locality"
},
  "geometry": {"coordinates":[35.898,15.1242],"type":"Point"}
}