{
  "type": "Feature",
  "properties": {
    "gn:admin1_code":"41.0",
    "gn:asciiname":"Um Sanqur al Lahamda",
    "gn:country_code":"SD",
    "gn:dem":428,
    "gn:feature_class":"P",
    "gn:feature_code":"PPL",
    "gn:name":"Um \u015eanq\u016br al La\u1e29\u0101mda",
    "gn:population":0,
    "gn:timezone":"Africa/Khartoum",
    "iso:country":"SD",
    "name:und_x_variant":[
        "Um \u015eanq\u016br al La\u1e29\u0101mda"
    ],
    "wof:lang_x_official":[
        "ara",
        "eng"
    ],
    "wof:lang_x_spoken":[
        "ara",
        "eng"
    ],
    "wof:name":"Um Sanqur al Lahamda",
    "wof:placetype":"locality"
},
  "geometry": {"coordinates":[33.0459,12.9077],"type":"Point"}
}