{
  "type": "Feature",
  "properties": {
    "gn:admin1_code":"41.0",
    "gn:asciiname":"Taqra`",
    "gn:country_code":"SD",
    "gn:dem":387,
    "gn:feature_class":"P",
    "gn:feature_code":"PPL",
    "gn:name":"Taqra\u2018",
    "gn:population":0,
    "gn:timezone":"Africa/Khartoum",
    "iso:country":"SD",
    "name:und_x_variant":[
        "Taqra\u2018"
    ],
    "wof:name":"Taqra`",
    "wof:placetype":"locality"
},
  "geometry": {"coordinates":[32.3731,13.9641],"type":"Point"}
}