{
  "type": "Feature",
  "properties": {
    "gn:admin1_code":"47.0",
    "gn:asciiname":"Maburikei",
    "gn:country_code":"SD",
    "gn:dem":778,
    "gn:feature_class":"P",
    "gn:feature_code":"PPL",
    "gn:name":"Maburikei",
    "gn:population":0,
    "gn:timezone":"Africa/Khartoum",
    "iso:country":"SD",
    "name:eng_x_preferred":[
        "Maburikei"
    ],
    "wof:name":"Maburikei",
    "wof:placetype":"locality"
},
  "geometry": {"coordinates":[22.18902000000001,13.13697],"type":"Point"}
}