{
  "type": "Feature",
  "properties": {
    "gn:admin1_code":"38.0",
    "gn:asciiname":"Kobjar",
    "gn:country_code":"SD",
    "gn:dem":404,
    "gn:feature_class":"P",
    "gn:feature_code":"PPL",
    "gn:name":"Kobjar",
    "gn:population":0,
    "gn:timezone":"Africa/Khartoum",
    "iso:country":"SD",
    "wof:name":"Kobjar",
    "wof:placetype":"locality"
},
  "geometry": {"coordinates":[33.2052,14.622],"type":"Point"}
}