{
  "type": "Feature",
  "properties": {
    "gn:admin1_code":"29.0",
    "gn:asciiname":"Hillat at Tires",
    "gn:country_code":"SD",
    "gn:dem":382,
    "gn:feature_class":"P",
    "gn:feature_code":"PPL",
    "gn:name":"Hillat at Tires",
    "gn:population":0,
    "gn:timezone":"Africa/Khartoum",
    "iso:country":"SD",
    "name:und_x_variant":[
        "Et Tireis",
        "At Tireis",
        "Hillat at Tires"
    ],
    "wof:name":"Hillat at Tires",
    "wof:placetype":"locality"
},
  "geometry": {"coordinates":[32.4647,15.358],"type":"Point"}
}