{
  "type": "Feature",
  "properties": {
    "gn:country":"SD",
    "gn:fcode":"PPL",
    "gn:population":9775,
    "iso:country":"SD",
    "name:und_x_variant":[
        "Kereimet"
    ],
    "qs:name":"Al Kiremit al \u2018Arakiyy\u012bn",
    "qs:photos_9r":0,
    "qs:photos_sr":0,
    "qs:pop_sr":"5",
    "wof:name":"Al Kiremit al \u2018Arakiyy\u012bn",
    "wof:placetype":"locality",
    "wof:population":9775
},
  "geometry": {"coordinates":[32.9437,14.3476],"type":"Point"}
}