{
  "type": "Feature",
  "properties": {
    "iso:country":"SD",
    "qs:gn_pop":0,
    "qs:name":"\u0627\u0644\u062e\u0631\u0637\u0648\u0645",
    "qs:name_adm0":"\u0627\u0644\u0633\u0648\u062f\u0627\u0646",
    "qs:name_adm1":"\u00a0\u0648\u0644\u0627\u064a\u0629 \u0627\u0644\u062e\u0631\u0637\u0648\u0645",
    "qs:photos":1019,
    "qs:photos_1k":206,
    "qs:photos_9k":9,
    "qs:photos_9r":9,
    "qs:photos_all":2031,
    "qs:photos_sr":11,
    "qs:placetype":"Town",
    "qs:pop_sr":"0",
    "qs:woe_adm0":23424952,
    "wof:name":"\u0627\u0644\u062e\u0631\u0637\u0648\u0645",
    "wof:placetype":"locality"
},
  "geometry": {"coordinates":[32.522106,15.59092],"type":"Point"}
}