{
  "type": "Feature",
  "properties": {
    "gn:admin1_code":"42.0",
    "gn:asciiname":"Abu Qudaf",
    "gn:country_code":"SD",
    "gn:dem":574,
    "gn:feature_class":"P",
    "gn:feature_code":"PPL",
    "gn:name":"Ab\u016b Qud\u0101f",
    "gn:population":0,
    "gn:timezone":"Africa/Khartoum",
    "iso:country":"SD",
    "name:und_x_variant":[
        "Abu Gedaf",
        "Ab\u016b Qud\u0101f"
    ],
    "wof:name":"Abu Qudaf",
    "wof:placetype":"locality"
},
  "geometry": {"coordinates":[34.83333,11.48333],"type":"Point"}
}