{
  "type": "Feature",
  "properties": {
    "gn:admin1_code":"55.0",
    "gn:asciiname":"Fazi",
    "gn:country_code":"SD",
    "gn:dem":888,
    "gn:feature_class":"P",
    "gn:feature_code":"PPL",
    "gn:name":"Fazi",
    "gn:population":0,
    "gn:timezone":"Africa/Khartoum",
    "iso:country":"SD",
    "wof:name":"Fazi",
    "wof:placetype":"locality"
},
  "geometry": {"coordinates":[25.51667,13.96667],"type":"Point"}
}