{
  "type": "Feature",
  "properties": {
    "gn:admin1_code":"62.0",
    "gn:asciiname":"Ya`qub",
    "gn:country_code":"SD",
    "gn:dem":501,
    "gn:feature_class":"P",
    "gn:feature_code":"PPL",
    "gn:name":"Ya\u2018q\u016bb",
    "gn:population":0,
    "gn:timezone":"Africa/Khartoum",
    "iso:country":"SD",
    "wof:name":"Ya`qub",
    "wof:placetype":"locality"
},
  "geometry": {"coordinates":[29.31667,11.11667],"type":"Point"}
}