{
  "type": "Feature",
  "properties": {
    "gn:admin1_code":"56.0",
    "gn:asciiname":"Hegam",
    "gn:country_code":"SD",
    "gn:dem":467,
    "gn:feature_class":"P",
    "gn:feature_code":"PPL",
    "gn:name":"Hegam",
    "gn:population":0,
    "gn:timezone":"Africa/Khartoum",
    "iso:country":"SD",
    "wof:name":"Hegam",
    "wof:placetype":"locality"
},
  "geometry": {"coordinates":[30.85,13.53333],"type":"Point"}
}