{
  "type": "Feature",
  "properties": {
    "gn:admin1_code":"38.0",
    "gn:asciiname":"Sukayranah",
    "gn:cc2":"SD",
    "gn:country_code":"SD",
    "gn:dem":407,
    "gn:feature_class":"P",
    "gn:feature_code":"PPL",
    "gn:name":"Sukayr\u0101nah",
    "gn:population":0,
    "gn:timezone":"Africa/Khartoum",
    "iso:country":"SD",
    "name:und_x_variant":[
        "Sukeirana",
        "Sukayr\u0101nah"
    ],
    "wof:name":"Sukayranah",
    "wof:placetype":"locality"
},
  "geometry": {"coordinates":[33.44389,15.1275],"type":"Point"}
}