{
  "type": "Feature",
  "properties": {
    "gn:admin1_code":"55.0",
    "gn:asciiname":"Seiger",
    "gn:country_code":"SD",
    "gn:dem":1029,
    "gn:feature_class":"P",
    "gn:feature_code":"PPL",
    "gn:name":"Seiger",
    "gn:population":0,
    "gn:timezone":"Africa/Khartoum",
    "iso:country":"SD",
    "wof:name":"Seiger",
    "wof:placetype":"locality"
},
  "geometry": {"coordinates":[23.8066,13.43048],"type":"Point"}
}