{
  "type": "Feature",
  "properties": {
    "gn:admin1_code":"53.0",
    "gn:asciiname":"Hillat el Hawya",
    "gn:country_code":"SD",
    "gn:dem":357,
    "gn:feature_class":"P",
    "gn:feature_code":"PPL",
    "gn:name":"Hillat el Hawya",
    "gn:population":0,
    "gn:timezone":"Africa/Khartoum",
    "iso:country":"SD",
    "wof:name":"Hillat el Hawya",
    "wof:placetype":"locality"
},
  "geometry": {"coordinates":[33.7938,17.3339],"type":"Point"}
}