{
  "type": "Feature",
  "properties": {
    "gn:admin1_code":"43.0",
    "gn:asciiname":"Mulwad",
    "gn:country_code":"SD",
    "gn:dem":237,
    "gn:feature_class":"P",
    "gn:feature_code":"PPL",
    "gn:name":"Mulwad",
    "gn:population":0,
    "gn:timezone":"Africa/Khartoum",
    "iso:country":"SD",
    "name:und_x_variant":[
        "Malwad",
        "Mulwad"
    ],
    "wof:name":"Mulwad",
    "wof:placetype":"locality"
},
  "geometry": {"coordinates":[30.58333,18.65],"type":"Point"}
}