{
  "type": "Feature",
  "properties": {
    "gn:admin1_code":"38.0",
    "gn:asciiname":"Fadasi Al `Amrab",
    "gn:country_code":"SD",
    "gn:dem":409,
    "gn:feature_class":"P",
    "gn:feature_code":"PPL",
    "gn:name":"Fad\u0101si Al \u2018Amrab",
    "gn:population":0,
    "gn:timezone":"Africa/Khartoum",
    "iso:country":"SD",
    "name:und_x_variant":[
        "Fadasi el Umarab",
        "Fadasi al \u2018Umar\u0101b",
        "Fad\u0101si Al \u2018Amrab"
    ],
    "wof:name":"Fadasi Al `Amrab",
    "wof:placetype":"locality"
},
  "geometry": {"coordinates":[33.4504,14.5352],"type":"Point"}
}