{
  "type": "Feature",
  "properties": {
    "gn:admin1_code":"47.0",
    "gn:asciiname":"Bardei",
    "gn:country_code":"SD",
    "gn:dem":810,
    "gn:feature_class":"P",
    "gn:feature_code":"PPL",
    "gn:name":"Bardei",
    "gn:population":0,
    "gn:timezone":"Africa/Khartoum",
    "iso:country":"SD",
    "name:eng_x_preferred":[
        "Bardei"
    ],
    "wof:name":"Bardei",
    "wof:placetype":"locality"
},
  "geometry": {"coordinates":[22.09626,13.13471],"type":"Point"}
}