{
  "type": "Feature",
  "properties": {
    "gn:admin1_code":"36.0",
    "gn:asciiname":"Dungunab",
    "gn:country_code":"SD",
    "gn:dem":6,
    "gn:feature_class":"P",
    "gn:feature_code":"PPL",
    "gn:name":"Dungun\u0101b",
    "gn:population":0,
    "gn:timezone":"Africa/Khartoum",
    "iso:country":"SD",
    "name:ara_x_preferred":[
        "Dungun\u0101b"
    ],
    "name:und_x_variant":[
        "Donganab",
        "Dunganab",
        "Dunjun\u0101b",
        "Dunqun\u0101b"
    ],
    "wof:name":"Dungunab",
    "wof:placetype":"locality"
},
  "geometry": {"coordinates":[37.1171,21.1076],"type":"Point"}
}