{
  "type": "Feature",
  "properties": {
    "gn:admin1_code":"29.0",
    "gn:asciiname":"Shaykh Talhah",
    "gn:cc2":"SD",
    "gn:country_code":"SD",
    "gn:dem":478,
    "gn:feature_class":"P",
    "gn:feature_code":"PPL",
    "gn:name":"Shaykh \u0162al\u1e29ah",
    "gn:population":0,
    "gn:timezone":"Africa/Khartoum",
    "iso:country":"SD",
    "name:und_x_variant":[
        "Sheikh Talha",
        "Shaykh \u0162al\u1e29ah"
    ],
    "wof:name":"Shaykh Talhah",
    "wof:placetype":"locality"
},
  "geometry": {"coordinates":[34.18333,15.86667],"type":"Point"}
}