{
  "type": "Feature",
  "properties": {
    "gn:admin1_code":"36.0",
    "gn:asciiname":"Dilay",
    "gn:country_code":"SD",
    "gn:dem":512,
    "gn:feature_class":"P",
    "gn:feature_code":"PPL",
    "gn:name":"Dil\u0101y",
    "gn:population":0,
    "gn:timezone":"Africa/Khartoum",
    "iso:country":"SD",
    "name:ara_x_preferred":[
        "Dil\u0101y"
    ],
    "wof:name":"Dilay",
    "wof:placetype":"locality"
},
  "geometry": {"coordinates":[36.0887,17.3705],"type":"Point"}
}