{
  "type": "Feature",
  "properties": {
    "gn:admin1_code":"58.0",
    "gn:asciiname":"Hilmi",
    "gn:country_code":"SD",
    "gn:dem":424,
    "gn:feature_class":"P",
    "gn:feature_code":"PPL",
    "gn:name":"Hilmi",
    "gn:population":0,
    "gn:timezone":"Africa/Khartoum",
    "iso:country":"SD",
    "wof:name":"Hilmi",
    "wof:placetype":"locality"
},
  "geometry": {"coordinates":[33.63333,13.65],"type":"Point"}
}