{
  "type": "Feature",
  "properties": {
    "gn:admin1_code":"38.0",
    "gn:asciiname":"Beriab al Hujayr",
    "gn:country_code":"SD",
    "gn:dem":406,
    "gn:feature_class":"P",
    "gn:feature_code":"PPL",
    "gn:name":"Beriab al \u1e28ujayr",
    "gn:population":0,
    "gn:timezone":"Africa/Khartoum",
    "iso:country":"SD",
    "name:und_x_variant":[
        "Beriab el Hugeir",
        "Beriab al \u1e28ujayr"
    ],
    "wof:name":"Beriab al Hujayr",
    "wof:placetype":"locality"
},
  "geometry": {"coordinates":[33.68333,14.11667],"type":"Point"}
}