{
  "type": "Feature",
  "properties": {
    "gn:admin1_code":"29.0",
    "gn:asciiname":"Farig Wlad al lamin Wad al `Ajab",
    "gn:country_code":"SD",
    "gn:dem":522,
    "gn:feature_class":"P",
    "gn:feature_code":"PPL",
    "gn:name":"Farig Wlad al lamin Wad al \u2018Ajab",
    "gn:population":0,
    "gn:timezone":"Africa/Khartoum",
    "iso:country":"SD",
    "name:und_x_variant":[
        "Farig Wlad al lamin Wad al \u2018Ajab"
    ],
    "wof:name":"Farig Wlad al lamin Wad al `Ajab",
    "wof:placetype":"locality"
},
  "geometry": {"coordinates":[33.4162,15.8568],"type":"Point"}
}