{
  "type": "Feature",
  "properties": {
    "gn:admin1_code":"42.0",
    "gn:asciiname":"Karri",
    "gn:country_code":"SD",
    "gn:dem":540,
    "gn:feature_class":"P",
    "gn:feature_code":"PPL",
    "gn:name":"Karri",
    "gn:population":0,
    "gn:timezone":"Africa/Khartoum",
    "iso:country":"SD",
    "wof:name":"Karri",
    "wof:placetype":"locality"
},
  "geometry": {"coordinates":[34.6332,11.8456],"type":"Point"}
}