{
  "type": "Feature",
  "properties": {
    "gn:admin1_code":"38.0",
    "gn:asciiname":"Addabba",
    "gn:country_code":"SD",
    "gn:dem":397,
    "gn:feature_class":"P",
    "gn:feature_code":"PPL",
    "gn:name":"Addabba",
    "gn:population":0,
    "gn:timezone":"Africa/Khartoum",
    "iso:country":"SD",
    "wof:name":"Addabba",
    "wof:placetype":"locality"
},
  "geometry": {"coordinates":[32.6813,14.0969],"type":"Point"}
}