{
  "type": "Feature",
  "properties": {
    "gn:admin1_code":"60.0",
    "gn:asciiname":"Bana",
    "gn:country_code":"SD",
    "gn:dem":437,
    "gn:feature_class":"P",
    "gn:feature_code":"PPL",
    "gn:name":"Bana",
    "gn:population":0,
    "gn:timezone":"Africa/Khartoum",
    "iso:country":"SD",
    "wof:name":"Bana",
    "wof:placetype":"locality"
},
  "geometry": {"coordinates":[26.83333,10.88333],"type":"Point"}
}