{
  "type": "Feature",
  "properties": {
    "gn:admin1_code":"58.0",
    "gn:asciiname":"`Abd al Karim",
    "gn:country_code":"SD",
    "gn:dem":438,
    "gn:feature_class":"P",
    "gn:feature_code":"PPL",
    "gn:name":"\u2018Abd al Kar\u012bm",
    "gn:population":0,
    "gn:timezone":"Africa/Khartoum",
    "iso:country":"SD",
    "name:und_x_variant":[
        "\u2018Abd el Karim",
        "\u2018Abd al Kar\u012bm"
    ],
    "wof:name":"`Abd al Karim",
    "wof:placetype":"locality"
},
  "geometry": {"coordinates":[33.81667,13.06667],"type":"Point"}
}