{
  "type": "Feature",
  "properties": {
    "gn:admin1_code":"58.0",
    "gn:asciiname":"Abu Hujar",
    "gn:country_code":"SD",
    "gn:dem":443,
    "gn:feature_class":"P",
    "gn:feature_code":"PPL",
    "gn:name":"Abu \u1e28uj\u0101r",
    "gn:population":0,
    "gn:timezone":"Africa/Khartoum",
    "iso:country":"SD",
    "name:ara_x_preferred":[
        "Abu \u1e28uj\u0101r"
    ],
    "name:und_x_variant":[
        "Abu Higar",
        "Ab\u016b \u1e28ij\u0101r"
    ],
    "wof:name":"Abu Hujar",
    "wof:placetype":"locality"
},
  "geometry": {"coordinates":[33.9885,12.8542],"type":"Point"}
}