{
  "type": "Feature",
  "properties": {
    "gn:admin1_code":"36.0",
    "gn:asciiname":"Hillat Ashat",
    "gn:country_code":"SD",
    "gn:dem":145,
    "gn:feature_class":"P",
    "gn:feature_code":"PPL",
    "gn:name":"Hillat Ashat",
    "gn:population":0,
    "gn:timezone":"Africa/Khartoum",
    "iso:country":"SD",
    "wof:name":"Hillat Ashat",
    "wof:placetype":"locality"
},
  "geometry": {"coordinates":[37.3541,18.6966],"type":"Point"}
}