{
  "type": "Feature",
  "properties": {
    "gn:admin1_code":"49.0",
    "gn:asciiname":"Rumalia",
    "gn:country_code":"SD",
    "gn:dem":871,
    "gn:feature_class":"P",
    "gn:feature_code":"PPL",
    "gn:name":"Rumalia",
    "gn:population":0,
    "gn:timezone":"Africa/Khartoum",
    "iso:country":"SD",
    "wof:name":"Rumalia",
    "wof:placetype":"locality"
},
  "geometry": {"coordinates":[23.91667,12.23333],"type":"Point"}
}