{
  "type": "Feature",
  "properties": {
    "gn:admin1_code":"47.0",
    "gn:asciiname":"Bandadito",
    "gn:country_code":"SD",
    "gn:dem":596,
    "gn:feature_class":"P",
    "gn:feature_code":"PPL",
    "gn:name":"Bandadito",
    "gn:population":0,
    "gn:timezone":"Africa/Khartoum",
    "iso:country":"SD",
    "name:und_x_variant":[
        "Bondetto",
        "Bandadito"
    ],
    "wof:name":"Bandadito",
    "wof:placetype":"locality"
},
  "geometry": {"coordinates":[22.50913,12.3516],"type":"Point"}
}