{
  "type": "Feature",
  "properties": {
    "gn:admin1_code":"56.0",
    "gn:asciiname":"An Nur",
    "gn:country_code":"SD",
    "gn:dem":498,
    "gn:feature_class":"P",
    "gn:feature_code":"PPL",
    "gn:name":"An N\u016br",
    "gn:population":0,
    "gn:timezone":"Africa/Khartoum",
    "iso:country":"SD",
    "name:und_x_variant":[
        "Nur",
        "En Nur",
        "An N\u016br"
    ],
    "wof:name":"An Nur",
    "wof:placetype":"locality"
},
  "geometry": {"coordinates":[30.61667000000001,12.66667],"type":"Point"}
}