{
  "type": "Feature",
  "properties": {
    "gn:admin1_code":"47.0",
    "gn:asciiname":"Wiwi",
    "gn:country_code":"SD",
    "gn:dem":1011,
    "gn:feature_class":"P",
    "gn:feature_code":"PPL",
    "gn:name":"Wiwi",
    "gn:population":0,
    "gn:timezone":"Africa/Khartoum",
    "iso:country":"SD",
    "wof:name":"Wiwi",
    "wof:placetype":"locality"
},
  "geometry": {"coordinates":[22.74547,14.15173],"type":"Point"}
}