{
  "type": "Feature",
  "properties": {
    "gn:admin1_code":"50.0",
    "gn:asciiname":"Kurundul",
    "gn:country_code":"SD",
    "gn:dem":660,
    "gn:feature_class":"P",
    "gn:feature_code":"PPL",
    "gn:name":"Kurundul",
    "gn:population":0,
    "gn:timezone":"Africa/Khartoum",
    "iso:country":"SD",
    "wof:name":"Kurundul",
    "wof:placetype":"locality"
},
  "geometry": {"coordinates":[30.2358,11.4166],"type":"Point"}
}