{
  "type": "Feature",
  "properties": {
    "gn:admin1_code":"58.0",
    "gn:asciiname":"Sharif al Amin",
    "gn:country_code":"SD",
    "gn:dem":420,
    "gn:feature_class":"P",
    "gn:feature_code":"PPL",
    "gn:name":"Shar\u012bf al Am\u012bn",
    "gn:population":0,
    "gn:timezone":"Africa/Khartoum",
    "iso:country":"SD",
    "name:und_x_variant":[
        "Sherif el Amin",
        "Shar\u012bf al Am\u012bn"
    ],
    "wof:name":"Sharif al Amin",
    "wof:placetype":"locality"
},
  "geometry": {"coordinates":[33.75,13.65],"type":"Point"}
}