{
  "type": "Feature",
  "properties": {
    "gn:admin1_code":"38.0",
    "gn:asciiname":"Abu Shineb",
    "gn:country_code":"SD",
    "gn:dem":398,
    "gn:feature_class":"P",
    "gn:feature_code":"PPL",
    "gn:name":"Abu Shineb",
    "gn:population":0,
    "gn:timezone":"Africa/Khartoum",
    "iso:country":"SD",
    "name:und_x_variant":[
        "Abu Shuneib",
        "Ab\u016b Shunayb",
        "Abu Shineb"
    ],
    "wof:name":"Abu Shineb",
    "wof:placetype":"locality"
},
  "geometry": {"coordinates":[32.9993,14.9006],"type":"Point"}
}