{
  "type": "Feature",
  "properties": {
    "gn:admin1_code":"52.0",
    "gn:asciiname":"Qaryah Sittata `Ashar",
    "gn:country_code":"SD",
    "gn:dem":450,
    "gn:feature_class":"P",
    "gn:feature_code":"PPL",
    "gn:name":"Qaryah Sittata \u2018Ashar",
    "gn:population":0,
    "gn:timezone":"Africa/Khartoum",
    "iso:country":"SD",
    "name:und_x_variant":[
        "Qaryah Sittata \u2018Ashar"
    ],
    "wof:name":"Qaryah Sittata `Ashar",
    "wof:placetype":"locality"
},
  "geometry": {"coordinates":[35.5555,15.3338],"type":"Point"}
}