{
  "type": "Feature",
  "properties": {
    "gn:admin1_code":"29.0",
    "gn:asciiname":"Ad Delatia",
    "gn:country_code":"SD",
    "gn:dem":389,
    "gn:feature_class":"P",
    "gn:feature_code":"PPL",
    "gn:name":"Ad Delatia",
    "gn:population":0,
    "gn:timezone":"Africa/Khartoum",
    "iso:country":"SD",
    "name:und_x_variant":[
        "Ed Delatia",
        "Ad Delatia"
    ],
    "wof:name":"Ad Delatia",
    "wof:placetype":"locality"
},
  "geometry": {"coordinates":[32.88333,15.36667],"type":"Point"}
}