{
  "type": "Feature",
  "properties": {
    "gn:admin1_code":"61.0",
    "gn:asciiname":"Kasoleri",
    "gn:country_code":"SD",
    "gn:dem":643,
    "gn:feature_class":"P",
    "gn:feature_code":"PPL",
    "gn:name":"Kasoleri",
    "gn:population":0,
    "gn:timezone":"Africa/Khartoum",
    "iso:country":"SD",
    "wof:name":"Kasoleri",
    "wof:placetype":"locality"
},
  "geometry": {"coordinates":[23.00944,11.98013],"type":"Point"}
}