{
  "type": "Feature",
  "properties": {
    "gn:admin1_code":"29.0",
    "gn:asciiname":"Hillat ed Dom",
    "gn:country_code":"SD",
    "gn:dem":380,
    "gn:feature_class":"P",
    "gn:feature_code":"PPL",
    "gn:name":"Hillat ed Dom",
    "gn:population":0,
    "gn:timezone":"Africa/Khartoum",
    "iso:country":"SD",
    "name:und_x_variant":[
        "Ad Dawm",
        "Ed Dom",
        "Hillat ed Dom"
    ],
    "wof:name":"Hillat ed Dom",
    "wof:placetype":"locality"
},
  "geometry": {"coordinates":[32.5847,16.0332],"type":"Point"}
}