{
  "type": "Feature",
  "properties": {
    "gn:admin1_code":"50.0",
    "gn:asciiname":"Kulubna",
    "gn:country_code":"SD",
    "gn:dem":789,
    "gn:feature_class":"P",
    "gn:feature_code":"PPL",
    "gn:name":"Kulubna",
    "gn:population":0,
    "gn:timezone":"Africa/Khartoum",
    "iso:country":"SD",
    "wof:name":"Kulubna",
    "wof:placetype":"locality"
},
  "geometry": {"coordinates":[30.3941,11.6644],"type":"Point"}
}