{
  "type": "Feature",
  "properties": {
    "gn:admin1_code":"49.0",
    "gn:asciiname":"Ma'adat el Eida",
    "gn:country_code":"SD",
    "gn:dem":467,
    "gn:feature_class":"P",
    "gn:feature_code":"PPL",
    "gn:name":"Ma\u2019adat el Eida",
    "gn:population":0,
    "gn:timezone":"Africa/Khartoum",
    "iso:country":"SD",
    "wof:name":"Ma'adat el Eida",
    "wof:placetype":"locality"
},
  "geometry": {"coordinates":[25.28651,10.3564],"type":"Point"}
}