{
  "type": "Feature",
  "properties": {
    "gn:admin1_code":"41.0",
    "gn:asciiname":"Qoz Marfa`in",
    "gn:country_code":"SD",
    "gn:dem":387,
    "gn:feature_class":"P",
    "gn:feature_code":"PPL",
    "gn:name":"Qoz Marfa\u2018\u012bn",
    "gn:population":0,
    "gn:timezone":"Africa/Khartoum",
    "iso:country":"SD",
    "name:und_x_variant":[
        "Qoz Marfa\u2018\u012bn"
    ],
    "wof:name":"Qoz Marfa`in",
    "wof:placetype":"locality"
},
  "geometry": {"coordinates":[32.2731,13.8145],"type":"Point"}
}