{
  "type": "Feature",
  "properties": {
    "gn:admin1_code":"38.0",
    "gn:asciiname":"Al Fawwara",
    "gn:country_code":"SD",
    "gn:dem":396,
    "gn:feature_class":"P",
    "gn:feature_code":"PPL",
    "gn:name":"Al Faww\u0101ra",
    "gn:population":0,
    "gn:timezone":"Africa/Khartoum",
    "iso:country":"SD",
    "name:und_x_variant":[
        "Al Faww\u0101ra"
    ],
    "wof:name":"Al Fawwara",
    "wof:placetype":"locality"
},
  "geometry": {"coordinates":[32.9257,14.9275],"type":"Point"}
}