{
  "type": "Feature",
  "properties": {
    "gn:admin1_code":"56.0",
    "gn:asciiname":"Maltut",
    "gn:country_code":"SD",
    "gn:dem":486,
    "gn:feature_class":"P",
    "gn:feature_code":"PPL",
    "gn:name":"Maltut",
    "gn:population":0,
    "gn:timezone":"Africa/Khartoum",
    "iso:country":"SD",
    "wof:name":"Maltut",
    "wof:placetype":"locality"
},
  "geometry": {"coordinates":[30.73333,13.16667],"type":"Point"}
}