{
  "type": "Feature",
  "properties": {
    "gn:admin1_code":"38.0",
    "gn:asciiname":"Miter",
    "gn:country_code":"SD",
    "gn:dem":398,
    "gn:feature_class":"P",
    "gn:feature_code":"PPL",
    "gn:name":"Miter",
    "gn:population":0,
    "gn:timezone":"Africa/Khartoum",
    "iso:country":"SD",
    "wof:name":"Miter",
    "wof:placetype":"locality"
},
  "geometry": {"coordinates":[32.7422,14.4659],"type":"Point"}
}