{
  "type": "Feature",
  "properties": {
    "gn:admin1_code":"50.0",
    "gn:asciiname":"Tuli",
    "gn:country_code":"SD",
    "gn:dem":659,
    "gn:feature_class":"P",
    "gn:feature_code":"PPL",
    "gn:name":"Tuli",
    "gn:population":0,
    "gn:timezone":"Africa/Khartoum",
    "iso:country":"SD",
    "name:bar_x_preferred":[
        "Tuli"
    ],
    "name:ceb_x_preferred":[
        "Tuli"
    ],
    "name:fra_x_preferred":[
        "Tuli"
    ],
    "name:swe_x_preferred":[
        "Tuli"
    ],
    "wof:name":"Tuli",
    "wof:placetype":"locality"
},
  "geometry": {"coordinates":[29.746,11.5731],"type":"Point"}
}