{
  "type": "Feature",
  "properties": {
    "gn:admin1_code":"41.0",
    "gn:asciiname":"Umm `Angareib",
    "gn:country_code":"SD",
    "gn:dem":397,
    "gn:feature_class":"P",
    "gn:feature_code":"PPL",
    "gn:name":"Umm \u2018Angareib",
    "gn:population":0,
    "gn:timezone":"Africa/Khartoum",
    "iso:country":"SD",
    "wof:name":"Umm `Angareib",
    "wof:placetype":"locality"
},
  "geometry": {"coordinates":[32.51667,12.88333],"type":"Point"}
}