{
  "type": "Feature",
  "properties": {
    "gn:admin1_code":"38.0",
    "gn:asciiname":"Wad Sider",
    "gn:country_code":"SD",
    "gn:dem":401,
    "gn:feature_class":"P",
    "gn:feature_code":"PPL",
    "gn:name":"Wad Sider",
    "gn:population":0,
    "gn:timezone":"Africa/Khartoum",
    "iso:country":"SD",
    "wof:name":"Wad Sider",
    "wof:placetype":"locality"
},
  "geometry": {"coordinates":[32.7818,14.3578],"type":"Point"}
}