{
  "type": "Feature",
  "properties": {
    "gn:admin1_code":"55.0",
    "gn:asciiname":"`Ali",
    "gn:country_code":"SD",
    "gn:dem":738,
    "gn:feature_class":"P",
    "gn:feature_code":"PPL",
    "gn:name":"\u2018Al\u012b",
    "gn:population":0,
    "gn:timezone":"Africa/Khartoum",
    "iso:country":"SD",
    "wof:name":"`Ali",
    "wof:placetype":"locality"
},
  "geometry": {"coordinates":[25.95,13.96667],"type":"Point"}
}