{
  "type": "Feature",
  "properties": {
    "gn:admin1_code":"49.0",
    "gn:asciiname":"Buram",
    "gn:country_code":"SD",
    "gn:dem":534,
    "gn:feature_class":"P",
    "gn:feature_code":"PPL",
    "gn:name":"Buram",
    "gn:population":0,
    "gn:timezone":"Africa/Khartoum",
    "iso:country":"SD",
    "wof:name":"Buram",
    "wof:placetype":"locality"
},
  "geometry": {"coordinates":[24.33333,11.01667],"type":"Point"}
}