{
  "type": "Feature",
  "properties": {
    "gn:admin1_code":"38.0",
    "gn:asciiname":"Taftish An Nadyana",
    "gn:country_code":"SD",
    "gn:dem":406,
    "gn:feature_class":"P",
    "gn:feature_code":"PPL",
    "gn:name":"Taftish An Nady\u0101na",
    "gn:population":0,
    "gn:timezone":"Africa/Khartoum",
    "iso:country":"SD",
    "name:und_x_variant":[
        "Taftish An Nady\u0101na"
    ],
    "wof:name":"Taftish An Nadyana",
    "wof:placetype":"locality"
},
  "geometry": {"coordinates":[33.292,14.6271],"type":"Point"}
}