{
  "type": "Feature",
  "properties": {
    "gn:admin1_code":"58.0",
    "gn:asciiname":"Um `Aqrab",
    "gn:country_code":"SD",
    "gn:dem":448,
    "gn:feature_class":"P",
    "gn:feature_code":"PPL",
    "gn:name":"Um \u2018Aqrab",
    "gn:population":0,
    "gn:timezone":"Africa/Khartoum",
    "iso:country":"SD",
    "name:und_x_variant":[
        "Um \u2018Aqrab"
    ],
    "wof:name":"Um `Aqrab",
    "wof:placetype":"locality"
},
  "geometry": {"coordinates":[34.6288,12.9524],"type":"Point"}
}