{
  "type": "Feature",
  "properties": {
    "gn:admin1_code":"49.0",
    "gn:asciiname":"Abu Qussah",
    "gn:country_code":"SD",
    "gn:dem":457,
    "gn:feature_class":"P",
    "gn:feature_code":"PPL",
    "gn:name":"Ab\u016b Qu\u015f\u015fah",
    "gn:population":0,
    "gn:timezone":"Africa/Khartoum",
    "iso:country":"SD",
    "name:und_x_variant":[
        "Abu Qussa",
        "Ab\u016b Qu\u015f\u015fah"
    ],
    "wof:lang_x_official":[
        "ara",
        "eng"
    ],
    "wof:lang_x_spoken":[
        "ara",
        "eng"
    ],
    "wof:name":"Abu Qussah",
    "wof:placetype":"locality"
},
  "geometry": {"coordinates":[25.53333,10.83333],"type":"Point"}
}