{
  "type": "Feature",
  "properties": {
    "gn:admin1_code":"38.0",
    "gn:asciiname":"Um Marrahi Masa`ad",
    "gn:country_code":"SD",
    "gn:dem":410,
    "gn:feature_class":"P",
    "gn:feature_code":"PPL",
    "gn:name":"Um Marra\u1e29i Mas\u0101\u2018ad",
    "gn:population":0,
    "gn:timezone":"Africa/Khartoum",
    "iso:country":"SD",
    "name:und_x_variant":[
        "Um Marra\u1e29i Mas\u0101\u2018ad"
    ],
    "wof:name":"Um Marrahi Masa`ad",
    "wof:placetype":"locality"
},
  "geometry": {"coordinates":[33.3635,14.2784],"type":"Point"}
}