{
  "type": "Feature",
  "properties": {
    "gn:admin1_code":"36.0",
    "gn:asciiname":"Afflanda",
    "gn:country_code":"SD",
    "gn:dem":12,
    "gn:feature_class":"P",
    "gn:feature_code":"PPL",
    "gn:name":"Afflanda",
    "gn:population":0,
    "gn:timezone":"Africa/Khartoum",
    "iso:country":"SD",
    "name:und_x_variant":[
        "Aflanda",
        "Afflanda"
    ],
    "wof:name":"Afflanda",
    "wof:placetype":"locality"
},
  "geometry": {"coordinates":[38.41667,18.05],"type":"Point"}
}