{
  "type": "Feature",
  "properties": {
    "gn:admin1_code":"38.0",
    "gn:asciiname":"Farah",
    "gn:country_code":"SD",
    "gn:dem":408,
    "gn:feature_class":"P",
    "gn:feature_code":"PPL",
    "gn:name":"Fara\u1e29",
    "gn:population":0,
    "gn:timezone":"Africa/Khartoum",
    "iso:country":"SD",
    "name:bpy_x_preferred":[
        "\u09ab\u09be\u09b0\u09be\u09b9"
    ],
    "name:ceb_x_preferred":[
        "Farah"
    ],
    "name:ces_x_preferred":[
        "Farah"
    ],
    "name:deu_x_preferred":[
        "Farah"
    ],
    "name:fas_x_preferred":[
        "\u0641\u0631\u062d"
    ],
    "name:ita_x_preferred":[
        "Farah"
    ],
    "name:msa_x_preferred":[
        "Farah"
    ],
    "name:new_x_preferred":[
        "\u092b\u0930\u093e\u0939"
    ],
    "name:nld_x_preferred":[
        "Farah"
    ],
    "name:pol_x_preferred":[
        "Farah"
    ],
    "name:rus_x_preferred":[
        "\u0424\u0430\u0440\u0430\u0445"
    ],
    "name:slk_x_preferred":[
        "Far\u00e1h"
    ],
    "name:swe_x_preferred":[
        "Farah"
    ],
    "name:ukr_x_preferred":[
        "\u0424\u0430\u0440\u0430\u0445"
    ],
    "name:und_x_variant":[
        "Fara\u1e29"
    ],
    "wof:name":"Farah",
    "wof:placetype":"locality"
},
  "geometry": {"coordinates":[33.2828,14.3815],"type":"Point"}
}