{
  "type": "Feature",
  "properties": {
    "gn:admin1_code":"61.0",
    "gn:asciiname":"Kulla",
    "gn:country_code":"SD",
    "gn:dem":955,
    "gn:feature_class":"P",
    "gn:feature_code":"PPL",
    "gn:name":"Kulla",
    "gn:population":0,
    "gn:timezone":"Africa/Khartoum",
    "iso:country":"SD",
    "name:deu_x_preferred":[
        "Kulla"
    ],
    "name:fin_x_preferred":[
        "Kulla"
    ],
    "name:swe_x_preferred":[
        "Kulla"
    ],
    "wof:name":"Kulla",
    "wof:placetype":"locality"
},
  "geometry": {"coordinates":[23.40468,12.51811],"type":"Point"}
}