{
  "type": "Feature",
  "properties": {
    "gn:admin1_code":"47.0",
    "gn:asciiname":"Taziriba",
    "gn:country_code":"SD",
    "gn:dem":853,
    "gn:feature_class":"P",
    "gn:feature_code":"PPL",
    "gn:name":"Taziriba",
    "gn:population":0,
    "gn:timezone":"Africa/Khartoum",
    "iso:country":"SD",
    "name:und_x_variant":[
        "Tegriba",
        "Tegiriba",
        "Taziriba"
    ],
    "wof:name":"Taziriba",
    "wof:placetype":"locality"
},
  "geometry": {"coordinates":[23.21667,14.15],"type":"Point"}
}