{
  "type": "Feature",
  "properties": {
    "gn:admin1_code":"47.0",
    "gn:asciiname":"Adariam",
    "gn:country_code":"SD",
    "gn:dem":915,
    "gn:feature_class":"P",
    "gn:feature_code":"PPL",
    "gn:name":"Adariam",
    "gn:population":0,
    "gn:timezone":"Africa/Khartoum",
    "iso:country":"SD",
    "wof:name":"Adariam",
    "wof:placetype":"locality"
},
  "geometry": {"coordinates":[22.54485,14.37243],"type":"Point"}
}