{
  "type": "Feature",
  "properties": {
    "gn:admin1_code":"38.0",
    "gn:asciiname":"Ahmad al Mustafa",
    "gn:country_code":"SD",
    "gn:dem":401,
    "gn:feature_class":"P",
    "gn:feature_code":"PPL",
    "gn:name":"A\u1e29mad al Mu\u015f\u0163afa",
    "gn:population":0,
    "gn:timezone":"Africa/Khartoum",
    "iso:country":"SD",
    "name:und_x_variant":[
        "A\u1e29mad al Mu\u015f\u0163afa"
    ],
    "wof:name":"Ahmad al Mustafa",
    "wof:placetype":"locality"
},
  "geometry": {"coordinates":[32.7403,14.1998],"type":"Point"}
}