{
  "type": "Feature",
  "properties": {
    "gn:admin1_code":"50.0",
    "gn:asciiname":"Al Hejeir",
    "gn:country_code":"SD",
    "gn:dem":595,
    "gn:feature_class":"P",
    "gn:feature_code":"PPL",
    "gn:name":"Al Hejeir",
    "gn:population":0,
    "gn:timezone":"Africa/Khartoum",
    "iso:country":"SD",
    "wof:name":"Al Hejeir",
    "wof:placetype":"locality"
},
  "geometry": {"coordinates":[30.1321,11.1014],"type":"Point"}
}