{
  "type": "Feature",
  "properties": {
    "gn:admin1_code":"41.0",
    "gn:asciiname":"Al `Iddah",
    "gn:country_code":"SD",
    "gn:dem":395,
    "gn:feature_class":"P",
    "gn:feature_code":"PPL",
    "gn:name":"Al \u2018Iddah",
    "gn:population":0,
    "gn:timezone":"Africa/Khartoum",
    "iso:country":"SD",
    "name:und_x_variant":[
        "\u2018Idda",
        "El \u2018Idda",
        "Al \u2018Iddah"
    ],
    "wof:name":"Al `Iddah",
    "wof:placetype":"locality"
},
  "geometry": {"coordinates":[32.66667,14.76667],"type":"Point"}
}