{
  "type": "Feature",
  "properties": {
    "gn:admin1_code":"29.0",
    "gn:asciiname":"Sawba at Tayyib",
    "gn:cc2":"SD",
    "gn:country_code":"SD",
    "gn:dem":386,
    "gn:feature_class":"P",
    "gn:feature_code":"PPL",
    "gn:name":"Sawb\u0101 a\u0163 \u0162ayyib",
    "gn:population":0,
    "gn:timezone":"Africa/Khartoum",
    "iso:country":"SD",
    "name:und_x_variant":[
        "Soba et Taiyib",
        "Sawb\u0101 a\u0163 \u0162ayyib"
    ],
    "wof:name":"Sawba at Tayyib",
    "wof:placetype":"locality"
},
  "geometry": {"coordinates":[32.68333,15.51667],"type":"Point"}
}