{
  "type": "Feature",
  "properties": {
    "gn:admin1_code":"43.0",
    "gn:asciiname":"Dahasira",
    "gn:country_code":"SD",
    "gn:dem":258,
    "gn:feature_class":"P",
    "gn:feature_code":"PPL",
    "gn:name":"Dahasira",
    "gn:population":0,
    "gn:timezone":"Africa/Khartoum",
    "iso:country":"SD",
    "wof:name":"Dahasira",
    "wof:placetype":"locality"
},
  "geometry": {"coordinates":[31.76667,18.38333],"type":"Point"}
}