{
  "type": "Feature",
  "properties": {
    "gn:admin1_code":"38.0",
    "gn:asciiname":"Al Masara`a",
    "gn:country_code":"SD",
    "gn:dem":403,
    "gn:feature_class":"P",
    "gn:feature_code":"PPL",
    "gn:name":"Al Masara\u2018a",
    "gn:population":0,
    "gn:timezone":"Africa/Khartoum",
    "iso:country":"SD",
    "name:und_x_variant":[
        "Al Masara\u2018a"
    ],
    "wof:name":"Al Masara`a",
    "wof:placetype":"locality"
},
  "geometry": {"coordinates":[32.7443,14.1629],"type":"Point"}
}