{
  "type": "Feature",
  "properties": {
    "gn:admin1_code":"50.0",
    "gn:asciiname":"Qadd al Habub",
    "gn:country_code":"SD",
    "gn:dem":618,
    "gn:feature_class":"P",
    "gn:feature_code":"PPL",
    "gn:name":"Qadd al Hab\u016bb",
    "gn:population":0,
    "gn:timezone":"Africa/Khartoum",
    "iso:country":"SD",
    "name:und_x_variant":[
        "Qadd el Habub",
        "Qadd al Hab\u016bb"
    ],
    "wof:lang_x_official":[
        "ara",
        "eng"
    ],
    "wof:lang_x_spoken":[
        "ara",
        "eng"
    ],
    "wof:name":"Qadd al Habub",
    "wof:placetype":"locality"
},
  "geometry": {"coordinates":[31.11667000000001,11.53333],"type":"Point"}
}