{
  "type": "Feature",
  "properties": {
    "gn:admin1_code":"29.0",
    "gn:asciiname":"Wad `Agib",
    "gn:country_code":"SD",
    "gn:dem":381,
    "gn:feature_class":"P",
    "gn:feature_code":"PPL",
    "gn:name":"Wad \u2018Agib",
    "gn:population":0,
    "gn:timezone":"Africa/Khartoum",
    "iso:country":"SD",
    "wof:name":"Wad `Agib",
    "wof:placetype":"locality"
},
  "geometry": {"coordinates":[32.48333,15.51667],"type":"Point"}
}