{
  "type": "Feature",
  "properties": {
    "gn:admin1_code":"0.0",
    "gn:asciiname":"Um Kura`",
    "gn:country_code":"SD",
    "gn:dem":471,
    "gn:feature_class":"P",
    "gn:feature_code":"PPL",
    "gn:name":"Um Kur\u0101\u2018",
    "gn:population":0,
    "gn:timezone":"Africa/Khartoum",
    "iso:country":"SD",
    "name:ara_x_preferred":[
        "Um Kur\u0101\u2018"
    ],
    "wof:name":"Um Kura`",
    "wof:placetype":"locality"
},
  "geometry": {"coordinates":[35.1444,12.8914],"type":"Point"}
}