{
  "type": "Feature",
  "properties": {
    "gn:admin1_code":"52.0",
    "gn:asciiname":"Tagug",
    "gn:country_code":"SD",
    "gn:dem":512,
    "gn:feature_class":"P",
    "gn:feature_code":"PPL",
    "gn:name":"Tag\u016bg",
    "gn:population":0,
    "gn:timezone":"Africa/Khartoum",
    "iso:country":"SD",
    "name:und_x_variant":[
        "Tag\u016bg"
    ],
    "wof:name":"Tagug",
    "wof:placetype":"locality"
},
  "geometry": {"coordinates":[36.3648,15.4071],"type":"Point"}
}