{
  "type": "Feature",
  "properties": {
    "gn:admin1_code":"41.0",
    "gn:asciiname":"Zaqalona Kanjara",
    "gn:country_code":"SD",
    "gn:dem":427,
    "gn:feature_class":"P",
    "gn:feature_code":"PPL",
    "gn:name":"Zaqalona Kanj\u0101ra",
    "gn:population":0,
    "gn:timezone":"Africa/Khartoum",
    "iso:country":"SD",
    "name:und_x_variant":[
        "Zaqalona Kanj\u0101ra"
    ],
    "wof:name":"Zaqalona Kanjara",
    "wof:placetype":"locality"
},
  "geometry": {"coordinates":[31.7742,12.9094],"type":"Point"}
}