{
  "type": "Feature",
  "properties": {
    "gn:admin1_code":"38.0",
    "gn:asciiname":"Al Halawiyyin",
    "gn:country_code":"SD",
    "gn:dem":396,
    "gn:feature_class":"P",
    "gn:feature_code":"PPL",
    "gn:name":"Al \u1e28alawiyy\u012bn",
    "gn:population":0,
    "gn:timezone":"Africa/Khartoum",
    "iso:country":"SD",
    "name:und_x_variant":[
        "Al \u1e28alawiyy\u012bn"
    ],
    "wof:name":"Al Halawiyyin",
    "wof:placetype":"locality"
},
  "geometry": {"coordinates":[33.0045,14.9979],"type":"Point"}
}