{
  "type": "Feature",
  "properties": {
    "gn:admin1_code":"38.0",
    "gn:asciiname":"Wad Al `Asha",
    "gn:country_code":"SD",
    "gn:dem":400,
    "gn:feature_class":"P",
    "gn:feature_code":"PPL",
    "gn:name":"Wad Al \u2018Asha",
    "gn:population":0,
    "gn:timezone":"Africa/Khartoum",
    "iso:country":"SD",
    "name:und_x_variant":[
        "Wad Al \u2018Asha"
    ],
    "wof:name":"Wad Al `Asha",
    "wof:placetype":"locality"
},
  "geometry": {"coordinates":[33.1035,14.7854],"type":"Point"}
}