{
  "type": "Feature",
  "properties": {
    "gn:admin1_code":"29.0",
    "gn:asciiname":"Qaryat ash Shetelab",
    "gn:country_code":"SD",
    "gn:dem":381,
    "gn:feature_class":"P",
    "gn:feature_code":"PPL",
    "gn:name":"Qaryat ash Shetelab",
    "gn:population":0,
    "gn:timezone":"Africa/Khartoum",
    "iso:country":"SD",
    "wof:name":"Qaryat ash Shetelab",
    "wof:placetype":"locality"
},
  "geometry": {"coordinates":[32.478,15.4227],"type":"Point"}
}