{
  "type": "Feature",
  "properties": {
    "gn:admin1_code":"56.0",
    "gn:asciiname":"As Sa`ata",
    "gn:country_code":"SD",
    "gn:dem":531,
    "gn:feature_class":"P",
    "gn:feature_code":"PPL",
    "gn:name":"As Sa\u2018ata",
    "gn:population":0,
    "gn:timezone":"Africa/Khartoum",
    "iso:country":"SD",
    "name:und_x_variant":[
        "Sa\u2018ata",
        "Es Sa\u2018ata",
        "As Sa\u2018ata"
    ],
    "wof:lang_x_official":[
        "ara",
        "eng"
    ],
    "wof:lang_x_spoken":[
        "ara",
        "eng"
    ],
    "wof:name":"As Sa`ata",
    "wof:placetype":"locality"
},
  "geometry": {"coordinates":[29.98333,13.61667],"type":"Point"}
}