{
  "type": "Feature",
  "properties": {
    "gn:admin1_code":"41.0",
    "gn:asciiname":"Ad Dubasi",
    "gn:country_code":"SD",
    "gn:dem":380,
    "gn:feature_class":"P",
    "gn:feature_code":"PPL",
    "gn:name":"Ad Dubasi",
    "gn:population":0,
    "gn:timezone":"Africa/Khartoum",
    "iso:country":"SD",
    "name:und_x_variant":[
        "Ed Dubasi",
        "Dubasi",
        "Ad Dubasi"
    ],
    "wof:name":"Ad Dubasi",
    "wof:placetype":"locality"
},
  "geometry": {"coordinates":[32.23333,14.21667],"type":"Point"}
}