{
  "type": "Feature",
  "properties": {
    "gn:admin1_code":"60.0",
    "gn:asciiname":"Habib",
    "gn:country_code":"SD",
    "gn:dem":470,
    "gn:feature_class":"P",
    "gn:feature_code":"PPL",
    "gn:name":"\u1e28ab\u012bb",
    "gn:population":0,
    "gn:timezone":"Africa/Khartoum",
    "iso:country":"SD",
    "name:aze_x_preferred":[
        "H\u0259bib"
    ],
    "name:cat_x_preferred":[
        "Habib"
    ],
    "name:deu_x_preferred":[
        "Habib"
    ],
    "name:fin_x_preferred":[
        "Habib"
    ],
    "name:fra_x_preferred":[
        "Habib"
    ],
    "name:ind_x_preferred":[
        "Habib"
    ],
    "name:jpn_x_preferred":[
        "\u30cf\u30d3\u30fc\u30d6"
    ],
    "name:msa_x_preferred":[
        "Habib"
    ],
    "name:nds_x_preferred":[
        "Habib"
    ],
    "name:pan_x_preferred":[
        "\u0a39\u0a2c\u0a40\u0a2c"
    ],
    "name:rus_x_preferred":[
        "\u0425\u0430\u0431\u0438\u0431"
    ],
    "name:spa_x_preferred":[
        "Habib"
    ],
    "name:swe_x_preferred":[
        "Habib"
    ],
    "name:tur_x_preferred":[
        "Habip"
    ],
    "name:und_x_variant":[
        "Hamid",
        "\u1e28ab\u012bb"
    ],
    "name:zho_x_preferred":[
        "\u54c8\u6bd4\u535c"
    ],
    "wof:name":"Habib",
    "wof:placetype":"locality"
},
  "geometry": {"coordinates":[26.93333,11.75],"type":"Point"}
}