{
  "type": "Feature",
  "properties": {
    "gn:admin1_code":"60.0",
    "gn:asciiname":"Habib",
    "gn:country_code":"SD",
    "gn:dem":470,
    "gn:feature_class":"P",
    "gn:feature_code":"PPL",
    "gn:name":"\u1e28ab\u012bb",
    "gn:population":0,
    "gn:timezone":"Africa/Khartoum",
    "iso:country":"SD",
    "name:und_x_variant":[
        "Hamid",
        "\u1e28ab\u012bb"
    ],
    "wof:name":"Habib",
    "wof:placetype":"locality"
},
  "geometry": {"coordinates":[26.93333,11.75],"type":"Point"}
}