{
  "type": "Feature",
  "properties": {
    "gn:admin1_code":"53.0",
    "gn:asciiname":"Ash Shekab",
    "gn:country_code":"SD",
    "gn:dem":382,
    "gn:feature_class":"P",
    "gn:feature_code":"PPL",
    "gn:name":"Ash Shekab",
    "gn:population":0,
    "gn:timezone":"Africa/Khartoum",
    "iso:country":"SD",
    "wof:name":"Ash Shekab",
    "wof:placetype":"locality"
},
  "geometry": {"coordinates":[32.839,16.4521],"type":"Point"}
}