{
  "type": "Feature",
  "properties": {
    "gn:admin1_code":"50.0",
    "gn:asciiname":"Orshard",
    "gn:country_code":"SD",
    "gn:dem":600,
    "gn:feature_class":"P",
    "gn:feature_code":"PPL",
    "gn:name":"Orsh\u0101rd",
    "gn:population":0,
    "gn:timezone":"Africa/Khartoum",
    "iso:country":"SD",
    "name:ara_x_preferred":[
        "Orsh\u0101rd"
    ],
    "wof:name":"Orshard",
    "wof:placetype":"locality"
},
  "geometry": {"coordinates":[31.4067,12.1853],"type":"Point"}
}