{
  "type": "Feature",
  "properties": {
    "gn:admin1_code":"58.0",
    "gn:asciiname":"Tayba",
    "gn:country_code":"SD",
    "gn:dem":447,
    "gn:feature_class":"P",
    "gn:feature_code":"PPL",
    "gn:name":"\u0162ayba",
    "gn:population":0,
    "gn:timezone":"Africa/Khartoum",
    "iso:country":"SD",
    "name:und_x_variant":[
        "\u0162ayba"
    ],
    "wof:name":"Tayba",
    "wof:placetype":"locality"
},
  "geometry": {"coordinates":[34.1446,12.7741],"type":"Point"}
}