{
  "type": "Feature",
  "properties": {
    "gn:admin1_code":"0.0",
    "gn:asciiname":"'As Ubri",
    "gn:country_code":"SD",
    "gn:dem":489,
    "gn:feature_class":"P",
    "gn:feature_code":"PPL",
    "gn:name":"\u2019As Ubri",
    "gn:population":0,
    "gn:timezone":"Africa/Khartoum",
    "iso:country":"SD",
    "name:ara_x_preferred":[
        "\u2019As Ubri"
    ],
    "wof:name":"'As Ubri",
    "wof:placetype":"locality"
},
  "geometry": {"coordinates":[35.3916,12.7426],"type":"Point"}
}