{
  "type": "Feature",
  "properties": {
    "gn:admin1_code":"42.0",
    "gn:asciiname":"Maqanza",
    "gn:country_code":"SD",
    "gn:dem":490,
    "gn:feature_class":"P",
    "gn:feature_code":"PPL",
    "gn:name":"Maqanza",
    "gn:population":0,
    "gn:timezone":"Africa/Khartoum",
    "iso:country":"SD",
    "name:und_x_variant":[
        "Maganza",
        "Maqanza"
    ],
    "wof:name":"Maqanza",
    "wof:placetype":"locality"
},
  "geometry": {"coordinates":[34.3627,11.5911],"type":"Point"}
}