{
  "type": "Feature",
  "properties": {
    "gn:admin1_code":"38.0",
    "gn:asciiname":"Kiter Masa`ad",
    "gn:country_code":"SD",
    "gn:dem":399,
    "gn:feature_class":"P",
    "gn:feature_code":"PPL",
    "gn:name":"Kiter Masa\u2018ad",
    "gn:population":0,
    "gn:timezone":"Africa/Khartoum",
    "iso:country":"SD",
    "name:und_x_variant":[
        "Kuteir",
        "Kutayr",
        "Kiter Masa\u2018ad"
    ],
    "wof:lang_x_official":[
        "ara",
        "eng"
    ],
    "wof:lang_x_spoken":[
        "ara",
        "eng"
    ],
    "wof:name":"Kiter Masa`ad",
    "wof:placetype":"locality"
},
  "geometry": {"coordinates":[33.0736,14.714],"type":"Point"}
}