{
  "type": "Feature",
  "properties": {
    "gn:admin1_code":"55.0",
    "gn:asciiname":"Umm Hashabah",
    "gn:country_code":"SD",
    "gn:dem":989,
    "gn:feature_class":"P",
    "gn:feature_code":"PPL",
    "gn:name":"Umm Hash\u0101bah",
    "gn:population":0,
    "gn:timezone":"Africa/Khartoum",
    "iso:country":"SD",
    "name:und_x_variant":[
        "Umm Hashab",
        "Umm Hashaba",
        "Umm Hash\u0101bah"
    ],
    "wof:lang_x_official":[
        "ara",
        "eng"
    ],
    "wof:lang_x_spoken":[
        "ara",
        "eng"
    ],
    "wof:name":"Umm Hashabah",
    "wof:placetype":"locality"
},
  "geometry": {"coordinates":[25.81667,14.46667],"type":"Point"}
}