{
  "type": "Feature",
  "properties": {
    "gn:country":"SD",
    "gn:fcode":"PPL",
    "gn:population":17345,
    "iso:country":"SD",
    "name:und_x_variant":[
        "Hilaliya"
    ],
    "qs:name":"Al Hil\u0101liyya",
    "qs:photos_9r":0,
    "qs:photos_sr":0,
    "qs:pop_sr":"6",
    "wof:name":"Al Hil\u0101liyya",
    "wof:placetype":"locality",
    "wof:population":17345
},
  "geometry": {"coordinates":[33.234,14.9398],"type":"Point"}
}