{
  "type": "Feature",
  "properties": {
    "gn:admin1_code":"62.0",
    "gn:asciiname":"Abu Mareiqa al Haggar",
    "gn:country_code":"SD",
    "gn:dem":611,
    "gn:feature_class":"P",
    "gn:feature_code":"PPL",
    "gn:name":"Ab\u016b Mareiqa al Haggar",
    "gn:population":0,
    "gn:timezone":"Africa/Khartoum",
    "iso:country":"SD",
    "wof:name":"Abu Mareiqa al Haggar",
    "wof:placetype":"locality"
},
  "geometry": {"coordinates":[28.55,12.76667],"type":"Point"}
}