{
  "type": "Feature",
  "properties": {
    "gn:admin1_code":"55.0",
    "gn:asciiname":"Shallakhah",
    "gn:country_code":"SD",
    "gn:dem":657,
    "gn:feature_class":"P",
    "gn:feature_code":"PPL",
    "gn:name":"Shall\u0101khah",
    "gn:population":0,
    "gn:timezone":"Africa/Khartoum",
    "iso:country":"SD",
    "name:und_x_variant":[
        "Shallakha",
        "Shall\u0101khah"
    ],
    "wof:name":"Shallakhah",
    "wof:placetype":"locality"
},
  "geometry": {"coordinates":[26.96667,13.61667],"type":"Point"}
}