{
  "type": "Feature",
  "properties": {
    "gn:admin1_code":"42.0",
    "gn:asciiname":"Abela",
    "gn:country_code":"SD",
    "gn:dem":502,
    "gn:feature_class":"P",
    "gn:feature_code":"PPL",
    "gn:name":"Abela",
    "gn:population":0,
    "gn:timezone":"Africa/Khartoum",
    "iso:country":"SD",
    "name:pol_x_preferred":[
        "Abela"
    ],
    "wof:name":"Abela",
    "wof:placetype":"locality"
},
  "geometry": {"coordinates":[34.58333,11.41667],"type":"Point"}
}