{
  "type": "Feature",
  "properties": {
    "gn:admin1_code":"56.0",
    "gn:asciiname":"Al Murrah",
    "gn:country_code":"SD",
    "gn:dem":510,
    "gn:feature_class":"P",
    "gn:feature_code":"PPL",
    "gn:name":"Al Murrah",
    "gn:population":0,
    "gn:timezone":"Africa/Khartoum",
    "iso:country":"SD",
    "name:und_x_variant":[
        "El Murra",
        "Al Murrah"
    ],
    "wof:name":"Al Murrah",
    "wof:placetype":"locality"
},
  "geometry": {"coordinates":[30.06667,13.73333],"type":"Point"}
}