{
  "type": "Feature",
  "properties": {
    "gn:admin1_code":"56.0",
    "gn:asciiname":"Al Murrah",
    "gn:country_code":"SD",
    "gn:dem":510,
    "gn:feature_class":"P",
    "gn:feature_code":"PPL",
    "gn:name":"Al Murrah",
    "gn:population":0,
    "gn:timezone":"Africa/Khartoum",
    "iso:country":"SD",
    "name:ara_x_preferred":[
        "\u0642\u0628\u064a\u0644\u0629 \u0622\u0644 \u0645\u0631\u0629"
    ],
    "name:fin_x_preferred":[
        "Al Murrah"
    ],
    "name:hin_x_preferred":[
        "\u0905\u0932 \u092e\u0941\u0930\u093e\u0939"
    ],
    "name:und_x_variant":[
        "El Murra",
        "Al Murrah"
    ],
    "wof:name":"Al Murrah",
    "wof:placetype":"locality"
},
  "geometry": {"coordinates":[30.06667,13.73333],"type":"Point"}
}