{
  "type": "Feature",
  "properties": {
    "gn:admin1_code":"38.0",
    "gn:asciiname":"Al Hadabah",
    "gn:country_code":"SD",
    "gn:dem":413,
    "gn:feature_class":"P",
    "gn:feature_code":"PPL",
    "gn:name":"Al Hadabah",
    "gn:population":0,
    "gn:timezone":"Africa/Khartoum",
    "iso:country":"SD",
    "name:und_x_variant":[
        "El Hadaba",
        "Al Hadabah"
    ],
    "wof:name":"Al Hadabah",
    "wof:placetype":"locality"
},
  "geometry": {"coordinates":[33.51667,14.71667],"type":"Point"}
}