{
  "type": "Feature",
  "properties": {
    "gn:admin1_code":"58.0",
    "gn:asciiname":"Maqdur",
    "gn:country_code":"SD",
    "gn:dem":423,
    "gn:feature_class":"P",
    "gn:feature_code":"PPL",
    "gn:name":"Maqd\u016br",
    "gn:population":0,
    "gn:timezone":"Africa/Khartoum",
    "iso:country":"SD",
    "wof:name":"Maqdur",
    "wof:placetype":"locality"
},
  "geometry": {"coordinates":[34.03333,13.65],"type":"Point"}
}