{
  "type": "Feature",
  "properties": {
    "gn:admin1_code":"56.0",
    "gn:asciiname":"Al Furay`",
    "gn:country_code":"SD",
    "gn:dem":475,
    "gn:feature_class":"P",
    "gn:feature_code":"PPL",
    "gn:name":"Al Furay\u2018",
    "gn:population":0,
    "gn:timezone":"Africa/Khartoum",
    "iso:country":"SD",
    "name:und_x_variant":[
        "El Furei\u2018",
        "Al Furay\u2018"
    ],
    "wof:name":"Al Furay`",
    "wof:placetype":"locality"
},
  "geometry": {"coordinates":[30.61667000000001,14.41667],"type":"Point"}
}