{
  "type": "Feature",
  "properties": {
    "gn:admin1_code":"55.0",
    "gn:asciiname":"Harhassa",
    "gn:country_code":"SD",
    "gn:dem":859,
    "gn:feature_class":"P",
    "gn:feature_code":"PPL",
    "gn:name":"Harhassa",
    "gn:population":0,
    "gn:timezone":"Africa/Khartoum",
    "iso:country":"SD",
    "wof:name":"Harhassa",
    "wof:placetype":"locality"
},
  "geometry": {"coordinates":[25.03333,13.86667],"type":"Point"}
}