{
  "type": "Feature",
  "properties": {
    "gn:admin1_code":"38.0",
    "gn:asciiname":"Wad Ra`iyya as Suq",
    "gn:country_code":"SD",
    "gn:dem":408,
    "gn:feature_class":"P",
    "gn:feature_code":"PPL",
    "gn:name":"Wad Ra\u2018iyya as S\u016bq",
    "gn:population":0,
    "gn:timezone":"Africa/Khartoum",
    "iso:country":"SD",
    "name:und_x_variant":[
        "Wad Raia",
        "Wad Raiya",
        "Wad Rayyah",
        "Wad Ra\u2018iyya as S\u016bq"
    ],
    "wof:name":"Wad Ra`iyya as Suq",
    "wof:placetype":"locality"
},
  "geometry": {"coordinates":[33.1658,14.4126],"type":"Point"}
}