{
  "type": "Feature",
  "properties": {
    "gn:admin1_code":"56.0",
    "gn:asciiname":"`Asidah",
    "gn:country_code":"SD",
    "gn:dem":484,
    "gn:feature_class":"P",
    "gn:feature_code":"PPL",
    "gn:name":"\u2018A\u015f\u012bdah",
    "gn:population":0,
    "gn:timezone":"Africa/Khartoum",
    "iso:country":"SD",
    "name:und_x_variant":[
        "\u2018Asida",
        "\u2018A\u015f\u012bdah"
    ],
    "wof:name":"`Asidah",
    "wof:placetype":"locality"
},
  "geometry": {"coordinates":[30.61667000000001,13.58333],"type":"Point"}
}