{
  "type": "Feature",
  "properties": {
    "gn:admin1_code":"56.0",
    "gn:asciiname":"Hajlij",
    "gn:country_code":"SD",
    "gn:dem":459,
    "gn:feature_class":"P",
    "gn:feature_code":"PPL",
    "gn:name":"\u1e28ajl\u012bj",
    "gn:population":0,
    "gn:timezone":"Africa/Khartoum",
    "iso:country":"SD",
    "name:und_x_variant":[
        "Hegleg",
        "Heglig",
        "\u1e28ajl\u012bj"
    ],
    "wof:lang_x_official":[
        "ara",
        "eng"
    ],
    "wof:lang_x_spoken":[
        "ara",
        "eng"
    ],
    "wof:name":"Hajlij",
    "wof:placetype":"locality"
},
  "geometry": {"coordinates":[30.73333,13.98333],"type":"Point"}
}