{
  "type": "Feature",
  "properties": {
    "gn:admin1_code":"56.0",
    "gn:asciiname":"Menfor",
    "gn:country_code":"SD",
    "gn:dem":461,
    "gn:feature_class":"P",
    "gn:feature_code":"PPL",
    "gn:name":"Menfor",
    "gn:population":0,
    "gn:timezone":"Africa/Khartoum",
    "iso:country":"SD",
    "wof:name":"Menfor",
    "wof:placetype":"locality"
},
  "geometry": {"coordinates":[31.03333,13.03333],"type":"Point"}
}