{
  "type": "Feature",
  "properties": {
    "gn:admin1_code":"38.0",
    "gn:asciiname":"Al Billiyab",
    "gn:country_code":"SD",
    "gn:dem":407,
    "gn:feature_class":"P",
    "gn:feature_code":"PPL",
    "gn:name":"Al Billiy\u0101b",
    "gn:population":0,
    "gn:timezone":"Africa/Khartoum",
    "iso:country":"SD",
    "name:ara_x_preferred":[
        "Al Billiy\u0101b"
    ],
    "name:und_x_variant":[
        "Beiliab",
        "Bayliy\u0101b"
    ],
    "wof:lang_x_official":[
        "ara",
        "eng"
    ],
    "wof:lang_x_spoken":[
        "ara",
        "eng"
    ],
    "wof:name":"Al Billiyab",
    "wof:placetype":"locality"
},
  "geometry": {"coordinates":[33.4438,14.8413],"type":"Point"}
}