{
  "type": "Feature",
  "properties": {
    "gn:country":"SD",
    "gn:fcode":"PPL",
    "gn:population":28727,
    "iso:country":"SD",
    "qs:name":"Maiurno",
    "qs:photos_9r":0,
    "qs:photos_sr":0,
    "qs:pop_sr":"7",
    "wof:lang_x_official":[
        "ara",
        "eng"
    ],
    "wof:lang_x_spoken":[
        "ara",
        "eng"
    ],
    "wof:name":"Maiurno",
    "wof:placetype":"locality",
    "wof:population":28727
},
  "geometry": {"coordinates":[33.66667,13.41667],"type":"Point"}
}