{
  "type": "Feature",
  "properties": {
    "gn:admin1_code":"41.0",
    "gn:asciiname":"Sharrat",
    "gn:country_code":"SD",
    "gn:dem":389,
    "gn:feature_class":"P",
    "gn:feature_code":"PPL",
    "gn:name":"Sharrat",
    "gn:population":0,
    "gn:timezone":"Africa/Khartoum",
    "iso:country":"SD",
    "wof:name":"Sharrat",
    "wof:placetype":"locality"
},
  "geometry": {"coordinates":[32.8153,12.8834],"type":"Point"}
}