{
  "type": "Feature",
  "properties": {
    "gn:admin1_code":"29.0",
    "gn:asciiname":"Abu Dawmah",
    "gn:cc2":"SD",
    "gn:country_code":"SD",
    "gn:dem":384,
    "gn:feature_class":"P",
    "gn:feature_code":"PPL",
    "gn:name":"Ab\u016b Dawmah",
    "gn:population":0,
    "gn:timezone":"Africa/Khartoum",
    "iso:country":"SD",
    "name:und_x_variant":[
        "Abu Doma",
        "Ab\u016b Dawmah"
    ],
    "wof:name":"Abu Dawmah",
    "wof:placetype":"locality"
},
  "geometry": {"coordinates":[32.49610999999999,15.44139],"type":"Point"}
}