{
  "type": "Feature",
  "properties": {
    "gn:admin1_code":"55.0",
    "gn:asciiname":"Abu Ku`",
    "gn:country_code":"SD",
    "gn:dem":812,
    "gn:feature_class":"P",
    "gn:feature_code":"PPL",
    "gn:name":"Ab\u016b K\u016b\u2018",
    "gn:population":0,
    "gn:timezone":"Africa/Khartoum",
    "iso:country":"SD",
    "wof:name":"Abu Ku`",
    "wof:placetype":"locality"
},
  "geometry": {"coordinates":[25.93333,14.05],"type":"Point"}
}