{
  "type": "Feature",
  "properties": {
    "gn:admin1_code":"56.0",
    "gn:asciiname":"Qawz Bisharah",
    "gn:country_code":"SD",
    "gn:dem":499,
    "gn:feature_class":"P",
    "gn:feature_code":"PPL",
    "gn:name":"Qawz Bish\u0101rah",
    "gn:population":0,
    "gn:timezone":"Africa/Khartoum",
    "iso:country":"SD",
    "name:und_x_variant":[
        "Qoz Bishara",
        "Qawz Bish\u0101rah"
    ],
    "wof:lang_x_official":[
        "ara",
        "eng"
    ],
    "wof:lang_x_spoken":[
        "ara",
        "eng"
    ],
    "wof:name":"Qawz Bisharah",
    "wof:placetype":"locality"
},
  "geometry": {"coordinates":[30.76667,12.65],"type":"Point"}
}