{
  "type": "Feature",
  "properties": {
    "gn:admin1_code":"50.0",
    "gn:asciiname":"Abu Nuwwara",
    "gn:country_code":"SD",
    "gn:dem":492,
    "gn:feature_class":"P",
    "gn:feature_code":"PPL",
    "gn:name":"Abu Nuww\u0101ra",
    "gn:population":0,
    "gn:timezone":"Africa/Khartoum",
    "iso:country":"SD",
    "name:und_x_variant":[
        "Abu Nuwara",
        "Abu Nuweira",
        "Ab\u016b Nuww\u0101rah",
        "Abu Nuww\u0101ra"
    ],
    "wof:name":"Abu Nuwwara",
    "wof:placetype":"locality"
},
  "geometry": {"coordinates":[31.5202,11.188],"type":"Point"}
}