{
  "type": "Feature",
  "properties": {
    "gn:admin1_code":"41.0",
    "gn:asciiname":"Um Sineta",
    "gn:country_code":"SD",
    "gn:dem":390,
    "gn:feature_class":"P",
    "gn:feature_code":"PPL",
    "gn:name":"Um Sine\u0163a",
    "gn:population":0,
    "gn:timezone":"Africa/Khartoum",
    "iso:country":"SD",
    "name:und_x_variant":[
        "Um Sine\u0163a"
    ],
    "wof:name":"Um Sineta",
    "wof:placetype":"locality"
},
  "geometry": {"coordinates":[32.0811,13.752],"type":"Point"}
}