{
  "type": "Feature",
  "properties": {
    "gn:admin1_code":"53.0",
    "gn:asciiname":"Hillat Shootak",
    "gn:country_code":"SD",
    "gn:dem":356,
    "gn:feature_class":"P",
    "gn:feature_code":"PPL",
    "gn:name":"Hillat Shootak",
    "gn:population":0,
    "gn:timezone":"Africa/Khartoum",
    "iso:country":"SD",
    "wof:name":"Hillat Shootak",
    "wof:placetype":"locality"
},
  "geometry": {"coordinates":[33.7257,17.2683],"type":"Point"}
}