{
  "type": "Feature",
  "properties": {
    "gn:admin1_code":"42.0",
    "gn:asciiname":"Abu Shunaynah",
    "gn:country_code":"SD",
    "gn:dem":485,
    "gn:feature_class":"P",
    "gn:feature_code":"PPL",
    "gn:name":"Ab\u016b Shunaynah",
    "gn:population":0,
    "gn:timezone":"Africa/Khartoum",
    "iso:country":"SD",
    "name:und_x_variant":[
        "Abu Shin\u0113na",
        "Abu Sheneina",
        "Ab\u016b Shunaynah"
    ],
    "wof:name":"Abu Shunaynah",
    "wof:placetype":"locality"
},
  "geometry": {"coordinates":[34.66667,11.38333],"type":"Point"}
}