{
  "type": "Feature",
  "properties": {
    "gn:admin1_code":"39.0",
    "gn:asciiname":"Kandawa",
    "gn:country_code":"SD",
    "gn:dem":618,
    "gn:feature_class":"P",
    "gn:feature_code":"PPL",
    "gn:name":"Kandawa",
    "gn:population":0,
    "gn:timezone":"Africa/Khartoum",
    "iso:country":"SD",
    "wof:name":"Kandawa",
    "wof:placetype":"locality"
},
  "geometry": {"coordinates":[35.36667,13.91667],"type":"Point"}
}