{
  "type": "Feature",
  "properties": {
    "gn:admin1_code":"39.0",
    "gn:asciiname":"Wad al Ammas",
    "gn:country_code":"SD",
    "gn:dem":526,
    "gn:feature_class":"P",
    "gn:feature_code":"PPL",
    "gn:name":"Wad al Ammas",
    "gn:population":0,
    "gn:timezone":"Africa/Khartoum",
    "iso:country":"SD",
    "name:und_x_variant":[
        "Wad el Ammas",
        "Vad el Ammas",
        "El Gezair",
        "Wad al Ammas"
    ],
    "wof:lang_x_official":[
        "ara",
        "eng"
    ],
    "wof:lang_x_spoken":[
        "ara",
        "eng"
    ],
    "wof:name":"Wad al Ammas",
    "wof:placetype":"locality"
},
  "geometry": {"coordinates":[36.0074,14.04278],"type":"Point"}
}