{
  "type": "Feature",
  "properties": {
    "gn:admin1_code":"50.0",
    "gn:asciiname":"Tera",
    "gn:country_code":"SD",
    "gn:dem":773,
    "gn:feature_class":"P",
    "gn:feature_code":"PPL",
    "gn:name":"Tera",
    "gn:population":0,
    "gn:timezone":"Africa/Khartoum",
    "iso:country":"SD",
    "wof:name":"Tera",
    "wof:placetype":"locality"
},
  "geometry": {"coordinates":[31.0491,12.1125],"type":"Point"}
}