{
  "type": "Feature",
  "properties": {
    "gn:admin1_code":"56.0",
    "gn:asciiname":"Takkal Ma`aqla",
    "gn:country_code":"SD",
    "gn:dem":439,
    "gn:feature_class":"P",
    "gn:feature_code":"PPL",
    "gn:name":"Takk\u0101l Ma\u2018\u0101qla",
    "gn:population":0,
    "gn:timezone":"Africa/Khartoum",
    "iso:country":"SD",
    "name:und_x_variant":[
        "Takk\u0101l Ma\u2018\u0101qla"
    ],
    "wof:lang_x_official":[
        "ara",
        "eng"
    ],
    "wof:lang_x_spoken":[
        "ara",
        "eng"
    ],
    "wof:name":"Takkal Ma`aqla",
    "wof:placetype":"locality"
},
  "geometry": {"coordinates":[31.6029,12.6714],"type":"Point"}
}