{
  "type": "Feature",
  "properties": {
    "gn:admin1_code":"53.0",
    "gn:asciiname":"Al `Amarin",
    "gn:country_code":"SD",
    "gn:dem":311,
    "gn:feature_class":"P",
    "gn:feature_code":"PPL",
    "gn:name":"Al \u2018Am\u0101r\u012bn",
    "gn:population":0,
    "gn:timezone":"Africa/Khartoum",
    "iso:country":"SD",
    "name:und_x_variant":[
        "El Amarin",
        "Al \u2018Am\u0101r\u012bn"
    ],
    "wof:name":"Al `Amarin",
    "wof:placetype":"locality"
},
  "geometry": {"coordinates":[32.56667,19.15],"type":"Point"}
}