{
  "type": "Feature",
  "properties": {
    "gn:admin1_code":"58.0",
    "gn:asciiname":"Ab Surra",
    "gn:country_code":"SD",
    "gn:dem":452,
    "gn:feature_class":"P",
    "gn:feature_code":"PPL",
    "gn:name":"Ab \u015eurra",
    "gn:population":0,
    "gn:timezone":"Africa/Khartoum",
    "iso:country":"SD",
    "name:und_x_variant":[
        "Ab \u015eurra"
    ],
    "wof:name":"Ab Surra",
    "wof:placetype":"locality"
},
  "geometry": {"coordinates":[34.3241,12.387],"type":"Point"}
}