{
  "type": "Feature",
  "properties": {
    "gn:admin1_code":"38.0",
    "gn:asciiname":"Wad Nu`man",
    "gn:country_code":"SD",
    "gn:dem":415,
    "gn:feature_class":"P",
    "gn:feature_code":"PPL",
    "gn:name":"Wad Nu\u2018m\u0101n",
    "gn:population":0,
    "gn:timezone":"Africa/Khartoum",
    "iso:country":"SD",
    "name:und_x_variant":[
        "Wad Nu\u2018m\u0101n"
    ],
    "wof:name":"Wad Nu`man",
    "wof:placetype":"locality"
},
  "geometry": {"coordinates":[33.4168,14.1444],"type":"Point"}
}