{
  "type": "Feature",
  "properties": {
    "gn:country":"SD",
    "gn:fcode":"PPL",
    "gn:pop":18321,
    "iso:country":"SD",
    "name:unk_x_variant":[
        "El Qeteina"
    ],
    "qs:name":"Al Qi\u0163ena",
    "qs:photos_9r":0,
    "qs:photos_sr":0,
    "qs:pop_sr":"6",
    "wof:name":"Al Qi\u0163ena",
    "wof:placetype":"locality",
    "wof:population":18321
},
  "geometry": {"coordinates":[32.3668,14.8648],"type":"Point"}
}