{
  "type": "Feature",
  "properties": {
    "gn:admin1_code":"39.0",
    "gn:asciiname":"Conry",
    "gn:country_code":"SD",
    "gn:dem":527,
    "gn:feature_class":"P",
    "gn:feature_code":"PPL",
    "gn:name":"Conry",
    "gn:population":0,
    "gn:timezone":"Africa/Khartoum",
    "iso:country":"SD",
    "wof:name":"Conry",
    "wof:placetype":"locality"
},
  "geometry": {"coordinates":[36.11667,13.85],"type":"Point"}
}