{
  "type": "Feature",
  "properties": {
    "gn:admin1_code":"41.0",
    "gn:asciiname":"Um Halalif",
    "gn:country_code":"SD",
    "gn:dem":406,
    "gn:feature_class":"P",
    "gn:feature_code":"PPL",
    "gn:name":"Um \u1e28al\u0101l\u012bf",
    "gn:population":0,
    "gn:timezone":"Africa/Khartoum",
    "iso:country":"SD",
    "name:und_x_variant":[
        "Um \u1e28al\u0101l\u012bf"
    ],
    "wof:name":"Um Halalif",
    "wof:placetype":"locality"
},
  "geometry": {"coordinates":[32.0578,13.1385],"type":"Point"}
}