{
  "type": "Feature",
  "properties": {
    "gn:admin1_code":"58.0",
    "gn:asciiname":"`En Aj Jamal",
    "gn:country_code":"SD",
    "gn:dem":471,
    "gn:feature_class":"P",
    "gn:feature_code":"PPL",
    "gn:name":"\u2018En Aj Jamal",
    "gn:population":0,
    "gn:timezone":"Africa/Khartoum",
    "iso:country":"SD",
    "name:und_x_variant":[
        "\u2018En Aj Jamal"
    ],
    "wof:name":"`En Aj Jamal",
    "wof:placetype":"locality"
},
  "geometry": {"coordinates":[35.1644,12.8599],"type":"Point"}
}