{
  "type": "Feature",
  "properties": {
    "gn:admin1_code":"49.0",
    "gn:asciiname":"Gurr Tobak",
    "gn:country_code":"SD",
    "gn:dem":690,
    "gn:feature_class":"P",
    "gn:feature_code":"PPL",
    "gn:name":"Gurr Tobak",
    "gn:population":0,
    "gn:timezone":"Africa/Khartoum",
    "iso:country":"SD",
    "name:und_x_variant":[
        "Gertobak",
        "Gurr Tobak"
    ],
    "wof:lang_x_official":[
        "ara",
        "eng"
    ],
    "wof:lang_x_spoken":[
        "ara",
        "eng"
    ],
    "wof:name":"Gurr Tobak",
    "wof:placetype":"locality"
},
  "geometry": {"coordinates":[25.36667000000001,12.75],"type":"Point"}
}