{
  "type": "Feature",
  "properties": {
    "gn:admin1_code":"38.0",
    "gn:asciiname":"Dafa` Allah",
    "gn:country_code":"SD",
    "gn:dem":409,
    "gn:feature_class":"P",
    "gn:feature_code":"PPL",
    "gn:name":"Dafa\u2018 Allah",
    "gn:population":0,
    "gn:timezone":"Africa/Khartoum",
    "iso:country":"SD",
    "name:und_x_variant":[
        "Dafa\u2018ullah",
        "Daf \u2018All\u0101h",
        "Dafa\u2018 Allah"
    ],
    "wof:lang_x_official":[
        "ara",
        "eng"
    ],
    "wof:lang_x_spoken":[
        "ara",
        "eng"
    ],
    "wof:name":"Dafa` Allah",
    "wof:placetype":"locality"
},
  "geometry": {"coordinates":[33.3978,14.4355],"type":"Point"}
}