{
  "type": "Feature",
  "properties": {
    "gn:admin1_code":"38.0",
    "gn:asciiname":"Balula",
    "gn:country_code":"SD",
    "gn:dem":415,
    "gn:feature_class":"P",
    "gn:feature_code":"PPL",
    "gn:name":"Balula",
    "gn:population":0,
    "gn:timezone":"Africa/Khartoum",
    "iso:country":"SD",
    "name:und_x_variant":[
        "Wad Balula",
        "Wad Bal\u016blah",
        "Balula"
    ],
    "wof:name":"Balula",
    "wof:placetype":"locality"
},
  "geometry": {"coordinates":[33.4643,14.0603],"type":"Point"}
}