{
  "type": "Feature",
  "properties": {
    "gn:admin1_code":"52.0",
    "gn:asciiname":"Qaryah Ithnan wa `Ishrun",
    "gn:country_code":"SD",
    "gn:dem":447,
    "gn:feature_class":"P",
    "gn:feature_code":"PPL",
    "gn:name":"Qaryah Ithn\u0101n wa \u2018Ishr\u016bn",
    "gn:population":0,
    "gn:timezone":"Africa/Khartoum",
    "iso:country":"SD",
    "name:und_x_variant":[
        "Qaryah Ithn\u0101n wa \u2018Ishr\u016bn"
    ],
    "wof:name":"Qaryah Ithnan wa `Ishrun",
    "wof:placetype":"locality"
},
  "geometry": {"coordinates":[35.6122,15.4158],"type":"Point"}
}