{
  "type": "Feature",
  "properties": {
    "gn:admin1_code":"38.0",
    "gn:asciiname":"Haraxa",
    "gn:country_code":"SD",
    "gn:dem":419,
    "gn:feature_class":"P",
    "gn:feature_code":"PPL",
    "gn:name":"Haraxa",
    "gn:population":0,
    "gn:timezone":"Africa/Khartoum",
    "iso:country":"SD",
    "wof:name":"Haraxa",
    "wof:placetype":"locality"
},
  "geometry": {"coordinates":[33.46667,15.18333],"type":"Point"}
}