{
  "type": "Feature",
  "properties": {
    "gn:admin1_code":"41.0",
    "gn:asciiname":"Qaryat al Kiremt",
    "gn:country_code":"SD",
    "gn:dem":394,
    "gn:feature_class":"P",
    "gn:feature_code":"PPL",
    "gn:name":"Qaryat al Kiremt",
    "gn:population":0,
    "gn:timezone":"Africa/Khartoum",
    "iso:country":"SD",
    "name:und_x_variant":[
        "El Kereimet",
        "Al Kereimet",
        "Qaryat al Kiremt"
    ],
    "wof:name":"Qaryat al Kiremt",
    "wof:placetype":"locality"
},
  "geometry": {"coordinates":[32.6251,15.0837],"type":"Point"}
}