{
  "type": "Feature",
  "properties": {
    "gn:admin1_code":"47.0",
    "gn:asciiname":"Daraba",
    "gn:country_code":"SD",
    "gn:dem":926,
    "gn:feature_class":"P",
    "gn:feature_code":"PPL",
    "gn:name":"Daraba",
    "gn:population":0,
    "gn:timezone":"Africa/Khartoum",
    "iso:country":"SD",
    "wof:name":"Daraba",
    "wof:placetype":"locality"
},
  "geometry": {"coordinates":[22.46392,14.50973],"type":"Point"}
}