{
  "type": "Feature",
  "properties": {
    "gn:admin1_code":"38.0",
    "gn:asciiname":"Rayyah",
    "gn:country_code":"SD",
    "gn:dem":405,
    "gn:feature_class":"P",
    "gn:feature_code":"PPL",
    "gn:name":"Rayy\u0101\u1e29",
    "gn:population":0,
    "gn:timezone":"Africa/Khartoum",
    "iso:country":"SD",
    "name:und_x_variant":[
        "Raiyah",
        "Rayy\u0101\u1e29"
    ],
    "wof:name":"Rayyah",
    "wof:placetype":"locality"
},
  "geometry": {"coordinates":[33.68333,14.15],"type":"Point"}
}