{
  "type": "Feature",
  "properties": {
    "gn:admin1_code":"38.0",
    "gn:asciiname":"Wad Jarras",
    "gn:country_code":"SD",
    "gn:dem":418,
    "gn:feature_class":"P",
    "gn:feature_code":"PPL",
    "gn:name":"Wad Jarr\u0101s",
    "gn:population":0,
    "gn:timezone":"Africa/Khartoum",
    "iso:country":"SD",
    "name:und_x_variant":[
        "Wad Garras",
        "Wad Jarr\u0101s"
    ],
    "wof:lang_x_official":[
        "ara",
        "eng"
    ],
    "wof:lang_x_spoken":[
        "ara",
        "eng"
    ],
    "wof:name":"Wad Jarras",
    "wof:placetype":"locality"
},
  "geometry": {"coordinates":[33.61667,14.61667],"type":"Point"}
}