{
  "type": "Feature",
  "properties": {
    "gn:admin1_code":"41.0",
    "gn:asciiname":"Hillat Wad Jar an Nabi",
    "gn:country_code":"SD",
    "gn:dem":385,
    "gn:feature_class":"P",
    "gn:feature_code":"PPL",
    "gn:name":"Hillat Wad Jar an Nabi",
    "gn:population":0,
    "gn:timezone":"Africa/Khartoum",
    "iso:country":"SD",
    "name:und_x_variant":[
        "Wad Gar en Nabi",
        "Wad J\u0101r an Nab\u012b",
        "Hillat Wad Jar an Nabi"
    ],
    "wof:lang_x_official":[
        "ara",
        "eng"
    ],
    "wof:lang_x_spoken":[
        "ara",
        "eng"
    ],
    "wof:name":"Hillat Wad Jar an Nabi",
    "wof:placetype":"locality"
},
  "geometry": {"coordinates":[32.4881,15.187],"type":"Point"}
}