{
  "type": "Feature",
  "properties": {
    "gn:admin1_code":"60.0",
    "gn:asciiname":"Tomat",
    "gn:country_code":"SD",
    "gn:dem":463,
    "gn:feature_class":"P",
    "gn:feature_code":"PPL",
    "gn:name":"Tomat",
    "gn:population":0,
    "gn:timezone":"Africa/Khartoum",
    "iso:country":"SD",
    "name:und_x_variant":[
        "Abu Zua",
        "Tomat"
    ],
    "wof:name":"Tomat",
    "wof:placetype":"locality"
},
  "geometry": {"coordinates":[27.03333,11.48333],"type":"Point"}
}