{
  "type": "Feature",
  "properties": {
    "gn:admin1_code":"50.0",
    "gn:asciiname":"Tarjoak",
    "gn:country_code":"SD",
    "gn:dem":641,
    "gn:feature_class":"P",
    "gn:feature_code":"PPL",
    "gn:name":"Tarjoak",
    "gn:population":0,
    "gn:timezone":"Africa/Khartoum",
    "iso:country":"SD",
    "wof:name":"Tarjoak",
    "wof:placetype":"locality"
},
  "geometry": {"coordinates":[30.56667,11.81667],"type":"Point"}
}