{
  "type": "Feature",
  "properties": {
    "iso:country":"SD",
    "name:dut_x_preferred":[
        "Shambat"
    ],
    "name:eng_x_preferred":[
        "Shambat"
    ],
    "qs:gn_country":"SD",
    "qs:gn_fcode":"PPL",
    "qs:gn_pop":0,
    "qs:name":"Shambat",
    "qs:name_adm0":"\u0627\u0644\u0633\u0648\u062f\u0627\u0646",
    "qs:name_adm1":"\u00a0\u0648\u0644\u0627\u064a\u0629 \u0627\u0644\u062e\u0631\u0637\u0648\u0645",
    "qs:photos":34,
    "qs:photos_1k":7,
    "qs:photos_9k":1,
    "qs:photos_9r":2,
    "qs:photos_all":34,
    "qs:photos_sr":2,
    "qs:placetype":"Town",
    "qs:pop_sr":"0",
    "qs:woe_adm0":23424952,
    "wd:wordcount":17,
    "wof:name":"Shambat",
    "wof:placetype":"locality"
},
  "geometry": {"coordinates":[32.5319,15.6636],"type":"Point"}
}