{
  "type": "Feature",
  "properties": {
    "gn:admin1_code":"38.0",
    "gn:asciiname":"Al `Awamra",
    "gn:country_code":"SD",
    "gn:dem":408,
    "gn:feature_class":"P",
    "gn:feature_code":"PPL",
    "gn:name":"Al \u2018Aw\u0101mra",
    "gn:population":0,
    "gn:timezone":"Africa/Khartoum",
    "iso:country":"SD",
    "name:und_x_variant":[
        "Al \u2018Aw\u0101mra"
    ],
    "wof:name":"Al `Awamra",
    "wof:placetype":"locality"
},
  "geometry": {"coordinates":[33.4063,14.4559],"type":"Point"}
}