{
  "type": "Feature",
  "properties": {
    "gn:admin1_code":"41.0",
    "gn:asciiname":"Sahalat az Zarqa",
    "gn:country_code":"SD",
    "gn:dem":390,
    "gn:feature_class":"P",
    "gn:feature_code":"PPL",
    "gn:name":"Sahalat az Zarq\u0101",
    "gn:population":0,
    "gn:timezone":"Africa/Khartoum",
    "iso:country":"SD",
    "name:und_x_variant":[
        "Sahalat az Zarq\u0101"
    ],
    "wof:name":"Sahalat az Zarqa",
    "wof:placetype":"locality"
},
  "geometry": {"coordinates":[32.2638,13.444],"type":"Point"}
}