{
  "type": "Feature",
  "properties": {
    "gn:admin1_code":"42.0",
    "gn:asciiname":"Qanis Gharb",
    "gn:country_code":"SD",
    "gn:dem":486,
    "gn:feature_class":"P",
    "gn:feature_code":"PPL",
    "gn:name":"Qan\u012bs Gharb",
    "gn:population":0,
    "gn:timezone":"Africa/Khartoum",
    "iso:country":"SD",
    "name:und_x_variant":[
        "Qan\u012bs Gharb"
    ],
    "wof:name":"Qanis Gharb",
    "wof:placetype":"locality"
},
  "geometry": {"coordinates":[34.3596,11.8184],"type":"Point"}
}