{
  "type": "Feature",
  "properties": {
    "gn:admin1_code":"47.0",
    "gn:asciiname":"Kododol",
    "gn:country_code":"SD",
    "gn:dem":777,
    "gn:feature_class":"P",
    "gn:feature_code":"PPL",
    "gn:name":"Kododol",
    "gn:population":0,
    "gn:timezone":"Africa/Khartoum",
    "iso:country":"SD",
    "name:eng_x_preferred":[
        "Kododol"
    ],
    "wof:name":"Kododol",
    "wof:placetype":"locality"
},
  "geometry": {"coordinates":[22.29458,13.33866],"type":"Point"}
}