{
  "type": "Feature",
  "properties": {
    "gn:admin1_code":"56.0",
    "gn:asciiname":"Alaga",
    "gn:country_code":"SD",
    "gn:dem":468,
    "gn:feature_class":"P",
    "gn:feature_code":"PPL",
    "gn:name":"Alaga",
    "gn:population":0,
    "gn:timezone":"Africa/Khartoum",
    "iso:country":"SD",
    "wof:name":"Alaga",
    "wof:placetype":"locality"
},
  "geometry": {"coordinates":[30.93333,13.23333],"type":"Point"}
}