{
  "type": "Feature",
  "properties": {
    "gn:admin1_code":"47.0",
    "gn:asciiname":"Koulbous",
    "gn:cc2":"TD",
    "gn:country_code":"SD",
    "gn:dem":955,
    "gn:feature_class":"P",
    "gn:feature_code":"PPL",
    "gn:name":"Koulbous",
    "gn:population":0,
    "gn:timezone":"Africa/Khartoum",
    "iso:country":"SD",
    "name:und_x_variant":[
        "Kulbus",
        "Koulbous"
    ],
    "wof:name":"Koulbous",
    "wof:placetype":"locality"
},
  "geometry": {"coordinates":[22.46172,14.36468],"type":"Point"}
}