{
  "type": "Feature",
  "properties": {
    "gn:admin1_code":"50.0",
    "gn:asciiname":"Nyukur",
    "gn:country_code":"SD",
    "gn:dem":741,
    "gn:feature_class":"P",
    "gn:feature_code":"PPL",
    "gn:name":"Nyukur",
    "gn:population":0,
    "gn:timezone":"Africa/Khartoum",
    "iso:country":"SD",
    "wof:name":"Nyukur",
    "wof:placetype":"locality"
},
  "geometry": {"coordinates":[30.3305,11.5376],"type":"Point"}
}