{
  "type": "Feature",
  "properties": {
    "gn:admin1_code":"41.0",
    "gn:asciiname":"Fariq al Fadul",
    "gn:country_code":"SD",
    "gn:dem":394,
    "gn:feature_class":"P",
    "gn:feature_code":"PPL",
    "gn:name":"Far\u012bq al Fadul",
    "gn:population":0,
    "gn:timezone":"Africa/Khartoum",
    "iso:country":"SD",
    "name:und_x_variant":[
        "Far\u012bq al Fadul"
    ],
    "wof:name":"Fariq al Fadul",
    "wof:placetype":"locality"
},
  "geometry": {"coordinates":[32.5749,14.2385],"type":"Point"}
}