{
  "type": "Feature",
  "properties": {
    "gn:admin1_code":"58.0",
    "gn:asciiname":"Hajju al Uhaymir",
    "gn:country_code":"SD",
    "gn:dem":441,
    "gn:feature_class":"P",
    "gn:feature_code":"PPL",
    "gn:name":"\u1e28\u0101jj\u016b al U\u1e29aymir",
    "gn:population":0,
    "gn:timezone":"Africa/Khartoum",
    "iso:country":"SD",
    "name:und_x_variant":[
        "Hago el Uheimir",
        "\u1e28\u0101jj\u016b al U\u1e29aymir"
    ],
    "wof:name":"Hajju al Uhaymir",
    "wof:placetype":"locality"
},
  "geometry": {"coordinates":[33.33333,13.78333],"type":"Point"}
}