{
  "type": "Feature",
  "properties": {
    "gn:admin1_code":"38.0",
    "gn:asciiname":"Fatha Al `Ushshab",
    "gn:country_code":"SD",
    "gn:dem":401,
    "gn:feature_class":"P",
    "gn:feature_code":"PPL",
    "gn:name":"F\u0101t\u1e29a Al \u2018Ushshab",
    "gn:population":0,
    "gn:timezone":"Africa/Khartoum",
    "iso:country":"SD",
    "name:und_x_variant":[
        "F\u0101t\u1e29a Al \u2018Ushshab"
    ],
    "wof:name":"Fatha Al `Ushshab",
    "wof:placetype":"locality"
},
  "geometry": {"coordinates":[33.3823,14.9679],"type":"Point"}
}