{
  "type": "Feature",
  "properties": {
    "gn:admin1_code":"50.0",
    "gn:asciiname":"Hantoby",
    "gn:country_code":"SD",
    "gn:dem":919,
    "gn:feature_class":"P",
    "gn:feature_code":"PPL",
    "gn:name":"\u1e28antoby",
    "gn:population":0,
    "gn:timezone":"Africa/Khartoum",
    "iso:country":"SD",
    "name:und_x_variant":[
        "\u1e28antoby"
    ],
    "wof:name":"Hantoby",
    "wof:placetype":"locality"
},
  "geometry": {"coordinates":[31.0813,11.8872],"type":"Point"}
}