{
  "type": "Feature",
  "properties": {
    "gn:admin1_code":"56.0",
    "gn:asciiname":"Al Hireziyya",
    "gn:country_code":"SD",
    "gn:dem":435,
    "gn:feature_class":"P",
    "gn:feature_code":"PPL",
    "gn:name":"Al \u1e28ireziyya",
    "gn:population":0,
    "gn:timezone":"Africa/Khartoum",
    "iso:country":"SD",
    "name:und_x_variant":[
        "Al \u1e28ireziyya"
    ],
    "wof:name":"Al Hireziyya",
    "wof:placetype":"locality"
},
  "geometry": {"coordinates":[31.5728,12.9398],"type":"Point"}
}