{
  "type": "Feature",
  "properties": {
    "gn:admin1_code":"38.0",
    "gn:asciiname":"Kambo az Zaghawa",
    "gn:country_code":"SD",
    "gn:dem":389,
    "gn:feature_class":"P",
    "gn:feature_code":"PPL",
    "gn:name":"Kambo az Zaghawa",
    "gn:population":0,
    "gn:timezone":"Africa/Khartoum",
    "iso:country":"SD",
    "wof:name":"Kambo az Zaghawa",
    "wof:placetype":"locality"
},
  "geometry": {"coordinates":[32.6967,15.2111],"type":"Point"}
}