{
  "type": "Feature",
  "properties": {
    "gn:admin1_code":"42.0",
    "gn:asciiname":"Wad Jum`ah",
    "gn:country_code":"SD",
    "gn:dem":594,
    "gn:feature_class":"P",
    "gn:feature_code":"PPL",
    "gn:name":"Wad Jum\u2018ah",
    "gn:population":0,
    "gn:timezone":"Africa/Khartoum",
    "iso:country":"SD",
    "name:und_x_variant":[
        "Wad Gum\u2018a",
        "Wad Jum\u2018ah"
    ],
    "wof:name":"Wad Jum`ah",
    "wof:placetype":"locality"
},
  "geometry": {"coordinates":[34.15,10.16667],"type":"Point"}
}