{
  "type": "Feature",
  "properties": {
    "gn:admin1_code":"49.0",
    "gn:asciiname":"El Hashima",
    "gn:country_code":"SD",
    "gn:dem":485,
    "gn:feature_class":"P",
    "gn:feature_code":"PPL",
    "gn:name":"El Hashima",
    "gn:population":0,
    "gn:timezone":"Africa/Khartoum",
    "iso:country":"SD",
    "name:und_x_variant":[
        "Al Hashima"
    ],
    "wof:name":"El Hashima",
    "wof:placetype":"locality"
},
  "geometry": {"coordinates":[24.85478,10.584],"type":"Point"}
}