{
  "type": "Feature",
  "properties": {
    "gn:admin1_code":"47.0",
    "gn:asciiname":"Abu Mina",
    "gn:country_code":"SD",
    "gn:dem":713,
    "gn:feature_class":"P",
    "gn:feature_code":"PPL",
    "gn:name":"Abu Mina",
    "gn:population":0,
    "gn:timezone":"Africa/Khartoum",
    "iso:country":"SD",
    "wof:name":"Abu Mina",
    "wof:placetype":"locality"
},
  "geometry": {"coordinates":[21.98333,13.05],"type":"Point"}
}