{
  "type": "Feature",
  "properties": {
    "gn:admin1_code":"38.0",
    "gn:asciiname":"Sarayat `Abd Ar Rahman",
    "gn:country_code":"SD",
    "gn:dem":406,
    "gn:feature_class":"P",
    "gn:feature_code":"PPL",
    "gn:name":"\u015ear\u0101yat \u2018Abd Ar Ra\u1e29man",
    "gn:population":0,
    "gn:timezone":"Africa/Khartoum",
    "iso:country":"SD",
    "name:und_x_variant":[
        "\u015ear\u0101yat \u2018Abd Ar Ra\u1e29man"
    ],
    "wof:name":"Sarayat `Abd Ar Rahman",
    "wof:placetype":"locality"
},
  "geometry": {"coordinates":[33.2407,14.5521],"type":"Point"}
}