{
  "type": "Feature",
  "properties": {
    "gn:admin1_code":"43.0",
    "gn:asciiname":"Debtod",
    "gn:country_code":"SD",
    "gn:dem":226,
    "gn:feature_class":"P",
    "gn:feature_code":"PPL",
    "gn:name":"Debtod",
    "gn:population":0,
    "gn:timezone":"Africa/Khartoum",
    "iso:country":"SD",
    "wof:name":"Debtod",
    "wof:placetype":"locality"
},
  "geometry": {"coordinates":[30.48333,19.36667000000001],"type":"Point"}
}