{
  "type": "Feature",
  "properties": {
    "gn:country":"SD",
    "gn:fcode":"PPL",
    "gn:population":37113,
    "iso:country":"SD",
    "name:ara_x_preferred":[
        "\u0627\u0644\u062f\u0644\u0646\u062c"
    ],
    "name:arz_x_preferred":[
        "\u0627\u0644\u062f\u0644\u0646\u062c"
    ],
    "name:azb_x_preferred":[
        "\u062f\u0644\u0646\u062c"
    ],
    "name:bul_x_preferred":[
        "\u0414\u0438\u043b\u0438\u043d\u0433"
    ],
    "name:ceb_x_preferred":[
        "Dilling"
    ],
    "name:eng_x_preferred":[
        "Dalang"
    ],
    "name:fas_x_preferred":[
        "\u062f\u0644\u0646\u062c"
    ],
    "name:jpn_x_preferred":[
        "\u30c7\u30a3\u30ea\u30f3\u30b0"
    ],
    "name:nld_x_preferred":[
        "Dalang"
    ],
    "name:pol_x_preferred":[
        "Ad-Dillind\u017c"
    ],
    "name:rus_x_preferred":[
        "\u0414\u0438\u043b\u043b\u0438\u043d\u0433"
    ],
    "name:und_x_variant":[
        "Ad Dalanj"
    ],
    "qs:name":"Dilling",
    "qs:photos_9r":0,
    "qs:photos_sr":0,
    "qs:pop_sr":"7",
    "wd:wordcount":76,
    "wof:name":"Dilling",
    "wof:placetype":"locality",
    "wof:population":37113
},
  "geometry": {"coordinates":[29.65,12.05],"type":"Point"}
}