{
  "type": "Feature",
  "properties": {
    "gn:admin1_code":"49.0",
    "gn:asciiname":"Saysaban",
    "gn:country_code":"SD",
    "gn:dem":605,
    "gn:feature_class":"P",
    "gn:feature_code":"PPL",
    "gn:name":"Saysab\u0101n",
    "gn:population":0,
    "gn:timezone":"Africa/Khartoum",
    "iso:country":"SD",
    "name:und_x_variant":[
        "Seisaban",
        "Sesban",
        "Teirab",
        "Saysab\u0101n"
    ],
    "wof:name":"Saysaban",
    "wof:placetype":"locality"
},
  "geometry": {"coordinates":[23.85,11.38333],"type":"Point"}
}