{
  "type": "Feature",
  "properties": {
    "gn:admin1_code":"41.0",
    "gn:asciiname":"Limemat Hamdan",
    "gn:country_code":"SD",
    "gn:dem":387,
    "gn:feature_class":"P",
    "gn:feature_code":"PPL",
    "gn:name":"Limemat \u1e28amd\u0101n",
    "gn:population":0,
    "gn:timezone":"Africa/Khartoum",
    "iso:country":"SD",
    "name:und_x_variant":[
        "Limemat \u1e28amd\u0101n"
    ],
    "wof:name":"Limemat Hamdan",
    "wof:placetype":"locality"
},
  "geometry": {"coordinates":[32.3706,13.48],"type":"Point"}
}