{
  "type": "Feature",
  "properties": {
    "gn:admin1_code":"47.0",
    "gn:asciiname":"Kurrur",
    "gn:country_code":"SD",
    "gn:dem":789,
    "gn:feature_class":"P",
    "gn:feature_code":"PPL",
    "gn:name":"Kurrur",
    "gn:population":0,
    "gn:timezone":"Africa/Khartoum",
    "iso:country":"SD",
    "name:und_x_variant":[
        "Kourrour",
        "Kurrur"
    ],
    "wof:name":"Kurrur",
    "wof:placetype":"locality"
},
  "geometry": {"coordinates":[22.20796,13.11869],"type":"Point"}
}