{
  "type": "Feature",
  "properties": {
    "gn:admin1_code":"41.0",
    "gn:asciiname":"Ad Dabba",
    "gn:country_code":"SD",
    "gn:dem":403,
    "gn:feature_class":"P",
    "gn:feature_code":"PPL",
    "gn:name":"Ad Dabba",
    "gn:population":0,
    "gn:timezone":"Africa/Khartoum",
    "iso:country":"SD",
    "wof:name":"Ad Dabba",
    "wof:placetype":"locality"
},
  "geometry": {"coordinates":[32.2801,12.8744],"type":"Point"}
}