{
  "type": "Feature",
  "properties": {
    "gn:admin1_code":"38.0",
    "gn:asciiname":"Qawz Wad Hamad",
    "gn:country_code":"SD",
    "gn:dem":400,
    "gn:feature_class":"P",
    "gn:feature_code":"PPL",
    "gn:name":"Qawz Wad \u1e28amad",
    "gn:population":0,
    "gn:timezone":"Africa/Khartoum",
    "iso:country":"SD",
    "name:und_x_variant":[
        "Qoz Wad Hamad",
        "Qawz Wad \u1e28amad"
    ],
    "wof:name":"Qawz Wad Hamad",
    "wof:placetype":"locality"
},
  "geometry": {"coordinates":[33.28333,15.18333],"type":"Point"}
}