{
  "type": "Feature",
  "properties": {
    "gn:admin1_code":"47.0",
    "gn:asciiname":"Abu Luk",
    "gn:country_code":"SD",
    "gn:dem":855,
    "gn:feature_class":"P",
    "gn:feature_code":"PPL",
    "gn:name":"Abu Luk",
    "gn:population":0,
    "gn:timezone":"Africa/Khartoum",
    "iso:country":"SD",
    "name:eng_x_preferred":[
        "Abu Luk"
    ],
    "wof:name":"Abu Luk",
    "wof:placetype":"locality"
},
  "geometry": {"coordinates":[22.46725,13.22493],"type":"Point"}
}