{
  "type": "Feature",
  "properties": {
    "gn:admin1_code":"50.0",
    "gn:asciiname":"Ad Dilebat",
    "gn:country_code":"SD",
    "gn:dem":562,
    "gn:feature_class":"P",
    "gn:feature_code":"PPL",
    "gn:name":"Ad Dileb\u0101t",
    "gn:population":0,
    "gn:timezone":"Africa/Khartoum",
    "iso:country":"SD",
    "name:ara_x_preferred":[
        "Ad Dileb\u0101t"
    ],
    "wof:name":"Ad Dilebat",
    "wof:placetype":"locality"
},
  "geometry": {"coordinates":[31.3621,11.4066],"type":"Point"}
}