{
  "type": "Feature",
  "properties": {
    "gn:admin1_code":"41.0",
    "gn:asciiname":"Um `Ud",
    "gn:country_code":"SD",
    "gn:dem":400,
    "gn:feature_class":"P",
    "gn:feature_code":"PPL",
    "gn:name":"Um \u2018\u016ad",
    "gn:population":0,
    "gn:timezone":"Africa/Khartoum",
    "iso:country":"SD",
    "name:ara_x_preferred":[
        "Um \u2018\u016ad"
    ],
    "wof:name":"Um `Ud",
    "wof:placetype":"locality"
},
  "geometry": {"coordinates":[32.4753,13.0171],"type":"Point"}
}