{
  "type": "Feature",
  "properties": {
    "gn:admin1_code":"50.0",
    "gn:asciiname":"Billiyya",
    "gn:country_code":"SD",
    "gn:dem":528,
    "gn:feature_class":"P",
    "gn:feature_code":"PPL",
    "gn:name":"Billiyya",
    "gn:population":0,
    "gn:timezone":"Africa/Khartoum",
    "iso:country":"SD",
    "wof:name":"Billiyya",
    "wof:placetype":"locality"
},
  "geometry": {"coordinates":[31.3004,12.4381],"type":"Point"}
}