{
  "type": "Feature",
  "properties": {
    "gn:admin1_code":"31.0",
    "gn:asciiname":"Al Fao",
    "gn:country_code":"SD",
    "gn:dem":427,
    "gn:feature_class":"P",
    "gn:feature_code":"PPL",
    "gn:name":"Al Fao",
    "gn:population":0,
    "gn:timezone":"Africa/Khartoum",
    "iso:country":"SD",
    "wof:name":"Al Fao",
    "wof:placetype":"locality"
},
  "geometry": {"coordinates":[34.08358,14.11246],"type":"Point"}
}