{
  "type": "Feature",
  "properties": {
    "gn:admin1_code":"38.0",
    "gn:asciiname":"Hajj Ibrahim",
    "gn:country_code":"SD",
    "gn:dem":425,
    "gn:feature_class":"P",
    "gn:feature_code":"PPL",
    "gn:name":"\u1e28\u0101jj Ibr\u0101h\u012bm",
    "gn:population":0,
    "gn:timezone":"Africa/Khartoum",
    "iso:country":"SD",
    "name:und_x_variant":[
        "Hag Ibrahim",
        "\u1e28\u0101jj Ibr\u0101h\u012bm"
    ],
    "wof:lang_x_official":[
        "ara",
        "eng"
    ],
    "wof:lang_x_spoken":[
        "ara",
        "eng"
    ],
    "wof:name":"Hajj Ibrahim",
    "wof:placetype":"locality"
},
  "geometry": {"coordinates":[33.55,14.63333],"type":"Point"}
}