{
  "type": "Feature",
  "properties": {
    "gn:admin1_code":"56.0",
    "gn:asciiname":"Sarar Baqar",
    "gn:country_code":"SD",
    "gn:dem":619,
    "gn:feature_class":"P",
    "gn:feature_code":"PPL",
    "gn:name":"Sar\u0101r Baqar",
    "gn:population":0,
    "gn:timezone":"Africa/Khartoum",
    "iso:country":"SD",
    "name:und_x_variant":[
        "Serar Baqar",
        "Sar\u0101r Baqar"
    ],
    "wof:name":"Sarar Baqar",
    "wof:placetype":"locality"
},
  "geometry": {"coordinates":[28.81667,14.06667],"type":"Point"}
}