{
  "type": "Feature",
  "properties": {
    "gn:admin1_code":"55.0",
    "gn:asciiname":"Wada`ah",
    "gn:country_code":"SD",
    "gn:dem":608,
    "gn:feature_class":"P",
    "gn:feature_code":"PPL",
    "gn:name":"Wada\u2018ah",
    "gn:population":0,
    "gn:timezone":"Africa/Khartoum",
    "iso:country":"SD",
    "name:und_x_variant":[
        "Wada\u2018a",
        "Wada\u2018ah"
    ],
    "wof:name":"Wada`ah",
    "wof:placetype":"locality"
},
  "geometry": {"coordinates":[25.75,12.83333],"type":"Point"}
}