{
  "type": "Feature",
  "properties": {
    "gn:admin1_code":"41.0",
    "gn:asciiname":"Hillat Idris",
    "gn:country_code":"SD",
    "gn:dem":385,
    "gn:feature_class":"P",
    "gn:feature_code":"PPL",
    "gn:name":"\u1e28illat Idr\u012bs",
    "gn:population":0,
    "gn:timezone":"Africa/Khartoum",
    "iso:country":"SD",
    "name:und_x_variant":[
        "\u1e28illat Idr\u012bs"
    ],
    "wof:name":"Hillat Idris",
    "wof:placetype":"locality"
},
  "geometry": {"coordinates":[32.1255,14.0596],"type":"Point"}
}