{
  "type": "Feature",
  "properties": {
    "gn:admin1_code":"61.0",
    "gn:asciiname":"Kelling",
    "gn:country_code":"SD",
    "gn:dem":1853,
    "gn:feature_class":"P",
    "gn:feature_code":"PPL",
    "gn:name":"Kelling",
    "gn:population":0,
    "gn:timezone":"Africa/Khartoum",
    "iso:country":"SD",
    "name:ceb_x_preferred":[
        "Kelling"
    ],
    "name:cym_x_preferred":[
        "Kelling"
    ],
    "name:fas_x_preferred":[
        "\u06a9\u0644\u06cc\u0646\u06af"
    ],
    "name:fra_x_preferred":[
        "Kelling"
    ],
    "name:ita_x_preferred":[
        "Kelling"
    ],
    "name:nld_x_preferred":[
        "Kelling"
    ],
    "name:pol_x_preferred":[
        "Kelling"
    ],
    "name:swe_x_preferred":[
        "Kelling"
    ],
    "wof:name":"Kelling",
    "wof:placetype":"locality"
},
  "geometry": {"coordinates":[24.31019,13.08747],"type":"Point"}
}