{
  "type": "Feature",
  "properties": {
    "gn:admin1_code":"29.0",
    "gn:asciiname":"Faki Hashim",
    "gn:country_code":"SD",
    "gn:dem":379,
    "gn:feature_class":"P",
    "gn:feature_code":"PPL",
    "gn:name":"Fak\u012b H\u0101shim",
    "gn:population":0,
    "gn:timezone":"Africa/Khartoum",
    "iso:country":"SD",
    "wof:name":"Faki Hashim",
    "wof:placetype":"locality"
},
  "geometry": {"coordinates":[32.55,15.83333],"type":"Point"}
}