{
  "type": "Feature",
  "properties": {
    "gn:admin1_code":"47.0",
    "gn:asciiname":"Konga",
    "gn:country_code":"SD",
    "gn:dem":780,
    "gn:feature_class":"P",
    "gn:feature_code":"PPL",
    "gn:name":"Konga",
    "gn:population":0,
    "gn:timezone":"Africa/Khartoum",
    "iso:country":"SD",
    "name:ceb_x_preferred":[
        "Konga"
    ],
    "name:ita_x_preferred":[
        "Konga"
    ],
    "name:nld_x_preferred":[
        "Konga"
    ],
    "name:nno_x_preferred":[
        "Konga"
    ],
    "name:nor_x_preferred":[
        "Konga"
    ],
    "name:sme_x_preferred":[
        "Konga"
    ],
    "name:swe_x_preferred":[
        "Konga"
    ],
    "name:und_x_variant":[
        "Rakou Kinga",
        "Konga"
    ],
    "wof:name":"Konga",
    "wof:placetype":"locality"
},
  "geometry": {"coordinates":[22.13703,13.13045],"type":"Point"}
}