{
  "type": "Feature",
  "properties": {
    "gn:admin1_code":"38.0",
    "gn:asciiname":"Kambo ar Rizeqal",
    "gn:country_code":"SD",
    "gn:dem":391,
    "gn:feature_class":"P",
    "gn:feature_code":"PPL",
    "gn:name":"Kambo ar Rizeqal",
    "gn:population":0,
    "gn:timezone":"Africa/Khartoum",
    "iso:country":"SD",
    "wof:lang_x_official":[
        "ara",
        "eng"
    ],
    "wof:lang_x_spoken":[
        "ara",
        "eng"
    ],
    "wof:name":"Kambo ar Rizeqal",
    "wof:placetype":"locality"
},
  "geometry": {"coordinates":[32.7453,15.2165],"type":"Point"}
}