{
  "type": "Feature",
  "properties": {
    "gn:admin1_code":"53.0",
    "gn:asciiname":"El Foqara",
    "gn:country_code":"SD",
    "gn:dem":367,
    "gn:feature_class":"P",
    "gn:feature_code":"PPL",
    "gn:name":"El Foqara",
    "gn:population":0,
    "gn:timezone":"Africa/Khartoum",
    "iso:country":"SD",
    "wof:name":"El Foqara",
    "wof:placetype":"locality"
},
  "geometry": {"coordinates":[32.9408,16.54],"type":"Point"}
}