{
  "type": "Feature",
  "properties": {
    "gn:admin1_code":"55.0",
    "gn:asciiname":"`Idd al Guddeim",
    "gn:country_code":"SD",
    "gn:dem":645,
    "gn:feature_class":"P",
    "gn:feature_code":"PPL",
    "gn:name":"\u2018Idd al Guddeim",
    "gn:population":0,
    "gn:timezone":"Africa/Khartoum",
    "iso:country":"SD",
    "name:und_x_variant":[
        "\u2018Idd el Guddeim",
        "\u2018Idd al Guddeim"
    ],
    "wof:lang_x_official":[
        "ara",
        "eng"
    ],
    "wof:lang_x_spoken":[
        "ara",
        "eng"
    ],
    "wof:name":"`Idd al Guddeim",
    "wof:placetype":"locality"
},
  "geometry": {"coordinates":[25.75,13.15],"type":"Point"}
}