{
  "type": "Feature",
  "properties": {
    "gn:admin1_code":"49.0",
    "gn:asciiname":"Hugeir el Kiazi",
    "gn:country_code":"SD",
    "gn:dem":475,
    "gn:feature_class":"P",
    "gn:feature_code":"PPL",
    "gn:name":"Hugeir el Kiazi",
    "gn:population":0,
    "gn:timezone":"Africa/Khartoum",
    "iso:country":"SD",
    "name:und_x_variant":[
        "Hugeir al Kiazi"
    ],
    "wof:name":"Hugeir el Kiazi",
    "wof:placetype":"locality"
},
  "geometry": {"coordinates":[25.08333,10.28333],"type":"Point"}
}