{
  "type": "Feature",
  "properties": {
    "gn:admin1_code":"47.0",
    "gn:asciiname":"Sandikoro",
    "gn:country_code":"SD",
    "gn:dem":825,
    "gn:feature_class":"P",
    "gn:feature_code":"PPL",
    "gn:name":"Sandikoro",
    "gn:population":0,
    "gn:timezone":"Africa/Khartoum",
    "iso:country":"SD",
    "name:eng_x_preferred":[
        "Sandikoro"
    ],
    "wof:name":"Sandikoro",
    "wof:placetype":"locality"
},
  "geometry": {"coordinates":[22.38331,13.31001],"type":"Point"}
}