{
  "type": "Feature",
  "properties": {
    "gn:admin1_code":"41.0",
    "gn:asciiname":"Saluqi",
    "gn:country_code":"SD",
    "gn:dem":388,
    "gn:feature_class":"P",
    "gn:feature_code":"PPL",
    "gn:name":"Sal\u016bq\u012b",
    "gn:population":0,
    "gn:timezone":"Africa/Khartoum",
    "iso:country":"SD",
    "name:und_x_variant":[
        "Salogi",
        "Sal\u016bq\u012b"
    ],
    "wof:name":"Saluqi",
    "wof:placetype":"locality"
},
  "geometry": {"coordinates":[32.45,13.15],"type":"Point"}
}