{
  "type": "Feature",
  "properties": {
    "gn:admin1_code":"38.0",
    "gn:asciiname":"Qoz Ash Shikenab",
    "gn:country_code":"SD",
    "gn:dem":415,
    "gn:feature_class":"P",
    "gn:feature_code":"PPL",
    "gn:name":"Qoz Ash Shiken\u0101b",
    "gn:population":0,
    "gn:timezone":"Africa/Khartoum",
    "iso:country":"SD",
    "name:ara_x_preferred":[
        "Qoz Ash Shiken\u0101b"
    ],
    "wof:lang_x_official":[
        "ara",
        "eng"
    ],
    "wof:lang_x_spoken":[
        "ara",
        "eng"
    ],
    "wof:name":"Qoz Ash Shikenab",
    "wof:placetype":"locality"
},
  "geometry": {"coordinates":[33.4956,14.5647],"type":"Point"}
}