{
  "type": "Feature",
  "properties": {
    "gn:admin1_code":"61.0",
    "gn:asciiname":"Kosormungia",
    "gn:country_code":"SD",
    "gn:dem":1003,
    "gn:feature_class":"P",
    "gn:feature_code":"PPL",
    "gn:name":"Kosormungia",
    "gn:population":0,
    "gn:timezone":"Africa/Khartoum",
    "iso:country":"SD",
    "name:und_x_variant":[
        "Kosourmongia",
        "Kosormungia"
    ],
    "wof:name":"Kosormungia",
    "wof:placetype":"locality"
},
  "geometry": {"coordinates":[23.56667,13.43333],"type":"Point"}
}