{
  "type": "Feature",
  "properties": {
    "gn:admin1_code":"38.0",
    "gn:asciiname":"`Uraq al Qala`ab",
    "gn:country_code":"SD",
    "gn:dem":393,
    "gn:feature_class":"P",
    "gn:feature_code":"PPL",
    "gn:name":"\u2018Uraq al Qala\u2018ab",
    "gn:population":0,
    "gn:timezone":"Africa/Khartoum",
    "iso:country":"SD",
    "name:und_x_variant":[
        "\u2018Uraq",
        "\u2018Uraq al Qala\u2018ab"
    ],
    "wof:name":"`Uraq al Qala`ab",
    "wof:placetype":"locality"
},
  "geometry": {"coordinates":[32.5179,14.4544],"type":"Point"}
}