{
  "type": "Feature",
  "properties": {
    "gn:admin1_code":"55.0",
    "gn:asciiname":"Kalma",
    "gn:country_code":"SD",
    "gn:dem":911,
    "gn:feature_class":"P",
    "gn:feature_code":"PPL",
    "gn:name":"Kalma",
    "gn:population":0,
    "gn:timezone":"Africa/Khartoum",
    "iso:country":"SD",
    "name:ceb_x_preferred":[
        "Kalma"
    ],
    "name:deu_x_preferred":[
        "Kalma"
    ],
    "name:fin_x_preferred":[
        "Kalma"
    ],
    "name:fra_x_preferred":[
        "Kalma"
    ],
    "name:hrv_x_preferred":[
        "Kalma"
    ],
    "name:nld_x_preferred":[
        "Kalma"
    ],
    "wof:name":"Kalma",
    "wof:placetype":"locality"
},
  "geometry": {"coordinates":[24.79547,13.44631],"type":"Point"}
}