{
  "type": "Feature",
  "properties": {
    "gn:admin1_code":"41.0",
    "gn:asciiname":"Al Ghawi Al `Aris",
    "gn:country_code":"SD",
    "gn:dem":394,
    "gn:feature_class":"P",
    "gn:feature_code":"PPL",
    "gn:name":"Al Gh\u0101wi Al \u2018Aris",
    "gn:population":0,
    "gn:timezone":"Africa/Khartoum",
    "iso:country":"SD",
    "name:ara_x_preferred":[
        "Al Gh\u0101wi Al \u2018Aris"
    ],
    "wof:lang_x_official":[
        "ara",
        "eng"
    ],
    "wof:lang_x_spoken":[
        "ara",
        "eng"
    ],
    "wof:name":"Al Ghawi Al `Aris",
    "wof:placetype":"locality"
},
  "geometry": {"coordinates":[32.5868,14.8679],"type":"Point"}
}