{
  "type": "Feature",
  "properties": {
    "gn:admin1_code":"41.0",
    "gn:asciiname":"'Abu Namil",
    "gn:country_code":"SD",
    "gn:dem":419,
    "gn:feature_class":"P",
    "gn:feature_code":"PPL",
    "gn:name":"\u2019Abu Namil",
    "gn:population":0,
    "gn:timezone":"Africa/Khartoum",
    "iso:country":"SD",
    "name:und_x_variant":[
        "\u2019Abu Namil"
    ],
    "wof:name":"'Abu Namil",
    "wof:placetype":"locality"
},
  "geometry": {"coordinates":[32.9407,12.8041],"type":"Point"}
}