{
  "type": "Feature",
  "properties": {
    "gn:admin1_code":"41.0",
    "gn:asciiname":"Wad `Abd Allah",
    "gn:country_code":"SD",
    "gn:dem":392,
    "gn:feature_class":"P",
    "gn:feature_code":"PPL",
    "gn:name":"Wad \u2018Abd Allah",
    "gn:population":0,
    "gn:timezone":"Africa/Khartoum",
    "iso:country":"SD",
    "name:und_x_variant":[
        "Wad \u2018Abd Allah"
    ],
    "wof:name":"Wad `Abd Allah",
    "wof:placetype":"locality"
},
  "geometry": {"coordinates":[32.2405,13.5607],"type":"Point"}
}