{
  "type": "Feature",
  "properties": {
    "gn:admin1_code":"38.0",
    "gn:asciiname":"Sabun",
    "gn:country_code":"SD",
    "gn:dem":411,
    "gn:feature_class":"P",
    "gn:feature_code":"PPL",
    "gn:name":"Sabun",
    "gn:population":0,
    "gn:timezone":"Africa/Khartoum",
    "iso:country":"SD",
    "name:ceb_x_preferred":[
        "Sabun"
    ],
    "name:deu_x_preferred":[
        "Sabun"
    ],
    "name:swe_x_preferred":[
        "Sabun"
    ],
    "wof:name":"Sabun",
    "wof:placetype":"locality"
},
  "geometry": {"coordinates":[33.48,14.1839],"type":"Point"}
}