{
  "type": "Feature",
  "properties": {
    "gn:admin1_code":"62.0",
    "gn:asciiname":"Abu Humayrah",
    "gn:country_code":"SD",
    "gn:dem":566,
    "gn:feature_class":"P",
    "gn:feature_code":"PPL",
    "gn:name":"Ab\u016b \u1e28umayrah",
    "gn:population":0,
    "gn:timezone":"Africa/Khartoum",
    "iso:country":"SD",
    "name:und_x_variant":[
        "Abu Humeira",
        "Ab\u016b \u1e28umayrah"
    ],
    "wof:name":"Abu Humayrah",
    "wof:placetype":"locality"
},
  "geometry": {"coordinates":[28.45,12.56667],"type":"Point"}
}