{
  "type": "Feature",
  "properties": {
    "gn:admin1_code":"41.0",
    "gn:asciiname":"Um Biwera",
    "gn:country_code":"SD",
    "gn:dem":385,
    "gn:feature_class":"P",
    "gn:feature_code":"PPL",
    "gn:name":"Um Biwera",
    "gn:population":0,
    "gn:timezone":"Africa/Khartoum",
    "iso:country":"SD",
    "wof:name":"Um Biwera",
    "wof:placetype":"locality"
},
  "geometry": {"coordinates":[32.1549,13.7879],"type":"Point"}
}