{
  "type": "Feature",
  "properties": {
    "gn:admin1_code":"38.0",
    "gn:asciiname":"Wad al `Ataya",
    "gn:country_code":"SD",
    "gn:dem":414,
    "gn:feature_class":"P",
    "gn:feature_code":"PPL",
    "gn:name":"Wad al \u2018A\u0163\u0101y\u0101",
    "gn:population":0,
    "gn:timezone":"Africa/Khartoum",
    "iso:country":"SD",
    "name:und_x_variant":[
        "Wad al \u2018A\u0163\u0101y\u0101"
    ],
    "wof:name":"Wad al `Ataya",
    "wof:placetype":"locality"
},
  "geometry": {"coordinates":[33.4976,14.173],"type":"Point"}
}