{
  "type": "Feature",
  "properties": {
    "gn:admin1_code":"60.0",
    "gn:asciiname":"`Iyal an Naji",
    "gn:country_code":"SD",
    "gn:dem":472,
    "gn:feature_class":"P",
    "gn:feature_code":"PPL",
    "gn:name":"\u2018Iy\u0101l an N\u0101j\u012b",
    "gn:population":0,
    "gn:timezone":"Africa/Khartoum",
    "iso:country":"SD",
    "name:und_x_variant":[
        "\u2018Iyal en Nagi",
        "\u2018Iy\u0101l an N\u0101j\u012b"
    ],
    "wof:name":"`Iyal an Naji",
    "wof:placetype":"locality"
},
  "geometry": {"coordinates":[26.63333,11.61667],"type":"Point"}
}