{
  "type": "Feature",
  "properties": {
    "gn:admin1_code":"50.0",
    "gn:asciiname":"Toro",
    "gn:country_code":"SD",
    "gn:dem":553,
    "gn:feature_class":"P",
    "gn:feature_code":"PPL",
    "gn:name":"Toro",
    "gn:population":0,
    "gn:timezone":"Africa/Khartoum",
    "iso:country":"SD",
    "wof:name":"Toro",
    "wof:placetype":"locality"
},
  "geometry": {"coordinates":[30.00817,10.69568],"type":"Point"}
}