{
  "type": "Feature",
  "properties": {
    "gn:admin1_code":"38.0",
    "gn:asciiname":"Al `Amara Kasir",
    "gn:country_code":"SD",
    "gn:dem":403,
    "gn:feature_class":"P",
    "gn:feature_code":"PPL",
    "gn:name":"Al \u2018Am\u0101ra K\u0101s\u012br",
    "gn:population":0,
    "gn:timezone":"Africa/Khartoum",
    "iso:country":"SD",
    "name:und_x_variant":[
        "Al \u2018Am\u0101ra K\u0101s\u012br"
    ],
    "wof:name":"Al `Amara Kasir",
    "wof:placetype":"locality"
},
  "geometry": {"coordinates":[33.1127,14.629],"type":"Point"}
}