{
  "type": "Feature",
  "properties": {
    "gn:admin1_code":"41.0",
    "gn:asciiname":"Um Sunut",
    "gn:country_code":"SD",
    "gn:dem":384,
    "gn:feature_class":"P",
    "gn:feature_code":"PPL",
    "gn:name":"Um Sunu\u0163",
    "gn:population":0,
    "gn:timezone":"Africa/Khartoum",
    "iso:country":"SD",
    "name:ara_x_preferred":[
        "Um Sunu\u0163"
    ],
    "wof:name":"Um Sunut",
    "wof:placetype":"locality"
},
  "geometry": {"coordinates":[32.23,13.9152],"type":"Point"}
}