{
  "type": "Feature",
  "properties": {
    "gn:admin1_code":"38.0",
    "gn:asciiname":"Ab Bara",
    "gn:country_code":"SD",
    "gn:dem":390,
    "gn:feature_class":"P",
    "gn:feature_code":"PPL",
    "gn:name":"Ab B\u0101ra",
    "gn:population":0,
    "gn:timezone":"Africa/Khartoum",
    "iso:country":"SD",
    "name:und_x_variant":[
        "Ab B\u0101ra"
    ],
    "wof:name":"Ab Bara",
    "wof:placetype":"locality"
},
  "geometry": {"coordinates":[32.9158,14.9705],"type":"Point"}
}