{
  "type": "Feature",
  "properties": {
    "gn:admin1_code":"56.0",
    "gn:asciiname":"Um Kheren",
    "gn:country_code":"SD",
    "gn:dem":469,
    "gn:feature_class":"P",
    "gn:feature_code":"PPL",
    "gn:name":"Um Kheren",
    "gn:population":0,
    "gn:timezone":"Africa/Khartoum",
    "iso:country":"SD",
    "wof:name":"Um Kheren",
    "wof:placetype":"locality"
},
  "geometry": {"coordinates":[31.3264,12.6694],"type":"Point"}
}