{
  "type": "Feature",
  "properties": {
    "gn:admin1_code":"38.0",
    "gn:asciiname":"Barakat",
    "gn:country_code":"SD",
    "gn:dem":392,
    "gn:feature_class":"P",
    "gn:feature_code":"PPL",
    "gn:name":"Barakat",
    "gn:population":0,
    "gn:timezone":"Africa/Khartoum",
    "iso:country":"SD",
    "name:cat_x_preferred":[
        "Barakat"
    ],
    "name:ceb_x_preferred":[
        "Barakat"
    ],
    "name:deu_x_preferred":[
        "Barakat"
    ],
    "name:fra_x_preferred":[
        "Barakat"
    ],
    "name:pol_x_preferred":[
        "Barakat"
    ],
    "name:rus_x_preferred":[
        "\u0411\u0430\u0440\u0430\u043a\u0430\u0442"
    ],
    "name:swe_x_preferred":[
        "Barakat"
    ],
    "wof:lang_x_official":[
        "ara",
        "eng"
    ],
    "wof:lang_x_spoken":[
        "ara",
        "eng"
    ],
    "wof:name":"Barakat",
    "wof:placetype":"locality"
},
  "geometry": {"coordinates":[33.01472,15.09917],"type":"Point"}
}