{
  "type": "Feature",
  "properties": {
    "gn:admin1_code":"41.0",
    "gn:asciiname":"Wad Ab Daqar",
    "gn:country_code":"SD",
    "gn:dem":400,
    "gn:feature_class":"P",
    "gn:feature_code":"PPL",
    "gn:name":"Wad Ab Daqar",
    "gn:population":0,
    "gn:timezone":"Africa/Khartoum",
    "iso:country":"SD",
    "wof:name":"Wad Ab Daqar",
    "wof:placetype":"locality"
},
  "geometry": {"coordinates":[32.2218,13.4447],"type":"Point"}
}