{
  "type": "Feature",
  "properties": {
    "gn:admin1_code":"56.0",
    "gn:asciiname":"Ash Shiqlah",
    "gn:country_code":"SD",
    "gn:dem":427,
    "gn:feature_class":"P",
    "gn:feature_code":"PPL",
    "gn:name":"Ash Shiqlah",
    "gn:population":0,
    "gn:timezone":"Africa/Khartoum",
    "iso:country":"SD",
    "name:und_x_variant":[
        "Shigla",
        "Ash Shiqlah"
    ],
    "wof:name":"Ash Shiqlah",
    "wof:placetype":"locality"
},
  "geometry": {"coordinates":[31.33333,13.75],"type":"Point"}
}