{
  "type": "Feature",
  "properties": {
    "gn:admin1_code":"38.0",
    "gn:asciiname":"Al Baranku",
    "gn:country_code":"SD",
    "gn:dem":395,
    "gn:feature_class":"P",
    "gn:feature_code":"PPL",
    "gn:name":"Al Barank\u016b",
    "gn:population":0,
    "gn:timezone":"Africa/Khartoum",
    "iso:country":"SD",
    "name:und_x_variant":[
        "Branko",
        "Brankaw",
        "Al Barank\u016b"
    ],
    "wof:name":"Al Baranku",
    "wof:placetype":"locality"
},
  "geometry": {"coordinates":[33.2587,14.9774],"type":"Point"}
}