{
  "type": "Feature",
  "properties": {
    "gn:admin1_code":"50.0",
    "gn:asciiname":"Hillat ash Shisha",
    "gn:country_code":"SD",
    "gn:dem":698,
    "gn:feature_class":"P",
    "gn:feature_code":"PPL",
    "gn:name":"Hillat ash Shisha",
    "gn:population":0,
    "gn:timezone":"Africa/Khartoum",
    "iso:country":"SD",
    "wof:name":"Hillat ash Shisha",
    "wof:placetype":"locality"
},
  "geometry": {"coordinates":[30.2735,11.5471],"type":"Point"}
}