{
  "type": "Feature",
  "properties": {
    "gn:admin1_code":"56.0",
    "gn:asciiname":"Ambabi",
    "gn:country_code":"SD",
    "gn:dem":481,
    "gn:feature_class":"P",
    "gn:feature_code":"PPL",
    "gn:name":"Amb\u0101bi",
    "gn:population":0,
    "gn:timezone":"Africa/Khartoum",
    "iso:country":"SD",
    "name:ara_x_preferred":[
        "Amb\u0101bi"
    ],
    "wof:name":"Ambabi",
    "wof:placetype":"locality"
},
  "geometry": {"coordinates":[31.1337,12.69],"type":"Point"}
}