{
  "type": "Feature",
  "properties": {
    "gn:admin1_code":"38.0",
    "gn:asciiname":"Um Hijer",
    "gn:country_code":"SD",
    "gn:dem":409,
    "gn:feature_class":"P",
    "gn:feature_code":"PPL",
    "gn:name":"Um \u1e28ijer",
    "gn:population":0,
    "gn:timezone":"Africa/Khartoum",
    "iso:country":"SD",
    "name:ara_x_preferred":[
        "Um \u1e28ijer"
    ],
    "wof:name":"Um Hijer",
    "wof:placetype":"locality"
},
  "geometry": {"coordinates":[33.4088,14.2387],"type":"Point"}
}