{
  "type": "Feature",
  "properties": {
    "gn:admin1_code":"53.0",
    "gn:asciiname":"Hilat et Tondob",
    "gn:country_code":"SD",
    "gn:dem":364,
    "gn:feature_class":"P",
    "gn:feature_code":"PPL",
    "gn:name":"Hilat et Tondob",
    "gn:population":0,
    "gn:timezone":"Africa/Khartoum",
    "iso:country":"SD",
    "wof:name":"Hilat et Tondob",
    "wof:placetype":"locality"
},
  "geometry": {"coordinates":[33.3222,16.6574],"type":"Point"}
}