{
  "type": "Feature",
  "properties": {
    "gn:admin1_code":"55.0",
    "gn:asciiname":"Kimang Kergil",
    "gn:country_code":"SD",
    "gn:dem":1408,
    "gn:feature_class":"P",
    "gn:feature_code":"PPL",
    "gn:name":"Kimang Kergil",
    "gn:population":0,
    "gn:timezone":"Africa/Khartoum",
    "iso:country":"SD",
    "wof:name":"Kimang Kergil",
    "wof:placetype":"locality"
},
  "geometry": {"coordinates":[24.35,13.51667],"type":"Point"}
}