{
  "type": "Feature",
  "properties": {
    "gn:admin1_code":"43.0",
    "gn:asciiname":"Usli",
    "gn:country_code":"SD",
    "gn:dem":250,
    "gn:feature_class":"P",
    "gn:feature_code":"PPL",
    "gn:name":"Usli",
    "gn:population":0,
    "gn:timezone":"Africa/Khartoum",
    "iso:country":"SD",
    "wof:name":"Usli",
    "wof:placetype":"locality"
},
  "geometry": {"coordinates":[31.65,18.21667],"type":"Point"}
}