{
  "type": "Feature",
  "properties": {
    "gn:admin1_code":"41.0",
    "gn:asciiname":"Al Hafayir Hamad",
    "gn:country_code":"SD",
    "gn:dem":395,
    "gn:feature_class":"P",
    "gn:feature_code":"PPL",
    "gn:name":"Al \u1e28af\u0101yir \u1e28amad",
    "gn:population":0,
    "gn:timezone":"Africa/Khartoum",
    "iso:country":"SD",
    "name:und_x_variant":[
        "Al \u1e28af\u0101yir \u1e28amad"
    ],
    "wof:name":"Al Hafayir Hamad",
    "wof:placetype":"locality"
},
  "geometry": {"coordinates":[32.637,14.8301],"type":"Point"}
}