{
  "type": "Feature",
  "properties": {
    "gn:admin1_code":"61.0",
    "gn:asciiname":"Myar",
    "gn:country_code":"SD",
    "gn:dem":621,
    "gn:feature_class":"P",
    "gn:feature_code":"PPL",
    "gn:name":"Myar",
    "gn:population":0,
    "gn:timezone":"Africa/Khartoum",
    "iso:country":"SD",
    "wof:name":"Myar",
    "wof:placetype":"locality"
},
  "geometry": {"coordinates":[23.0945,11.52046],"type":"Point"}
}