{
  "type": "Feature",
  "properties": {
    "gn:admin1_code":"41.0",
    "gn:asciiname":"Hillat Umm Shaba`",
    "gn:country_code":"SD",
    "gn:dem":385,
    "gn:feature_class":"P",
    "gn:feature_code":"PPL",
    "gn:name":"Hillat Umm Shaba\u2018",
    "gn:population":0,
    "gn:timezone":"Africa/Khartoum",
    "iso:country":"SD",
    "name:und_x_variant":[
        "Umm Shaba\u2018",
        "Hillat Umm Shaba\u2018"
    ],
    "wof:name":"Hillat Umm Shaba`",
    "wof:placetype":"locality"
},
  "geometry": {"coordinates":[32.4457,15.0243],"type":"Point"}
}