{
  "type": "Feature",
  "properties": {
    "gn:admin1_code":"56.0",
    "gn:asciiname":"`Ubayd",
    "gn:country_code":"SD",
    "gn:dem":428,
    "gn:feature_class":"P",
    "gn:feature_code":"PPL",
    "gn:name":"\u2018Ubayd",
    "gn:population":0,
    "gn:timezone":"Africa/Khartoum",
    "iso:country":"SD",
    "name:und_x_variant":[
        "\u2018Ubeid",
        "\u2018Udeid",
        "\u2018Ubayd"
    ],
    "wof:name":"`Ubayd",
    "wof:placetype":"locality"
},
  "geometry": {"coordinates":[31.61667000000001,12.78333],"type":"Point"}
}