{
  "type": "Feature",
  "properties": {
    "gn:admin1_code":"61.0",
    "gn:asciiname":"Rumalia",
    "gn:country_code":"SD",
    "gn:dem":611,
    "gn:feature_class":"P",
    "gn:feature_code":"PPL",
    "gn:name":"Rumalia",
    "gn:population":0,
    "gn:timezone":"Africa/Khartoum",
    "iso:country":"SD",
    "name:und_x_variant":[
        "Roumalia",
        "Rumalia"
    ],
    "wof:name":"Rumalia",
    "wof:placetype":"locality"
},
  "geometry": {"coordinates":[22.71353,12.38723],"type":"Point"}
}