{
  "type": "Feature",
  "properties": {
    "gn:admin1_code":"49.0",
    "gn:asciiname":"Kashalongo",
    "gn:country_code":"SD",
    "gn:dem":635,
    "gn:feature_class":"P",
    "gn:feature_code":"PPL",
    "gn:name":"Kashalongo",
    "gn:population":0,
    "gn:timezone":"Africa/Khartoum",
    "iso:country":"SD",
    "wof:name":"Kashalongo",
    "wof:placetype":"locality"
},
  "geometry": {"coordinates":[24.93317,11.93035],"type":"Point"}
}