{
  "type": "Feature",
  "properties": {
    "gn:admin1_code":"52.0",
    "gn:asciiname":"Argin N.",
    "gn:country_code":"SD",
    "gn:dem":461,
    "gn:feature_class":"P",
    "gn:feature_code":"PPL",
    "gn:name":"Argin N.",
    "gn:population":0,
    "gn:timezone":"Africa/Khartoum",
    "iso:country":"SD",
    "wof:name":"Argin N.",
    "wof:placetype":"locality"
},
  "geometry": {"coordinates":[35.65,15.18333],"type":"Point"}
}