{
  "type": "Feature",
  "properties": {
    "gn:admin1_code":"53.0",
    "gn:asciiname":"El Konoz",
    "gn:country_code":"SD",
    "gn:dem":348,
    "gn:feature_class":"P",
    "gn:feature_code":"PPL",
    "gn:name":"El Konoz",
    "gn:population":0,
    "gn:timezone":"Africa/Khartoum",
    "iso:country":"SD",
    "wof:name":"El Konoz",
    "wof:placetype":"locality"
},
  "geometry": {"coordinates":[33.9927,17.9711],"type":"Point"}
}