{
  "type": "Feature",
  "properties": {
    "gn:admin1_code":"55.0",
    "gn:asciiname":"Karkur",
    "gn:country_code":"SD",
    "gn:dem":532,
    "gn:feature_class":"P",
    "gn:feature_code":"PPL",
    "gn:name":"Karkur",
    "gn:population":0,
    "gn:timezone":"Africa/Khartoum",
    "iso:country":"SD",
    "wof:name":"Karkur",
    "wof:placetype":"locality"
},
  "geometry": {"coordinates":[26.28333,12.45],"type":"Point"}
}