{
  "type": "Feature",
  "properties": {
    "gn:admin1_code":"53.0",
    "gn:asciiname":"Gaddik",
    "gn:country_code":"SD",
    "gn:dem":362,
    "gn:feature_class":"P",
    "gn:feature_code":"PPL",
    "gn:name":"Gaddik",
    "gn:population":0,
    "gn:timezone":"Africa/Khartoum",
    "iso:country":"SD",
    "wof:name":"Gaddik",
    "wof:placetype":"locality"
},
  "geometry": {"coordinates":[34.4279,17.3168],"type":"Point"}
}