{
  "type": "Feature",
  "properties": {
    "gn:admin1_code":"29.0",
    "gn:asciiname":"Butry",
    "gn:country_code":"SD",
    "gn:dem":386,
    "gn:feature_class":"P",
    "gn:feature_code":"PPL",
    "gn:name":"Butry",
    "gn:population":0,
    "gn:timezone":"Africa/Khartoum",
    "iso:country":"SD",
    "name:und_x_variant":[
        "Butri",
        "Butry"
    ],
    "wof:name":"Butry",
    "wof:placetype":"locality"
},
  "geometry": {"coordinates":[32.7014,15.4677],"type":"Point"}
}