{
  "type": "Feature",
  "properties": {
    "gn:admin1_code":"53.0",
    "gn:asciiname":"El Khamesab",
    "gn:country_code":"SD",
    "gn:dem":389,
    "gn:feature_class":"P",
    "gn:feature_code":"PPL",
    "gn:name":"El Khamesab",
    "gn:population":0,
    "gn:timezone":"Africa/Khartoum",
    "iso:country":"SD",
    "wof:name":"El Khamesab",
    "wof:placetype":"locality"
},
  "geometry": {"coordinates":[32.6428,16.3629],"type":"Point"}
}