{
  "type": "Feature",
  "properties": {
    "gn:admin1_code":"47.0",
    "gn:asciiname":"Manganyo",
    "gn:country_code":"SD",
    "gn:dem":759,
    "gn:feature_class":"P",
    "gn:feature_code":"PPL",
    "gn:name":"Manganyo",
    "gn:population":0,
    "gn:timezone":"Africa/Khartoum",
    "iso:country":"SD",
    "name:eng_x_preferred":[
        "Manganyo"
    ],
    "wof:name":"Manganyo",
    "wof:placetype":"locality"
},
  "geometry": {"coordinates":[21.97925,12.97479],"type":"Point"}
}