{
  "type": "Feature",
  "properties": {
    "gn:admin1_code":"41.0",
    "gn:asciiname":"Al Qarrasa ash Sharqiyya",
    "gn:country_code":"SD",
    "gn:dem":386,
    "gn:feature_class":"P",
    "gn:feature_code":"PPL",
    "gn:name":"Al Qarr\u0101sa ash Sharqiyya",
    "gn:population":0,
    "gn:timezone":"Africa/Khartoum",
    "iso:country":"SD",
    "name:und_x_variant":[
        "Al Qarr\u0101sa ash Sharqiyya"
    ],
    "wof:name":"Al Qarrasa ash Sharqiyya",
    "wof:placetype":"locality"
},
  "geometry": {"coordinates":[32.2255,14.6509],"type":"Point"}
}