{
  "type": "Feature",
  "properties": {
    "gn:admin1_code":"36.0",
    "gn:asciiname":"Inha",
    "gn:country_code":"SD",
    "gn:dem":612,
    "gn:feature_class":"P",
    "gn:feature_code":"PPL",
    "gn:name":"Inha",
    "gn:population":0,
    "gn:timezone":"Africa/Khartoum",
    "iso:country":"SD",
    "name:und_x_variant":[
        "Ehna",
        "Inha"
    ],
    "wof:name":"Inha",
    "wof:placetype":"locality"
},
  "geometry": {"coordinates":[36.2712,18.3387],"type":"Point"}
}