{
  "type": "Feature",
  "properties": {
    "gn:admin1_code":"29.0",
    "gn:asciiname":"Hillat ar Raboub",
    "gn:country_code":"SD",
    "gn:dem":444,
    "gn:feature_class":"P",
    "gn:feature_code":"PPL",
    "gn:name":"Hillat ar Raboub",
    "gn:population":0,
    "gn:timezone":"Africa/Khartoum",
    "iso:country":"SD",
    "wof:name":"Hillat ar Raboub",
    "wof:placetype":"locality"
},
  "geometry": {"coordinates":[33.1683,15.7118],"type":"Point"}
}