{
  "type": "Feature",
  "properties": {
    "gn:admin1_code":"58.0",
    "gn:asciiname":"Ab Nura",
    "gn:country_code":"SD",
    "gn:dem":452,
    "gn:feature_class":"P",
    "gn:feature_code":"PPL",
    "gn:name":"Ab N\u016bra",
    "gn:population":0,
    "gn:timezone":"Africa/Khartoum",
    "iso:country":"SD",
    "name:und_x_variant":[
        "Ab N\u016bra"
    ],
    "wof:name":"Ab Nura",
    "wof:placetype":"locality"
},
  "geometry": {"coordinates":[34.21,12.4643],"type":"Point"}
}