{
  "type": "Feature",
  "properties": {
    "gn:admin1_code":"62.0",
    "gn:asciiname":"Kujur",
    "gn:country_code":"SD",
    "gn:dem":770,
    "gn:feature_class":"P",
    "gn:feature_code":"PPL",
    "gn:name":"Kujur",
    "gn:population":0,
    "gn:timezone":"Africa/Khartoum",
    "iso:country":"SD",
    "name:deu_x_preferred":[
        "Kujur"
    ],
    "name:fin_x_preferred":[
        "Kujur"
    ],
    "wof:name":"Kujur",
    "wof:placetype":"locality"
},
  "geometry": {"coordinates":[29.08333,11.61667],"type":"Point"}
}