{
  "type": "Feature",
  "properties": {
    "gn:admin1_code":"55.0",
    "gn:asciiname":"Mirkan",
    "gn:country_code":"SD",
    "gn:dem":888,
    "gn:feature_class":"P",
    "gn:feature_code":"PPL",
    "gn:name":"Mirkan",
    "gn:population":0,
    "gn:timezone":"Africa/Khartoum",
    "iso:country":"SD",
    "wof:name":"Mirkan",
    "wof:placetype":"locality"
},
  "geometry": {"coordinates":[25.23333,13.88333],"type":"Point"}
}