{
  "type": "Feature",
  "properties": {
    "gn:admin1_code":"53.0",
    "gn:asciiname":"Hillat Qoz Badur",
    "gn:country_code":"SD",
    "gn:dem":358,
    "gn:feature_class":"P",
    "gn:feature_code":"PPL",
    "gn:name":"Hillat Qoz Badur",
    "gn:population":0,
    "gn:timezone":"Africa/Khartoum",
    "iso:country":"SD",
    "name:und_x_variant":[
        "Qoz Burra",
        "Qawz Burra",
        "Hillat Qoz Badur"
    ],
    "wof:name":"Hillat Qoz Badur",
    "wof:placetype":"locality"
},
  "geometry": {"coordinates":[33.6292,16.8936],"type":"Point"}
}