{
  "type": "Feature",
  "properties": {
    "gn:admin1_code":"43.0",
    "gn:asciiname":"Kudayn",
    "gn:country_code":"SD",
    "gn:dem":215,
    "gn:feature_class":"P",
    "gn:feature_code":"PPL",
    "gn:name":"Kudayn",
    "gn:population":0,
    "gn:timezone":"Africa/Khartoum",
    "iso:country":"SD",
    "name:und_x_variant":[
        "Kadein",
        "Kudayn"
    ],
    "wof:name":"Kudayn",
    "wof:placetype":"locality"
},
  "geometry": {"coordinates":[30.56667,19.96667],"type":"Point"}
}