{
  "type": "Feature",
  "properties": {
    "gn:admin1_code":"55.0",
    "gn:asciiname":"Kutayrayah",
    "gn:country_code":"SD",
    "gn:dem":677,
    "gn:feature_class":"P",
    "gn:feature_code":"PPL",
    "gn:name":"Kutayr\u0101yah",
    "gn:population":0,
    "gn:timezone":"Africa/Khartoum",
    "iso:country":"SD",
    "name:und_x_variant":[
        "Kiteirala",
        "Kiteiraia",
        "Kutayr\u0101yah"
    ],
    "wof:name":"Kutayrayah",
    "wof:placetype":"locality"
},
  "geometry": {"coordinates":[25.55,13.38333],"type":"Point"}
}