{
  "type": "Feature",
  "properties": {
    "gn:admin1_code":"41.0",
    "gn:asciiname":"Fallata",
    "gn:country_code":"SD",
    "gn:dem":383,
    "gn:feature_class":"P",
    "gn:feature_code":"PPL",
    "gn:name":"Fall\u0101ta",
    "gn:population":0,
    "gn:timezone":"Africa/Khartoum",
    "iso:country":"SD",
    "name:und_x_variant":[
        "Fall\u0101ta"
    ],
    "wof:name":"Fallata",
    "wof:placetype":"locality"
},
  "geometry": {"coordinates":[32.8304,12.9719],"type":"Point"}
}