{
  "type": "Feature",
  "properties": {
    "gn:admin1_code":"41.0",
    "gn:asciiname":"Qutaynah",
    "gn:country_code":"SD",
    "gn:dem":390,
    "gn:feature_class":"P",
    "gn:feature_code":"PPL",
    "gn:name":"Qu\u0163aynah",
    "gn:population":0,
    "gn:timezone":"Africa/Khartoum",
    "iso:country":"SD",
    "name:und_x_variant":[
        "Geteina",
        "Qu\u0163aynah"
    ],
    "wof:name":"Qutaynah",
    "wof:placetype":"locality"
},
  "geometry": {"coordinates":[32.41305999999999,15.17222],"type":"Point"}
}