{
  "type": "Feature",
  "properties": {
    "gn:admin1_code":"36.0",
    "gn:asciiname":"Adobana",
    "gn:country_code":"SD",
    "gn:dem":9,
    "gn:feature_class":"P",
    "gn:feature_code":"PPL",
    "gn:name":"Adobana",
    "gn:population":0,
    "gn:timezone":"Africa/Khartoum",
    "iso:country":"SD",
    "wof:name":"Adobana",
    "wof:placetype":"locality"
},
  "geometry": {"coordinates":[38.265,18.1817],"type":"Point"}
}