{
  "type": "Feature",
  "properties": {
    "gn:admin1_code":"52.0",
    "gn:asciiname":"Hillat al Azazah",
    "gn:country_code":"SD",
    "gn:dem":420,
    "gn:feature_class":"P",
    "gn:feature_code":"PPL",
    "gn:name":"Hillat al Az\u0101zah",
    "gn:population":0,
    "gn:timezone":"Africa/Khartoum",
    "iso:country":"SD",
    "name:und_x_variant":[
        "Hillat al Az\u0101zah"
    ],
    "wof:name":"Hillat al Azazah",
    "wof:placetype":"locality"
},
  "geometry": {"coordinates":[35.4596,15.8814],"type":"Point"}
}