{
  "type": "Feature",
  "properties": {
    "gn:admin1_code":"49.0",
    "gn:asciiname":"Karkangi",
    "gn:country_code":"SD",
    "gn:dem":542,
    "gn:feature_class":"P",
    "gn:feature_code":"PPL",
    "gn:name":"Karkangi",
    "gn:population":0,
    "gn:timezone":"Africa/Khartoum",
    "iso:country":"SD",
    "name:und_x_variant":[
        "Karkang"
    ],
    "wof:name":"Karkangi",
    "wof:placetype":"locality"
},
  "geometry": {"coordinates":[24.2282,10.98704],"type":"Point"}
}