{
  "type": "Feature",
  "properties": {
    "gn:admin1_code":"50.0",
    "gn:asciiname":"Tozi",
    "gn:country_code":"SD",
    "gn:dem":524,
    "gn:feature_class":"P",
    "gn:feature_code":"PPL",
    "gn:name":"Tozi",
    "gn:population":0,
    "gn:timezone":"Africa/Khartoum",
    "iso:country":"SD",
    "name:eng_x_preferred":[
        "Tosi"
    ],
    "wof:name":"Tozi",
    "wof:placetype":"locality"
},
  "geometry": {"coordinates":[30.83779,10.8548],"type":"Point"}
}