{
  "type": "Feature",
  "properties": {
    "gn:admin1_code":"55.0",
    "gn:asciiname":"Abu Kutni",
    "gn:country_code":"SD",
    "gn:dem":856,
    "gn:feature_class":"P",
    "gn:feature_code":"PPL",
    "gn:name":"Ab\u016b Kutni",
    "gn:population":0,
    "gn:timezone":"Africa/Khartoum",
    "iso:country":"SD",
    "wof:name":"Abu Kutni",
    "wof:placetype":"locality"
},
  "geometry": {"coordinates":[22.81667,15.01667],"type":"Point"}
}