{
  "type": "Feature",
  "properties": {
    "gn:admin1_code":"49.0",
    "gn:asciiname":"Serir",
    "gn:country_code":"SD",
    "gn:dem":541,
    "gn:feature_class":"P",
    "gn:feature_code":"PPL",
    "gn:name":"Serir",
    "gn:population":0,
    "gn:timezone":"Africa/Khartoum",
    "iso:country":"SD",
    "name:und_x_variant":[
        "Sar\u012br"
    ],
    "wof:name":"Serir",
    "wof:placetype":"locality"
},
  "geometry": {"coordinates":[24.05193,10.9748],"type":"Point"}
}