{
  "type": "Feature",
  "properties": {
    "gn:admin1_code":"38.0",
    "gn:asciiname":"Kasambar",
    "gn:country_code":"SD",
    "gn:dem":392,
    "gn:feature_class":"P",
    "gn:feature_code":"PPL",
    "gn:name":"Kasambar",
    "gn:population":0,
    "gn:timezone":"Africa/Khartoum",
    "iso:country":"SD",
    "wof:name":"Kasambar",
    "wof:placetype":"locality"
},
  "geometry": {"coordinates":[33.15639,15.11389],"type":"Point"}
}