{
  "type": "Feature",
  "properties": {
    "gn:admin1_code":"29.0",
    "gn:asciiname":"Ad Dushaynab",
    "gn:cc2":"SD",
    "gn:country_code":"SD",
    "gn:dem":381,
    "gn:feature_class":"P",
    "gn:feature_code":"PPL",
    "gn:name":"Ad Dushayn\u0101b",
    "gn:population":0,
    "gn:timezone":"Africa/Khartoum",
    "iso:country":"SD",
    "name:und_x_variant":[
        "Ed Disheinab",
        "Ad Dushayn\u0101b"
    ],
    "wof:name":"Ad Dushaynab",
    "wof:placetype":"locality"
},
  "geometry": {"coordinates":[32.55,15.98333],"type":"Point"}
}