{
  "type": "Feature",
  "properties": {
    "gn:admin1_code":"55.0",
    "gn:asciiname":"Tonigerri",
    "gn:country_code":"SD",
    "gn:dem":861,
    "gn:feature_class":"P",
    "gn:feature_code":"PPL",
    "gn:name":"Tonigerri",
    "gn:population":0,
    "gn:timezone":"Africa/Khartoum",
    "iso:country":"SD",
    "wof:name":"Tonigerri",
    "wof:placetype":"locality"
},
  "geometry": {"coordinates":[23.38333,14.98333],"type":"Point"}
}