{
  "type": "Feature",
  "properties": {
    "gn:country":"SD",
    "gn:fcode":"PPLA",
    "gn:pop":135281,
    "iso:country":"SD",
    "name:ara_x_preferred":[
        "\u0631\u0628\u0643"
    ],
    "name:ben_x_preferred":[
        "\u09b0\u09be\u09ac\u09be\u0995"
    ],
    "name:dan_x_preferred":[
        "Rabak"
    ],
    "name:deu_x_preferred":[
        "Rabak"
    ],
    "name:ell_x_preferred":[
        "\u03a1\u03ac\u03bc\u03c0\u03b1\u03ba"
    ],
    "name:eng_x_preferred":[
        "Rabak"
    ],
    "name:epo_x_preferred":[
        "Rabak"
    ],
    "name:fas_x_preferred":[
        "\u0631\u0628\u06a9"
    ],
    "name:fin_x_preferred":[
        "Rabak"
    ],
    "name:fra_x_preferred":[
        "Rabak"
    ],
    "name:guj_x_preferred":[
        "\u0ab0\u0aac\u0a95"
    ],
    "name:hin_x_preferred":[
        "\u0930\u092c\u093e\u0915"
    ],
    "name:ind_x_preferred":[
        "Rabak"
    ],
    "name:ita_x_preferred":[
        "Rabak"
    ],
    "name:jpn_x_preferred":[
        "\u30e9\u30d0\u30af"
    ],
    "name:kan_x_preferred":[
        "\u0cb0\u0cac\u0c95\u0ccd"
    ],
    "name:kor_x_preferred":[
        "\ub77c\ubc15"
    ],
    "name:lav_x_preferred":[
        "Rabaka"
    ],
    "name:lit_x_preferred":[
        "Rabakas"
    ],
    "name:mar_x_preferred":[
        "\u0930\u092c\u0915"
    ],
    "name:msa_x_preferred":[
        "Rabak"
    ],
    "name:nld_x_preferred":[
        "Rabak"
    ],
    "name:nob_x_preferred":[
        "Rabak"
    ],
    "name:pol_x_preferred":[
        "Rabak"
    ],
    "name:por_x_preferred":[
        "Rabak"
    ],
    "name:ron_x_preferred":[
        "Rabak"
    ],
    "name:rus_x_preferred":[
        "\u0420\u0430\u0431\u0430\u043a"
    ],
    "name:sin_x_preferred":[
        "\u0dbb\u0db6\u0d9a\u0dca"
    ],
    "name:spa_x_preferred":[
        "Rabak"
    ],
    "name:swe_x_preferred":[
        "Rabak"
    ],
    "name:tam_x_preferred":[
        "\u0bb0\u0bbe\u0baa\u0bbe\u0b95\u0bcd"
    ],
    "name:tel_x_preferred":[
        "\u0c30\u0c2c\u0c3e\u0c15\u0c4d"
    ],
    "name:tha_x_preferred":[
        "\u0e23\u0e32\u0e1a\u0e31\u0e04"
    ],
    "name:tur_x_preferred":[
        "Rabak"
    ],
    "name:ukr_x_preferred":[
        "\u0420\u0430\u0431\u0430\u043a"
    ],
    "name:unk_x_variant":[
        "Rabaq"
    ],
    "name:urd_x_preferred":[
        "\u0631\u0627\u0628\u0627\u06a9"
    ],
    "name:vie_x_preferred":[
        "Rabak"
    ],
    "name:war_x_preferred":[
        "Rabak"
    ],
    "name:zho_x_preferred":[
        "\u62c9\u5df4\u514b"
    ],
    "qs:name":"Rabak",
    "qs:photos_9r":0,
    "qs:photos_sr":0,
    "qs:pop_sr":"9",
    "wd:wordcount":224,
    "wof:name":"Rabak",
    "wof:placetype":"locality",
    "wof:population":135281
},
  "geometry": {"coordinates":[32.73999,13.18087],"type":"Point"}
}