{
  "type": "Feature",
  "properties": {
    "gn:admin1_code":"50.0",
    "gn:asciiname":"Tufin",
    "gn:country_code":"SD",
    "gn:dem":654,
    "gn:feature_class":"P",
    "gn:feature_code":"PPL",
    "gn:name":"T\u016bf\u012bn",
    "gn:population":0,
    "gn:timezone":"Africa/Khartoum",
    "iso:country":"SD",
    "name:ara_x_preferred":[
        "T\u016bf\u012bn"
    ],
    "name:und_x_variant":[
        "Tofein"
    ],
    "wof:name":"Tufin",
    "wof:placetype":"locality"
},
  "geometry": {"coordinates":[31.233,12.2289],"type":"Point"}
}