{
  "type": "Feature",
  "properties": {
    "gn:admin1_code":"38.0",
    "gn:asciiname":"Al `Azzazi",
    "gn:country_code":"SD",
    "gn:dem":396,
    "gn:feature_class":"P",
    "gn:feature_code":"PPL",
    "gn:name":"Al \u2018Azz\u0101zi",
    "gn:population":0,
    "gn:timezone":"Africa/Khartoum",
    "iso:country":"SD",
    "name:ara_x_preferred":[
        "Al \u2018Azz\u0101zi"
    ],
    "name:und_x_variant":[
        "El \u2018Azazi",
        "Al \u2018Az\u0101z\u012b"
    ],
    "wof:name":"Al `Azzazi",
    "wof:placetype":"locality"
},
  "geometry": {"coordinates":[32.7508,14.4702],"type":"Point"}
}