{
  "type": "Feature",
  "properties": {
    "gn:admin1_code":"38.0",
    "gn:asciiname":"At Talha",
    "gn:country_code":"SD",
    "gn:dem":399,
    "gn:feature_class":"P",
    "gn:feature_code":"PPL",
    "gn:name":"A\u0163 \u0162al\u1e29a",
    "gn:population":0,
    "gn:timezone":"Africa/Khartoum",
    "iso:country":"SD",
    "name:und_x_variant":[
        "A\u0163 \u0162al\u1e29a"
    ],
    "wof:name":"At Talha",
    "wof:placetype":"locality"
},
  "geometry": {"coordinates":[33.3152,14.9402],"type":"Point"}
}