{
  "type": "Feature",
  "properties": {
    "gn:admin1_code":"38.0",
    "gn:asciiname":"Kidebat",
    "gn:country_code":"SD",
    "gn:dem":416,
    "gn:feature_class":"P",
    "gn:feature_code":"PPL",
    "gn:name":"Ki\u1e11eb\u0101t",
    "gn:population":0,
    "gn:timezone":"Africa/Khartoum",
    "iso:country":"SD",
    "name:ara_x_preferred":[
        "Ki\u1e11eb\u0101t"
    ],
    "name:und_x_variant":[
        "Kudeibat",
        "Kudayb\u0101t"
    ],
    "wof:name":"Kidebat",
    "wof:placetype":"locality"
},
  "geometry": {"coordinates":[32.971,14.018],"type":"Point"}
}