{
  "type": "Feature",
  "properties": {
    "gn:admin1_code":"42.0",
    "gn:asciiname":"Babarros",
    "gn:country_code":"SD",
    "gn:dem":572,
    "gn:feature_class":"P",
    "gn:feature_code":"PPL",
    "gn:name":"Babarros",
    "gn:population":0,
    "gn:timezone":"Africa/Khartoum",
    "iso:country":"SD",
    "wof:name":"Babarros",
    "wof:placetype":"locality"
},
  "geometry": {"coordinates":[34.21667,10.33333],"type":"Point"}
}