{
  "type": "Feature",
  "properties": {
    "gn:admin1_code":"56.0",
    "gn:asciiname":"Jinjir",
    "gn:country_code":"SD",
    "gn:dem":449,
    "gn:feature_class":"P",
    "gn:feature_code":"PPL",
    "gn:name":"Jinjir",
    "gn:population":0,
    "gn:timezone":"Africa/Khartoum",
    "iso:country":"SD",
    "wof:name":"Jinjir",
    "wof:placetype":"locality"
},
  "geometry": {"coordinates":[31.3519,12.7748],"type":"Point"}
}