{
  "type": "Feature",
  "properties": {
    "gn:admin1_code":"49.0",
    "gn:asciiname":"`Abd Allah Bashir",
    "gn:country_code":"SD",
    "gn:dem":1230,
    "gn:feature_class":"P",
    "gn:feature_code":"PPL",
    "gn:name":"\u2018Abd All\u0101h Bash\u012br",
    "gn:population":0,
    "gn:timezone":"Africa/Khartoum",
    "iso:country":"SD",
    "name:und_x_variant":[
        "\u2018Abdullah Beshir",
        "Abdalakh Beshir",
        "\u2018Abd All\u0101h Bash\u012br"
    ],
    "wof:lang_x_official":[
        "ara",
        "eng"
    ],
    "wof:lang_x_spoken":[
        "ara",
        "eng"
    ],
    "wof:name":"`Abd Allah Bashir",
    "wof:placetype":"locality"
},
  "geometry": {"coordinates":[24.58659,12.98759],"type":"Point"}
}