{
  "type": "Feature",
  "properties": {
    "gn:admin1_code":"47.0",
    "gn:asciiname":"Koyos",
    "gn:country_code":"SD",
    "gn:dem":872,
    "gn:feature_class":"P",
    "gn:feature_code":"PPL",
    "gn:name":"Koyos",
    "gn:population":0,
    "gn:timezone":"Africa/Khartoum",
    "iso:country":"SD",
    "wof:name":"Koyos",
    "wof:placetype":"locality"
},
  "geometry": {"coordinates":[22.87584,14.11957],"type":"Point"}
}