{
  "type": "Feature",
  "properties": {
    "gn:admin1_code":"39.0",
    "gn:asciiname":"Al Halimab",
    "gn:country_code":"SD",
    "gn:dem":440,
    "gn:feature_class":"P",
    "gn:feature_code":"PPL",
    "gn:name":"Al \u1e28al\u012bm\u0101b",
    "gn:population":0,
    "gn:timezone":"Africa/Khartoum",
    "iso:country":"SD",
    "name:und_x_variant":[
        "El Halimab",
        "Al \u1e28al\u012bm\u0101b"
    ],
    "wof:lang_x_official":[
        "ara",
        "eng"
    ],
    "wof:lang_x_spoken":[
        "ara",
        "eng"
    ],
    "wof:name":"Al Halimab",
    "wof:placetype":"locality"
},
  "geometry": {"coordinates":[34.53333,13.71667],"type":"Point"}
}