{
  "type": "Feature",
  "properties": {
    "gn:country":"SD",
    "gn:fcode":"PPL",
    "gn:pop":12108,
    "iso:country":"SD",
    "name:eng_x_preferred":[
        "Marabba"
    ],
    "qs:name":"Marabba",
    "qs:photos_9r":0,
    "qs:photos_sr":0,
    "qs:pop_sr":"6",
    "wd:wordcount":92,
    "wof:name":"Marabba",
    "wof:placetype":"locality",
    "wof:population":12108
},
  "geometry": {"coordinates":[32.18333,12.35],"type":"Point"}
}