{
  "type": "Feature",
  "properties": {
    "gn:admin1_code":"38.0",
    "gn:asciiname":"`Abd ad Dayim",
    "gn:country_code":"SD",
    "gn:dem":410,
    "gn:feature_class":"P",
    "gn:feature_code":"PPL",
    "gn:name":"\u2018Abd ad D\u0101y\u012bm",
    "gn:population":0,
    "gn:timezone":"Africa/Khartoum",
    "iso:country":"SD",
    "name:und_x_variant":[
        "\u2018Abd ed Daim",
        "\u2018Abd ad D\u0101\u2019im",
        "\u2018Abd ad D\u0101y\u012bm"
    ],
    "wof:lang_x_official":[
        "ara",
        "eng"
    ],
    "wof:lang_x_spoken":[
        "ara",
        "eng"
    ],
    "wof:name":"`Abd ad Dayim",
    "wof:placetype":"locality"
},
  "geometry": {"coordinates":[33.4537,14.3551],"type":"Point"}
}