{
  "type": "Feature",
  "properties": {
    "gn:admin1_code":"38.0",
    "gn:asciiname":"Al Khishem",
    "gn:country_code":"SD",
    "gn:dem":409,
    "gn:feature_class":"P",
    "gn:feature_code":"PPL",
    "gn:name":"Al Khishem",
    "gn:population":0,
    "gn:timezone":"Africa/Khartoum",
    "iso:country":"SD",
    "name:und_x_variant":[
        "El Khasheim",
        "Al Khushaym",
        "Al Khishem"
    ],
    "wof:name":"Al Khishem",
    "wof:placetype":"locality"
},
  "geometry": {"coordinates":[33.1295,14.4764],"type":"Point"}
}