{
  "type": "Feature",
  "properties": {
    "gn:admin1_code":"50.0",
    "gn:asciiname":"Maghani",
    "gn:country_code":"SD",
    "gn:dem":449,
    "gn:feature_class":"P",
    "gn:feature_code":"PPL",
    "gn:name":"Maghani",
    "gn:population":0,
    "gn:timezone":"Africa/Khartoum",
    "iso:country":"SD",
    "wof:name":"Maghani",
    "wof:placetype":"locality"
},
  "geometry": {"coordinates":[31.63773,10.98396],"type":"Point"}
}