{
  "type": "Feature",
  "properties": {
    "gn:admin1_code":"62.0",
    "gn:asciiname":"Umm Dobia",
    "gn:country_code":"SD",
    "gn:dem":515,
    "gn:feature_class":"P",
    "gn:feature_code":"PPL",
    "gn:name":"Umm Dobia",
    "gn:population":0,
    "gn:timezone":"Africa/Khartoum",
    "iso:country":"SD",
    "wof:name":"Umm Dobia",
    "wof:placetype":"locality"
},
  "geometry": {"coordinates":[27.61667000000001,12.36667],"type":"Point"}
}