{
  "type": "Feature",
  "properties": {
    "gn:admin1_code":"38.0",
    "gn:asciiname":"Wad Zarruq",
    "gn:country_code":"SD",
    "gn:dem":401,
    "gn:feature_class":"P",
    "gn:feature_code":"PPL",
    "gn:name":"Wad Zarr\u016bq",
    "gn:population":0,
    "gn:timezone":"Africa/Khartoum",
    "iso:country":"SD",
    "name:und_x_variant":[
        "Wad Zarr\u016bq"
    ],
    "wof:name":"Wad Zarruq",
    "wof:placetype":"locality"
},
  "geometry": {"coordinates":[32.8882,14.3945],"type":"Point"}
}