{
  "type": "Feature",
  "properties": {
    "gn:admin1_code":"42.0",
    "gn:asciiname":"Al Humara Al Hawsa",
    "gn:country_code":"SD",
    "gn:dem":458,
    "gn:feature_class":"P",
    "gn:feature_code":"PPL",
    "gn:name":"Al \u1e28umara Al \u1e28awsa",
    "gn:population":0,
    "gn:timezone":"Africa/Khartoum",
    "iso:country":"SD",
    "name:und_x_variant":[
        "Al \u1e28umara Al \u1e28awsa"
    ],
    "wof:lang_x_official":[
        "ara",
        "eng"
    ],
    "wof:lang_x_spoken":[
        "ara",
        "eng"
    ],
    "wof:name":"Al Humara Al Hawsa",
    "wof:placetype":"locality"
},
  "geometry": {"coordinates":[34.3032,12.1172],"type":"Point"}
}