{
  "type": "Feature",
  "properties": {
    "gn:admin1_code":"52.0",
    "gn:asciiname":"Ariel",
    "gn:country_code":"SD",
    "gn:dem":444,
    "gn:feature_class":"P",
    "gn:feature_code":"PPL",
    "gn:name":"Ariel",
    "gn:population":0,
    "gn:timezone":"Africa/Khartoum",
    "iso:country":"SD",
    "name:afr_x_preferred":[
        "Ariel"
    ],
    "name:bul_x_preferred":[
        "\u0410\u0440\u0438\u0435\u043b"
    ],
    "name:cat_x_preferred":[
        "Ariel"
    ],
    "name:ceb_x_preferred":[
        "Ariel"
    ],
    "name:ces_x_preferred":[
        "Ariel"
    ],
    "name:cym_x_preferred":[
        "Ariel"
    ],
    "name:dan_x_preferred":[
        "Ariel"
    ],
    "name:deu_x_preferred":[
        "Ariel"
    ],
    "name:eus_x_preferred":[
        "Ariel"
    ],
    "name:fas_x_preferred":[
        "\u0622\u0631\u06cc\u0644"
    ],
    "name:fin_x_preferred":[
        "Ariel"
    ],
    "name:fra_x_preferred":[
        "Ariel"
    ],
    "name:glg_x_preferred":[
        "Ariel"
    ],
    "name:heb_x_preferred":[
        "\u05d0\u05e8\u05d9\u05d0\u05dc"
    ],
    "name:hrv_x_preferred":[
        "Ariel"
    ],
    "name:hye_x_preferred":[
        "\u0531\u0580\u056b\u0565\u056c"
    ],
    "name:ind_x_preferred":[
        "Ariel"
    ],
    "name:ita_x_preferred":[
        "Ariel"
    ],
    "name:jpn_x_preferred":[
        "\u30a2\u30ea\u30a8\u30eb"
    ],
    "name:kor_x_preferred":[
        "\uc544\ub9ac\uc5d8"
    ],
    "name:nds_x_preferred":[
        "Ariel"
    ],
    "name:nld_x_preferred":[
        "Ari\u00ebl"
    ],
    "name:nno_x_preferred":[
        "Ariel"
    ],
    "name:nor_x_preferred":[
        "Ariel"
    ],
    "name:pol_x_preferred":[
        "Ariel"
    ],
    "name:por_x_preferred":[
        "Ariel"
    ],
    "name:ron_x_preferred":[
        "Ariel"
    ],
    "name:rus_x_preferred":[
        "\u0410\u0440\u0438\u044d\u043b\u044c"
    ],
    "name:slk_x_preferred":[
        "Ariel"
    ],
    "name:slv_x_preferred":[
        "Ariel"
    ],
    "name:spa_x_preferred":[
        "Ariel"
    ],
    "name:srp_x_preferred":[
        "\u0410\u0440\u0438\u0458\u0435\u043b"
    ],
    "name:swe_x_preferred":[
        "Ariel"
    ],
    "name:tur_x_preferred":[
        "Ariel"
    ],
    "name:ukr_x_preferred":[
        "\u0410\u0440\u0456\u0435\u043b\u044c"
    ],
    "wof:name":"Ariel",
    "wof:placetype":"locality"
},
  "geometry": {"coordinates":[35.71667,15.53333],"type":"Point"}
}