{
  "type": "Feature",
  "properties": {
    "gn:admin1_code":"52.0",
    "gn:asciiname":"Ariel",
    "gn:country_code":"SD",
    "gn:dem":444,
    "gn:feature_class":"P",
    "gn:feature_code":"PPL",
    "gn:name":"Ariel",
    "gn:population":0,
    "gn:timezone":"Africa/Khartoum",
    "iso:country":"SD",
    "wof:name":"Ariel",
    "wof:placetype":"locality"
},
  "geometry": {"coordinates":[35.71667,15.53333],"type":"Point"}
}