{
  "type": "Feature",
  "properties": {
    "gn:admin1_code":"61.0",
    "gn:asciiname":"Korgojok",
    "gn:country_code":"SD",
    "gn:dem":664,
    "gn:feature_class":"P",
    "gn:feature_code":"PPL",
    "gn:name":"Korgojok",
    "gn:population":0,
    "gn:timezone":"Africa/Khartoum",
    "iso:country":"SD",
    "wof:name":"Korgojok",
    "wof:placetype":"locality"
},
  "geometry": {"coordinates":[22.65,12.61667],"type":"Point"}
}