{
  "type": "Feature",
  "properties": {
    "gn:admin1_code":"58.0",
    "gn:asciiname":"Barankawa",
    "gn:country_code":"SD",
    "gn:dem":448,
    "gn:feature_class":"P",
    "gn:feature_code":"PPL",
    "gn:name":"Barankawa",
    "gn:population":0,
    "gn:timezone":"Africa/Khartoum",
    "iso:country":"SD",
    "name:und_x_variant":[
        "Barankwa",
        "Barankwah",
        "Barankawa"
    ],
    "wof:name":"Barankawa",
    "wof:placetype":"locality"
},
  "geometry": {"coordinates":[34.1335,12.7535],"type":"Point"}
}