{
  "type": "Feature",
  "properties": {
    "gn:admin1_code":"55.0",
    "gn:asciiname":"Turdi",
    "gn:country_code":"SD",
    "gn:dem":1033,
    "gn:feature_class":"P",
    "gn:feature_code":"PPL",
    "gn:name":"Turd\u012b",
    "gn:population":0,
    "gn:timezone":"Africa/Khartoum",
    "iso:country":"SD",
    "wof:name":"Turdi",
    "wof:placetype":"locality"
},
  "geometry": {"coordinates":[25.11667000000001,14.61667],"type":"Point"}
}