{
  "type": "Feature",
  "properties": {
    "gn:admin1_code":"41.0",
    "gn:asciiname":"Abu Shuk",
    "gn:country_code":"SD",
    "gn:dem":386,
    "gn:feature_class":"P",
    "gn:feature_code":"PPL",
    "gn:name":"Ab\u016b Sh\u016bk",
    "gn:population":0,
    "gn:timezone":"Africa/Khartoum",
    "iso:country":"SD",
    "name:ara_x_preferred":[
        "Ab\u016b Sh\u016bk"
    ],
    "wof:lang_x_official":[
        "ara",
        "eng"
    ],
    "wof:lang_x_spoken":[
        "ara",
        "eng"
    ],
    "wof:name":"Abu Shuk",
    "wof:placetype":"locality"
},
  "geometry": {"coordinates":[32.3899,13.7321],"type":"Point"}
}