{
  "type": "Feature",
  "properties": {
    "gn:admin1_code":"42.0",
    "gn:asciiname":"As Sirajiyya",
    "gn:country_code":"SD",
    "gn:dem":464,
    "gn:feature_class":"P",
    "gn:feature_code":"PPL",
    "gn:name":"As Sir\u0101jiyya",
    "gn:population":0,
    "gn:timezone":"Africa/Khartoum",
    "iso:country":"SD",
    "name:und_x_variant":[
        "As Sir\u0101jiyya"
    ],
    "wof:name":"As Sirajiyya",
    "wof:placetype":"locality"
},
  "geometry": {"coordinates":[34.3225,12.1783],"type":"Point"}
}