{
  "type": "Feature",
  "properties": {
    "gn:admin1_code":"50.0",
    "gn:asciiname":"Dogilli",
    "gn:country_code":"SD",
    "gn:dem":576,
    "gn:feature_class":"P",
    "gn:feature_code":"PPL",
    "gn:name":"Dogilli",
    "gn:population":0,
    "gn:timezone":"Africa/Khartoum",
    "iso:country":"SD",
    "wof:name":"Dogilli",
    "wof:placetype":"locality"
},
  "geometry": {"coordinates":[30.96595,10.94752],"type":"Point"}
}