{
  "type": "Feature",
  "properties": {
    "gn:admin1_code":"58.0",
    "gn:asciiname":"Wad Siwar",
    "gn:country_code":"SD",
    "gn:dem":411,
    "gn:feature_class":"P",
    "gn:feature_code":"PPL",
    "gn:name":"Wad Siw\u0101r",
    "gn:population":0,
    "gn:timezone":"Africa/Khartoum",
    "iso:country":"SD",
    "wof:name":"Wad Siwar",
    "wof:placetype":"locality"
},
  "geometry": {"coordinates":[33.66667,14.05],"type":"Point"}
}