{
  "type": "Feature",
  "properties": {
    "gn:admin1_code":"42.0",
    "gn:asciiname":"Banagelada",
    "gn:country_code":"SD",
    "gn:dem":714,
    "gn:feature_class":"P",
    "gn:feature_code":"PPL",
    "gn:name":"Banagelada",
    "gn:population":0,
    "gn:timezone":"Africa/Khartoum",
    "iso:country":"SD",
    "wof:name":"Banagelada",
    "wof:placetype":"locality"
},
  "geometry": {"coordinates":[34.48333,10.95],"type":"Point"}
}