{
  "type": "Feature",
  "properties": {
    "gn:admin1_code":"53.0",
    "gn:asciiname":"Umm Shql",
    "gn:country_code":"SD",
    "gn:dem":369,
    "gn:feature_class":"P",
    "gn:feature_code":"PPL",
    "gn:name":"Umm Shql",
    "gn:population":0,
    "gn:timezone":"Africa/Khartoum",
    "iso:country":"SD",
    "wof:name":"Umm Shql",
    "wof:placetype":"locality"
},
  "geometry": {"coordinates":[33.2402,16.6137],"type":"Point"}
}