{
  "type": "Feature",
  "properties": {
    "gn:admin1_code":"58.0",
    "gn:asciiname":"Um Salala",
    "gn:country_code":"SD",
    "gn:dem":477,
    "gn:feature_class":"P",
    "gn:feature_code":"PPL",
    "gn:name":"Um Sal\u0101la",
    "gn:population":0,
    "gn:timezone":"Africa/Khartoum",
    "iso:country":"SD",
    "name:und_x_variant":[
        "Um Sal\u0101la"
    ],
    "wof:name":"Um Salala",
    "wof:placetype":"locality"
},
  "geometry": {"coordinates":[35.1733,12.8484],"type":"Point"}
}