{
  "type": "Feature",
  "properties": {
    "gn:admin1_code":"41.0",
    "gn:asciiname":"Ashshekh at Tijani",
    "gn:country_code":"SD",
    "gn:dem":401,
    "gn:feature_class":"P",
    "gn:feature_code":"PPL",
    "gn:name":"Ashshekh at Tijani",
    "gn:population":0,
    "gn:timezone":"Africa/Khartoum",
    "iso:country":"SD",
    "wof:name":"Ashshekh at Tijani",
    "wof:placetype":"locality"
},
  "geometry": {"coordinates":[32.3685,13.1864],"type":"Point"}
}