{
  "type": "Feature",
  "properties": {
    "gn:admin1_code":"56.0",
    "gn:asciiname":"Qinebila",
    "gn:country_code":"SD",
    "gn:dem":470,
    "gn:feature_class":"P",
    "gn:feature_code":"PPL",
    "gn:name":"Qineb\u012bla",
    "gn:population":0,
    "gn:timezone":"Africa/Khartoum",
    "iso:country":"SD",
    "name:und_x_variant":[
        "Qineb\u012bla"
    ],
    "wof:name":"Qinebila",
    "wof:placetype":"locality"
},
  "geometry": {"coordinates":[31.1091,12.772],"type":"Point"}
}