{
  "type": "Feature",
  "properties": {
    "gn:admin1_code":"38.0",
    "gn:asciiname":"Umm Sunaytah",
    "gn:country_code":"SD",
    "gn:dem":395,
    "gn:feature_class":"P",
    "gn:feature_code":"PPL",
    "gn:name":"Umm Sunay\u0163ah",
    "gn:population":0,
    "gn:timezone":"Africa/Khartoum",
    "iso:country":"SD",
    "name:und_x_variant":[
        "Umm Suneita",
        "Umm Sunay\u0163ah"
    ],
    "wof:lang_x_official":[
        "ara",
        "eng"
    ],
    "wof:lang_x_spoken":[
        "ara",
        "eng"
    ],
    "wof:name":"Umm Sunaytah",
    "wof:placetype":"locality"
},
  "geometry": {"coordinates":[32.58333,13.95],"type":"Point"}
}