{
  "type": "Feature",
  "properties": {
    "gn:admin1_code":"56.0",
    "gn:asciiname":"Ath Thumayd",
    "gn:country_code":"SD",
    "gn:dem":543,
    "gn:feature_class":"P",
    "gn:feature_code":"PPL",
    "gn:name":"Ath Thumayd",
    "gn:population":0,
    "gn:timezone":"Africa/Khartoum",
    "iso:country":"SD",
    "name:und_x_variant":[
        "Et Tumeid",
        "Tumeid",
        "Ath Thumayd"
    ],
    "wof:name":"Ath Thumayd",
    "wof:placetype":"locality"
},
  "geometry": {"coordinates":[30.16667,12.88333],"type":"Point"}
}