{
  "type": "Feature",
  "properties": {
    "gn:admin1_code":"50.0",
    "gn:asciiname":"Kaloqi",
    "gn:country_code":"SD",
    "gn:dem":518,
    "gn:feature_class":"P",
    "gn:feature_code":"PPL",
    "gn:name":"Kaloqi",
    "gn:population":0,
    "gn:timezone":"Africa/Khartoum",
    "iso:country":"SD",
    "name:eng_x_preferred":[
        "Kalogi"
    ],
    "wof:name":"Kaloqi",
    "wof:placetype":"locality"
},
  "geometry": {"coordinates":[30.98409,10.85776],"type":"Point"}
}