{
  "type": "Feature",
  "properties": {
    "gn:admin1_code":"42.0",
    "gn:asciiname":"Taybat al Bilelab",
    "gn:country_code":"SD",
    "gn:dem":454,
    "gn:feature_class":"P",
    "gn:feature_code":"PPL",
    "gn:name":"Taybat al Bilel\u0101b",
    "gn:population":0,
    "gn:timezone":"Africa/Khartoum",
    "iso:country":"SD",
    "name:und_x_variant":[
        "Taybat al Bilel\u0101b"
    ],
    "wof:name":"Taybat al Bilelab",
    "wof:placetype":"locality"
},
  "geometry": {"coordinates":[34.3501,11.9967],"type":"Point"}
}