{
  "type": "Feature",
  "properties": {
    "gn:admin1_code":"50.0",
    "gn:asciiname":"Khash Khashaia",
    "gn:country_code":"SD",
    "gn:dem":451,
    "gn:feature_class":"P",
    "gn:feature_code":"PPL",
    "gn:name":"Khash Khashaia",
    "gn:population":0,
    "gn:timezone":"Africa/Khartoum",
    "iso:country":"SD",
    "wof:name":"Khash Khashaia",
    "wof:placetype":"locality"
},
  "geometry": {"coordinates":[30.62092,10.32338],"type":"Point"}
}