{
  "type": "Feature",
  "properties": {
    "gn:admin1_code":"50.0",
    "gn:asciiname":"Chado",
    "gn:country_code":"SD",
    "gn:dem":781,
    "gn:feature_class":"P",
    "gn:feature_code":"PPL",
    "gn:name":"Chado",
    "gn:population":0,
    "gn:timezone":"Africa/Khartoum",
    "iso:country":"SD",
    "wof:name":"Chado",
    "wof:placetype":"locality"
},
  "geometry": {"coordinates":[31.03333,11.78333],"type":"Point"}
}