{
  "type": "Feature",
  "properties": {
    "gn:admin1_code":"47.0",
    "gn:asciiname":"Kortei",
    "gn:country_code":"SD",
    "gn:dem":804,
    "gn:feature_class":"P",
    "gn:feature_code":"PPL",
    "gn:name":"Kortei",
    "gn:population":0,
    "gn:timezone":"Africa/Khartoum",
    "iso:country":"SD",
    "name:eng_x_preferred":[
        "Kortei"
    ],
    "wof:name":"Kortei",
    "wof:placetype":"locality"
},
  "geometry": {"coordinates":[22.28753,12.77913],"type":"Point"}
}