{
  "type": "Feature",
  "properties": {
    "gn:admin1_code":"38.0",
    "gn:asciiname":"Tayba Hasat Allah",
    "gn:country_code":"SD",
    "gn:dem":398,
    "gn:feature_class":"P",
    "gn:feature_code":"PPL",
    "gn:name":"\u0162ayba \u1e28asat Allah",
    "gn:population":0,
    "gn:timezone":"Africa/Khartoum",
    "iso:country":"SD",
    "name:und_x_variant":[
        "\u0162ayba \u1e28asat Allah"
    ],
    "wof:lang_x_official":[
        "ara",
        "eng"
    ],
    "wof:lang_x_spoken":[
        "ara",
        "eng"
    ],
    "wof:name":"Tayba Hasat Allah",
    "wof:placetype":"locality"
},
  "geometry": {"coordinates":[33.1504,14.9946],"type":"Point"}
}