{
  "type": "Feature",
  "properties": {
    "gn:admin1_code":"38.0",
    "gn:asciiname":"Kumur aj Ja`aliyyin",
    "gn:country_code":"SD",
    "gn:dem":412,
    "gn:feature_class":"P",
    "gn:feature_code":"PPL",
    "gn:name":"Kumur aj Ja\u2018aliyy\u012bn",
    "gn:population":0,
    "gn:timezone":"Africa/Khartoum",
    "iso:country":"SD",
    "name:und_x_variant":[
        "El Kumur",
        "Al Kumur",
        "Kumur aj Ja\u2018aliyy\u012bn"
    ],
    "wof:lang_x_official":[
        "ara",
        "eng"
    ],
    "wof:lang_x_spoken":[
        "ara",
        "eng"
    ],
    "wof:name":"Kumur aj Ja`aliyyin",
    "wof:placetype":"locality"
},
  "geometry": {"coordinates":[33.3928,14.2795],"type":"Point"}
}