{
  "type": "Feature",
  "properties": {
    "gn:admin1_code":"42.0",
    "gn:asciiname":"Gharbas",
    "gn:country_code":"SD",
    "gn:dem":1028,
    "gn:feature_class":"P",
    "gn:feature_code":"PPL",
    "gn:name":"Gharbas",
    "gn:population":0,
    "gn:timezone":"Africa/Khartoum",
    "iso:country":"SD",
    "wof:name":"Gharbas",
    "wof:placetype":"locality"
},
  "geometry": {"coordinates":[34.28333,10.56667],"type":"Point"}
}