{
  "type": "Feature",
  "properties": {
    "gn:admin1_code":"62.0",
    "gn:asciiname":"Humayr",
    "gn:country_code":"SD",
    "gn:dem":497,
    "gn:feature_class":"P",
    "gn:feature_code":"PPL",
    "gn:name":"\u1e28umayr",
    "gn:population":0,
    "gn:timezone":"Africa/Khartoum",
    "iso:country":"SD",
    "name:und_x_variant":[
        "Humeir",
        "\u1e28umayr"
    ],
    "wof:lang_x_official":[
        "ara",
        "eng"
    ],
    "wof:lang_x_spoken":[
        "ara",
        "eng"
    ],
    "wof:name":"Humayr",
    "wof:placetype":"locality"
},
  "geometry": {"coordinates":[27.91667,12.06667],"type":"Point"}
}