{
  "type": "Feature",
  "properties": {
    "gn:admin1_code":"50.0",
    "gn:asciiname":"Gardud Tabaldi",
    "gn:country_code":"SD",
    "gn:dem":759,
    "gn:feature_class":"P",
    "gn:feature_code":"PPL",
    "gn:name":"Gardud Tabaldi",
    "gn:population":0,
    "gn:timezone":"Africa/Khartoum",
    "iso:country":"SD",
    "wof:name":"Gardud Tabaldi",
    "wof:placetype":"locality"
},
  "geometry": {"coordinates":[30.3451,11.6671],"type":"Point"}
}