{
  "type": "Feature",
  "properties": {
    "gn:admin1_code":"42.0",
    "gn:asciiname":"`Amarat Sabuni",
    "gn:country_code":"SD",
    "gn:dem":463,
    "gn:feature_class":"P",
    "gn:feature_code":"PPL",
    "gn:name":"\u2018Am\u0101rat S\u0101b\u016bn\u012b",
    "gn:population":0,
    "gn:timezone":"Africa/Khartoum",
    "iso:country":"SD",
    "name:und_x_variant":[
        "\u2018Am\u0101rat S\u0101b\u016bn\u012b"
    ],
    "wof:lang_x_official":[
        "ara",
        "eng"
    ],
    "wof:lang_x_spoken":[
        "ara",
        "eng"
    ],
    "wof:name":"`Amarat Sabuni",
    "wof:placetype":"locality"
},
  "geometry": {"coordinates":[34.347,12.0038],"type":"Point"}
}