{
  "type": "Feature",
  "properties": {
    "gn:admin1_code":"55.0",
    "gn:asciiname":"Mu`allaqa",
    "gn:country_code":"SD",
    "gn:dem":1096,
    "gn:feature_class":"P",
    "gn:feature_code":"PPL",
    "gn:name":"Mu\u2018allaqa",
    "gn:population":0,
    "gn:timezone":"Africa/Khartoum",
    "iso:country":"SD",
    "name:und_x_variant":[
        "Mu\u2018allaqa",
        "Mu\u2018allaqah"
    ],
    "wof:lang_x_official":[
        "ara",
        "eng"
    ],
    "wof:lang_x_spoken":[
        "ara",
        "eng"
    ],
    "wof:name":"Mu`allaqa",
    "wof:placetype":"locality"
},
  "geometry": {"coordinates":[23.95112,13.47081],"type":"Point"}
}