{
  "type": "Feature",
  "properties": {
    "gn:admin1_code":"41.0",
    "gn:asciiname":"Al `Aqir",
    "gn:country_code":"SD",
    "gn:dem":395,
    "gn:feature_class":"P",
    "gn:feature_code":"PPL",
    "gn:name":"Al \u2018\u0100qir",
    "gn:population":0,
    "gn:timezone":"Africa/Khartoum",
    "iso:country":"SD",
    "name:ara_x_preferred":[
        "Al \u2018\u0100qir"
    ],
    "wof:name":"Al `Aqir",
    "wof:placetype":"locality"
},
  "geometry": {"coordinates":[32.5567,12.4727],"type":"Point"}
}