{
  "type": "Feature",
  "properties": {
    "gn:admin1_code":"55.0",
    "gn:asciiname":"Shaqq an Nimr",
    "gn:country_code":"SD",
    "gn:dem":573,
    "gn:feature_class":"P",
    "gn:feature_code":"PPL",
    "gn:name":"Shaqq an Nimr",
    "gn:population":0,
    "gn:timezone":"Africa/Khartoum",
    "iso:country":"SD",
    "name:und_x_variant":[
        "Shaqq en Nimr",
        "Shaqq an Nimr"
    ],
    "wof:lang_x_official":[
        "ara",
        "eng"
    ],
    "wof:lang_x_spoken":[
        "ara",
        "eng"
    ],
    "wof:name":"Shaqq an Nimr",
    "wof:placetype":"locality"
},
  "geometry": {"coordinates":[27.28333,13.33333],"type":"Point"}
}