{
  "type": "Feature",
  "properties": {
    "gn:admin1_code":"58.0",
    "gn:asciiname":"Sharif",
    "gn:country_code":"SD",
    "gn:dem":424,
    "gn:feature_class":"P",
    "gn:feature_code":"PPL",
    "gn:name":"Shar\u012bf",
    "gn:population":0,
    "gn:timezone":"Africa/Khartoum",
    "iso:country":"SD",
    "name:ast_x_preferred":[
        "Jerife"
    ],
    "name:aze_x_preferred":[
        "\u015e\u0259rif"
    ],
    "name:cat_x_preferred":[
        "Xerif"
    ],
    "name:dan_x_preferred":[
        "Sharif"
    ],
    "name:deu_x_preferred":[
        "Scherif"
    ],
    "name:div_x_preferred":[
        "\u0789\u07a6\u0787\u07b0\u0786\u07a7\u078e\u07ac \u079d\u07a6\u0783\u07a9\u078a\u07aa"
    ],
    "name:epo_x_preferred":[
        "\u015carifo"
    ],
    "name:fin_x_preferred":[
        "\u0160arif"
    ],
    "name:fra_x_preferred":[
        "Ch\u00e9rif"
    ],
    "name:fry_x_preferred":[
        "Sjaryf"
    ],
    "name:heb_x_preferred":[
        "\u05e9\u05e8\u05d9\u05e3"
    ],
    "name:ita_x_preferred":[
        "Shar\u012bf"
    ],
    "name:lav_x_preferred":[
        "\u0160arifs"
    ],
    "name:nld_x_preferred":[
        "Sjarief"
    ],
    "name:nor_x_preferred":[
        "Sharif"
    ],
    "name:pol_x_preferred":[
        "Szarif"
    ],
    "name:por_x_preferred":[
        "Xarife"
    ],
    "name:rus_x_preferred":[
        "\u0428\u0435\u0440\u0438\u0444"
    ],
    "name:spa_x_preferred":[
        "Jerife"
    ],
    "name:swe_x_preferred":[
        "Sharif"
    ],
    "name:tur_x_preferred":[
        "\u015eerif"
    ],
    "name:ukr_x_preferred":[
        "\u0428\u0430\u0440\u0456\u0444"
    ],
    "name:und_x_variant":[
        "Sherif"
    ],
    "name:urd_x_preferred":[
        "\u0634\u0631\u06cc\u0641"
    ],
    "name:wuu_x_preferred":[
        "\u8c22\u91cc\u592b"
    ],
    "name:zho_x_preferred":[
        "\u8c22\u91cc\u592b"
    ],
    "wof:lang_x_official":[
        "ara",
        "eng"
    ],
    "wof:lang_x_spoken":[
        "ara",
        "eng"
    ],
    "wof:name":"Sharif",
    "wof:placetype":"locality"
},
  "geometry": {"coordinates":[33.61667,13.63333],"type":"Point"}
}