{
  "type": "Feature",
  "properties": {
    "gn:admin1_code":"58.0",
    "gn:asciiname":"Sharif",
    "gn:country_code":"SD",
    "gn:dem":424,
    "gn:feature_class":"P",
    "gn:feature_code":"PPL",
    "gn:name":"Shar\u012bf",
    "gn:population":0,
    "gn:timezone":"Africa/Khartoum",
    "iso:country":"SD",
    "name:und_x_variant":[
        "Sherif",
        "Shar\u012bf"
    ],
    "wof:name":"Sharif",
    "wof:placetype":"locality"
},
  "geometry": {"coordinates":[33.61667,13.63333],"type":"Point"}
}