{
  "type": "Feature",
  "properties": {
    "gn:admin1_code":"41.0",
    "gn:asciiname":"`Id Um `Ush",
    "gn:country_code":"SD",
    "gn:dem":389,
    "gn:feature_class":"P",
    "gn:feature_code":"PPL",
    "gn:name":"\u2018Id Um \u2018Ush",
    "gn:population":0,
    "gn:timezone":"Africa/Khartoum",
    "iso:country":"SD",
    "name:ara_x_preferred":[
        "\u2018Id Um \u2018Ush"
    ],
    "wof:name":"`Id Um `Ush",
    "wof:placetype":"locality"
},
  "geometry": {"coordinates":[32.1166,14.6886],"type":"Point"}
}