{
  "type": "Feature",
  "properties": {
    "gn:admin1_code":"53.0",
    "gn:asciiname":"Banat",
    "gn:country_code":"SD",
    "gn:dem":365,
    "gn:feature_class":"P",
    "gn:feature_code":"PPL",
    "gn:name":"Banat",
    "gn:population":0,
    "gn:timezone":"Africa/Khartoum",
    "iso:country":"SD",
    "wof:name":"Banat",
    "wof:placetype":"locality"
},
  "geometry": {"coordinates":[33.3311,16.6534],"type":"Point"}
}