{
  "type": "Feature",
  "properties": {
    "gn:admin1_code":"53.0",
    "gn:asciiname":"Banat",
    "gn:country_code":"SD",
    "gn:dem":365,
    "gn:feature_class":"P",
    "gn:feature_code":"PPL",
    "gn:name":"Banat",
    "gn:population":0,
    "gn:timezone":"Africa/Khartoum",
    "iso:country":"SD",
    "name:als_x_preferred":[
        "Banat"
    ],
    "name:ara_x_preferred":[
        "\u0628\u0627\u0646\u0627\u062a"
    ],
    "name:arg_x_preferred":[
        "Banato"
    ],
    "name:aze_x_preferred":[
        "Banat"
    ],
    "name:bel_x_preferred":[
        "\u0411\u0430\u043d\u0430\u0442"
    ],
    "name:bos_x_preferred":[
        "Banat"
    ],
    "name:bul_x_preferred":[
        "\u0411\u0430\u043d\u0430\u0442"
    ],
    "name:cat_x_preferred":[
        "Banat"
    ],
    "name:ces_x_preferred":[
        "Ban\u00e1t"
    ],
    "name:chv_x_preferred":[
        "\u0411\u0430\u043d\u0430\u0442"
    ],
    "name:dan_x_preferred":[
        "Banatet"
    ],
    "name:deu_x_preferred":[
        "Banat"
    ],
    "name:ell_x_preferred":[
        "\u0392\u03b1\u03bd\u03ac\u03c4\u03bf"
    ],
    "name:epo_x_preferred":[
        "Banato"
    ],
    "name:est_x_preferred":[
        "Banaat"
    ],
    "name:eus_x_preferred":[
        "Banat"
    ],
    "name:fas_x_preferred":[
        "\u0628\u0627\u0646\u0627\u062a"
    ],
    "name:fin_x_preferred":[
        "Baanaatti"
    ],
    "name:fra_x_preferred":[
        "Banat historique"
    ],
    "name:glg_x_preferred":[
        "Banato"
    ],
    "name:heb_x_preferred":[
        "\u05d1\u05d0\u05e0\u05d0\u05d8"
    ],
    "name:hrv_x_preferred":[
        "Banat"
    ],
    "name:hun_x_preferred":[
        "B\u00e1ns\u00e1g"
    ],
    "name:hye_x_preferred":[
        "\u0532\u0561\u0576\u0561\u057f"
    ],
    "name:ind_x_preferred":[
        "Banat"
    ],
    "name:ita_x_preferred":[
        "Banato"
    ],
    "name:jpn_x_preferred":[
        "\u30d0\u30ca\u30c8"
    ],
    "name:kor_x_preferred":[
        "\ubc14\ub098\ud2b8"
    ],
    "name:lat_x_preferred":[
        "Banatus"
    ],
    "name:lav_x_preferred":[
        "Banata"
    ],
    "name:lit_x_preferred":[
        "Banatas"
    ],
    "name:msa_x_preferred":[
        "Banat"
    ],
    "name:nld_x_preferred":[
        "Banaat"
    ],
    "name:nno_x_preferred":[
        "Banat"
    ],
    "name:nor_x_preferred":[
        "Banat"
    ],
    "name:oci_x_preferred":[
        "Banat"
    ],
    "name:pnb_x_preferred":[
        "\u0628\u0627\u0646\u0627\u062a"
    ],
    "name:pol_x_preferred":[
        "Banat"
    ],
    "name:por_x_preferred":[
        "Banato"
    ],
    "name:ron_x_preferred":[
        "Banat"
    ],
    "name:rus_x_preferred":[
        "\u0411\u0430\u043d\u0430\u0442"
    ],
    "name:scn_x_preferred":[
        "Banat"
    ],
    "name:sco_x_preferred":[
        "Banat"
    ],
    "name:slk_x_preferred":[
        "Ban\u00e1t"
    ],
    "name:slv_x_preferred":[
        "Banat"
    ],
    "name:spa_x_preferred":[
        "Banato"
    ],
    "name:srp_x_preferred":[
        "\u0411\u0430\u043d\u0430\u0442"
    ],
    "name:swe_x_preferred":[
        "Banatet"
    ],
    "name:tur_x_preferred":[
        "Banat"
    ],
    "name:ukr_x_preferred":[
        "\u0411\u0430\u043d\u0430\u0442"
    ],
    "name:urd_x_preferred":[
        "\u0628\u0627\u0646\u0627\u062a"
    ],
    "name:vie_x_preferred":[
        "Banat"
    ],
    "name:zho_x_preferred":[
        "\u5df4\u7d0d\u7279"
    ],
    "wof:name":"Banat",
    "wof:placetype":"locality"
},
  "geometry": {"coordinates":[33.3311,16.6534],"type":"Point"}
}