{
  "type": "Feature",
  "properties": {
    "gn:admin1_code":"50.0",
    "gn:asciiname":"Orshard",
    "gn:country_code":"SD",
    "gn:dem":808,
    "gn:feature_class":"P",
    "gn:feature_code":"PPL",
    "gn:name":"Orshard",
    "gn:population":0,
    "gn:timezone":"Africa/Khartoum",
    "iso:country":"SD",
    "wof:name":"Orshard",
    "wof:placetype":"locality"
},
  "geometry": {"coordinates":[31.0073,11.9091],"type":"Point"}
}