{
  "type": "Feature",
  "properties": {
    "gn:admin1_code":"50.0",
    "gn:asciiname":"Jabrin",
    "gn:country_code":"SD",
    "gn:dem":649,
    "gn:feature_class":"P",
    "gn:feature_code":"PPL",
    "gn:name":"Jabr\u012bn",
    "gn:population":0,
    "gn:timezone":"Africa/Khartoum",
    "iso:country":"SD",
    "name:ara_x_preferred":[
        "\u062c\u0628\u0631\u064a\u0646"
    ],
    "name:fas_x_preferred":[
        "\u062c\u0628\u0631\u06cc\u0646"
    ],
    "name:ita_x_preferred":[
        "Jabrin"
    ],
    "name:nno_x_preferred":[
        "Jabrin"
    ],
    "name:por_x_preferred":[
        "Jabrine"
    ],
    "name:und_x_variant":[
        "Gabrin",
        "Jabr\u012bn"
    ],
    "name:urd_x_preferred":[
        "\u062c\u0628\u0631\u06cc\u0646"
    ],
    "wof:lang_x_official":[
        "ara",
        "eng"
    ],
    "wof:lang_x_spoken":[
        "ara",
        "eng"
    ],
    "wof:name":"Jabrin",
    "wof:placetype":"locality"
},
  "geometry": {"coordinates":[30.26667,12.15],"type":"Point"}
}