{
  "type": "Feature",
  "properties": {
    "gn:admin1_code":"38.0",
    "gn:asciiname":"Kambu um Talaqo",
    "gn:country_code":"SD",
    "gn:dem":407,
    "gn:feature_class":"P",
    "gn:feature_code":"PPL",
    "gn:name":"Kambu um \u0162alaqo",
    "gn:population":0,
    "gn:timezone":"Africa/Khartoum",
    "iso:country":"SD",
    "name:und_x_variant":[
        "Kambu um \u0162alaqo"
    ],
    "wof:name":"Kambu um Talaqo",
    "wof:placetype":"locality"
},
  "geometry": {"coordinates":[33.1708,14.4712],"type":"Point"}
}