{
  "type": "Feature",
  "properties": {
    "gn:admin1_code":"53.0",
    "gn:asciiname":"Bannaqa",
    "gn:country_code":"SD",
    "gn:dem":370,
    "gn:feature_class":"P",
    "gn:feature_code":"PPL",
    "gn:name":"Bannaqa",
    "gn:population":0,
    "gn:timezone":"Africa/Khartoum",
    "iso:country":"SD",
    "wof:name":"Bannaqa",
    "wof:placetype":"locality"
},
  "geometry": {"coordinates":[33.1194,16.5148],"type":"Point"}
}