{
  "type": "Feature",
  "properties": {
    "gn:admin1_code":"41.0",
    "gn:asciiname":"Hillat esh Sheikh Taha",
    "gn:country_code":"SD",
    "gn:dem":406,
    "gn:feature_class":"P",
    "gn:feature_code":"PPL",
    "gn:name":"Hillat esh Sheikh Taha",
    "gn:population":0,
    "gn:timezone":"Africa/Khartoum",
    "iso:country":"SD",
    "wof:name":"Hillat esh Sheikh Taha",
    "wof:placetype":"locality"
},
  "geometry": {"coordinates":[32.3056,15.0389],"type":"Point"}
}