{
  "type": "Feature",
  "properties": {
    "gn:admin1_code":"55.0",
    "gn:asciiname":"Sabun Gardia",
    "gn:country_code":"SD",
    "gn:dem":881,
    "gn:feature_class":"P",
    "gn:feature_code":"PPL",
    "gn:name":"Sabun Gardia",
    "gn:population":0,
    "gn:timezone":"Africa/Khartoum",
    "iso:country":"SD",
    "wof:name":"Sabun Gardia",
    "wof:placetype":"locality"
},
  "geometry": {"coordinates":[23.68333,15.33333],"type":"Point"}
}