{
  "type": "Feature",
  "properties": {
    "gn:admin1_code":"41.0",
    "gn:asciiname":"Hillat Domor al Kirer",
    "gn:country_code":"SD",
    "gn:dem":388,
    "gn:feature_class":"P",
    "gn:feature_code":"PPL",
    "gn:name":"Hillat Domor al Kirer",
    "gn:population":0,
    "gn:timezone":"Africa/Khartoum",
    "iso:country":"SD",
    "name:und_x_variant":[
        "Wad el Kereil",
        "Wad al Kereil",
        "Hillat Domor al Kirer"
    ],
    "wof:lang_x_official":[
        "ara",
        "eng"
    ],
    "wof:lang_x_spoken":[
        "ara",
        "eng"
    ],
    "wof:name":"Hillat Domor al Kirer",
    "wof:placetype":"locality"
},
  "geometry": {"coordinates":[32.4792,15.1457],"type":"Point"}
}