{
  "type": "Feature",
  "properties": {
    "gn:admin1_code":"56.0",
    "gn:asciiname":"Um `Ali",
    "gn:country_code":"SD",
    "gn:dem":460,
    "gn:feature_class":"P",
    "gn:feature_code":"PPL",
    "gn:name":"Um \u2018Ali",
    "gn:population":0,
    "gn:timezone":"Africa/Khartoum",
    "iso:country":"SD",
    "name:ara_x_preferred":[
        "Um \u2018Ali"
    ],
    "wof:name":"Um `Ali",
    "wof:placetype":"locality"
},
  "geometry": {"coordinates":[31.2968,12.7253],"type":"Point"}
}