{
  "type": "Feature",
  "properties": {
    "gn:admin1_code":"0.0",
    "gn:asciiname":"Kirakira",
    "gn:country_code":"SD",
    "gn:dem":535,
    "gn:feature_class":"P",
    "gn:feature_code":"PPL",
    "gn:name":"Kirakira",
    "gn:population":0,
    "gn:timezone":"Africa/Khartoum",
    "iso:country":"SD",
    "wof:name":"Kirakira",
    "wof:placetype":"locality"
},
  "geometry": {"coordinates":[23.65251,10.87949],"type":"Point"}
}