{
  "type": "Feature",
  "properties": {
    "gn:admin1_code":"0.0",
    "gn:asciiname":"Kirakira",
    "gn:country_code":"SD",
    "gn:dem":535,
    "gn:feature_class":"P",
    "gn:feature_code":"PPL",
    "gn:name":"Kirakira",
    "gn:population":0,
    "gn:timezone":"Africa/Khartoum",
    "iso:country":"SD",
    "name:ceb_x_preferred":[
        "Kirakira"
    ],
    "name:ces_x_preferred":[
        "Kirakira"
    ],
    "name:deu_x_preferred":[
        "Kirakira"
    ],
    "name:fas_x_preferred":[
        "\u06a9\u06cc\u0631\u0627\u06a9\u06cc\u0631\u0627"
    ],
    "name:fra_x_preferred":[
        "Kirakira"
    ],
    "name:glg_x_preferred":[
        "Kirakira"
    ],
    "name:hrv_x_preferred":[
        "Kirakira"
    ],
    "name:ita_x_preferred":[
        "Kirakira"
    ],
    "name:jpn_x_preferred":[
        "\u30ad\u30e9\u30ad\u30e9"
    ],
    "name:lit_x_preferred":[
        "Kirakira"
    ],
    "name:mrj_x_preferred":[
        "\u041a\u0438\u0440\u0430\u043a\u0438\u0440\u0430"
    ],
    "name:nau_x_preferred":[
        "Kirakira"
    ],
    "name:pol_x_preferred":[
        "Kirakira"
    ],
    "name:por_x_preferred":[
        "Kirakira"
    ],
    "name:spa_x_preferred":[
        "Kirakira"
    ],
    "name:urd_x_preferred":[
        "\u06a9\u06cc\u0631\u0627\u06a9\u06cc\u0631\u0627"
    ],
    "name:vie_x_preferred":[
        "Kirakira"
    ],
    "name:zho_x_preferred":[
        "\u57fa\u62c9\u57fa\u62c9"
    ],
    "wof:name":"Kirakira",
    "wof:placetype":"locality"
},
  "geometry": {"coordinates":[23.65251,10.87949],"type":"Point"}
}