{
  "type": "Feature",
  "properties": {
    "gn:admin1_code":"58.0",
    "gn:asciiname":"Shamiyyat `Umar",
    "gn:country_code":"SD",
    "gn:dem":451,
    "gn:feature_class":"P",
    "gn:feature_code":"PPL",
    "gn:name":"Sh\u0101miyyat \u2018Umar",
    "gn:population":0,
    "gn:timezone":"Africa/Khartoum",
    "iso:country":"SD",
    "name:und_x_variant":[
        "Shamiya \u2018Umar",
        "Sh\u0101miyyat \u2018Umar"
    ],
    "wof:name":"Shamiyyat `Umar",
    "wof:placetype":"locality"
},
  "geometry": {"coordinates":[34.1436,12.6121],"type":"Point"}
}