{
  "type": "Feature",
  "properties": {
    "gn:admin1_code":"50.0",
    "gn:asciiname":"Kudba",
    "gn:country_code":"SD",
    "gn:dem":658,
    "gn:feature_class":"P",
    "gn:feature_code":"PPL",
    "gn:name":"Kudba",
    "gn:population":0,
    "gn:timezone":"Africa/Khartoum",
    "iso:country":"SD",
    "name:und_x_variant":[
        "Kudbir",
        "Kudba"
    ],
    "wof:name":"Kudba",
    "wof:placetype":"locality"
},
  "geometry": {"coordinates":[30.53333,11.83333],"type":"Point"}
}