{
  "type": "Feature",
  "properties": {
    "gn:admin1_code":"38.0",
    "gn:asciiname":"At Tileh az Ziber",
    "gn:country_code":"SD",
    "gn:dem":419,
    "gn:feature_class":"P",
    "gn:feature_code":"PPL",
    "gn:name":"A\u0163 \u0162ile\u1e29 az Ziber",
    "gn:population":0,
    "gn:timezone":"Africa/Khartoum",
    "iso:country":"SD",
    "name:und_x_variant":[
        "A\u0163 \u0162ile\u1e29 az Ziber"
    ],
    "wof:name":"At Tileh az Ziber",
    "wof:placetype":"locality"
},
  "geometry": {"coordinates":[33.2364,14.1178],"type":"Point"}
}