{
  "type": "Feature",
  "properties": {
    "gn:admin1_code":"41.0",
    "gn:asciiname":"Aj Jikhesat",
    "gn:country_code":"SD",
    "gn:dem":390,
    "gn:feature_class":"P",
    "gn:feature_code":"PPL",
    "gn:name":"Aj Jikhe\u015f\u0101t",
    "gn:population":0,
    "gn:timezone":"Africa/Khartoum",
    "iso:country":"SD",
    "name:ara_x_preferred":[
        "Aj Jikhe\u015f\u0101t"
    ],
    "wof:name":"Aj Jikhesat",
    "wof:placetype":"locality"
},
  "geometry": {"coordinates":[32.0769,13.8357],"type":"Point"}
}