{
  "type": "Feature",
  "properties": {
    "gn:admin1_code":"38.0",
    "gn:asciiname":"Hasan al Ghazali",
    "gn:country_code":"SD",
    "gn:dem":418,
    "gn:feature_class":"P",
    "gn:feature_code":"PPL",
    "gn:name":"\u1e28asan al Ghaz\u0101l\u012b",
    "gn:population":0,
    "gn:timezone":"Africa/Khartoum",
    "iso:country":"SD",
    "name:und_x_variant":[
        "Hasan el Ghazali",
        "\u1e28asan al Ghaz\u0101l\u012b"
    ],
    "wof:name":"Hasan al Ghazali",
    "wof:placetype":"locality"
},
  "geometry": {"coordinates":[33.78333,14.06667],"type":"Point"}
}