{
  "type": "Feature",
  "properties": {
    "gn:admin1_code":"58.0",
    "gn:asciiname":"Misher`at Gharib",
    "gn:country_code":"SD",
    "gn:dem":456,
    "gn:feature_class":"P",
    "gn:feature_code":"PPL",
    "gn:name":"Misher\u2018\u0101t Gharib",
    "gn:population":0,
    "gn:timezone":"Africa/Khartoum",
    "iso:country":"SD",
    "name:und_x_variant":[
        "Misher\u2018\u0101t Gharib"
    ],
    "wof:name":"Misher`at Gharib",
    "wof:placetype":"locality"
},
  "geometry": {"coordinates":[34.1263,12.6351],"type":"Point"}
}