{
  "type": "Feature",
  "properties": {
    "gn:admin1_code":"42.0",
    "gn:asciiname":"Ab Zur",
    "gn:country_code":"SD",
    "gn:dem":461,
    "gn:feature_class":"P",
    "gn:feature_code":"PPL",
    "gn:name":"Ab Z\u016br",
    "gn:population":0,
    "gn:timezone":"Africa/Khartoum",
    "iso:country":"SD",
    "name:ara_x_preferred":[
        "Ab Z\u016br"
    ],
    "name:und_x_variant":[
        "Abu Zor",
        "Ab\u016b Zawr"
    ],
    "wof:name":"Ab Zur",
    "wof:placetype":"locality"
},
  "geometry": {"coordinates":[34.352,12.3877],"type":"Point"}
}