{
  "type": "Feature",
  "properties": {
    "gn:admin1_code":"50.0",
    "gn:asciiname":"Tijur",
    "gn:country_code":"SD",
    "gn:dem":578,
    "gn:feature_class":"P",
    "gn:feature_code":"PPL",
    "gn:name":"Tij\u016br",
    "gn:population":0,
    "gn:timezone":"Africa/Khartoum",
    "iso:country":"SD",
    "name:ara_x_preferred":[
        "Tij\u016br"
    ],
    "wof:name":"Tijur",
    "wof:placetype":"locality"
},
  "geometry": {"coordinates":[31.3925,12.2521],"type":"Point"}
}