{
  "type": "Feature",
  "properties": {
    "gn:admin1_code":"38.0",
    "gn:asciiname":"Ad Dibeba",
    "gn:country_code":"SD",
    "gn:dem":394,
    "gn:feature_class":"P",
    "gn:feature_code":"PPL",
    "gn:name":"Ad Dibeba",
    "gn:population":0,
    "gn:timezone":"Africa/Khartoum",
    "iso:country":"SD",
    "name:und_x_variant":[
        "Dubeiba",
        "Dubeiba ed Dubasiyin",
        "Dubaybat ad Dubasiyin",
        "Ad Dibeba"
    ],
    "wof:name":"Ad Dibeba",
    "wof:placetype":"locality"
},
  "geometry": {"coordinates":[33.0176,14.955],"type":"Point"}
}