{
  "type": "Feature",
  "properties": {
    "gn:admin1_code":"41.0",
    "gn:asciiname":"Hurrah",
    "gn:country_code":"SD",
    "gn:dem":407,
    "gn:feature_class":"P",
    "gn:feature_code":"PPL",
    "gn:name":"\u1e28urrah",
    "gn:population":0,
    "gn:timezone":"Africa/Khartoum",
    "iso:country":"SD",
    "name:und_x_variant":[
        "Hurra",
        "\u1e28urrah"
    ],
    "wof:name":"Hurrah",
    "wof:placetype":"locality"
},
  "geometry": {"coordinates":[32.11667,12.96667],"type":"Point"}
}