{
  "type": "Feature",
  "properties": {
    "gn:admin1_code":"62.0",
    "gn:asciiname":"Wad Kutna",
    "gn:country_code":"SD",
    "gn:dem":582,
    "gn:feature_class":"P",
    "gn:feature_code":"PPL",
    "gn:name":"Wad Kutna",
    "gn:population":0,
    "gn:timezone":"Africa/Khartoum",
    "iso:country":"SD",
    "wof:name":"Wad Kutna",
    "wof:placetype":"locality"
},
  "geometry": {"coordinates":[28.58333,13.18333],"type":"Point"}
}