{
  "type": "Feature",
  "properties": {
    "gn:admin1_code":"42.0",
    "gn:asciiname":"Al Watawit",
    "gn:country_code":"SD",
    "gn:dem":770,
    "gn:feature_class":"P",
    "gn:feature_code":"PPL",
    "gn:name":"Al Wa\u0163\u0101w\u012b\u0163",
    "gn:population":0,
    "gn:timezone":"Africa/Khartoum",
    "iso:country":"SD",
    "name:und_x_variant":[
        "El Watawit",
        "Al Wa\u0163\u0101w\u012b\u0163"
    ],
    "wof:lang_x_official":[
        "ara",
        "eng"
    ],
    "wof:lang_x_spoken":[
        "ara",
        "eng"
    ],
    "wof:name":"Al Watawit",
    "wof:placetype":"locality"
},
  "geometry": {"coordinates":[34.33333,10.83333],"type":"Point"}
}