{
  "type": "Feature",
  "properties": {
    "gn:admin1_code":"41.0",
    "gn:asciiname":"Ghireqa",
    "gn:country_code":"SD",
    "gn:dem":414,
    "gn:feature_class":"P",
    "gn:feature_code":"PPL",
    "gn:name":"Ghireqa",
    "gn:population":0,
    "gn:timezone":"Africa/Khartoum",
    "iso:country":"SD",
    "wof:name":"Ghireqa",
    "wof:placetype":"locality"
},
  "geometry": {"coordinates":[31.9181,12.8954],"type":"Point"}
}