{
  "type": "Feature",
  "properties": {
    "gn:admin1_code":"38.0",
    "gn:asciiname":"Ash Sharef Mukhtar",
    "gn:country_code":"SD",
    "gn:dem":415,
    "gn:feature_class":"P",
    "gn:feature_code":"PPL",
    "gn:name":"Ash Sharef Mukhtar",
    "gn:population":0,
    "gn:timezone":"Africa/Khartoum",
    "iso:country":"SD",
    "name:und_x_variant":[
        "Shar\u012bf Mukhtar",
        "Ash Sharef Mukhtar"
    ],
    "wof:name":"Ash Sharef Mukhtar",
    "wof:placetype":"locality"
},
  "geometry": {"coordinates":[33.4317,14.0152],"type":"Point"}
}