{
  "type": "Feature",
  "properties": {
    "gn:admin1_code":"56.0",
    "gn:asciiname":"Musa",
    "gn:country_code":"SD",
    "gn:dem":450,
    "gn:feature_class":"P",
    "gn:feature_code":"PPL",
    "gn:name":"Musa",
    "gn:population":0,
    "gn:timezone":"Africa/Khartoum",
    "iso:country":"SD",
    "wof:name":"Musa",
    "wof:placetype":"locality"
},
  "geometry": {"coordinates":[31.3874,12.7554],"type":"Point"}
}