{
  "type": "Feature",
  "properties": {
    "gn:admin1_code":"29.0",
    "gn:asciiname":"Al Msodiya",
    "gn:country_code":"SD",
    "gn:dem":389,
    "gn:feature_class":"P",
    "gn:feature_code":"PPL",
    "gn:name":"Al Msodiya",
    "gn:population":0,
    "gn:timezone":"Africa/Khartoum",
    "iso:country":"SD",
    "name:und_x_variant":[
        "El Mas\u2018udiya",
        "Al Mas\u2018\u016bd\u012byah",
        "Al Msodiya"
    ],
    "wof:lang_x_official":[
        "ara",
        "eng"
    ],
    "wof:lang_x_spoken":[
        "ara",
        "eng"
    ],
    "wof:name":"Al Msodiya",
    "wof:placetype":"locality"
},
  "geometry": {"coordinates":[32.8664,15.3111],"type":"Point"}
}