{
  "type": "Feature",
  "properties": {
    "gn:admin1_code":"42.0",
    "gn:asciiname":"Wirkit",
    "gn:country_code":"SD",
    "gn:dem":530,
    "gn:feature_class":"P",
    "gn:feature_code":"PPL",
    "gn:name":"Wirkit",
    "gn:population":0,
    "gn:timezone":"Africa/Khartoum",
    "iso:country":"SD",
    "wof:name":"Wirkit",
    "wof:placetype":"locality"
},
  "geometry": {"coordinates":[33.7729,12.1112],"type":"Point"}
}