{
  "type": "Feature",
  "properties": {
    "gn:admin1_code":"29.0",
    "gn:asciiname":"Hillat Karari",
    "gn:country_code":"SD",
    "gn:dem":385,
    "gn:feature_class":"P",
    "gn:feature_code":"PPL",
    "gn:name":"Hillat Karari",
    "gn:population":0,
    "gn:timezone":"Africa/Khartoum",
    "iso:country":"SD",
    "name:und_x_variant":[
        "Marari",
        "Karari",
        "Hillat Karari"
    ],
    "wof:name":"Hillat Karari",
    "wof:placetype":"locality"
},
  "geometry": {"coordinates":[32.5304,15.7912],"type":"Point"}
}