{
  "type": "Feature",
  "properties": {
    "gn:admin1_code":"41.0",
    "gn:asciiname":"Dankuj ash Shluk",
    "gn:country_code":"SD",
    "gn:dem":385,
    "gn:feature_class":"P",
    "gn:feature_code":"PPL",
    "gn:name":"Dank\u016bj ash Shluk",
    "gn:population":0,
    "gn:timezone":"Africa/Khartoum",
    "iso:country":"SD",
    "name:und_x_variant":[
        "Dank\u016bj ash Shluk"
    ],
    "wof:name":"Dankuj ash Shluk",
    "wof:placetype":"locality"
},
  "geometry": {"coordinates":[32.7468,12.8915],"type":"Point"}
}