{
  "type": "Feature",
  "properties": {
    "gn:admin1_code":"53.0",
    "gn:asciiname":"Hillat el Hasanab",
    "gn:country_code":"SD",
    "gn:dem":378,
    "gn:feature_class":"P",
    "gn:feature_code":"PPL",
    "gn:name":"Hillat el Hasanab",
    "gn:population":0,
    "gn:timezone":"Africa/Khartoum",
    "iso:country":"SD",
    "wof:lang_x_official":[
        "ara",
        "eng"
    ],
    "wof:lang_x_spoken":[
        "ara",
        "eng"
    ],
    "wof:name":"Hillat el Hasanab",
    "wof:placetype":"locality"
},
  "geometry": {"coordinates":[32.9327,16.5133],"type":"Point"}
}