{
  "type": "Feature",
  "properties": {
    "gn:admin1_code":"56.0",
    "gn:asciiname":"Habobiyya Ash Shami",
    "gn:country_code":"SD",
    "gn:dem":471,
    "gn:feature_class":"P",
    "gn:feature_code":"PPL",
    "gn:name":"Habobiyya Ash Sh\u0101mi",
    "gn:population":0,
    "gn:timezone":"Africa/Khartoum",
    "iso:country":"SD",
    "name:und_x_variant":[
        "Habobiyya Ash Sh\u0101mi"
    ],
    "wof:name":"Habobiyya Ash Shami",
    "wof:placetype":"locality"
},
  "geometry": {"coordinates":[31.1843,12.7543],"type":"Point"}
}