{
  "type": "Feature",
  "properties": {
    "gn:admin1_code":"50.0",
    "gn:asciiname":"Karkaray",
    "gn:country_code":"SD",
    "gn:dem":637,
    "gn:feature_class":"P",
    "gn:feature_code":"PPL",
    "gn:name":"Karkaray",
    "gn:population":0,
    "gn:timezone":"Africa/Khartoum",
    "iso:country":"SD",
    "wof:name":"Karkaray",
    "wof:placetype":"locality"
},
  "geometry": {"coordinates":[29.9688,11.6414],"type":"Point"}
}