{
  "type": "Feature",
  "properties": {
    "gn:admin1_code":"56.0",
    "gn:asciiname":"Fadliyah",
    "gn:country_code":"SD",
    "gn:dem":428,
    "gn:feature_class":"P",
    "gn:feature_code":"PPL",
    "gn:name":"Fa\u1e11l\u012byah",
    "gn:population":0,
    "gn:timezone":"Africa/Khartoum",
    "iso:country":"SD",
    "name:und_x_variant":[
        "Fadliya",
        "Fa\u1e11l\u012byah"
    ],
    "wof:name":"Fadliyah",
    "wof:placetype":"locality"
},
  "geometry": {"coordinates":[30.93333,14.46667],"type":"Point"}
}