{
  "type": "Feature",
  "properties": {
    "gn:admin1_code":"42.0",
    "gn:asciiname":"Ar Riqeba Sharq",
    "gn:country_code":"SD",
    "gn:dem":489,
    "gn:feature_class":"P",
    "gn:feature_code":"PPL",
    "gn:name":"Ar Riqeba Sharq",
    "gn:population":0,
    "gn:timezone":"Africa/Khartoum",
    "iso:country":"SD",
    "name:und_x_variant":[
        "Er Ruqeiba",
        "Ar Ruqaybah",
        "Ar Riqeba Sharq"
    ],
    "wof:lang_x_official":[
        "ara",
        "eng"
    ],
    "wof:lang_x_spoken":[
        "ara",
        "eng"
    ],
    "wof:name":"Ar Riqeba Sharq",
    "wof:placetype":"locality"
},
  "geometry": {"coordinates":[34.3922,11.6609],"type":"Point"}
}