{
  "type": "Feature",
  "properties": {
    "gn:admin1_code":"56.0",
    "gn:asciiname":"Sawani",
    "gn:country_code":"SD",
    "gn:dem":499,
    "gn:feature_class":"P",
    "gn:feature_code":"PPL",
    "gn:name":"Saw\u0101n\u012b",
    "gn:population":0,
    "gn:timezone":"Africa/Khartoum",
    "iso:country":"SD",
    "name:ell_x_preferred":[
        "\u03a3\u03b1\u03bf\u03c5\u03ac\u03bd\u03b9"
    ],
    "name:hin_x_preferred":[
        "\u0915\u091c\u0930\u0940"
    ],
    "name:und_x_variant":[
        "Sowani",
        "Saw\u0101n\u012b"
    ],
    "wof:name":"Sawani",
    "wof:placetype":"locality"
},
  "geometry": {"coordinates":[30.58333,12.81667],"type":"Point"}
}