{
  "type": "Feature",
  "properties": {
    "gn:admin1_code":"47.0",
    "gn:asciiname":"Meirdaila",
    "gn:country_code":"SD",
    "gn:dem":681,
    "gn:feature_class":"P",
    "gn:feature_code":"PPL",
    "gn:name":"Meirdaila",
    "gn:population":0,
    "gn:timezone":"Africa/Khartoum",
    "iso:country":"SD",
    "name:eng_x_preferred":[
        "Meirdaila"
    ],
    "name:und_x_variant":[
        "Meirdmta"
    ],
    "wof:name":"Meirdaila",
    "wof:placetype":"locality"
},
  "geometry": {"coordinates":[21.98701,12.81505],"type":"Point"}
}