{
  "type": "Feature",
  "properties": {
    "gn:admin1_code":"38.0",
    "gn:asciiname":"La`ota",
    "gn:country_code":"SD",
    "gn:dem":397,
    "gn:feature_class":"P",
    "gn:feature_code":"PPL",
    "gn:name":"La\u2018ota",
    "gn:population":0,
    "gn:timezone":"Africa/Khartoum",
    "iso:country":"SD",
    "wof:name":"La`ota",
    "wof:placetype":"locality"
},
  "geometry": {"coordinates":[33.11056,15.02667],"type":"Point"}
}