{
  "type": "Feature",
  "properties": {
    "gn:admin1_code":"41.0",
    "gn:asciiname":"Zireqa",
    "gn:country_code":"SD",
    "gn:dem":395,
    "gn:feature_class":"P",
    "gn:feature_code":"PPL",
    "gn:name":"Zireqa",
    "gn:population":0,
    "gn:timezone":"Africa/Khartoum",
    "iso:country":"SD",
    "name:und_x_variant":[
        "Zureiqa",
        "Zur\u0113qa",
        "Zurayq\u0101\u2019",
        "Zireqa"
    ],
    "wof:name":"Zireqa",
    "wof:placetype":"locality"
},
  "geometry": {"coordinates":[32.0484,13.5756],"type":"Point"}
}