{
  "type": "Feature",
  "properties": {
    "gn:admin1_code":"38.0",
    "gn:asciiname":"Um Bosha 'Abd Al Baqi",
    "gn:country_code":"SD",
    "gn:dem":400,
    "gn:feature_class":"P",
    "gn:feature_code":"PPL",
    "gn:name":"Um B\u014dsha \u2018Abd Al B\u0101qi",
    "gn:population":0,
    "gn:timezone":"Africa/Khartoum",
    "iso:country":"SD",
    "name:und_x_variant":[
        "Um B\u014dsha \u2018Abd Al B\u0101qi"
    ],
    "wof:name":"Um Bosha 'Abd Al Baqi",
    "wof:placetype":"locality"
},
  "geometry": {"coordinates":[32.9768,14.747],"type":"Point"}
}