{
  "type": "Feature",
  "properties": {
    "gn:admin1_code":"50.0",
    "gn:asciiname":"Kurkuru",
    "gn:country_code":"SD",
    "gn:dem":663,
    "gn:feature_class":"P",
    "gn:feature_code":"PPL",
    "gn:name":"Kurkuru",
    "gn:population":0,
    "gn:timezone":"Africa/Khartoum",
    "iso:country":"SD",
    "wof:name":"Kurkuru",
    "wof:placetype":"locality"
},
  "geometry": {"coordinates":[30.1953,11.6557],"type":"Point"}
}