{
  "type": "Feature",
  "properties": {
    "gn:admin1_code":"61.0",
    "gn:asciiname":"Kulmo",
    "gn:country_code":"SD",
    "gn:dem":904,
    "gn:feature_class":"P",
    "gn:feature_code":"PPL",
    "gn:name":"Kulmo",
    "gn:population":0,
    "gn:timezone":"Africa/Khartoum",
    "iso:country":"SD",
    "wof:name":"Kulmo",
    "wof:placetype":"locality"
},
  "geometry": {"coordinates":[23.31181,12.60247],"type":"Point"}
}