{
  "type": "Feature",
  "properties": {
    "gn:admin1_code":"38.0",
    "gn:asciiname":"Hillat al Qal`a",
    "gn:country_code":"SD",
    "gn:dem":393,
    "gn:feature_class":"P",
    "gn:feature_code":"PPL",
    "gn:name":"Hillat al Qal\u2018a",
    "gn:population":0,
    "gn:timezone":"Africa/Khartoum",
    "iso:country":"SD",
    "name:und_x_variant":[
        "Hillat al Qal\u2018a"
    ],
    "wof:name":"Hillat al Qal`a",
    "wof:placetype":"locality"
},
  "geometry": {"coordinates":[32.8351,15.0981],"type":"Point"}
}