{
  "type": "Feature",
  "properties": {
    "gn:admin1_code":"38.0",
    "gn:asciiname":"`Ifena",
    "gn:country_code":"SD",
    "gn:dem":409,
    "gn:feature_class":"P",
    "gn:feature_code":"PPL",
    "gn:name":"\u2018Ifena",
    "gn:population":0,
    "gn:timezone":"Africa/Khartoum",
    "iso:country":"SD",
    "name:und_x_variant":[
        "\u2018Ufeina",
        "\u2018Ufaynah",
        "\u2018Ifena"
    ],
    "wof:name":"`Ifena",
    "wof:placetype":"locality"
},
  "geometry": {"coordinates":[33.1926,14.3738],"type":"Point"}
}