{
  "type": "Feature",
  "properties": {
    "gn:admin1_code":"61.0",
    "gn:asciiname":"Karkulli",
    "gn:country_code":"SD",
    "gn:dem":747,
    "gn:feature_class":"P",
    "gn:feature_code":"PPL",
    "gn:name":"Karkulli",
    "gn:population":0,
    "gn:timezone":"Africa/Khartoum",
    "iso:country":"SD",
    "name:und_x_variant":[
        "Karkouli",
        "Karkulli"
    ],
    "wof:name":"Karkulli",
    "wof:placetype":"locality"
},
  "geometry": {"coordinates":[23.25,12.05],"type":"Point"}
}