{
  "type": "Feature",
  "properties": {
    "gn:admin1_code":"42.0",
    "gn:asciiname":"Abu Maugud",
    "gn:country_code":"SD",
    "gn:dem":502,
    "gn:feature_class":"P",
    "gn:feature_code":"PPL",
    "gn:name":"Abu Maugud",
    "gn:population":0,
    "gn:timezone":"Africa/Khartoum",
    "iso:country":"SD",
    "name:und_x_variant":[
        "Abu Muqud",
        "Abu Maugud"
    ],
    "wof:name":"Abu Maugud",
    "wof:placetype":"locality"
},
  "geometry": {"coordinates":[33.97034,10.21161],"type":"Point"}
}