{
  "type": "Feature",
  "properties": {
    "gn:admin1_code":"50.0",
    "gn:asciiname":"Qinesiyya",
    "gn:country_code":"SD",
    "gn:dem":718,
    "gn:feature_class":"P",
    "gn:feature_code":"PPL",
    "gn:name":"Qinesiyya",
    "gn:population":0,
    "gn:timezone":"Africa/Khartoum",
    "iso:country":"SD",
    "wof:name":"Qinesiyya",
    "wof:placetype":"locality"
},
  "geometry": {"coordinates":[30.2867,11.6831],"type":"Point"}
}