{
  "type": "Feature",
  "properties": {
    "gn:admin1_code":"52.0",
    "gn:asciiname":"Maktab Taftish",
    "gn:country_code":"SD",
    "gn:dem":436,
    "gn:feature_class":"P",
    "gn:feature_code":"PPL",
    "gn:name":"Maktab Taftish",
    "gn:population":0,
    "gn:timezone":"Africa/Khartoum",
    "iso:country":"SD",
    "wof:name":"Maktab Taftish",
    "wof:placetype":"locality"
},
  "geometry": {"coordinates":[35.4979,15.659],"type":"Point"}
}