{
  "type": "Feature",
  "properties": {
    "gn:admin1_code":"60.0",
    "gn:asciiname":"Shaqq Tayyib",
    "gn:country_code":"SD",
    "gn:dem":460,
    "gn:feature_class":"P",
    "gn:feature_code":"PPL",
    "gn:name":"Shaqq \u0162ayyib",
    "gn:population":0,
    "gn:timezone":"Africa/Khartoum",
    "iso:country":"SD",
    "name:und_x_variant":[
        "Shaqq Taiyib",
        "Shaqq \u0162ayyib"
    ],
    "wof:name":"Shaqq Tayyib",
    "wof:placetype":"locality"
},
  "geometry": {"coordinates":[27.11667000000001,11.53333],"type":"Point"}
}