{
  "type": "Feature",
  "properties": {
    "gn:admin1_code":"50.0",
    "gn:asciiname":"Tabuli",
    "gn:country_code":"SD",
    "gn:dem":461,
    "gn:feature_class":"P",
    "gn:feature_code":"PPL",
    "gn:name":"Tabuli",
    "gn:population":0,
    "gn:timezone":"Africa/Khartoum",
    "iso:country":"SD",
    "wof:name":"Tabuli",
    "wof:placetype":"locality"
},
  "geometry": {"coordinates":[30.1776,10.62525],"type":"Point"}
}