{
  "type": "Feature",
  "properties": {
    "gn:admin1_code":"39.0",
    "gn:asciiname":"`Abbudah",
    "gn:country_code":"SD",
    "gn:dem":493,
    "gn:feature_class":"P",
    "gn:feature_code":"PPL",
    "gn:name":"\u2018Abb\u016bdah",
    "gn:population":0,
    "gn:timezone":"Africa/Khartoum",
    "iso:country":"SD",
    "name:und_x_variant":[
        "Abbuda",
        "\u2018Abb\u016bdah"
    ],
    "wof:name":"`Abbudah",
    "wof:placetype":"locality"
},
  "geometry": {"coordinates":[35.88333,14.33333],"type":"Point"}
}