{
  "type": "Feature",
  "properties": {
    "gn:admin1_code":"58.0",
    "gn:asciiname":"Senada",
    "gn:country_code":"SD",
    "gn:dem":435,
    "gn:feature_class":"P",
    "gn:feature_code":"PPL",
    "gn:name":"Senada",
    "gn:population":0,
    "gn:timezone":"Africa/Khartoum",
    "iso:country":"SD",
    "name:ara_x_preferred":[
        "\u0632\u0646\u0627\u062f\u0629"
    ],
    "name:cat_x_preferred":[
        "Senada"
    ],
    "name:ceb_x_preferred":[
        "Senada"
    ],
    "name:ita_x_preferred":[
        "Senada"
    ],
    "name:por_x_preferred":[
        "Snada"
    ],
    "name:spa_x_preferred":[
        "Snada"
    ],
    "name:swe_x_preferred":[
        "Senada"
    ],
    "name:urd_x_preferred":[
        "\u0632\u0646\u0627\u062f\u06c1"
    ],
    "wof:lang_x_official":[
        "ara",
        "eng"
    ],
    "wof:lang_x_spoken":[
        "ara",
        "eng"
    ],
    "wof:name":"Senada",
    "wof:placetype":"locality"
},
  "geometry": {"coordinates":[33.83333,13.03333],"type":"Point"}
}