{
  "type": "Feature",
  "properties": {
    "gn:admin1_code":"58.0",
    "gn:asciiname":"Senada",
    "gn:country_code":"SD",
    "gn:dem":435,
    "gn:feature_class":"P",
    "gn:feature_code":"PPL",
    "gn:name":"Senada",
    "gn:population":0,
    "gn:timezone":"Africa/Khartoum",
    "iso:country":"SD",
    "wof:name":"Senada",
    "wof:placetype":"locality"
},
  "geometry": {"coordinates":[33.83333,13.03333],"type":"Point"}
}