{
  "type": "Feature",
  "properties": {
    "gn:admin1_code":"55.0",
    "gn:asciiname":"Dardaqa",
    "gn:country_code":"SD",
    "gn:dem":555,
    "gn:feature_class":"P",
    "gn:feature_code":"PPL",
    "gn:name":"Dardaqa",
    "gn:population":0,
    "gn:timezone":"Africa/Khartoum",
    "iso:country":"SD",
    "wof:name":"Dardaqa",
    "wof:placetype":"locality"
},
  "geometry": {"coordinates":[26.93333,13.15],"type":"Point"}
}