{
  "type": "Feature",
  "properties": {
    "gn:country":"SD",
    "gn:fcode":"PPL",
    "gn:pop":22395,
    "iso:country":"SD",
    "name:ara_x_preferred":[
        "\u0628\u0631\u0628\u0631"
    ],
    "name:ben_x_preferred":[
        "\u09ac\u09be\u09b0\u09ac\u09be\u09b0"
    ],
    "name:cat_x_preferred":[
        "Berber"
    ],
    "name:dut_x_preferred":[
        "Berber"
    ],
    "name:eng_x_preferred":[
        "Berber"
    ],
    "name:ger_x_preferred":[
        "Barbar"
    ],
    "name:ita_x_preferred":[
        "Berber"
    ],
    "name:jpn_x_preferred":[
        "\u30d9\u30eb\u30d9\u30eb"
    ],
    "name:pol_x_preferred":[
        "Barbar"
    ],
    "name:por_x_preferred":[
        "Berber"
    ],
    "name:swe_x_preferred":[
        "Berber"
    ],
    "name:unk_x_variant":[
        "Barbar"
    ],
    "name:urd_x_preferred":[
        "\u0628\u0631\u0628\u0631\u060c \u0633\u0648\u0688\u0627\u0646"
    ],
    "ne:ADM0CAP":0.0,
    "ne:ADM0NAME":"Sudan",
    "ne:ADM0_A3":"SDN",
    "ne:ADM1NAME":"River Nile",
    "ne:ADMIN1_COD":30,
    "ne:CAPALT":0,
    "ne:CHANGED":4,
    "ne:CHECKME":0,
    "ne:COMPARE":0,
    "ne:DIFFASCII":0,
    "ne:DIFFNOTE":"Changed scale rank.",
    "ne:ELEVATION":0.0,
    "ne:FEATURECLA":"Populated place",
    "ne:FEATURE_CL":"P",
    "ne:FEATURE_CO":"PPL",
    "ne:GEONAMEID":377690,
    "ne:GEONAMESNO":"GeoNames spatial join with similar names only.",
    "ne:GN_ASCII":"Barbar",
    "ne:GN_POP":22395,
    "ne:GTOPO30":334.0,
    "ne:ISO_A2":"SD",
    "ne:LABELRANK":5,
    "ne:LATITUDE":18.017026,
    "ne:LONGITUDE":33.98329,
    "ne:LS_MATCH":1,
    "ne:LS_NAME":"Berber",
    "ne:MAX_AREAKM":20.0,
    "ne:MAX_AREAMI":8.0,
    "ne:MAX_BBXMAX":34.0,
    "ne:MAX_BBXMIN":33.966667,
    "ne:MAX_BBYMAX":18.091667,
    "ne:MAX_BBYMIN":17.983333,
    "ne:MAX_NATSCA":10.0,
    "ne:MAX_PERKM":30.0,
    "ne:MAX_PERMI":19.0,
    "ne:MAX_POP10":49556,
    "ne:MAX_POP20":0,
    "ne:MAX_POP300":0,
    "ne:MAX_POP310":0,
    "ne:MAX_POP50":0,
    "ne:MEAN_BBXC":33.984167,
    "ne:MEAN_BBYC":18.040833,
    "ne:MEGACITY":0,
    "ne:MIN_AREAKM":20.0,
    "ne:MIN_AREAMI":8.0,
    "ne:MIN_BBXMAX":34.0,
    "ne:MIN_BBXMIN":33.966667,
    "ne:MIN_BBYMAX":18.091667,
    "ne:MIN_BBYMIN":17.983333,
    "ne:MIN_PERKM":30.0,
    "ne:MIN_PERMI":19.0,
    "ne:NAME":"Berber",
    "ne:NAMEASCII":"Berber",
    "ne:NAMEDIFF":0,
    "ne:NATSCALE":20,
    "ne:POP1950":0,
    "ne:POP1955":0,
    "ne:POP1960":0,
    "ne:POP1965":0,
    "ne:POP1970":0,
    "ne:POP1975":0,
    "ne:POP1980":0,
    "ne:POP1985":0,
    "ne:POP1990":0,
    "ne:POP1995":0,
    "ne:POP2000":0,
    "ne:POP2005":0,
    "ne:POP2010":0,
    "ne:POP2015":0,
    "ne:POP2020":0,
    "ne:POP2025":0,
    "ne:POP2050":0,
    "ne:POP_MAX":49556,
    "ne:POP_MIN":22395,
    "ne:POP_OTHER":0,
    "ne:RANK_MAX":7,
    "ne:RANK_MIN":7,
    "ne:SCALERANK":7,
    "ne:SOV0NAME":"Sudan",
    "ne:SOV_A3":"SDN",
    "ne:TIMEZONE":"Africa/Khartoum",
    "ne:UN_FID":0,
    "ne:UN_LAT":0.0,
    "ne:UN_LONG":0.0,
    "ne:WORLDCITY":0,
    "qs:name":"Berber",
    "qs:photos_9r":0,
    "qs:photos_sr":0,
    "qs:pop_sr":"7",
    "wd:wordcount":147,
    "wof:name":"Berber",
    "wof:placetype":"locality",
    "wof:population":22395
},
  "geometry": {"coordinates":[33.98299,18.02158],"type":"Point"}
}