{
  "type": "Feature",
  "properties": {
    "gn:admin1_code":"41.0",
    "gn:asciiname":"`Id Aj Jim",
    "gn:country_code":"SD",
    "gn:dem":403,
    "gn:feature_class":"P",
    "gn:feature_code":"PPL",
    "gn:name":"\u2018Id Aj Jim",
    "gn:population":0,
    "gn:timezone":"Africa/Khartoum",
    "iso:country":"SD",
    "name:ara_x_preferred":[
        "\u2018Id Aj Jim"
    ],
    "wof:name":"`Id Aj Jim",
    "wof:placetype":"locality"
},
  "geometry": {"coordinates":[32.3115,12.5129],"type":"Point"}
}