{
  "type": "Feature",
  "properties": {
    "gn:admin1_code":"50.0",
    "gn:asciiname":"Alleira Kuta",
    "gn:country_code":"SD",
    "gn:dem":858,
    "gn:feature_class":"P",
    "gn:feature_code":"PPL",
    "gn:name":"Alleira Kuta",
    "gn:population":0,
    "gn:timezone":"Africa/Khartoum",
    "iso:country":"SD",
    "wof:name":"Alleira Kuta",
    "wof:placetype":"locality"
},
  "geometry": {"coordinates":[30.51667,11.36667],"type":"Point"}
}