{
  "type": "Feature",
  "properties": {
    "gn:admin1_code":"47.0",
    "gn:asciiname":"Bir Daqiq",
    "gn:country_code":"SD",
    "gn:dem":875,
    "gn:feature_class":"P",
    "gn:feature_code":"PPL",
    "gn:name":"Bir Daqiq",
    "gn:population":0,
    "gn:timezone":"Africa/Khartoum",
    "iso:country":"SD",
    "name:eng_x_preferred":[
        "Bir Daqiq"
    ],
    "name:und_x_variant":[
        "Bir Dagig",
        "Bi\u2019r Daq\u012bq"
    ],
    "wof:name":"Bir Daqiq",
    "wof:placetype":"locality"
},
  "geometry": {"coordinates":[22.48486,13.70348],"type":"Point"}
}