{
  "type": "Feature",
  "properties": {
    "gn:admin1_code":"61.0",
    "gn:asciiname":"Murundu",
    "gn:country_code":"SD",
    "gn:dem":787,
    "gn:feature_class":"P",
    "gn:feature_code":"PPL",
    "gn:name":"Murundu",
    "gn:population":0,
    "gn:timezone":"Africa/Khartoum",
    "iso:country":"SD",
    "wof:name":"Murundu",
    "wof:placetype":"locality"
},
  "geometry": {"coordinates":[23.14274,12.8375],"type":"Point"}
}