{
  "type": "Feature",
  "properties": {
    "gn:admin1_code":"58.0",
    "gn:asciiname":"Tayba al Qur`an",
    "gn:country_code":"SD",
    "gn:dem":448,
    "gn:feature_class":"P",
    "gn:feature_code":"PPL",
    "gn:name":"\u0162ayba al Qur\u2018\u0101n",
    "gn:population":0,
    "gn:timezone":"Africa/Khartoum",
    "iso:country":"SD",
    "name:und_x_variant":[
        "\u0162ayba al Qur\u2018\u0101n"
    ],
    "wof:lang_x_official":[
        "ara",
        "eng"
    ],
    "wof:lang_x_spoken":[
        "ara",
        "eng"
    ],
    "wof:name":"Tayba al Qur`an",
    "wof:placetype":"locality"
},
  "geometry": {"coordinates":[34.1514,12.6094],"type":"Point"}
}