{
  "type": "Feature",
  "properties": {
    "gn:admin1_code":"41.0",
    "gn:asciiname":"As Sawajir",
    "gn:country_code":"SD",
    "gn:dem":392,
    "gn:feature_class":"P",
    "gn:feature_code":"PPL",
    "gn:name":"As Sawaj\u012br",
    "gn:population":0,
    "gn:timezone":"Africa/Khartoum",
    "iso:country":"SD",
    "name:und_x_variant":[
        "As Sawaj\u012br"
    ],
    "wof:name":"As Sawajir",
    "wof:placetype":"locality"
},
  "geometry": {"coordinates":[32.353,13.4362],"type":"Point"}
}