{
  "type": "Feature",
  "properties": {
    "gn:admin1_code":"56.0",
    "gn:asciiname":"Sinnayn",
    "gn:country_code":"SD",
    "gn:dem":452,
    "gn:feature_class":"P",
    "gn:feature_code":"PPL",
    "gn:name":"Sinnayn",
    "gn:population":0,
    "gn:timezone":"Africa/Khartoum",
    "iso:country":"SD",
    "name:und_x_variant":[
        "Sinnein",
        "Sinnayn"
    ],
    "wof:name":"Sinnayn",
    "wof:placetype":"locality"
},
  "geometry": {"coordinates":[31.21667,13.08333],"type":"Point"}
}