{
  "type": "Feature",
  "properties": {
    "gn:admin1_code":"41.0",
    "gn:asciiname":"Kambu",
    "gn:country_code":"SD",
    "gn:dem":391,
    "gn:feature_class":"P",
    "gn:feature_code":"PPL",
    "gn:name":"Kambu",
    "gn:population":0,
    "gn:timezone":"Africa/Khartoum",
    "iso:country":"SD",
    "wof:name":"Kambu",
    "wof:placetype":"locality"
},
  "geometry": {"coordinates":[32.4284,14.1357],"type":"Point"}
}