{
  "type": "Feature",
  "properties": {
    "gn:admin1_code":"38.0",
    "gn:asciiname":"At Tekeina",
    "gn:country_code":"SD",
    "gn:dem":383,
    "gn:feature_class":"P",
    "gn:feature_code":"PPL",
    "gn:name":"At Tekeina",
    "gn:population":0,
    "gn:timezone":"Africa/Khartoum",
    "iso:country":"SD",
    "name:und_x_variant":[
        "Et Tekeina",
        "At Tekeina"
    ],
    "wof:name":"At Tekeina",
    "wof:placetype":"locality"
},
  "geometry": {"coordinates":[33.06667,15.21667],"type":"Point"}
}