{
  "type": "Feature",
  "properties": {
    "gn:admin1_code":"49.0",
    "gn:asciiname":"Barum Barum",
    "gn:country_code":"SD",
    "gn:dem":821,
    "gn:feature_class":"P",
    "gn:feature_code":"PPL",
    "gn:name":"Barum Barum",
    "gn:population":0,
    "gn:timezone":"Africa/Khartoum",
    "iso:country":"SD",
    "wof:name":"Barum Barum",
    "wof:placetype":"locality"
},
  "geometry": {"coordinates":[24.55,12.31667],"type":"Point"}
}