{
  "type": "Feature",
  "properties": {
    "gn:admin1_code":"50.0",
    "gn:asciiname":"Hillat Fagusa",
    "gn:country_code":"SD",
    "gn:dem":693,
    "gn:feature_class":"P",
    "gn:feature_code":"PPL",
    "gn:name":"Hillat Fagusa",
    "gn:population":0,
    "gn:timezone":"Africa/Khartoum",
    "iso:country":"SD",
    "wof:name":"Hillat Fagusa",
    "wof:placetype":"locality"
},
  "geometry": {"coordinates":[29.7456,11.8873],"type":"Point"}
}