{
  "type": "Feature",
  "properties": {
    "gn:admin1_code":"49.0",
    "gn:asciiname":"El Murraya",
    "gn:country_code":"SD",
    "gn:dem":496,
    "gn:feature_class":"P",
    "gn:feature_code":"PPL",
    "gn:name":"El Murraya",
    "gn:population":0,
    "gn:timezone":"Africa/Khartoum",
    "iso:country":"SD",
    "name:und_x_variant":[
        "Al Murr\u0101yah"
    ],
    "wof:name":"El Murraya",
    "wof:placetype":"locality"
},
  "geometry": {"coordinates":[24.97071,9.9302],"type":"Point"}
}