{
  "type": "Feature",
  "properties": {
    "gn:admin1_code":"50.0",
    "gn:asciiname":"Kachama",
    "gn:country_code":"SD",
    "gn:dem":940,
    "gn:feature_class":"P",
    "gn:feature_code":"PPL",
    "gn:name":"Kachama",
    "gn:population":0,
    "gn:timezone":"Africa/Khartoum",
    "iso:country":"SD",
    "wof:name":"Kachama",
    "wof:placetype":"locality"
},
  "geometry": {"coordinates":[30.53333,11.13333],"type":"Point"}
}