{
  "type": "Feature",
  "properties": {
    "gn:admin1_code":"27.0",
    "gn:asciiname":"Al Humur Jubara",
    "gn:country_code":"SD",
    "gn:dem":431,
    "gn:feature_class":"P",
    "gn:feature_code":"PPL",
    "gn:name":"Al \u1e28umur Jubara",
    "gn:population":0,
    "gn:timezone":"Africa/Khartoum",
    "iso:country":"SD",
    "name:und_x_variant":[
        "Humur",
        "\u1e28umr",
        "Al \u1e28umur Jubara"
    ],
    "wof:name":"Al Humur Jubara",
    "wof:placetype":"locality"
},
  "geometry": {"coordinates":[33.2767,14.0434],"type":"Point"}
}