{
  "type": "Feature",
  "properties": {
    "gn:admin1_code":"61.0",
    "gn:asciiname":"Kurro",
    "gn:country_code":"SD",
    "gn:dem":998,
    "gn:feature_class":"P",
    "gn:feature_code":"PPL",
    "gn:name":"Kurro",
    "gn:population":0,
    "gn:timezone":"Africa/Khartoum",
    "iso:country":"SD",
    "name:und_x_variant":[
        "Kourro",
        "Kurria",
        "Kurro"
    ],
    "wof:name":"Kurro",
    "wof:placetype":"locality"
},
  "geometry": {"coordinates":[23.48333,13.18333],"type":"Point"}
}