{
  "type": "Feature",
  "properties": {
    "gn:admin1_code":"41.0",
    "gn:asciiname":"Ash Shukri al `Aqaliyyin",
    "gn:country_code":"SD",
    "gn:dem":387,
    "gn:feature_class":"P",
    "gn:feature_code":"PPL",
    "gn:name":"Ash Shukri al \u2018Aqaliyyin",
    "gn:population":0,
    "gn:timezone":"Africa/Khartoum",
    "iso:country":"SD",
    "name:und_x_variant":[
        "Ash Shukri al \u2018Aqaliyyin"
    ],
    "wof:name":"Ash Shukri al `Aqaliyyin",
    "wof:placetype":"locality"
},
  "geometry": {"coordinates":[32.3471,14.2849],"type":"Point"}
}