{
  "type": "Feature",
  "properties": {
    "gn:admin1_code":"38.0",
    "gn:asciiname":"Umm Mulayhah",
    "gn:country_code":"SD",
    "gn:dem":410,
    "gn:feature_class":"P",
    "gn:feature_code":"PPL",
    "gn:name":"Umm Mulay\u1e29ah",
    "gn:population":0,
    "gn:timezone":"Africa/Khartoum",
    "iso:country":"SD",
    "name:und_x_variant":[
        "Umm Muleiha",
        "Umm Mulay\u1e29ah"
    ],
    "wof:lang_x_official":[
        "ara",
        "eng"
    ],
    "wof:lang_x_spoken":[
        "ara",
        "eng"
    ],
    "wof:name":"Umm Mulayhah",
    "wof:placetype":"locality"
},
  "geometry": {"coordinates":[32.95,13.96667],"type":"Point"}
}