{
  "type": "Feature",
  "properties": {
    "gn:admin1_code":"38.0",
    "gn:asciiname":"Mahala Ashshekh `Abd Allah",
    "gn:country_code":"SD",
    "gn:dem":401,
    "gn:feature_class":"P",
    "gn:feature_code":"PPL",
    "gn:name":"Mahala Ashshekh \u2018Abd Allah",
    "gn:population":0,
    "gn:timezone":"Africa/Khartoum",
    "iso:country":"SD",
    "name:und_x_variant":[
        "Mahala Ashshekh \u2018Abd Allah"
    ],
    "wof:name":"Mahala Ashshekh `Abd Allah",
    "wof:placetype":"locality"
},
  "geometry": {"coordinates":[32.876,14.494],"type":"Point"}
}