{
  "type": "Feature",
  "properties": {
    "gn:admin1_code":"58.0",
    "gn:asciiname":"Shab`ana",
    "gn:country_code":"SD",
    "gn:dem":454,
    "gn:feature_class":"P",
    "gn:feature_code":"PPL",
    "gn:name":"Shab\u2018\u0101na",
    "gn:population":0,
    "gn:timezone":"Africa/Khartoum",
    "iso:country":"SD",
    "name:und_x_variant":[
        "Shab\u2018\u0101na"
    ],
    "wof:name":"Shab`ana",
    "wof:placetype":"locality"
},
  "geometry": {"coordinates":[34.6271,12.8893],"type":"Point"}
}