{
  "type": "Feature",
  "properties": {
    "gn:admin1_code":"38.0",
    "gn:asciiname":"`Amarat `Ali",
    "gn:country_code":"SD",
    "gn:dem":421,
    "gn:feature_class":"P",
    "gn:feature_code":"PPL",
    "gn:name":"\u2018Am\u0101rat \u2018Al\u012b",
    "gn:population":0,
    "gn:timezone":"Africa/Khartoum",
    "iso:country":"SD",
    "wof:name":"`Amarat `Ali",
    "wof:placetype":"locality"
},
  "geometry": {"coordinates":[33.66667,14.58333],"type":"Point"}
}