{
  "type": "Feature",
  "properties": {
    "gn:admin1_code":"47.0",
    "gn:asciiname":"Howanakerak",
    "gn:country_code":"SD",
    "gn:dem":861,
    "gn:feature_class":"P",
    "gn:feature_code":"PPL",
    "gn:name":"Howanakerak",
    "gn:population":0,
    "gn:timezone":"Africa/Khartoum",
    "iso:country":"SD",
    "name:eng_x_preferred":[
        "Howanakerak"
    ],
    "wof:name":"Howanakerak",
    "wof:placetype":"locality"
},
  "geometry": {"coordinates":[22.1767,13.69172],"type":"Point"}
}