{
  "type": "Feature",
  "properties": {
    "gn:admin1_code":"50.0",
    "gn:asciiname":"Umm Duju",
    "gn:country_code":"SD",
    "gn:dem":575,
    "gn:feature_class":"P",
    "gn:feature_code":"PPL",
    "gn:name":"Umm Duj\u016b",
    "gn:population":0,
    "gn:timezone":"Africa/Khartoum",
    "iso:country":"SD",
    "name:ara_x_preferred":[
        "Umm Duj\u016b"
    ],
    "wof:name":"Umm Duju",
    "wof:placetype":"locality"
},
  "geometry": {"coordinates":[29.5264,11.1147],"type":"Point"}
}