{
  "type": "Feature",
  "properties": {
    "gn:admin1_code":"43.0",
    "gn:asciiname":"Mansurkotti",
    "gn:country_code":"SD",
    "gn:dem":252,
    "gn:feature_class":"P",
    "gn:feature_code":"PPL",
    "gn:name":"Mansurkotti",
    "gn:population":0,
    "gn:timezone":"Africa/Khartoum",
    "iso:country":"SD",
    "name:und_x_variant":[
        "Mansur Koti",
        "Mansurkotti"
    ],
    "wof:name":"Mansurkotti",
    "wof:placetype":"locality"
},
  "geometry": {"coordinates":[31.33333,18.03333],"type":"Point"}
}