{
  "type": "Feature",
  "properties": {
    "gn:admin1_code":"53.0",
    "gn:asciiname":"Hawad",
    "gn:country_code":"SD",
    "gn:dem":369,
    "gn:feature_class":"P",
    "gn:feature_code":"PPL",
    "gn:name":"Hawad",
    "gn:population":0,
    "gn:timezone":"Africa/Khartoum",
    "iso:country":"SD",
    "name:ara_x_preferred":[
        "\u0645\u062d\u0645\u062f\u064a\u0646 \u062e\u0648\u0627\u062f"
    ],
    "name:deu_x_preferred":[
        "Hawad"
    ],
    "name:fra_x_preferred":[
        "Hawad"
    ],
    "name:glg_x_preferred":[
        "Hawad"
    ],
    "wof:name":"Hawad",
    "wof:placetype":"locality"
},
  "geometry": {"coordinates":[34.65,17.25],"type":"Point"}
}