{
  "type": "Feature",
  "properties": {
    "gn:admin1_code":"56.0",
    "gn:asciiname":"Umm Daymayn",
    "gn:country_code":"SD",
    "gn:dem":414,
    "gn:feature_class":"P",
    "gn:feature_code":"PPL",
    "gn:name":"Umm Daymayn",
    "gn:population":0,
    "gn:timezone":"Africa/Khartoum",
    "iso:country":"SD",
    "name:und_x_variant":[
        "Umm Deimin",
        "Umm Deimein",
        "Umm Daymayn"
    ],
    "wof:lang_x_official":[
        "ara",
        "eng"
    ],
    "wof:lang_x_spoken":[
        "ara",
        "eng"
    ],
    "wof:name":"Umm Daymayn",
    "wof:placetype":"locality"
},
  "geometry": {"coordinates":[31.13333,14.41667],"type":"Point"}
}