{
  "type": "Feature",
  "properties": {
    "gn:admin1_code":"50.0",
    "gn:asciiname":"Qindil",
    "gn:country_code":"SD",
    "gn:dem":545,
    "gn:feature_class":"P",
    "gn:feature_code":"PPL",
    "gn:name":"Qind\u012bl",
    "gn:population":0,
    "gn:timezone":"Africa/Khartoum",
    "iso:country":"SD",
    "name:und_x_variant":[
        "Qandil",
        "Qind\u012bl"
    ],
    "wof:name":"Qindil",
    "wof:placetype":"locality"
},
  "geometry": {"coordinates":[31.66667,11.56667],"type":"Point"}
}