{
  "type": "Feature",
  "properties": {
    "gn:admin1_code":"38.0",
    "gn:asciiname":"Shasha",
    "gn:country_code":"SD",
    "gn:dem":408,
    "gn:feature_class":"P",
    "gn:feature_code":"PPL",
    "gn:name":"Sh\u0101sha",
    "gn:population":0,
    "gn:timezone":"Africa/Khartoum",
    "iso:country":"SD",
    "name:ceb_x_preferred":[
        "Shasha"
    ],
    "name:heb_x_preferred":[
        "\u05e9\u05d0\u05e9\u05d0"
    ],
    "name:swe_x_preferred":[
        "Shasha"
    ],
    "name:ukr_x_preferred":[
        "\u0428\u0430\u0448\u0430"
    ],
    "name:und_x_variant":[
        "Sh\u0101sha"
    ],
    "wof:name":"Shasha",
    "wof:placetype":"locality"
},
  "geometry": {"coordinates":[32.985,14.3262],"type":"Point"}
}