{
  "type": "Feature",
  "properties": {
    "gn:admin1_code":"47.0",
    "gn:asciiname":"Merise",
    "gn:country_code":"SD",
    "gn:dem":568,
    "gn:feature_class":"P",
    "gn:feature_code":"PPL",
    "gn:name":"Merise",
    "gn:population":0,
    "gn:timezone":"Africa/Khartoum",
    "iso:country":"SD",
    "name:fra_x_preferred":[
        "Merise"
    ],
    "name:nld_x_preferred":[
        "Merise"
    ],
    "wof:name":"Merise",
    "wof:placetype":"locality"
},
  "geometry": {"coordinates":[22.50696,12.04978],"type":"Point"}
}