{
  "type": "Feature",
  "properties": {
    "gn:admin1_code":"53.0",
    "gn:asciiname":"Al Hajar",
    "gn:cc2":"SD",
    "gn:country_code":"SD",
    "gn:dem":369,
    "gn:feature_class":"P",
    "gn:feature_code":"PPL",
    "gn:name":"Al \u1e28ajar",
    "gn:population":0,
    "gn:timezone":"Africa/Khartoum",
    "iso:country":"SD",
    "name:und_x_variant":[
        "El Hagar",
        "Al \u1e28ajar"
    ],
    "wof:name":"Al Hajar",
    "wof:placetype":"locality"
},
  "geometry": {"coordinates":[34.72972,17.1475],"type":"Point"}
}