{
  "type": "Feature",
  "properties": {
    "gn:admin1_code":"49.0",
    "gn:asciiname":"Amergu",
    "gn:country_code":"SD",
    "gn:dem":469,
    "gn:feature_class":"P",
    "gn:feature_code":"PPL",
    "gn:name":"Amergu",
    "gn:population":0,
    "gn:timezone":"Africa/Khartoum",
    "iso:country":"SD",
    "wof:name":"Amergu",
    "wof:placetype":"locality"
},
  "geometry": {"coordinates":[25.16667,10.56667],"type":"Point"}
}