{
  "type": "Feature",
  "properties": {
    "gn:admin1_code":"58.0",
    "gn:asciiname":"Khawr al Fil",
    "gn:country_code":"SD",
    "gn:dem":429,
    "gn:feature_class":"P",
    "gn:feature_code":"PPL",
    "gn:name":"Khawr al F\u012bl",
    "gn:population":0,
    "gn:timezone":"Africa/Khartoum",
    "iso:country":"SD",
    "name:und_x_variant":[
        "Khor el Fil",
        "Khawr al F\u012bl"
    ],
    "wof:lang_x_official":[
        "ara",
        "eng"
    ],
    "wof:lang_x_spoken":[
        "ara",
        "eng"
    ],
    "wof:name":"Khawr al Fil",
    "wof:placetype":"locality"
},
  "geometry": {"coordinates":[33.83333,13.41667],"type":"Point"}
}