{
  "type": "Feature",
  "properties": {
    "gn:admin1_code":"56.0",
    "gn:asciiname":"Umm Buraysh",
    "gn:country_code":"SD",
    "gn:dem":437,
    "gn:feature_class":"P",
    "gn:feature_code":"PPL",
    "gn:name":"Umm Buraysh",
    "gn:population":0,
    "gn:timezone":"Africa/Khartoum",
    "iso:country":"SD",
    "name:und_x_variant":[
        "Umm Breish",
        "Umm Bereish",
        "Umm Buraysh"
    ],
    "wof:name":"Umm Buraysh",
    "wof:placetype":"locality"
},
  "geometry": {"coordinates":[31.33333,13.46667],"type":"Point"}
}