{
  "type": "Feature",
  "properties": {
    "gn:admin1_code":"31.0",
    "gn:asciiname":"Humari",
    "gn:cc2":"SD",
    "gn:country_code":"SD",
    "gn:dem":403,
    "gn:feature_class":"P",
    "gn:feature_code":"PPL",
    "gn:name":"\u1e28umar\u012b",
    "gn:population":0,
    "gn:timezone":"Africa/Khartoum",
    "iso:country":"SD",
    "name:und_x_variant":[
        "Homari",
        "\u1e28umar\u012b"
    ],
    "wof:lang_x_official":[
        "ara",
        "eng"
    ],
    "wof:lang_x_spoken":[
        "ara",
        "eng"
    ],
    "wof:name":"Humari",
    "wof:placetype":"locality"
},
  "geometry": {"coordinates":[35.28333,16.35],"type":"Point"}
}