{
  "type": "Feature",
  "properties": {
    "gn:admin1_code":"38.0",
    "gn:asciiname":"Hillat al Qwez",
    "gn:country_code":"SD",
    "gn:dem":393,
    "gn:feature_class":"P",
    "gn:feature_code":"PPL",
    "gn:name":"Hillat al Qwez",
    "gn:population":0,
    "gn:timezone":"Africa/Khartoum",
    "iso:country":"SD",
    "name:und_x_variant":[
        "Quweia",
        "Hillat al Qwez"
    ],
    "wof:name":"Hillat al Qwez",
    "wof:placetype":"locality"
},
  "geometry": {"coordinates":[32.8593,15.0375],"type":"Point"}
}