{
  "type": "Feature",
  "properties": {
    "gn:admin1_code":"38.0",
    "gn:asciiname":"Qutayfab",
    "gn:country_code":"SD",
    "gn:dem":394,
    "gn:feature_class":"P",
    "gn:feature_code":"PPL",
    "gn:name":"Qu\u0163ayf\u0101b",
    "gn:population":0,
    "gn:timezone":"Africa/Khartoum",
    "iso:country":"SD",
    "name:und_x_variant":[
        "Qiteifab",
        "Qu\u0163ayf\u0101b"
    ],
    "wof:name":"Qutayfab",
    "wof:placetype":"locality"
},
  "geometry": {"coordinates":[32.78333,14.98333],"type":"Point"}
}