{
  "type": "Feature",
  "properties": {
    "gn:admin1_code":"49.0",
    "gn:asciiname":"Hammur",
    "gn:country_code":"SD",
    "gn:dem":483,
    "gn:feature_class":"P",
    "gn:feature_code":"PPL",
    "gn:name":"Hammur",
    "gn:population":0,
    "gn:timezone":"Africa/Khartoum",
    "iso:country":"SD",
    "wof:name":"Hammur",
    "wof:placetype":"locality"
},
  "geometry": {"coordinates":[24.87565,10.59936],"type":"Point"}
}