{
  "type": "Feature",
  "properties": {
    "gn:admin1_code":"62.0",
    "gn:asciiname":"Zakfero",
    "gn:country_code":"SD",
    "gn:dem":506,
    "gn:feature_class":"P",
    "gn:feature_code":"PPL",
    "gn:name":"Zakfero",
    "gn:population":0,
    "gn:timezone":"Africa/Khartoum",
    "iso:country":"SD",
    "wof:name":"Zakfero",
    "wof:placetype":"locality"
},
  "geometry": {"coordinates":[27.58333,12.16667],"type":"Point"}
}