{
  "type": "Feature",
  "properties": {
    "gn:admin1_code":"58.0",
    "gn:asciiname":"Al `Aradeiba Jazirah",
    "gn:country_code":"SD",
    "gn:dem":429,
    "gn:feature_class":"P",
    "gn:feature_code":"PPL",
    "gn:name":"Al \u2018Aradeiba Jaz\u012brah",
    "gn:population":0,
    "gn:timezone":"Africa/Khartoum",
    "iso:country":"SD",
    "name:und_x_variant":[
        "El \u2018Aradeiba Gezira",
        "Al \u2018Aradeiba Jaz\u012brah"
    ],
    "wof:name":"Al `Aradeiba Jazirah",
    "wof:placetype":"locality"
},
  "geometry": {"coordinates":[34.03333,13.41667],"type":"Point"}
}