{
  "type": "Feature",
  "properties": {
    "gn:admin1_code":"41.0",
    "gn:asciiname":"Al Qile`a",
    "gn:country_code":"SD",
    "gn:dem":395,
    "gn:feature_class":"P",
    "gn:feature_code":"PPL",
    "gn:name":"Al Qile\u2018a",
    "gn:population":0,
    "gn:timezone":"Africa/Khartoum",
    "iso:country":"SD",
    "name:und_x_variant":[
        "Kuna",
        "El Qulei\u2018a",
        "Al Qulay\u2018ah",
        "Al Qile\u2018a"
    ],
    "wof:name":"Al Qile`a",
    "wof:placetype":"locality"
},
  "geometry": {"coordinates":[32.5614,12.8949],"type":"Point"}
}