{
  "type": "Feature",
  "properties": {
    "gn:admin1_code":"52.0",
    "gn:asciiname":"Hillat al Sab`at",
    "gn:country_code":"SD",
    "gn:dem":433,
    "gn:feature_class":"P",
    "gn:feature_code":"PPL",
    "gn:name":"Hillat al Sab\u2018at",
    "gn:population":0,
    "gn:timezone":"Africa/Khartoum",
    "iso:country":"SD",
    "name:und_x_variant":[
        "Hillat al Sab\u2018at"
    ],
    "wof:name":"Hillat al Sab`at",
    "wof:placetype":"locality"
},
  "geometry": {"coordinates":[35.4455,15.7167],"type":"Point"}
}