{
  "type": "Feature",
  "properties": {
    "gn:admin1_code":"61.0",
    "gn:asciiname":"Kulli",
    "gn:country_code":"SD",
    "gn:dem":1184,
    "gn:feature_class":"P",
    "gn:feature_code":"PPL",
    "gn:name":"Kulli",
    "gn:population":0,
    "gn:timezone":"Africa/Khartoum",
    "iso:country":"SD",
    "wof:name":"Kulli",
    "wof:placetype":"locality"
},
  "geometry": {"coordinates":[24.05148,12.96313],"type":"Point"}
}