{
  "type": "Feature",
  "properties": {
    "gn:admin1_code":"56.0",
    "gn:asciiname":"Baqbaqi",
    "gn:country_code":"SD",
    "gn:dem":498,
    "gn:feature_class":"P",
    "gn:feature_code":"PPL",
    "gn:name":"Baqbaq\u012b",
    "gn:population":0,
    "gn:timezone":"Africa/Khartoum",
    "iso:country":"SD",
    "name:und_x_variant":[
        "Bagbagi",
        "Baqbaq\u012b"
    ],
    "wof:name":"Baqbaqi",
    "wof:placetype":"locality"
},
  "geometry": {"coordinates":[30.46667,13.51667],"type":"Point"}
}