{
  "type": "Feature",
  "properties": {
    "gn:admin1_code":"38.0",
    "gn:asciiname":"Awaida",
    "gn:country_code":"SD",
    "gn:dem":425,
    "gn:feature_class":"P",
    "gn:feature_code":"PPL",
    "gn:name":"Awaida",
    "gn:population":0,
    "gn:timezone":"Africa/Khartoum",
    "iso:country":"SD",
    "wof:name":"Awaida",
    "wof:placetype":"locality"
},
  "geometry": {"coordinates":[33.36167,15.23917],"type":"Point"}
}