{
  "type": "Feature",
  "properties": {
    "gn:admin1_code":"49.0",
    "gn:asciiname":"Nuni",
    "gn:country_code":"SD",
    "gn:dem":448,
    "gn:feature_class":"P",
    "gn:feature_code":"PPL",
    "gn:name":"Nuni",
    "gn:population":0,
    "gn:timezone":"Africa/Khartoum",
    "iso:country":"SD",
    "wof:name":"Nuni",
    "wof:placetype":"locality"
},
  "geometry": {"coordinates":[25.73653,10.42922],"type":"Point"}
}