{
  "type": "Feature",
  "properties": {
    "gn:admin1_code":"49.0",
    "gn:asciiname":"Fatala",
    "gn:country_code":"SD",
    "gn:dem":1481,
    "gn:feature_class":"P",
    "gn:feature_code":"PPL",
    "gn:name":"Fatala",
    "gn:population":0,
    "gn:timezone":"Africa/Khartoum",
    "iso:country":"SD",
    "wof:name":"Fatala",
    "wof:placetype":"locality"
},
  "geometry": {"coordinates":[24.50466,13.03125],"type":"Point"}
}