{
  "type": "Feature",
  "properties": {
    "gn:admin1_code":"38.0",
    "gn:asciiname":"Al Baraqna",
    "gn:country_code":"SD",
    "gn:dem":446,
    "gn:feature_class":"P",
    "gn:feature_code":"PPL",
    "gn:name":"Al Bar\u0101qna",
    "gn:population":0,
    "gn:timezone":"Africa/Khartoum",
    "iso:country":"SD",
    "name:und_x_variant":[
        "El Baragna",
        "Baragna",
        "Al Baragna",
        "Al Bar\u0101qna"
    ],
    "wof:name":"Al Baraqna",
    "wof:placetype":"locality"
},
  "geometry": {"coordinates":[33.1354,14.0978],"type":"Point"}
}