{
  "type": "Feature",
  "properties": {
    "gn:admin1_code":"41.0",
    "gn:asciiname":"Al `Amara",
    "gn:country_code":"SD",
    "gn:dem":385,
    "gn:feature_class":"P",
    "gn:feature_code":"PPL",
    "gn:name":"Al \u2018Am\u0101ra",
    "gn:population":0,
    "gn:timezone":"Africa/Khartoum",
    "iso:country":"SD",
    "name:und_x_variant":[
        "Al \u2018Am\u0101ra"
    ],
    "wof:name":"Al `Amara",
    "wof:placetype":"locality"
},
  "geometry": {"coordinates":[32.28,13.9013],"type":"Point"}
}