{
  "type": "Feature",
  "properties": {
    "gn:admin1_code":"38.0",
    "gn:asciiname":"Tarfaya",
    "gn:country_code":"SD",
    "gn:dem":402,
    "gn:feature_class":"P",
    "gn:feature_code":"PPL",
    "gn:name":"\u0162arfaya",
    "gn:population":0,
    "gn:timezone":"Africa/Khartoum",
    "iso:country":"SD",
    "name:und_x_variant":[
        "\u0162arfaya"
    ],
    "wof:name":"Tarfaya",
    "wof:placetype":"locality"
},
  "geometry": {"coordinates":[33.098,14.6942],"type":"Point"}
}