{
  "type": "Feature",
  "properties": {
    "gn:admin1_code":"38.0",
    "gn:asciiname":"Tarfaya",
    "gn:country_code":"SD",
    "gn:dem":402,
    "gn:feature_class":"P",
    "gn:feature_code":"PPL",
    "gn:name":"\u0162arfaya",
    "gn:population":0,
    "gn:timezone":"Africa/Khartoum",
    "iso:country":"SD",
    "name:ara_x_preferred":[
        "\u0637\u0631\u0641\u0627\u064a\u0629"
    ],
    "name:azb_x_preferred":[
        "\u0637\u0631\u0641\u0627\u06cc\u0647"
    ],
    "name:cat_x_preferred":[
        "Tarfaya"
    ],
    "name:ceb_x_preferred":[
        "Tarfaya"
    ],
    "name:ces_x_preferred":[
        "Tarfaja"
    ],
    "name:dan_x_preferred":[
        "Tarfaya"
    ],
    "name:deu_x_preferred":[
        "Tarfaya"
    ],
    "name:eus_x_preferred":[
        "Tarfaya"
    ],
    "name:fas_x_preferred":[
        "\u0637\u0631\u0641\u0627\u06cc\u0647"
    ],
    "name:fra_x_preferred":[
        "Tarfaya"
    ],
    "name:ita_x_preferred":[
        "Tarfaya"
    ],
    "name:jpn_x_preferred":[
        "\u30bf\u30eb\u30d5\u30a1\u30e4"
    ],
    "name:lit_x_preferred":[
        "Tarfaja"
    ],
    "name:nld_x_preferred":[
        "Tarfaya"
    ],
    "name:nor_x_preferred":[
        "Tarfaya"
    ],
    "name:pol_x_preferred":[
        "Tarfaja"
    ],
    "name:por_x_preferred":[
        "Tarfaya"
    ],
    "name:ron_x_preferred":[
        "Tarfaya"
    ],
    "name:rus_x_preferred":[
        "\u0422\u0430\u0440\u0444\u0430\u044f"
    ],
    "name:spa_x_preferred":[
        "Tarfaya"
    ],
    "name:swe_x_preferred":[
        "Tarfaya"
    ],
    "name:ukr_x_preferred":[
        "\u0422\u0430\u0440\u0444\u0430\u0439\u044f"
    ],
    "name:und_x_variant":[
        "\u0162arfaya"
    ],
    "name:zho_x_preferred":[
        "\u5854\u5c14\u6cd5\u4e9a"
    ],
    "wof:name":"Tarfaya",
    "wof:placetype":"locality"
},
  "geometry": {"coordinates":[33.098,14.6942],"type":"Point"}
}