{
  "type": "Feature",
  "properties": {
    "gn:admin1_code":"52.0",
    "gn:asciiname":"Sarra East",
    "gn:country_code":"SD",
    "gn:dem":462,
    "gn:feature_class":"P",
    "gn:feature_code":"PPL",
    "gn:name":"Sarra East",
    "gn:population":0,
    "gn:timezone":"Africa/Khartoum",
    "iso:country":"SD",
    "wof:name":"Sarra East",
    "wof:placetype":"locality"
},
  "geometry": {"coordinates":[35.76667,15.18333],"type":"Point"}
}