{
  "type": "Feature",
  "properties": {
    "gn:admin1_code":"47.0",
    "gn:asciiname":"Beida",
    "gn:country_code":"SD",
    "gn:dem":796,
    "gn:feature_class":"P",
    "gn:feature_code":"PPL",
    "gn:name":"Beida",
    "gn:population":0,
    "gn:timezone":"Africa/Khartoum",
    "iso:country":"SD",
    "name:ceb_x_preferred":[
        "Beida"
    ],
    "name:eng_x_preferred":[
        "Beida"
    ],
    "name:fra_x_preferred":[
        "Beida"
    ],
    "name:nld_x_preferred":[
        "Beida"
    ],
    "name:swe_x_preferred":[
        "Beida"
    ],
    "wof:name":"Beida",
    "wof:placetype":"locality"
},
  "geometry": {"coordinates":[22.23573,12.81542],"type":"Point"}
}