{
  "type": "Feature",
  "properties": {
    "gn:admin1_code":"47.0",
    "gn:asciiname":"Manzula",
    "gn:country_code":"SD",
    "gn:dem":849,
    "gn:feature_class":"P",
    "gn:feature_code":"PPL",
    "gn:name":"Manzula",
    "gn:population":0,
    "gn:timezone":"Africa/Khartoum",
    "iso:country":"SD",
    "name:und_x_variant":[
        "Manz\u016blah"
    ],
    "wof:name":"Manzula",
    "wof:placetype":"locality"
},
  "geometry": {"coordinates":[22.45996,13.22316],"type":"Point"}
}