{
  "type": "Feature",
  "properties": {
    "gn:admin1_code":"38.0",
    "gn:asciiname":"At Tayyarah",
    "gn:country_code":"SD",
    "gn:dem":411,
    "gn:feature_class":"P",
    "gn:feature_code":"PPL",
    "gn:name":"A\u0163 \u0162ayy\u0101rah",
    "gn:population":0,
    "gn:timezone":"Africa/Khartoum",
    "iso:country":"SD",
    "name:und_x_variant":[
        "Et Taiyara",
        "A\u0163 \u0162ayy\u0101rah"
    ],
    "wof:name":"At Tayyarah",
    "wof:placetype":"locality"
},
  "geometry": {"coordinates":[33.31667,14.13333],"type":"Point"}
}