{
  "type": "Feature",
  "properties": {
    "gn:admin1_code":"56.0",
    "gn:asciiname":"Umm `Ushayrah",
    "gn:country_code":"SD",
    "gn:dem":518,
    "gn:feature_class":"P",
    "gn:feature_code":"PPL",
    "gn:name":"Umm \u2018Ushayrah",
    "gn:population":0,
    "gn:timezone":"Africa/Khartoum",
    "iso:country":"SD",
    "name:und_x_variant":[
        "Umm \u2018Ushira",
        "Umm \u2018Usheira",
        "Umm \u2018Ushayrah"
    ],
    "wof:name":"Umm `Ushayrah",
    "wof:placetype":"locality"
},
  "geometry": {"coordinates":[30.01667,13.88333],"type":"Point"}
}