{
  "type": "Feature",
  "properties": {
    "gn:admin1_code":"52.0",
    "gn:asciiname":"Maktab Arba`ah wa `Ishrun al Sabat Gharb",
    "gn:country_code":"SD",
    "gn:dem":425,
    "gn:feature_class":"P",
    "gn:feature_code":"PPL",
    "gn:name":"Maktab Arba\u2018ah wa \u2018Ishr\u016bn al Sabat Gharb",
    "gn:population":0,
    "gn:timezone":"Africa/Khartoum",
    "iso:country":"SD",
    "name:und_x_variant":[
        "Maktab Arba\u2018ah wa \u2018Ishr\u016bn al Sabat Gharb"
    ],
    "wof:name":"Maktab Arba`ah wa `Ishrun al Sabat Gharb",
    "wof:placetype":"locality"
},
  "geometry": {"coordinates":[35.3665,15.752],"type":"Point"}
}