{
  "type": "Feature",
  "properties": {
    "gn:admin1_code":"55.0",
    "gn:asciiname":"Udu",
    "gn:country_code":"SD",
    "gn:dem":1071,
    "gn:feature_class":"P",
    "gn:feature_code":"PPL",
    "gn:name":"Udu",
    "gn:population":0,
    "gn:timezone":"Africa/Khartoum",
    "iso:country":"SD",
    "name:bul_x_preferred":[
        "\u0423\u0434\u0443"
    ],
    "name:cat_x_preferred":[
        "Udu"
    ],
    "name:ces_x_preferred":[
        "Udu"
    ],
    "name:deu_x_preferred":[
        "Udu"
    ],
    "name:fas_x_preferred":[
        "\u06a9\u0648\u0632\u0647"
    ],
    "name:fin_x_preferred":[
        "Udu"
    ],
    "name:fra_x_preferred":[
        "Udu"
    ],
    "name:ind_x_preferred":[
        "Udu"
    ],
    "name:mal_x_preferred":[
        "\u0d09\u0d26\u0d41"
    ],
    "name:nld_x_preferred":[
        "Udu"
    ],
    "name:pol_x_preferred":[
        "Udu"
    ],
    "name:por_x_preferred":[
        "Udu"
    ],
    "name:rus_x_preferred":[
        "\u0423\u0434\u0443"
    ],
    "name:slk_x_preferred":[
        "Udu"
    ],
    "name:spa_x_preferred":[
        "Udu"
    ],
    "wof:name":"Udu",
    "wof:placetype":"locality"
},
  "geometry": {"coordinates":[23.82662,13.38756],"type":"Point"}
}