{
  "type": "Feature",
  "properties": {
    "gn:admin1_code":"55.0",
    "gn:asciiname":"Udu",
    "gn:country_code":"SD",
    "gn:dem":1071,
    "gn:feature_class":"P",
    "gn:feature_code":"PPL",
    "gn:name":"Udu",
    "gn:population":0,
    "gn:timezone":"Africa/Khartoum",
    "iso:country":"SD",
    "wof:name":"Udu",
    "wof:placetype":"locality"
},
  "geometry": {"coordinates":[23.82662,13.38756],"type":"Point"}
}