{
  "type": "Feature",
  "properties": {
    "gn:admin1_code":"36.0",
    "gn:asciiname":"Hillat Mohammad Sa'di",
    "gn:country_code":"SD",
    "gn:dem":25,
    "gn:feature_class":"P",
    "gn:feature_code":"PPL",
    "gn:name":"Hillat Mohammad Sa\u2019di",
    "gn:population":0,
    "gn:timezone":"Africa/Khartoum",
    "iso:country":"SD",
    "name:und_x_variant":[
        "Hillat Mohammad Sa\u2019di"
    ],
    "wof:name":"Hillat Mohammad Sa'di",
    "wof:placetype":"locality"
},
  "geometry": {"coordinates":[37.8545,18.2682],"type":"Point"}
}