{
  "type": "Feature",
  "properties": {
    "gn:admin1_code":"47.0",
    "gn:asciiname":"Guranei",
    "gn:country_code":"SD",
    "gn:dem":803,
    "gn:feature_class":"P",
    "gn:feature_code":"PPL",
    "gn:name":"Guranei",
    "gn:population":0,
    "gn:timezone":"Africa/Khartoum",
    "iso:country":"SD",
    "name:eng_x_preferred":[
        "Guranei"
    ],
    "wof:name":"Guranei",
    "wof:placetype":"locality"
},
  "geometry": {"coordinates":[22.43268,13.42463],"type":"Point"}
}