{
  "type": "Feature",
  "properties": {
    "gn:admin1_code":"38.0",
    "gn:asciiname":"Al `Awayda `Iweda",
    "gn:country_code":"SD",
    "gn:dem":416,
    "gn:feature_class":"P",
    "gn:feature_code":"PPL",
    "gn:name":"Al \u2018Awayda \u2018Iwe\u1e11a",
    "gn:population":0,
    "gn:timezone":"Africa/Khartoum",
    "iso:country":"SD",
    "name:und_x_variant":[
        "Fawaida Uweida",
        "Al \u2018Awayda \u2018Iwe\u1e11a"
    ],
    "wof:name":"Al `Awayda `Iweda",
    "wof:placetype":"locality"
},
  "geometry": {"coordinates":[33.4723,14.1387],"type":"Point"}
}