{
  "type": "Feature",
  "properties": {
    "gn:admin1_code":"38.0",
    "gn:asciiname":"Wad Faraj Allah",
    "gn:country_code":"SD",
    "gn:dem":402,
    "gn:feature_class":"P",
    "gn:feature_code":"PPL",
    "gn:name":"Wad Faraj Allah",
    "gn:population":0,
    "gn:timezone":"Africa/Khartoum",
    "iso:country":"SD",
    "wof:name":"Wad Faraj Allah",
    "wof:placetype":"locality"
},
  "geometry": {"coordinates":[33.1312,14.5654],"type":"Point"}
}