{
  "type": "Feature",
  "properties": {
    "gn:admin1_code":"41.0",
    "gn:asciiname":"Qileb Assrriyya",
    "gn:country_code":"SD",
    "gn:dem":386,
    "gn:feature_class":"P",
    "gn:feature_code":"PPL",
    "gn:name":"Qileb Assrriyya",
    "gn:population":0,
    "gn:timezone":"Africa/Khartoum",
    "iso:country":"SD",
    "wof:name":"Qileb Assrriyya",
    "wof:placetype":"locality"
},
  "geometry": {"coordinates":[32.1317,13.8623],"type":"Point"}
}