{
  "type": "Feature",
  "properties": {
    "gn:admin1_code":"56.0",
    "gn:asciiname":"Marakha",
    "gn:country_code":"SD",
    "gn:dem":482,
    "gn:feature_class":"P",
    "gn:feature_code":"PPL",
    "gn:name":"Marakha",
    "gn:population":0,
    "gn:timezone":"Africa/Khartoum",
    "iso:country":"SD",
    "wof:name":"Marakha",
    "wof:placetype":"locality"
},
  "geometry": {"coordinates":[30.83333,12.98333],"type":"Point"}
}