{
  "type": "Feature",
  "properties": {
    "gn:admin1_code":"53.0",
    "gn:asciiname":"Umm Dibei",
    "gn:country_code":"SD",
    "gn:dem":360,
    "gn:feature_class":"P",
    "gn:feature_code":"PPL",
    "gn:name":"Umm Dibei",
    "gn:population":0,
    "gn:timezone":"Africa/Khartoum",
    "iso:country":"SD",
    "wof:name":"Umm Dibei",
    "wof:placetype":"locality"
},
  "geometry": {"coordinates":[34.1989,17.4651],"type":"Point"}
}