{
  "type": "Feature",
  "properties": {
    "gn:admin1_code":"49.0",
    "gn:asciiname":"Firo",
    "gn:country_code":"SD",
    "gn:dem":1117,
    "gn:feature_class":"P",
    "gn:feature_code":"PPL",
    "gn:name":"Firo",
    "gn:population":0,
    "gn:timezone":"Africa/Khartoum",
    "iso:country":"SD",
    "wof:name":"Firo",
    "wof:placetype":"locality"
},
  "geometry": {"coordinates":[24.36112,12.69136],"type":"Point"}
}