{
  "type": "Feature",
  "properties": {
    "gn:admin1_code":"56.0",
    "gn:asciiname":"Kol",
    "gn:country_code":"SD",
    "gn:dem":485,
    "gn:feature_class":"P",
    "gn:feature_code":"PPL",
    "gn:name":"Kol",
    "gn:population":0,
    "gn:timezone":"Africa/Khartoum",
    "iso:country":"SD",
    "name:cat_x_preferred":[
        "Kol"
    ],
    "name:ceb_x_preferred":[
        "Kol"
    ],
    "name:fra_x_preferred":[
        "Kol"
    ],
    "name:nld_x_preferred":[
        "Kol"
    ],
    "name:por_x_preferred":[
        "Kol"
    ],
    "name:swe_x_preferred":[
        "Kol"
    ],
    "name:tur_x_preferred":[
        "Kol"
    ],
    "wof:name":"Kol",
    "wof:placetype":"locality"
},
  "geometry": {"coordinates":[30.85,13.13333],"type":"Point"}
}