{
  "type": "Feature",
  "properties": {
    "gn:admin1_code":"42.0",
    "gn:asciiname":"Al Kharaba Balla",
    "gn:country_code":"SD",
    "gn:dem":492,
    "gn:feature_class":"P",
    "gn:feature_code":"PPL",
    "gn:name":"Al Khar\u0101ba Balla",
    "gn:population":0,
    "gn:timezone":"Africa/Khartoum",
    "iso:country":"SD",
    "name:und_x_variant":[
        "Kharaba West",
        "Khar\u0101bah",
        "Al Khar\u0101ba Balla"
    ],
    "wof:name":"Al Kharaba Balla",
    "wof:placetype":"locality"
},
  "geometry": {"coordinates":[34.3351,11.6943],"type":"Point"}
}