{
  "type": "Feature",
  "properties": {
    "gn:admin1_code":"53.0",
    "gn:asciiname":"Umm Ba`ashim",
    "gn:country_code":"SD",
    "gn:dem":379,
    "gn:feature_class":"P",
    "gn:feature_code":"PPL",
    "gn:name":"Umm Ba\u2018\u0101sh\u012bm",
    "gn:population":0,
    "gn:timezone":"Africa/Khartoum",
    "iso:country":"SD",
    "wof:name":"Umm Ba`ashim",
    "wof:placetype":"locality"
},
  "geometry": {"coordinates":[34.96,17.035],"type":"Point"}
}