{
  "type": "Feature",
  "properties": {
    "gn:admin1_code":"49.0",
    "gn:asciiname":"Sahabaia",
    "gn:country_code":"SD",
    "gn:dem":549,
    "gn:feature_class":"P",
    "gn:feature_code":"PPL",
    "gn:name":"Sahabaia",
    "gn:population":0,
    "gn:timezone":"Africa/Khartoum",
    "iso:country":"SD",
    "wof:name":"Sahabaia",
    "wof:placetype":"locality"
},
  "geometry": {"coordinates":[23.10828,10.64103],"type":"Point"}
}