{
  "type": "Feature",
  "properties": {
    "gn:admin1_code":"38.0",
    "gn:asciiname":"Kulliyyat az Zira`a",
    "gn:country_code":"SD",
    "gn:dem":409,
    "gn:feature_class":"P",
    "gn:feature_code":"PPL",
    "gn:name":"Kulliyyat az Zir\u0101\u2018a",
    "gn:population":0,
    "gn:timezone":"Africa/Khartoum",
    "iso:country":"SD",
    "name:und_x_variant":[
        "Kulliyyat az Zir\u0101\u2018a"
    ],
    "wof:name":"Kulliyyat az Zira`a",
    "wof:placetype":"locality"
},
  "geometry": {"coordinates":[33.4988,14.4991],"type":"Point"}
}