{
  "type": "Feature",
  "properties": {
    "gn:admin1_code":"49.0",
    "gn:asciiname":"Mugguduma",
    "gn:country_code":"SD",
    "gn:dem":472,
    "gn:feature_class":"P",
    "gn:feature_code":"PPL",
    "gn:name":"Mugguduma",
    "gn:population":0,
    "gn:timezone":"Africa/Khartoum",
    "iso:country":"SD",
    "wof:name":"Mugguduma",
    "wof:placetype":"locality"
},
  "geometry": {"coordinates":[25.10094,10.31846],"type":"Point"}
}