{
  "type": "Feature",
  "properties": {
    "gn:admin1_code":"38.0",
    "gn:asciiname":"`Ufaynah",
    "gn:country_code":"SD",
    "gn:dem":411,
    "gn:feature_class":"P",
    "gn:feature_code":"PPL",
    "gn:name":"\u2018Ufaynah",
    "gn:population":0,
    "gn:timezone":"Africa/Khartoum",
    "iso:country":"SD",
    "name:und_x_variant":[
        "\u2018Ufeina",
        "\u2018Ufaynah"
    ],
    "wof:name":"`Ufaynah",
    "wof:placetype":"locality"
},
  "geometry": {"coordinates":[33.51667,14.76667],"type":"Point"}
}