{
  "type": "Feature",
  "properties": {
    "gn:admin1_code":"56.0",
    "gn:asciiname":"Shatib",
    "gn:country_code":"SD",
    "gn:dem":440,
    "gn:feature_class":"P",
    "gn:feature_code":"PPL",
    "gn:name":"Sha\u0163\u012bb",
    "gn:population":0,
    "gn:timezone":"Africa/Khartoum",
    "iso:country":"SD",
    "wof:name":"Shatib",
    "wof:placetype":"locality"
},
  "geometry": {"coordinates":[31.05,14.01667],"type":"Point"}
}