{
  "type": "Feature",
  "properties": {
    "gn:admin1_code":"56.0",
    "gn:asciiname":"Shatib",
    "gn:country_code":"SD",
    "gn:dem":440,
    "gn:feature_class":"P",
    "gn:feature_code":"PPL",
    "gn:name":"Sha\u0163\u012bb",
    "gn:population":0,
    "gn:timezone":"Africa/Khartoum",
    "iso:country":"SD",
    "name:ara_x_preferred":[
        "\u0634\u0637\u064a\u0628"
    ],
    "name:fas_x_preferred":[
        "\u0634\u0637\u06cc\u0628"
    ],
    "name:pol_x_preferred":[
        "Szutajb"
    ],
    "name:vie_x_preferred":[
        "Shatib"
    ],
    "wof:lang_x_official":[
        "ara",
        "eng"
    ],
    "wof:lang_x_spoken":[
        "ara",
        "eng"
    ],
    "wof:name":"Shatib",
    "wof:placetype":"locality"
},
  "geometry": {"coordinates":[31.05,14.01667],"type":"Point"}
}