{
  "type": "Feature",
  "properties": {
    "gn:admin1_code":"50.0",
    "gn:asciiname":"Alleira Elmuna",
    "gn:country_code":"SD",
    "gn:dem":1073,
    "gn:feature_class":"P",
    "gn:feature_code":"PPL",
    "gn:name":"Alleira Elmuna",
    "gn:population":0,
    "gn:timezone":"Africa/Khartoum",
    "iso:country":"SD",
    "wof:name":"Alleira Elmuna",
    "wof:placetype":"locality"
},
  "geometry": {"coordinates":[30.48333,11.28333],"type":"Point"}
}