{
  "type": "Feature",
  "properties": {
    "gn:admin1_code":"55.0",
    "gn:asciiname":"Shingil Tobaya",
    "gn:country_code":"SD",
    "gn:dem":713,
    "gn:feature_class":"P",
    "gn:feature_code":"PPL",
    "gn:name":"Shingil Tobaya",
    "gn:population":0,
    "gn:timezone":"Africa/Khartoum",
    "iso:country":"SD",
    "name:und_x_variant":[
        "Tertura",
        "Shingil Tobaya"
    ],
    "wof:lang_x_official":[
        "ara",
        "eng"
    ],
    "wof:lang_x_spoken":[
        "ara",
        "eng"
    ],
    "wof:name":"Shingil Tobaya",
    "wof:placetype":"locality"
},
  "geometry": {"coordinates":[25.25,13.01667],"type":"Point"}
}