{
  "type": "Feature",
  "properties": {
    "gn:admin1_code":"49.0",
    "gn:asciiname":"Al Bayda'",
    "gn:country_code":"SD",
    "gn:dem":456,
    "gn:feature_class":"P",
    "gn:feature_code":"PPL",
    "gn:name":"Al Bay\u1e11\u0101\u2019",
    "gn:population":0,
    "gn:timezone":"Africa/Khartoum",
    "iso:country":"SD",
    "name:ceb_x_preferred":[
        "Al Bayda'"
    ],
    "name:nld_x_preferred":[
        "Al Bayda'"
    ],
    "name:sco_x_preferred":[
        "Al Bayda'"
    ],
    "name:swe_x_preferred":[
        "Al Bayda'"
    ],
    "name:und_x_variant":[
        "El Beida",
        "Al Bay\u1e11\u0101\u2019"
    ],
    "wof:name":"Al Bayda'",
    "wof:placetype":"locality"
},
  "geometry": {"coordinates":[25.56667,10.68333],"type":"Point"}
}