{
  "type": "Feature",
  "properties": {
    "gn:admin1_code":"38.0",
    "gn:asciiname":"Al Fashir",
    "gn:country_code":"SD",
    "gn:dem":401,
    "gn:feature_class":"P",
    "gn:feature_code":"PPL",
    "gn:name":"Al F\u0101shir",
    "gn:population":0,
    "gn:timezone":"Africa/Khartoum",
    "iso:country":"SD",
    "name:ara_x_preferred":[
        "Al F\u0101shir"
    ],
    "wof:name":"Al Fashir",
    "wof:placetype":"locality"
},
  "geometry": {"coordinates":[33.04,14.7377],"type":"Point"}
}